Workbook

Sheet summary_table_v26_27SIs
A1: Code | B1: Innovation Name | C1: Spatial Scale | D1: Indicator Number | E1: Indicator Name | F1: Description | G1: Metric | H1: Category | I1: slope_log | J1: slope_exp | K1: slope_lin | L1: log_t0 | M1: log_Dt | N1: log_K | O1: exp_a | P1: exp_c | Q1: lin_intercept | R1: log_r2 | S1: log_r2adj | T1: log_rmse | U1: log_mae | V1: exp_r2 | W1: exp_r2adj | X1: exp_rmse | Y1: exp_mae | Z1: lin_r2 | AA1: lin_r2adj | AB1: lin_rmse | AC1: lin_mae | AD1: n_data_points | AE1: n_non_zero_data_points | AF1: max_over_K | AG1: min_over_K | AH1: range_over_k | AI1: length_trimmed_series_years | AJ1: n_data_points_beyond_max | AK1: n_data_points_beyond_min | AL1: suspected_reversal_up2down | AM1: suspected_reversal_down2up | AN1: at_least_one_big_jump | AO1: autocorr_l1 | AP1: all_values_less_than_or_equal_to_1 | AQ1: all_values_less_than_or_equal_to_100 | AR1: C1_R2 | AS1: C2_threshold_non_zero_value_years | AT1: C3_pct_non_zero | AU1: C4_less_than_250_jump_in_second_half | AV1: C4_less_than_80_fall_in_second_half | AW1: C4_combined_less_than_80_fall_and_250_jump_in_second_half | AX1: C5_volatility_autocorrelation_lag1_threshold_0.7 | AY1: C6_{K_COVERAGE_THRESHOLD}_of_k_covered_by_data | AZ1: C7_lin_r2 | BA1: use_log_x | BB1: use_lin_x | BC1: use_log_y | BD1: use_lin_y | BE1: old GN scoring @retreat | BF1: old GN comments | BG1: old CW scoring @retreat | BH1: comments_fit_CW | BI1: comments_delete_CW | BJ1: comments_alternativeseries_CW | BK1: comments_transformations_CW | BL1: use_logfit_CW | BM1: use_linfit_CW | BN1: select_1.1_earegion_CW | BO1: select_1.1_allregions_CW | BP1: select_non1.1s_earegion_CW | BQ1: select_non1.1s_allregions_CW | BR1: GN final scoring | BS1: use_logfit_GN | BT1: use_linfit_GN | BU1: select_1.1_earegion_GN | BV1: select_1.1_allregions_GN | BW1: select_non1.1s_earegion_GN | BX1: select_non1.1s_allregions_GN | BY1: PDF page | BZ1: use_logfit_AGREE? | CA1: use_linfit_AGREE? | CB1: select_1.1_earegion_AGREE? | CC1: select_1.1_allregions_AGREE? | CD1: select_non1.1s_earegion_AGREE? | CE1: select_non1.1s_allregions_AGREE? | CF1: FINAL_AGREED | CG1: use_logfit_FIN | CH1: use_linfit_FIN | CI1: select_1.1_earegion_FIN | CJ1: select_1.1_allregions_FIN | CK1: select_non1.1s_earegion_FIN | CL1: select_non1.1s_allregions_FIN | CM1: CWnotes_6May | CN1: GN notes 9 may
A2: act_ams_1.1Ado_d063_m028 | B2: active mobility | C2: Amsterdam | D2: 1.1 | E2: Adoption over time | F2: Bike ownership | G2: % | H2: b7 | I2: 6.1161 | J2: 0.0054776 | K2: 0.0038502 | L2: 1984.7 | M2: 0.7185 | N2: 0.71167 | O2: 0.76729 | P2: 2018.3 | Q2: -7.0056 | R2: 0.67402 | S2: 0.34804 | T2: 0.022307 | U2: 0.018571 | V2: 0.78529 | W2: 0.67794 | X2: 0.018104 | Y2: 0.017715 | Z2: 0.79629 | AA2: 0.69443 | AB2: 0.017635 | AC2: 0.017232 | AD2: 7 | AE2: 7 | AF2: 1.0539 | AG2: 0.87119 | AH2: 0.18267 | AI2: 29 | AJ2: 1 | AK2: 6 | AL2: 0 | AM2: 0 | AN2: 0 | AO2: 0.86693 | AP2: 1 | AQ2: 1 | AR2: m | AS2: y | AT2: y | AU2: y | AV2: y | AW2: y | AX2: y | AY2: m | AZ2: y | BA2: m | BB2: y | BC2: n | BD2: y | BE2: 1 | BI2: 0 | BL2: 0 | BM2: 1 | BN2: 0 | BO2: 0 | BP2: 0 | BQ2: 0 | BS2: 0 | BT2: 1 | BU2: 0 | BV2: 0 | BW2: 0 | BX2: 0 | BY2: 1 | CG2: 0 | CH2: 1 | CI2: 0 | CJ2: 0 | CK2: 0 | CL2: 0 | CO2: means I've changed 0 to 1 or vice versa
A3: act_ams_1.1Ado_d121_m090 | B3: active mobility | C3: Amsterdam | D3: 1.1 | E3: Adoption over time | F3: Modal share of all trips by residents (bike) | G3: % trips by bike | H3: b7 | I3: -0.0023618 | J3: -0.0023613 | K3: -0.00056291 | L3: -1564.6 | M3: -1860.6 | N3: 1091.8 | O3: 0.67031 | P3: 1566.4 | Q3: 1.3672 | R3: 0.17886 | S3: -0.31382 | T3: 0.03044 | U3: 0.027427 | V3: 0.17886 | W3: -0.094847 | X3: 0.03044 | Y3: 0.027427 | Z3: 0.16499 | AA3: -0.11334 | AB3: 0.030696 | AC3: 0.027808 | AD3: 9 | AE3: 9 | AF3: 0.00028395 | AG3: 0.00018319 | AH3: 0.00010076 | AI3: 84 | AJ3: 8 | AK3: 2 | AL3: 0 | AM3: 0 | AN3: 0 | AO3: 0.84023 | AP3: 1 | AQ3: 1 | AR3: n | AS3: y | AT3: y | AU3: y | AV3: y | AW3: y | AX3: y | AY3: m | AZ3: m | BA3: n | BB3: m | BC3: n | BD3: m | BE3: 2 | BI3: 0 | BL3: 1 | BM3: 1 | BN3: 0 | BO3: 0 | BP3: 0 | BQ3: 0 | BS3: 1 | BT3: 1 | BU3: 0 | BV3: 0 | BW3: 0 | BX3: 0 | BY3: 2 | CG3: 1 | CH3: 1 | CI3: 0 | CJ3: 0 | CK3: 0 | CL3: 0 | CO3: means problem, dicuss with GN
A4: act_ams_1.1Ado_d122_m091 | B4: active mobility | C4: Amsterdam | D4: 1.1 | E4: Adoption over time | F4: Modal share of all trips by residents (walk) | G4: % trips by walking | H4: b7 | I4: -16.742 | J4: -0.0042167 | K4: -0.0010874 | L4: 1996.2 | M4: -0.26248 | N4: 0.272 | O4: 0.083316 | P4: 2247.9 | Q4: 2.4124 | R4: -4.8878 | S4: -8.4205 | T4: 0.16055 | U4: 0.13267 | V4: 0.1654 | W4: -0.1128 | X4: 0.060446 | Y4: 0.045681 | Z4: 0.15869 | AA4: -0.12175 | AB4: 0.060688 | AC4: 0.045795 | AD4: 9 | AE4: 9 | AF4: 1.2868 | AG4: 0.44118 | AH4: 0.84559 | AI4: 84 | AJ4: 8 | AK4: 7 | AL4: 0 | AM4: 1 | AN4: 1 | AO4: 0.78584 | AP4: 1 | AQ4: 1 | AR4: n | AS4: y | AT4: y | AU4: y | AV4: y | AW4: y | AX4: y | AY4: y | AZ4: m | BA4: n | BB4: m | BC4: n | BD4: m | BE4: 4 | BG4: ok, use logfit | BI4: 0 | BL4: 1 | BM4: 1 | BN4: 0 | BO4: 0 | BP4: 0 | BQ4: 0 | BS4: 1 | BT4: 1 | BU4: 0 | BV4: 0 | BW4: 0 | BX4: 0 | BY4: 3 | CG4: 0 | CH4: 1 | CI4: 0 | CJ4: 0 | CK4: 0 | CL4: 0 | CM4: SdS: fit partial from 1979 (drop 1930 peak year) | CO4: means new coding for changed indicators post Feb
A5: act_ams_1.1Ado_d332_m185 | B5: active mobility | C5: Amsterdam | D5: 1.1 | E5: Adoption over time | F5: % trips by walking and biking | G5: market share | H5: b7 | I5: -0.0087911 | J5: -0.0033221 | K5: -0.0016503 | L5: 2033.8 | M5: -499.87 | N5: 0.83407 | O5: 0.0026073 | P5: 3568.5 | Q5: 3.7796 | R5: 0.19777 | S5: -0.28356 | T5: 0.078513 | U5: 0.059173 | V5: 0.22115 | W5: -0.038465 | X5: 0.07736 | Y5: 0.058997 | Z5: 0.20825 | AA5: -0.055671 | AB5: 0.077999 | AC5: 0.059339 | AD5: 9 | AE5: 9 | AF5: 0.79131 | AG5: 0.40764 | AH5: 0.38366 | AI5: 84 | AJ5: 8 | AK5: 7 | AL5: 0 | AM5: 1 | AN5: 0 | AO5: 0.82455 | AP5: 1 | AQ5: 1 | AR5: n | AS5: y | AT5: y | AU5: y | AV5: y | AW5: y | AX5: y | AY5: y | AZ5: m | BA5: n | BB5: m | BC5: n | BD5: m | BI5: 0 | BJ5: prefer-relative | BK5: transformed-marketshare | BL5: 1 | BM5: 1 | BN5: 0 | BO5: 1 | BP5: 0 | BQ5: 0 | BS5: 1 | BT5: 1 | BU5: 0 | BV5: 1 | BW5: 0 | BX5: 0 | BY5: 4 | CG5: 1 | CH5: 1 | CI5: 0 | CJ5: 0 | CK5: 0 | CL5: 0 | CO5: means didn't survive _v24 to _v25 transfer
A6: act_ams_1.1Ado_d359_m091 | B6: active mobility | C6: Amsterdam | D6: 1.1 | E6: Adoption over time | F6: Modal share of all trips by residents (walk) EXCLUDING 1930 | G6: % trips by walking | H6: b7 | I6: 1.9434 | J6: 0.0020703 | K6: 0.00060028 | L6: 1970.1 | M6: 2.2612 | N6: 0.25429 | O6: 0.068688 | P6: 1396.9 | Q6: -0.96066 | R6: 0.56052 | S6: 0.23091 | T6: 0.039325 | U6: 0.033214 | V6: 0.014739 | W6: -0.37937 | X6: 0.05888 | Y6: 0.051788 | Z6: 0.018126 | AA6: -0.37462 | AB6: 0.058779 | AC6: 0.052101 | AD6: 8 | AE6: 8 | AF6: 1.2191 | AG6: 0.47191 | AH6: 0.74719 | AI6: 44 | AJ6: 6 | AK6: 7 | AL6: 1 | AM6: 0 | AN6: 1 | AO6: 0.89904 | AP6: 1 | AQ6: 1 | AR6: m | AS6: y | AT6: y | AU6: y | AV6: y | AW6: y | AX6: y | AY6: y | AZ6: m | BA6: m | BB6: m | CG6: 0 | CH6: 1 | CI6: 0 | CJ6: 0 | CK6: 0 | CL6: 0
A7: act_ams_1.1Ado_d360_m185 | B7: active mobility | C7: Amsterdam | D7: 1.1 | E7: Adoption over time | F7: % trips by walking and biking EXCLUDING 1930 | G7: market share | H7: b7 | I7: 1.0857 | J7: 0.0026517 | K7: 0.0013983 | L7: 1969.3 | M7: 4.0475 | N7: 0.49714 | O7: 0.10663 | P7: 1430.8 | Q7: -2.3135 | R7: 0.54632 | S7: 0.20607 | T7: 0.047359 | U7: 0.036072 | V7: 0.062786 | W7: -0.3121 | X7: 0.068069 | Y7: 0.06083 | Z7: 0.070004 | AA7: -0.30199 | AB7: 0.067806 | AC7: 0.060625 | AD7: 8 | AE7: 8 | AF7: 1.1264 | AG7: 0.68391 | AH7: 0.44253 | AI7: 44 | AJ7: 4 | AK7: 7 | AL7: 1 | AM7: 0 | AN7: 0 | AO7: 0.89687 | AP7: 1 | AQ7: 1 | AR7: m | AS7: y | AT7: y | AU7: y | AV7: y | AW7: y | AX7: y | AY7: y | AZ7: m | BA7: m | BB7: m | CG7: 0 | CH7: 1 | CI7: 0 | CJ7: 1 | CK7: 0 | CL7: 0
A8: act_bei_1.1Ado_d060_m028 | B8: active mobility | C8: Beijing | D8: 1.1 | E8: Adoption over time | F8: Bicycle modal share | G8: % | H8: b7 | I8: -128.93 | J8: -0.00040147 | K8: -0.01425 | L8: 1999.7 | M8: -0.034083 | N8: 0.5403 | O8: -1544.5 | P8: -152600 | Q8: 28.852 | R8: -3.1777 | S8: 9.3553 | T8: 0.25892 | U8: 0.205 | V8: -9.2413 | W8: =-inf -> #NAME? | X8: 0.4054 | Y8: 0.3851 | Z8: 0.96449 | AA8: =-inf -> #NAME? | AB8: 0.023871 | AC8: 0.0221 | AD8: 3 | AE8: 3 | AF8: 1 | AG8: 0.42569 | AH8: 0.57431 | AI8: 22 | AJ8: 2 | AK8: 0 | AL8: 0 | AM8: 0 | AN8: 0 | AO8: 0.60149 | AP8: 1 | AQ8: 1 | AR8: n | AS8: m | AT8: y | AU8: y | AV8: y | AW8: y | AX8: m | AY8: y | AZ8: y | BA8: n | BB8: m | BC8: m | BD8: m | BE8: 2 | BI8: 0 | BL8: 1 | BM8: 1 | BN8: 0 | BO8: 0 | BP8: 0 | BQ8: 0 | BS8: 1 | BT8: 1 | BU8: 0 | BV8: 0 | BW8: 0 | BX8: 0 | BY8: 5 | CG8: 0 | CH8: 1 | CI8: 0 | CJ8: 0 | CK8: 0 | CL8: 0
A9: act_bei_1.1Ado_d332_m185 | B9: active mobility | C9: Beijing | D9: 1.1 | E9: Adoption over time | F9: % trips by walking and biking | G9: market share | H9: b7 | I9: -128.93 | J9: -0.00040147 | K9: -0.01425 | L9: 1999.7 | M9: -0.034083 | N9: 0.5403 | O9: -1544.5 | P9: -152600 | Q9: 28.852 | R9: -3.1777 | S9: 9.3553 | T9: 0.25892 | U9: 0.205 | V9: -9.2413 | W9: =-inf -> #NAME? | X9: 0.4054 | Y9: 0.3851 | Z9: 0.96449 | AA9: =-inf -> #NAME? | AB9: 0.023871 | AC9: 0.0221 | AD9: 3 | AE9: 3 | AF9: 1 | AG9: 0.42569 | AH9: 0.57431 | AI9: 22 | AJ9: 2 | AK9: 0 | AL9: 0 | AM9: 0 | AN9: 0 | AO9: 0.60149 | AP9: 1 | AQ9: 1 | AR9: n | AS9: m | AT9: y | AU9: y | AV9: y | AW9: y | AX9: m | AY9: y | AZ9: y | BA9: n | BB9: m | BC9: m | BD9: m | BI9: 0 | BJ9: prefer-relative | BK9: transformed-marketshare | BL9: 1 | BM9: 1 | BN9: 0 | BO9: 1 | BP9: 0 | BQ9: 0 | BS9: 1 | BT9: 1 | BU9: 0 | BV9: 1 | BW9: 0 | BX9: 0 | BY9: 6 | CG9: 0 | CH9: 1 | CI9: 0 | CJ9: 1 | CK9: 0 | CL9: 0
A10: act_chi_1.1Ado_d061_m002 | B10: active mobility | C10: China | D10: 1.1 | E10: Adoption over time | F10: Bicycle ownership | G10: # bikes per hundred households | H10: b7 | I10: 15.465 | J10: 0.020393 | K10: 2.6286 | L10: 1814.4 | M10: 0.28415 | N10: 110.03 | O10: 3.2025 | P10: 1817.7 | Q10: -5121 | R10: 0 | S10: =-inf -> #NAME? | T10: 61.847 | U10: 47.333 | V10: 0.20425 | W10: -1.3873 | X10: 55.17 | Y10: 49.509 | Z10: 0.23213 | AA10: -1.3036 | AB10: 54.195 | AC10: 50.322 | AD10: 4 | AE10: 4 | AF10: 1.7918 | AG10: 0.20794 | AH10: 1.5839 | AI10: 30 | AJ10: 1 | AK10: 2 | AL10: 1 | AM10: 1 | AN10: 1 | AO10: 0.47132 | AP10: 0 | AQ10: 0 | AR10: n | AS10: m | AT10: y | AU10: m | AV10: y | AW10: m | AX10: m | AY10: y | AZ10: m | BA10: n | BB10: m | BC10: m | BD10: m | BE10: 4 | BG10: reject, too few points | BI10: 0 | BL10: 0 | BM10: 1 | BN10: 0 | BO10: 0 | BP10: 0 | BQ10: 0 | BS10: 0 | BT10: 1 | BU10: 0 | BV10: 0 | BW10: 0 | BX10: 0 | BY10: 7 | CG10: 0 | CH10: 1 | CI10: 0 | CJ10: 0 | CK10: 0 | CL10: 0
A11: act_chi_3.2Adc_d062_m003 | B11: active mobility | C11: China | D11: 3.2 | E11: Adopter characteristics | F11: Bicycle ownership among income groups | G11: # bikes per hundred households (highest 10% income) | H11: b7 | I11: -0.25049 | J11: -0.017188 | K11: -3.0744 | L11: 2008 | M11: -17.543 | N11: 187.66 | O11: 280.33 | P11: 1964.3 | Q11: 6300.3 | R11: 0.82934 | S11: =-inf -> #NAME? | T11: 12.667 | U11: 10.677 | V11: 0.51703 | W11: -0.4489 | X11: 21.309 | Y11: 19.229 | Z11: 0.56489 | AA11: -0.30533 | AB11: 20.226 | AC11: 18.246 | AD11: 4 | AE11: 4 | AF11: 1.0823 | AG11: 0.62879 | AH11: 0.45353 | AI11: 21 | AJ11: 2 | AK11: 0 | AL11: 1 | AM11: 0 | AN11: 0 | AO11: 0.78003 | AP11: 0 | AQ11: 0 | AR11: y | AS11: m | AT11: y | AU11: y | AV11: y | AW11: y | AX11: y | AY11: y | AZ11: y | BA11: m | BB11: m | BC11: m | BD11: m | BE11: 2 | BI11: 0 | BL11: 0 | BM11: 1 | BS11: 1 | BT11: 1 | BU11: 0 | BV11: 0 | BW11: 0 | BX11: 0 | BY11: 8 | BZ11: check | CG11: 1 | CH11: 1 | CI11: 0 | CJ11: 0 | CK11: 0 | CL11: 0
A12: act_chi_3.2Adc_d062_m004 | B12: active mobility | C12: China | D12: 3.2 | E12: Adopter characteristics | F12: Bicycle ownership among income groups | G12: # bikes per hundred households (lowest 10% income) | H12: b7 | I12: -2.6167 | J12: -0.0083411 | K12: -1.3736 | L12: 2006.3 | M12: -1.6794 | N12: 157.06 | O12: 227.52 | P12: 1941.8 | Q12: 2886.7 | R12: 0.61758 | S12: =-inf -> #NAME? | T12: 16.895 | U12: 12.122 | V12: 0.12506 | W12: -1.6248 | X12: 25.555 | Y12: 25.04 | Z12: 0.14203 | AA12: -1.5739 | AB12: 25.306 | AC12: 24.861 | AD12: 4 | AE12: 4 | AF12: 1.1498 | AG12: 0.68431 | AH12: 0.46548 | AI12: 21 | AJ12: 2 | AK12: 0 | AL12: 1 | AM12: 0 | AN12: 0 | AO12: 0.80089 | AP12: 0 | AQ12: 0 | AR12: m | AS12: m | AT12: y | AU12: y | AV12: y | AW12: y | AX12: y | AY12: y | AZ12: m | BA12: m | BB12: m | BC12: m | BD12: m | BE12: 2 | BI12: 0 | BL12: 0 | BM12: 1 | BS12: 0 | BT12: 1 | BU12: 0 | BV12: 0 | BW12: 0 | BX12: 0 | BY12: 9 | CG12: 0 | CH12: 1 | CI12: 0 | CJ12: 0 | CK12: 0 | CL12: 0
A13: act_chi_3.2Adc_d062_m005 | B13: active mobility | C13: China | D13: 3.2 | E13: Adopter characteristics | F13: Bicycle ownership among income groups | G13: # bikes per hundred households (middle income groups) | H13: b7 | I13: -0.35805 | J13: -0.013207 | K13: -2.4015 | L13: 2007.8 | M13: -12.273 | N13: 181.57 | O13: 267.65 | P13: 1958.3 | Q13: 4957 | R13: 0.75315 | S13: =-inf -> #NAME? | T13: 14.824 | U13: 11.464 | V13: 0.32729 | W13: -1.0181 | X13: 24.472 | Y13: 23.3 | Z13: 0.364 | AA13: -0.90799 | AB13: 23.795 | AC13: 22.74 | AD13: 4 | AE13: 4 | AF13: 1.1186 | AG13: 0.65538 | AH13: 0.46323 | AI13: 21 | AJ13: 2 | AK13: 0 | AL13: 1 | AM13: 0 | AN13: 0 | AO13: 0.79113 | AP13: 0 | AQ13: 0 | AR13: y | AS13: m | AT13: y | AU13: y | AV13: y | AW13: y | AX13: y | AY13: y | AZ13: y | BA13: m | BB13: m | BC13: m | BD13: m | BE13: 2 | BI13: 0 | BL13: 0 | BM13: 1 | BS13: 1 | BT13: 1 | BU13: 0 | BV13: 0 | BW13: 0 | BX13: 1 | BY13: 10 | BZ13: check | CG13: 1 | CH13: 1 | CI13: 0 | CJ13: 0 | CK13: 0 | CL13: 1
A14: act_chi_4.1Sal_d213_m100 | B14: active mobility | C14: China | D14: 4.1 | E14: Knowledge Flows (social networks) | F14: annualised Google search frequency (index 100=monthly max.) | G14: Index 0-100 | H14: b7 | I14: 2.095 | J14: 0.076912 | K14: 3.6253 | L14: 2013.4 | M14: 2.0976 | N14: 61.747 | O14: 0.65739 | P14: 1963.6 | Q14: -7267.6 | R14: 0.79934 | S14: 0.76393 | T14: 14.129 | U14: 9.9398 | V14: 0.36338 | W14: 0.29265 | X14: 25.166 | Y14: 21.242 | Z14: 0.48439 | AA14: 0.4271 | AB14: 22.649 | AC14: 17.771 | AD14: 21 | AE14: 20 | AF14: 1.6195 | AG14: 0.017461 | AH14: 1.6021 | AI14: 21 | AJ14: 8 | AK14: 20 | AL14: 1 | AM14: 0 | AN14: 1 | AO14: 0.93024 | AP14: 0 | AQ14: 1 | AR14: y | AS14: y | AT14: y | AU14: y | AV14: y | AW14: y | AX14: y | AY14: y | AZ14: y | BA14: y | BB14: y | BC14: y | BD14: y | BI14: 0 | BJ14: hide | BK14: original | BL14: 1 | BM14: 1 | BN14: 0 | BO14: 0 | BP14: 0 | BQ14: 0 | BS14: 1 | BT14: 0 | BU14: 0 | BV14: 0 | BW14: 0 | BX14: 0 | BY14: 11 | CA14: check | CG14: 1 | CH14: 1 | CI14: 0 | CJ14: 0 | CK14: 0 | CL14: 0
A15: act_chi_4.1Sal_d239_m153 | B15: active mobility | C15: China | D15: 4.1 | E15: Knowledge Flows (social networks) | F15: Partial up to max annualised Google search frequency (index 100=monthly max.) | G15: Partial up to max Index 0-100 | H15: b7 | I15: 1.0431 | J15: 0.49369 | K15: 6.5779 | L15: 2014.6 | M15: 4.213 | N15: 123.43 | O15: 0.019473 | P15: 1998.6 | Q15: -13201 | R15: 0.99639 | S15: 0.99519 | T15: 1.8903 | U15: 1.5688 | V15: 0.97515 | W15: 0.97018 | X15: 4.9601 | Y15: 3.8128 | Z15: 0.61177 | AA15: 0.53412 | AB15: 19.606 | AC15: 16.835 | AD15: 13 | AE15: 12 | AF15: 0.81017 | AG15: 0.0087349 | AH15: 0.80143 | AI15: 13 | AJ15: 0 | AK15: 12 | AL15: 0 | AM15: 0 | AN15: 1 | AO15: 0.66032 | AP15: 0 | AQ15: 1 | AR15: y | AS15: y | AT15: y | AU15: y | AV15: y | AW15: y | AX15: m | AY15: y | AZ15: y | BA15: m | BB15: m | BC15: y | BD15: y | BI15: 0 | BJ15: prefer | BK15: transformed-partial | BL15: 1 | BM15: 1 | BN15: 0 | BO15: 0 | BP15: 0 | BQ15: 1 | BS15: 1 | BT15: 1 | BU15: 0 | BV15: 0 | BW15: 0 | BX15: 1 | BY15: 12 | CG15: 1 | CH15: 1 | CI15: 0 | CJ15: 0 | CK15: 0 | CL15: 1
A16: act_cop_1.1Ado_d121_m090 | B16: active mobility | C16: Copenhagen | D16: 1.1 | E16: Adoption over time | F16: Modal share of all trips by residents (bike) | G16: % trips by bike | H16: b7 | I16: 0.014241 | J16: 0.0012979 | K16: 0.0033675 | L16: 2734.2 | M16: 308.58 | N16: 8643.2 | O16: 1555.1 | P16: 157450 | Q16: -6.4834 | R16: 0.784 | S16: =-inf -> #NAME? | T16: 0.018985 | U16: 0.018338 | V16: -38.206 | W16: -116.62 | X16: 0.25578 | Y16: 0.2525 | Z16: 0.7454 | AA16: 0.23619 | AB16: 0.020612 | AC16: 0.020026 | AD16: 4 | AE16: 4 | AF16: 3.7023e-05 | AG16: 2.5454e-05 | AH16: 1.157e-05 | AI16: 28 | AJ16: 0 | AK16: 3 | AL16: 0 | AM16: 0 | AN16: 0 | AO16: 0.7008 | AP16: 1 | AQ16: 1 | AR16: y | AS16: m | AT16: y | AU16: y | AV16: y | AW16: y | AX16: y | AY16: m | AZ16: y | BA16: m | BB16: m | BC16: m | BD16: m | BE16: 2 | BI16: 0 | BL16: 1 | BM16: 1 | BN16: 0 | BO16: 0 | BP16: 0 | BQ16: 0 | BS16: 1 | BT16: 1 | BU16: 0 | BV16: 0 | BW16: 0 | BX16: 0 | BY16: 13 | CG16: 1 | CH16: 1 | CI16: 0 | CJ16: 0 | CK16: 0 | CL16: 0
A17: act_cop_1.1Ado_d122_m091 | B17: active mobility | C17: Copenhagen | D17: 1.1 | E17: Adoption over time | F17: Modal share of all trips by residents (walk) | G17: % trips by walking | H17: b7 | I17: 0.0018687 | J17: 0.0010136 | K17: 0.00030769 | L17: 5039 | M17: 2351.6 | N17: 54.298 | O17: 1555.1 | P17: 157440 | Q17: -0.43046 | R17: 0.007873 | S17: =-inf -> #NAME? | T17: 0.038254 | U17: 0.031585 | V17: -23.203 | W17: -71.61 | X17: 0.18894 | Y17: 0.185 | Z17: 0.0070404 | AA17: -1.9789 | AB17: 0.03827 | AC17: 0.031692 | AD17: 4 | AE17: 4 | AF17: 0.0040517 | AG17: 0.00221 | AH17: 0.0018417 | AI17: 28 | AJ17: 3 | AK17: 2 | AL17: 0 | AM17: 1 | AN17: 0 | AO17: 0.63305 | AP17: 1 | AQ17: 1 | AR17: n | AS17: m | AT17: y | AU17: y | AV17: y | AW17: y | AX17: m | AY17: m | AZ17: m | BA17: n | BB17: m | BC17: n | BD17: m | BE17: 4 | BG17: ok, use logfit | BI17: 0 | BL17: 0 | BM17: 0 | BN17: 0 | BO17: 0 | BP17: 0 | BQ17: 0 | BS17: 1 | BT17: 1 | BU17: 0 | BV17: 0 | BW17: 0 | BX17: 0 | BY17: 14 | BZ17: check | CA17: check | CG17: 1 | CH17: 1 | CI17: 0 | CJ17: 0 | CK17: 0 | CL17: 0
A18: act_cop_1.1Ado_d332_m185 | B18: active mobility | C18: Copenhagen | D18: 1.1 | E18: Adoption over time | F18: % trips by walking and biking | G18: market share | H18: b7 | I18: 0.015233 | J18: 0.0013115 | K18: 0.0036752 | L18: 2016.9 | M18: 288.48 | N18: 1 | O18: 1555.2 | P18: 157440 | Q18: -6.9138 | R18: 0.36641 | S18: =-inf -> #NAME? | T18: 0.051084 | U18: 0.045033 | V18: -46.472 | W18: -141.42 | X18: 0.44218 | Y18: 0.4375 | Z18: 0.35971 | AA18: -0.92086 | AB18: 0.051353 | AC18: 0.045256 | AD18: 4 | AE18: 4 | AF18: 0.52 | AG18: 0.34 | AH18: 0.18 | AI18: 28 | AJ18: 0 | AK18: 2 | AL18: 0 | AM18: 1 | AN18: 0 | AO18: 0.6861 | AP18: 1 | AQ18: 1 | AR18: m | AS18: m | AT18: y | AU18: y | AV18: y | AW18: y | AX18: m | AY18: m | AZ18: y | BA18: m | BB18: m | BC18: m | BD18: m | BI18: 0 | BJ18: prefer-relative | BK18: transformed-marketshare | BL18: 1 | BM18: 1 | BN18: 0 | BO18: 1 | BP18: 0 | BQ18: 0 | BS18: 1 | BT18: 1 | BU18: 0 | BV18: 1 | BW18: 0 | BX18: 0 | BY18: 15 | CG18: 1 | CH18: 1 | CI18: 0 | CJ18: 1 | CK18: 0 | CL18: 0
A19: act_den_4.1Sal_d213_m100 | B19: active mobility | C19: Denmark | D19: 4.1 | E19: Knowledge Flows (social networks) | F19: annualised Google search frequency (index 100=monthly max.) | G19: Index 0-100 | H19: b7 | I19: 5.3821 | J19: 0.046164 | K19: 2.6871 | L19: 2011.1 | M19: 0.81649 | N19: 61.49 | O19: 1.3191 | P19: 1940.1 | Q19: -5371.1 | R19: 0.6915 | S19: 0.63706 | T19: 17.672 | U19: 13.516 | V19: 0.18602 | W19: 0.095577 | X19: 28.705 | Y19: 24.86 | Z19: 0.26155 | AA19: 0.1795 | AB19: 27.341 | AC19: 23.166 | AD19: 21 | AE19: 20 | AF19: 1.6263 | AG19: 0.0025937 | AH19: 1.6237 | AI19: 21 | AJ19: 9 | AK19: 16 | AL19: 1 | AM19: 1 | AN19: 1 | AO19: 0.94961 | AP19: 0 | AQ19: 1 | AR19: m | AS19: y | AT19: y | AU19: y | AV19: y | AW19: y | AX19: y | AY19: y | AZ19: m | BA19: m | BB19: m | BC19: m | BD19: m | BI19: 0 | BJ19: hide | BK19: original | BL19: 1 | BM19: 1 | BN19: 0 | BO19: 0 | BP19: 0 | BQ19: 0 | BS19: 1 | BT19: 0 | BU19: 0 | BV19: 0 | BW19: 0 | BX19: 0 | BY19: 16 | CA19: check | CG19: 1 | CH19: 1 | CI19: 0 | CJ19: 0 | CK19: 0 | CL19: 0
A20: act_den_4.1Sal_d239_m153 | B20: active mobility | C20: Denmark | D20: 4.1 | E20: Knowledge Flows (social networks) | F20: Partial up to max annualised Google search frequency (index 100=monthly max.) | G20: Partial up to max Index 0-100 | H20: b7 | I20: 1.43 | J20: 0.31327 | K20: 9.5766 | L20: 2011.7 | M20: 3.073 | N20: 98.11 | O20: 0.0079377 | P20: 1984.4 | Q20: -19211 | R20: 0.987 | S20: 0.98212 | T20: 4.3211 | U20: 3.2716 | V20: 0.89193 | W20: 0.86791 | X20: 12.458 | Y20: 10.933 | Z20: 0.76106 | AA20: 0.70796 | AB20: 18.524 | AC20: 16.71 | AD20: 12 | AE20: 11 | AF20: 1.0193 | AG20: 0.0016256 | AH20: 1.0176 | AI20: 12 | AJ20: 0 | AK20: 7 | AL20: 0 | AM20: 1 | AN20: 1 | AO20: 0.79251 | AP20: 0 | AQ20: 1 | AR20: y | AS20: y | AT20: y | AU20: y | AV20: y | AW20: y | AX20: y | AY20: y | AZ20: y | BA20: y | BB20: y | BC20: y | BD20: y | BI20: 0 | BJ20: prefer | BK20: transformed-partial | BL20: 1 | BM20: 1 | BN20: 0 | BO20: 0 | BP20: 0 | BQ20: 1 | BS20: 1 | BT20: 1 | BU20: 0 | BV20: 0 | BW20: 0 | BX20: 1 | BY20: 17 | CG20: 1 | CH20: 1 | CI20: 0 | CJ20: 0 | CK20: 0 | CL20: 1
A21: act_glo_3.3Sci_d235_m020 | B21: active mobility | C21: Global | D21: 3.3 | E21: Risk & Uncertainty (Shared Expectations) | F21: scientific publications | G21: # publications | H21: b7 | I21: 0.098082 | J21: 0.075253 | K21: 339.27 | L21: 2026.2 | M21: 44.804 | N21: 47724 | O21: 0.0059608 | P21: 1822.8 | Q21: -672090 | R21: 0.98746 | S21: 0.98672 | T21: 674.84 | U21: 429.14 | V21: 0.98322 | W21: 0.98257 | X21: 780.65 | Y21: 440.85 | Z21: 0.79877 | AA21: 0.79103 | AB21: 2703.1 | AC21: 2313.6 | AD21: 55 | AE21: 55 | AF21: 0.43486 | AG21: 0.0017811 | AH21: 0.43307 | AI21: 55 | AJ21: 2 | AK21: 54 | AL21: 0 | AM21: 0 | AN21: 1 | AO21: 0.95068 | AP21: 0 | AQ21: 0 | AR21: y | AS21: y | AT21: y | AU21: y | AV21: y | AW21: y | AX21: y | AY21: y | AZ21: y | BA21: y | BB21: y | BC21: y | BD21: y | BH21: good; only available global, apply to all EA regions | BI21: 0 | BL21: 1 | BM21: 1 | BN21: 0 | BO21: 0 | BP21: 1 | BQ21: 1 | BS21: 1 | BT21: 1 | BU21: 0 | BV21: 0 | BW21: 1 | BX21: 1 | BY21: 18 | CG21: 1 | CH21: 1 | CI21: 0 | CJ21: 0 | CK21: 1 | CL21: 1
A22: act_net_1.1Ado_d167_m096 | B22: active mobility | C22: The Netherlands | D22: 1.1 | E22: Adoption over time | F22: Passenger kilometres travelled by¬†bike | G22: Billion p.km | H22: b7 | I22: 0.17814 | J22: 0.013226 | K22: 0.21626 | L22: 1998.6 | M22: 24.668 | N22: 17.492 | O22: 6.6659 | P22: 1947.9 | Q22: -419.53 | R22: 0.71531 | S22: 0.64961 | T22: 0.77647 | U22: 0.65529 | V22: 0.60366 | W22: 0.54704 | X22: 0.91615 | Y22: 0.789 | Z22: 0.62081 | AA22: 0.56664 | AB22: 0.89611 | AC22: 0.75497 | AD22: 17 | AE22: 17 | AF22: 1.0233 | AG22: 0.79466 | AH22: 0.22868 | AI22: 18 | AJ22: 0 | AK22: 16 | AL22: 0 | AM22: 0 | AN22: 0 | AO22: 0.93926 | AP22: 0 | AQ22: 1 | AR22: y | AS22: y | AT22: y | AU22: y | AV22: y | AW22: y | AX22: y | AY22: y | AZ22: y | BA22: y | BB22: y | BC22: y | BD22: y | BE22: 1 | BI22: 0 | BJ22: prefer-absolute | BL22: 1 | BM22: 1 | BN22: 2 | BO22: 2 | BP22: 0 | BQ22: 0 | BS22: 1 | BT22: 1 | BU22: 0 | BV22: 0 | BW22: 0 | BX22: 0 | BY22: 19 | CG22: 1 | CH22: 1 | CI22: 0 | CJ22: 0 | CK22: 0 | CL22: 0
A23: act_net_1.1Ado_d168_m096 | B23: active mobility | C23: The Netherlands | D23: 1.1 | E23: Adoption over time | F23: Passenger kilometres travelled by¬†foot | G23: Billion p.km | H23: b7 | I23: 0.046231 | J23: 0.04623 | K23: 0.21548 | L23: 2244.5 | M23: 95.054 | N23: 206610 | O23: 7.9825 | P23: 2024.7 | Q23: -428.98 | R23: 0.82968 | S23: 0.79038 | T23: 0.52885 | U23: 0.38906 | V23: 0.82968 | W23: 0.80535 | X23: 0.52885 | Y23: 0.38906 | Z23: 0.7949 | AA23: 0.7656 | AB23: 0.58034 | AC23: 0.44108 | AD23: 17 | AE23: 17 | AF23: 3.9204e-05 | AG23: 1.6456e-05 | AH23: 2.2748e-05 | AI23: 18 | AJ23: 1 | AK23: 16 | AL23: 0 | AM23: 0 | AN23: 0 | AO23: 0.92009 | AP23: 0 | AQ23: 1 | AR23: y | AS23: y | AT23: y | AU23: y | AV23: y | AW23: y | AX23: y | AY23: m | AZ23: y | BA23: m | BB23: y | BC23: m | BD23: y | BE23: 2 | BI23: 0 | BL23: 1 | BM23: 1 | BN23: 0 | BO23: 0 | BP23: 0 | BQ23: 0 | BS23: 1 | BT23: 1 | BU23: 0 | BV23: 0 | BW23: 0 | BX23: 0 | BY23: 20 | CG23: 1 | CH23: 1 | CI23: 0 | CJ23: 0 | CK23: 0 | CL23: 0
A24: act_net_1.1Ado_d332_m185 | B24: active mobility | C24: The Netherlands | D24: 1.1 | E24: Adoption over time | F24: % trips by walking and biking | G24: market share | H24: b7 | I24: 0.070443 | J24: 0.026144 | K24: 0.0035545 | L24: 2006.4 | M24: 62.383 | N24: 0.21832 | O24: 0.00085118 | P24: 1820 | Q24: -7.0219 | R24: 0.97061 | S24: 0.96383 | T24: 0.0032828 | U24: 0.0025168 | V24: 0.96078 | W24: 0.95518 | X24: 0.0037921 | Y24: 0.0030679 | Z24: 0.96855 | AA24: 0.96406 | AB24: 0.0033959 | AC24: 0.0025786 | AD24: 17 | AE24: 17 | AF24: 0.7503 | AG24: 0.49115 | AH24: 0.25914 | AI24: 18 | AJ24: 0 | AK24: 16 | AL24: 0 | AM24: 0 | AN24: 0 | AO24: 0.93891 | AP24: 1 | AQ24: 1 | AR24: y | AS24: y | AT24: y | AU24: y | AV24: y | AW24: y | AX24: y | AY24: y | AZ24: y | BA24: y | BB24: y | BC24: y | BD24: y | BI24: 0 | BJ24: prefer-relative | BK24: transformed-marketshare | BL24: 1 | BM24: 1 | BN24: 1 | BO24: 1 | BP24: 0 | BQ24: 0 | BS24: 1 | BT24: 1 | BU24: 1 | BV24: 1 | BW24: 0 | BX24: 0 | BY24: 21 | CG24: 1 | CH24: 1 | CI24: 1 | CJ24: 1 | CK24: 0 | CL24: 0
A25: act_net_2.9Int_d133_m139 | B25: active mobility | C25: The Netherlands | D25: 2.9 | E25: Interdependence with hardware | F25: Number of bicycles | G25: million | H25: b7 | I25: 0.049239 | J25: 0.016526 | K25: 0.34781 | L25: 1998.8 | M25: 89.248 | N25: 31.855 | O25: 5.1298 | P25: 1927.5 | Q25: -678.94 | R25: 0.87013 | S25: 0.84416 | T25: 0.79224 | U25: 0.66204 | V25: 0.85896 | W25: 0.84133 | X25: 0.82561 | Y25: 0.71719 | Z25: 0.86573 | AA25: 0.84894 | AB25: 0.80556 | AC25: 0.69208 | AD25: 19 | AE25: 19 | AF25: 0.75026 | AG25: 0.55877 | AH25: 0.19149 | AI25: 23 | AJ25: 0 | AK25: 18 | AL25: 0 | AM25: 0 | AN25: 0 | AO25: 0.94783 | AP25: 0 | AQ25: 1 | AR25: y | AS25: y | AT25: y | AU25: y | AV25: y | AW25: y | AX25: y | AY25: m | AZ25: y | BA25: m | BB25: y | BC25: m | BD25: y | BE25: 4 | BG25: ok, use logfit | BI25: 0 | BL25: 1 | BM25: 1 | BS25: 1 | BT25: 1 | BU25: 0 | BV25: 0 | BW25: 1 | BX25: 1 | BY25: 22 | CG25: 1 | CH25: 1 | CI25: 0 | CJ25: 0 | CK25: 1 | CL25: 1
A26: act_net_4.1Sal_d213_m100 | B26: active mobility | C26: The Netherlands | D26: 4.1 | E26: Knowledge Flows (social networks) | F26: annualised Google search frequency (index 100=monthly max.) | G26: Index 0-100 | H26: b7 | I26: 3.0888 | J26: 0.038321 | K26: 1.8942 | L26: 2011.4 | M26: 1.4227 | N26: 51.304 | O26: 2.0418 | P26: 1941 | Q26: -3780.9 | R26: 0.52841 | S26: 0.44519 | T26: 19.881 | U26: 15.557 | V26: 0.10943 | W26: 0.010474 | X26: 27.321 | Y26: 22.73 | Z26: 0.15696 | AA26: 0.063294 | AB26: 26.582 | AC26: 21.903 | AD26: 21 | AE26: 20 | AF26: 1.9492 | AG26: 0.061706 | AH26: 1.8875 | AI26: 21 | AJ26: 8 | AK26: 17 | AL26: 1 | AM26: 1 | AN26: 1 | AO26: 0.93508 | AP26: 0 | AQ26: 1 | AR26: m | AS26: y | AT26: y | AU26: y | AV26: y | AW26: y | AX26: y | AY26: y | AZ26: m | BA26: m | BB26: m | BC26: m | BD26: m | BI26: 0 | BJ26: hide | BK26: original | BL26: 1 | BM26: 1 | BN26: 0 | BO26: 0 | BP26: 0 | BQ26: 0 | BS26: 1 | BT26: 0 | BU26: 0 | BV26: 0 | BW26: 0 | BX26: 0 | BY26: 23 | CA26: check | CG26: 1 | CH26: 1 | CI26: 0 | CJ26: 0 | CK26: 0 | CL26: 0
A27: act_net_4.1Sal_d239_m153 | B27: active mobility | C27: The Netherlands | D27: 4.1 | E27: Knowledge Flows (social networks) | F27: Partial up to max annualised Google search frequency (index 100=monthly max.) | G27: Partial up to max Index 0-100 | H27: b7 | I27: 1.1394 | J27: 0.28364 | K27: 8.1967 | L27: 2012.4 | M27: 3.8569 | N27: 96.414 | O27: 0.012954 | P27: 1984 | Q27: -16442 | R27: 0.96663 | S27: 0.95551 | T27: 6.5285 | U27: 5.043 | V27: 0.89473 | W27: 0.87368 | X27: 11.596 | Y27: 10.341 | Z27: 0.73634 | AA27: 0.68361 | AB27: 18.352 | AC27: 16.877 | AD27: 13 | AE27: 12 | AF27: 1.0372 | AG27: 0.032835 | AH27: 1.0044 | AI27: 13 | AJ27: 0 | AK27: 9 | AL27: 0 | AM27: 1 | AN27: 1 | AO27: 0.80207 | AP27: 0 | AQ27: 1 | AR27: y | AS27: y | AT27: y | AU27: m | AV27: y | AW27: m | AX27: y | AY27: y | AZ27: y | BA27: m | BB27: m | BC27: m | BD27: m | BI27: 0 | BJ27: prefer | BK27: transformed-partial | BL27: 1 | BM27: 1 | BN27: 0 | BO27: 0 | BP27: 1 | BQ27: 1 | BS27: 1 | BT27: 1 | BU27: 0 | BV27: 0 | BW27: 1 | BX27: 1 | BY27: 24 | CG27: 1 | CH27: 1 | CI27: 0 | CJ27: 0 | CK27: 1 | CL27: 1
A28: cli_ban_1.1Ado_d072_m017 | B28: climate protest | C28: Bangladesh | D28: 1.1 | E28: Adoption over Time | F28: Count of participants at protest events related to climate | G28: # people (estimated) | H28: s3 | I28: 41.944 | J28: 0.089972 | K28: 18.132 | L28: 2018.2 | M28: 0.10477 | N28: 290 | O28: 0.023617 | P28: 1923.1 | Q28: -36460 | R28: 0.19742 | S28: -0.07011 | T28: 284.47 | U28: 140 | V28: 0.026697 | W28: -0.16796 | X28: 313.27 | Y28: 169.47 | Z28: 0.045649 | AA28: -0.14522 | AB28: 310.2 | AC28: 161.88 | AD28: 13 | AE28: 3 | AF28: 4.1379 | AG28: 0.34483 | AH28: 3.7931 | AI28: 3 | AJ28: 2 | AK28: 1 | AL28: 0 | AM28: 1 | AN28: 1 | AO28: 0.091681 | AP28: 0 | AQ28: 0 | AR28: n | AS28: n | AT28: y | AU28: y | AV28: y | AW28: y | AX28: m | AY28: y | AZ28: m | BA28: n | BB28: n | BC28: n | BD28: n | BE28: 4 | BG28: convert to cum | BI28: 0 | BJ28: hide | BK28: original | BL28: 0 | BM28: 1 | BN28: 0 | BO28: 0 | BP28: 0 | BQ28: 0 | BS28: 0 | BT28: 0 | BU28: 0 | BV28: 0 | BW28: 0 | BX28: 0 | BY28: 25 | CA28: check | CG28: 0 | CH28: 1 | CI28: 0 | CJ28: 0 | CK28: 0 | CL28: 0
A29: cli_ban_1.1Ado_d073_m019 | B29: climate protest | C29: Bangladesh | D29: 1.1 | E29: Adoption over Time | F29: Count of protest events related to climate | G29: # protest events | H29: s3 | I29: 30.435 | J29: 0.12799 | K29: 1.8187 | L29: 2018.3 | M29: 0.14439 | N29: 23.8 | O29: 9.1992 | P29: 2017.2 | Q29: -3658.9 | R29: 0.45368 | S29: 0.27158 | T29: 12.502 | U29: 6.1386 | V29: 0.11556 | W29: -0.061327 | X29: 15.907 | Y29: 10.359 | Z29: 0.16186 | AA29: -0.0057636 | AB29: 15.485 | AC29: 9.6932 | AD29: 13 | AE29: 6 | AF29: 2.605 | AG29: 0.12605 | AH29: 2.479 | AI29: 13 | AJ29: 4 | AK29: 12 | AL29: 1 | AM29: 0 | AN29: 1 | AO29: 0.43956 | AP29: 0 | AQ29: 1 | AR29: m | AS29: y | AT29: y | AU29: m | AV29: m | AW29: m | AX29: m | AY29: y | AZ29: m | BA29: m | BB29: m | BC29: n | BD29: m | BE29: 4 | BG29: convert to cum | BI29: 0 | BJ29: hide | BK29: original | BL29: 0 | BM29: 1 | BN29: 0 | BO29: 0 | BP29: 0 | BQ29: 0 | BS29: 0 | BT29: 0 | BU29: 0 | BV29: 0 | BW29: 0 | BX29: 0 | BY29: 26 | CA29: check | CG29: 0 | CH29: 1 | CI29: 0 | CJ29: 0 | CK29: 0 | CL29: 0
A30: cli_ban_1.1Ado_d240_m154 | B30: climate protest | C30: Bangladesh | D30: 1.1 | E30: Adoption over Time | F30: cumulative Count of participants at protest events related to climate | G30: cumulative # people (estimated) | H30: s3 | I30: 7.7138 | J30: 0.26593 | K30: 154.12 | L30: 2018.8 | M30: 0.56969 | N30: 1412.6 | O30: 1.2771e-07 | P30: 1935.1 | Q30: -310330 | R30: 0.99711 | S30: 0.99614 | T30: 36.015 | U30: 17.574 | V30: 0.76035 | W30: 0.71241 | X30: 327.78 | Y30: 282.62 | Z30: 0.74177 | AA30: 0.69012 | AB30: 340.25 | AC30: 287.02 | AD30: 13 | AE30: 5 | AF30: 1.0265 | AG30: 0.84952 | AH30: 0.17698 | AI30: 5 | AJ30: 2 | AK30: 4 | AL30: 1 | AM30: 0 | AN30: 0 | AO30: 0.8106 | AP30: 0 | AQ30: 0 | AR30: y | AS30: n | AT30: y | AU30: y | AV30: y | AW30: y | AX30: y | AY30: m | AZ30: y | BA30: n | BB30: n | BC30: n | BD30: n | BI30: 0 | BK30: transformed-cumulative | BL30: 1 | BM30: 1 | BN30: 0 | BO30: 0 | BP30: 0 | BQ30: 0 | BS30: 1 | BT30: 1 | BU30: 0 | BV30: 1 | BW30: 0 | BX30: 0 | BY30: 27 | CC30: **check** | CG30: 1 | CH30: 1 | CI30: 0 | CJ30: 0 | CK30: 0 | CL30: 0
A31: cli_ban_1.1Ado_d241_m155 | B31: climate protest | C31: Bangladesh | D31: 1.1 | E31: Adoption over Time | F31: cumulative Count of protest events related to climate | G31: cumulative # protest events | H31: s3 | I31: 1.7709 | J31: 0.2891 | K31: 11.418 | L31: 2019.1 | M31: 2.4814 | N31: 115.39 | O31: 0.0021787 | P31: 1984.6 | Q31: -22989 | R31: 0.98523 | S31: 0.9803 | T31: 5.9341 | U31: 4.8395 | V31: 0.8599 | W31: 0.83188 | X31: 18.274 | Y31: 15.554 | Z31: 0.76568 | AA31: 0.71882 | AB31: 23.633 | AC31: 19.856 | AD31: 13 | AE31: 13 | AF31: 1.0572 | AG31: 0.025998 | AH31: 1.0312 | AI31: 13 | AJ31: 0 | AK31: 12 | AL31: 0 | AM31: 0 | AN31: 1 | AO31: 0.81021 | AP31: 0 | AQ31: 0 | AR31: y | AS31: y | AT31: y | AU31: m | AV31: y | AW31: m | AX31: y | AY31: y | AZ31: y | BA31: m | BB31: m | BC31: m | BD31: m | BI31: 0 | BJ31: prefer-absolute | BK31: transformed-cumulative | BL31: 1 | BM31: 1 | BN31: 0 | BO31: 2 | BP31: 0 | BQ31: 0 | BS31: 1 | BT31: 1 | BU31: 0 | BV31: 0 | BW31: 0 | BX31: 0 | BY31: 28 | CG31: 1 | CH31: 1 | CI31: 0 | CJ31: 0 | CK31: 0 | CL31: 0
A32: cli_ban_1.1Ado_d346_m185 | B32: climate protest | C32: Bangladesh | D32: 1.1 | E32: Adoption over Time | F32: cumulative share of population participating in protest events related to climate | G32: market share | H32: s3 | I32: 8.3951 | J32: 0.26242 | K32: 9.1286e-07 | L32: 2018.8 | M32: 0.52345 | N32: 8.3708e-06 | O32: 122.11 | P32: 2084.9 | Q32: -0.0018381 | R32: 0.99793 | S32: 0.99724 | T32: 1.8115e-07 | U32: 8.6081e-08 | V32: 0.7489 | W32: 0.69867 | X32: 1.994e-06 | Y32: 1.7168e-06 | Z32: 0.73674 | AA32: 0.68409 | AB32: 2.0417e-06 | AC32: 1.7336e-06 | AD32: 13 | AE32: 5 | AF32: 1.0332 | AG32: 0.86928 | AH32: 0.1639 | AI32: 5 | AJ32: 2 | AK32: 4 | AL32: 1 | AM32: 0 | AN32: 0 | AO32: 0.81198 | AP32: 1 | AQ32: 1 | AR32: y | AS32: n | AT32: y | AU32: y | AV32: y | AW32: y | AX32: y | AY32: m | AZ32: y | BA32: n | BB32: n | BC32: n | BD32: n | BH32: weird data | BI32: 0 | BJ32: prefer-relative | BK32: transformed-marketshare | BL32: 0 | BM32: 1 | BN32: 0 | BO32: 1 | BP32: 0 | BQ32: 0 | BS32: 1 | BT32: 1 | BU32: 0 | BV32: 0 | BW32: 0 | BX32: 0 | BY32: 29 | BZ32: check | CC32: **check** | CG32: 1 | CH32: 1 | CI32: 0 | CJ32: 1 | CK32: 0 | CL32: 0
A33: cli_ban_4.1Sal_d213_m100 | B33: climate protest | C33: Bangladesh | D33: 4.1 | E33: Knowledge Flows (social networks) | F33: annualised Google search frequency (index 100=monthly max.) | G33: Index 0-100 | H33: s3 | I33: -38.414 | J33: -0.060495 | K33: -0.64935 | L33: 2009.8 | M33: -0.1144 | N33: 16.667 | O33: -1523.3 | P33: -154770 | Q33: 1312.6 | R33: 0.125 | S33: -0.029412 | T33: 19.92 | U33: 7.9366 | V33: -0.05 | W33: -0.16667 | X33: 21.822 | Y33: 4.7619 | Z33: 0.034091 | AA33: -0.073232 | AB33: 20.93 | AC33: 9.0703 | AD33: 21 | AE33: 1 | AF33: 6 | AG33: 6 | AH33: 0 | AI33: 1 | AJ33: 0 | AK33: 0 | AL33: 0 | AM33: 0 | AP33: 0 | AQ33: 1 | AR33: n | AS33: n | AT33: m | AU33: m | AV33: m | AW33: m | AX33: m | AY33: m | AZ33: m | BA33: n | BB33: n | BC33: n | BD33: n | BH33: too few | BI33: 0 | BJ33: hide | BK33: original | BL33: 0 | BM33: 0 | BN33: 0 | BO33: 0 | BP33: 0 | BQ33: 0 | BS33: 0 | BT33: 0 | BU33: 0 | BV33: 0 | BW33: 0 | BX33: 0 | BY33: 30 | CG33: 0 | CH33: 0 | CI33: 0 | CJ33: 0 | CK33: 0 | CL33: 0
A34: cli_ban_4.1Sal_d239_m153 | B34: climate protest | C34: Bangladesh | D34: 4.1 | E34: Knowledge Flows (social networks) | F34: Partial up to max annualised Google search frequency (index 100=monthly max.) | G34: Partial up to max Index 0-100 | H34: s3 | I34: 17.735 | K34: 14.286 | L34: 2009 | M34: 0.24779 | N34: 220.71 | Q34: -28648 | R34: 1 | S34: 1 | T34: 1.4826e-06 | U34: 6.1813e-07 | Z34: 0.42857 | AA34: 0.047619 | AB34: 28.172 | AC34: 23.81 | AD34: 6 | AE34: 1 | AF34: 0.45308 | AG34: 0.45308 | AH34: 0 | AI34: 1 | AJ34: 0 | AK34: 0 | AL34: 0 | AM34: 0 | AP34: 0 | AQ34: 1 | AR34: y | AS34: n | AT34: y | AU34: m | AV34: m | AW34: m | AX34: m | AY34: m | AZ34: y | BA34: n | BB34: n | BC34: n | BD34: n | BH34: too few | BI34: 0 | BJ34: prefer | BK34: transformed-partial | BL34: 0 | BM34: 0 | BN34: 0 | BO34: 0 | BP34: 0 | BQ34: 1 | BS34: 0 | BT34: 0 | BU34: 0 | BV34: 0 | BW34: 0 | BX34: 1 | BY34: 31 | CG34: 0 | CH34: 0 | CI34: 0 | CJ34: 0 | CK34: 0 | CL34: 1
A35: cli_ger_1.1Ado_d072_m017 | B35: climate protest | C35: Germany | D35: 1.1 | E35: Adoption over Time | F35: Count of participants at protest events related to climate | G35: # people (estimated) | H35: s3 | I35: 22.928 | J35: 0.20014 | K35: 45.856 | L35: 2020 | M35: 0.19167 | N35: 570.82 | O35: 0.00038393 | P35: 1953 | Q35: -92329 | R35: 0.36992 | S35: 0.1599 | T35: 322.67 | U35: 146.14 | V35: 0.14896 | W35: -0.021243 | X35: 375 | Y35: 229.31 | Z35: 0.17816 | AA35: 0.013788 | AB35: 368.51 | AC35: 227.02 | AD35: 13 | AE35: 4 | AF35: 2.6641 | AG35: 0.15783 | AH35: 2.5063 | AI35: 4 | AJ35: 2 | AK35: 1 | AL35: 1 | AM35: 1 | AN35: 1 | AO35: 0.30332 | AP35: 0 | AQ35: 0 | AR35: m | AS35: n | AT35: y | AU35: y | AV35: m | AW35: m | AX35: m | AY35: y | AZ35: m | BA35: n | BB35: n | BC35: n | BD35: n | BE35: 4 | BG35: convert to cum | BI35: 0 | BJ35: hide | BK35: original | BL35: 0 | BM35: 1 | BN35: 0 | BO35: 0 | BP35: 0 | BQ35: 0 | BS35: 0 | BT35: 1 | BU35: 0 | BV35: 0 | BW35: 0 | BX35: 0 | BY35: 32 | CG35: 0 | CH35: 1 | CI35: 0 | CJ35: 0 | CK35: 0 | CL35: 0
A36: cli_ger_1.1Ado_d073_m019 | B36: climate protest | C36: Germany | D36: 1.1 | E36: Adoption over Time | F36: Count of protest events related to climate | G36: # protest events | H36: s3 | I36: 0.5546 | J36: 0.51177 | K36: 54.467 | L36: 2026 | M36: 7.9237 | N36: 5215.2 | O36: 3.6135e-08 | P36: 1976.3 | Q36: -109700 | R36: 0.92641 | S36: 0.90188 | T36: 71.314 | U36: 50.781 | V36: 0.92613 | W36: 0.91136 | X36: 71.446 | Y36: 51.438 | Z36: 0.601 | AA36: 0.5212 | AB36: 166.05 | AC36: 124.63 | AD36: 13 | AE36: 4 | AF36: 0.16854 | AG36: 0.062126 | AH36: 0.10642 | AI36: 4 | AJ36: 0 | AK36: 3 | AL36: 0 | AM36: 0 | AN36: 1 | AO36: 0.53716 | AP36: 0 | AQ36: 0 | AR36: y | AS36: n | AT36: y | AU36: y | AV36: y | AW36: y | AX36: m | AY36: m | AZ36: y | BA36: n | BB36: n | BC36: n | BD36: n | BE36: 1 | BI36: 0 | BJ36: hide | BK36: original | BL36: 0 | BM36: 1 | BN36: 0 | BO36: 0 | BP36: 0 | BQ36: 0 | BS36: 1 | BT36: 1 | BU36: 0 | BV36: 0 | BW36: 0 | BX36: 0 | BY36: 33 | BZ36: check | CG36: 1 | CH36: 1 | CI36: 0 | CJ36: 0 | CK36: 0 | CL36: 0
A37: cli_ger_1.1Ado_d240_m154 | B37: climate protest | C37: Germany | D37: 1.1 | E37: Adoption over Time | F37: cumulative Count of participants at protest events related to climate | G37: cumulative # people (estimated) | H37: s3 | I37: 4.0104 | J37: 0.42036 | K37: 173.78 | L37: 2020.4 | M37: 1.0958 | N37: 2064.6 | O37: 4.5604e-10 | P37: 1953.2 | Q37: -350010 | R37: 0.99946 | S37: 0.99928 | T37: 19.559 | U37: 8.4271 | V37: 0.83947 | W37: 0.80737 | X37: 336.47 | Y37: 247.98 | Z37: 0.59945 | AA37: 0.51934 | AB37: 531.5 | AC37: 476.34 | AD37: 13 | AE37: 4 | AF37: 1.0236 | AG37: 0.19417 | AH37: 0.82942 | AI37: 4 | AJ37: 0 | AK37: 3 | AL37: 0 | AM37: 0 | AN37: 1 | AO37: 0.71867 | AP37: 0 | AQ37: 0 | AR37: y | AS37: n | AT37: y | AU37: y | AV37: y | AW37: y | AX37: y | AY37: y | AZ37: y | BA37: n | BB37: n | BC37: n | BD37: n | BI37: 0 | BK37: transformed-cumulative | BL37: 1 | BM37: 1 | BN37: 0 | BO37: 0 | BP37: 0 | BQ37: 0 | BS37: 1 | BT37: 1 | BU37: 0 | BV37: 1 | BW37: 0 | BX37: 0 | BY37: 34 | CC37: **check** | CG37: 1 | CH37: 1 | CI37: 0 | CJ37: 0 | CK37: 0 | CL37: 0
A38: cli_ger_1.1Ado_d241_m155 | B38: climate protest | C38: Germany | D38: 1.1 | E38: Adoption over Time | F38: cumulative Count of protest events related to climate | G38: cumulative # protest events | H38: s3 | I38: 0.88528 | J38: 0.6116 | K38: 119.76 | L38: 2022.7 | M38: 4.9639 | N38: 3601.9 | O38: 8.3646e-12 | P38: 1968.8 | Q38: -241230 | R38: 0.99123 | S38: 0.98831 | T38: 56.143 | U38: 36.018 | V38: 0.98566 | W38: 0.98279 | X38: 71.805 | Y38: 45.767 | Z38: 0.55863 | AA38: 0.47035 | AB38: 398.3 | AC38: 314.95 | AD38: 13 | AE38: 4 | AF38: 0.56109 | AG38: 0.089951 | AH38: 0.47113 | AI38: 4 | AJ38: 0 | AK38: 3 | AL38: 0 | AM38: 0 | AN38: 1 | AO38: 0.56235 | AP38: 0 | AQ38: 0 | AR38: y | AS38: n | AT38: y | AU38: y | AV38: y | AW38: y | AX38: m | AY38: y | AZ38: y | BA38: n | BB38: n | BC38: n | BD38: n | BI38: 0 | BJ38: prefer-absolute | BK38: transformed-cumulative | BL38: 1 | BM38: 1 | BN38: 0 | BO38: 2 | BP38: 0 | BQ38: 0 | BS38: 1 | BT38: 1 | BU38: 0 | BV38: 0 | BW38: 0 | BX38: 0 | BY38: 35 | CG38: 1 | CH38: 1 | CI38: 0 | CJ38: 0 | CK38: 0 | CL38: 0
A39: cli_ger_1.1Ado_d346_m185 | B39: climate protest | C39: Germany | D39: 1.1 | E39: Adoption over Time | F39: cumulative share of population participating in protest events related to climate | G39: market share | H39: s3 | I39: 4.1188 | J39: 0.4186 | K39: 2.0649e-06 | L39: 2020.3 | M39: 1.0669 | N39: 2.4479e-05 | O39: 6.8771 | P39: 2052.5 | Q39: -0.004159 | R39: 0.99957 | S39: 0.99943 | T39: 2.0681e-07 | U39: 8.9035e-08 | V39: 0.83679 | W39: 0.80415 | X39: 4.0322e-06 | Y39: 2.9704e-06 | Z39: 0.59922 | AA39: 0.51906 | AB39: 6.3186e-06 | AC39: 5.6597e-06 | AD39: 13 | AE39: 4 | AF39: 1.0211 | AG39: 0.19582 | AH39: 0.82527 | AI39: 4 | AJ39: 0 | AK39: 3 | AL39: 0 | AM39: 0 | AN39: 1 | AO39: 0.71961 | AP39: 1 | AQ39: 1 | AR39: y | AS39: n | AT39: y | AU39: y | AV39: y | AW39: y | AX39: y | AY39: y | AZ39: y | BA39: n | BB39: n | BC39: n | BD39: n | BH39: weird data | BI39: 0 | BJ39: prefer-relative | BK39: transformed-marketshare | BL39: 0 | BM39: 1 | BN39: 0 | BO39: 1 | BP39: 0 | BQ39: 0 | BS39: 1 | BT39: 1 | BU39: 0 | BV39: 0 | BW39: 0 | BX39: 0 | BY39: 36 | BZ39: check | CC39: **check** | CG39: 1 | CH39: 1 | CI39: 0 | CJ39: 1 | CK39: 0 | CL39: 0
A40: cli_ger_4.1Sal_d213_m100 | B40: climate protest | C40: Germany | D40: 4.1 | E40: Knowledge Flows (social networks) | F40: annualised Google search frequency (index 100=monthly max.) | G40: Index 0-100 | H40: s3 | I40: 40.641 | J40: 0.51165 | K40: 1.778 | L40: 2022.3 | M40: 0.10813 | N40: 73.455 | O40: 6.8564 | P40: 2019.5 | Q40: -3574 | R40: 0.87386 | S40: 0.8516 | T40: 8.1921 | U40: 2.5282 | V40: 0.56273 | W40: 0.51414 | X40: 15.253 | Y40: 6.7587 | Z40: 0.21788 | AA40: 0.13098 | AB40: 20.399 | AC40: 13.075 | AD40: 21 | AE40: 2 | AF40: 1.3614 | AG40: 0.63861 | AH40: 0.72277 | AI40: 2 | AJ40: 1 | AK40: 0 | AL40: 0 | AM40: 0 | AN40: 1 | AO40: 0.38449 | AP40: 0 | AQ40: 1 | AR40: y | AS40: n | AT40: m | AU40: y | AV40: y | AW40: y | AX40: m | AY40: y | AZ40: m | BA40: n | BB40: n | BC40: n | BD40: n | BI40: 0 | BJ40: hide | BK40: original | BL40: 1 | BM40: 1 | BN40: 0 | BO40: 0 | BP40: 0 | BQ40: 0 | BS40: 1 | BT40: 1 | BU40: 0 | BV40: 0 | BW40: 0 | BX40: 0 | BY40: 37 | CG40: 1 | CH40: 1 | CI40: 0 | CJ40: 0 | CK40: 0 | CL40: 0
A41: cli_ger_4.1Sal_d239_m153 | B41: climate protest | C41: Germany | D41: 4.1 | E41: Knowledge Flows (social networks) | F41: Partial up to max annualised Google search frequency (index 100=monthly max.) | G41: Partial up to max Index 0-100 | H41: s3 | I41: 17.794 | J41: 0.1354 | K41: 1.4286 | L41: 2023 | M41: 0.24696 | N41: 171.19 | O41: 1514.9 | P41: 161510 | Q41: -2871.4 | R41: 1 | S41: 1 | T41: 1.0066e-06 | U41: 2.3193e-07 | V41: -0.052632 | W41: -0.17647 | X41: 22.361 | Y41: 5 | Z41: 0.14286 | AA41: 0.042017 | AB41: 20.178 | AC41: 11.143 | AD41: 20 | AE41: 1 | AF41: 0.58414 | AG41: 0.58414 | AH41: 0 | AI41: 1 | AJ41: 0 | AK41: 0 | AL41: 0 | AM41: 0 | AP41: 0 | AQ41: 1 | AR41: y | AS41: n | AT41: m | AU41: m | AV41: m | AW41: m | AX41: m | AY41: m | AZ41: m | BA41: n | BB41: n | BC41: n | BD41: n | BI41: 0 | BJ41: prefer | BK41: transformed-partial | BL41: 1 | BM41: 1 | BN41: 0 | BO41: 0 | BP41: 0 | BQ41: 1 | BS41: 1 | BT41: 1 | BU41: 0 | BV41: 0 | BW41: 0 | BX41: 1 | BY41: 38 | CG41: 1 | CH41: 1 | CI41: 0 | CJ41: 0 | CK41: 0 | CL41: 1
A42: cli_glo_1.1Ado_d072_m017 | B42: climate protest | C42: Global | D42: 1.1 | E42: Adoption over Time | F42: Count of participants at protest events related to climate | G42: # people (estimated) | H42: s3 | I42: 22.791 | J42: 0.22821 | K42: 23497 | L42: 2020 | M42: 0.19282 | N42: 282330 | O42: 1.1765e-10 | P42: 1868.3 | Q42: -47314000 | R42: 0.53678 | S42: 0.38238 | T42: 108200 | U42: 52396 | V42: 0.28074 | W42: 0.13688 | X42: 134830 | Y42: 80313 | Z42: 0.30582 | AA42: 0.16698 | AB42: 132460 | AC42: 82335 | AD42: 13 | AE42: 6 | AF42: 2.1159 | AG42: 0.0025856 | AH42: 2.1133 | AI42: 6 | AJ42: 2 | AK42: 5 | AL42: 1 | AM42: 0 | AN42: 1 | AO42: 0.47317 | AP42: 0 | AQ42: 0 | AR42: m | AS42: y | AT42: y | AU42: m | AV42: y | AW42: m | AX42: m | AY42: y | AZ42: y | BA42: m | BB42: m | BC42: m | BD42: m | BE42: 4 | BG42: convert to cum | BI42: 0 | BJ42: hide | BK42: original | BL42: 0 | BM42: 1 | BN42: 0 | BO42: 0 | BP42: 0 | BQ42: 0 | BS42: 1 | BT42: 1 | BU42: 0 | BV42: 0 | BW42: 0 | BX42: 0 | BY42: 39 | BZ42: check | CG42: 1 | CH42: 1 | CI42: 0 | CJ42: 0 | CK42: 0 | CL42: 0
A43: cli_glo_1.1Ado_d073_m019 | B43: climate protest | C43: Global | D43: 1.1 | E43: Adoption over Time | F43: Count of protest events related to climate | G43: # protest events | H43: s3 | I43: 2.5664 | J43: 0.32388 | K43: 286.75 | L43: 2019.6 | M43: 1.7123 | N43: 3020.5 | O43: 1.4801e-08 | P43: 1942 | Q43: -577480 | R43: 0.98971 | S43: 0.98629 | T43: 130.03 | U43: 65.569 | V43: 0.8161 | W43: 0.77932 | X43: 549.83 | Y43: 425.8 | Z43: 0.70027 | AA43: 0.64032 | AB43: 701.95 | AC43: 606.4 | AD43: 13 | AE43: 11 | AF43: 1.0826 | AG43: 0.00066214 | AH43: 1.0819 | AI43: 13 | AJ43: 2 | AK43: 9 | AL43: 1 | AM43: 1 | AN43: 1 | AO43: 0.78507 | AP43: 0 | AQ43: 0 | AR43: y | AS43: y | AT43: y | AU43: m | AV43: y | AW43: m | AX43: y | AY43: y | AZ43: y | BA43: m | BB43: m | BC43: m | BD43: m | BE43: 1 | BI43: 0 | BJ43: hide | BK43: original | BL43: 0 | BM43: 1 | BN43: 0 | BO43: 0 | BP43: 0 | BQ43: 0 | BS43: 1 | BT43: 1 | BU43: 0 | BV43: 0 | BW43: 0 | BX43: 0 | BY43: 40 | BZ43: check | CG43: 1 | CH43: 1 | CI43: 0 | CJ43: 0 | CK43: 0 | CL43: 0
A44: cli_glo_1.1Ado_d240_m154 | B44: climate protest | C44: Global | D44: 1.1 | E44: Adoption over Time | F44: cumulative Count of participants at protest events related to climate | G44: cumulative # people (estimated) | H44: s3 | I44: 2.5763 | J44: 0.43694 | K44: 81308 | L44: 2020.5 | M44: 1.7057 | N44: 1006300 | O44: 2.4566e-18 | P44: 1898.2 | Q44: -163770000 | R44: 0.99742 | S44: 0.99656 | T44: 19581 | U44: 11049 | V44: 0.89207 | W44: 0.87049 | X44: 126660 | Y44: 96862 | Z44: 0.62265 | AA44: 0.54718 | AB44: 236840 | AC44: 213900 | AD44: 13 | AE44: 6 | AF44: 1.0357 | AG44: 0.00072541 | AH44: 1.0349 | AI44: 6 | AJ44: 0 | AK44: 5 | AL44: 0 | AM44: 0 | AN44: 1 | AO44: 0.71552 | AP44: 0 | AQ44: 0 | AR44: y | AS44: y | AT44: y | AU44: m | AV44: y | AW44: m | AX44: y | AY44: y | AZ44: y | BA44: m | BB44: m | BC44: m | BD44: m | BI44: 0 | BK44: transformed-cumulative | BL44: 1 | BM44: 1 | BN44: 0 | BO44: 0 | BP44: 0 | BQ44: 0 | BS44: 1 | BT44: 1 | BU44: 0 | BV44: 1 | BW44: 0 | BX44: 0 | BY44: 41 | CC44: **check** | CG44: 1 | CH44: 1 | CI44: 0 | CJ44: 0 | CK44: 0 | CL44: 0
A45: cli_glo_1.1Ado_d241_m155 | B45: climate protest | C45: Global | D45: 1.1 | E45: Adoption over Time | F45: cumulative Count of protest events related to climate | G45: cumulative # protest events | H45: s3 | I45: 1.1151 | J45: 0.48939 | K45: 804.64 | L45: 2021.3 | M45: 3.941 | N45: 13189 | O45: 2.9411e-13 | P45: 1944.8 | Q45: -1620700 | R45: 0.99673 | S45: 0.99564 | T45: 216.78 | U45: 146.76 | V45: 0.96643 | W45: 0.95972 | X45: 694.65 | Y45: 536.66 | Z45: 0.63057 | AA45: 0.55668 | AB45: 2304.5 | AC45: 1960.4 | AD45: 13 | AE45: 13 | AF45: 0.8874 | AG45: 0.00053074 | AH45: 0.88687 | AI45: 13 | AJ45: 0 | AK45: 12 | AL45: 0 | AM45: 0 | AN45: 1 | AO45: 0.66871 | AP45: 0 | AQ45: 0 | AR45: y | AS45: y | AT45: y | AU45: m | AV45: y | AW45: m | AX45: m | AY45: y | AZ45: y | BA45: m | BB45: m | BC45: m | BD45: m | BI45: 0 | BJ45: prefer-absolute | BK45: transformed-cumulative | BL45: 1 | BM45: 1 | BN45: 0 | BO45: 2 | BP45: 0 | BQ45: 0 | BS45: 1 | BT45: 1 | BU45: 0 | BV45: 0 | BW45: 0 | BX45: 0 | BY45: 42 | CG45: 1 | CH45: 1 | CI45: 0 | CJ45: 0 | CK45: 0 | CL45: 0
A46: cli_glo_1.1Ado_d346_m185 | B46: climate protest | C46: Global | D46: 1.1 | E46: Adoption over Time | F46: cumulative share of population participating in protest events related to climate | G46: market share | H46: s3 | I46: 2.6284 | J46: 0.43329 | K46: 1.0126e-05 | L46: 2020.5 | M46: 1.6719 | N46: 0.00012465 | O46: 8.9459 | P46: 2048.4 | Q46: -0.020396 | R46: 0.99765 | S46: 0.99687 | T46: 2.323e-06 | U46: 1.3116e-06 | V46: 0.88883 | W46: 0.86659 | X46: 1.5994e-05 | Y46: 1.2227e-05 | Z46: 0.62392 | AA46: 0.5487 | AB46: 2.9416e-05 | AC46: 2.6592e-05 | AD46: 13 | AE46: 6 | AF46: 1.0333 | AG46: 0.00075761 | AH46: 1.0325 | AI46: 6 | AJ46: 0 | AK46: 5 | AL46: 0 | AM46: 0 | AN46: 1 | AO46: 0.71818 | AP46: 1 | AQ46: 1 | AR46: y | AS46: y | AT46: y | AU46: m | AV46: y | AW46: m | AX46: y | AY46: y | AZ46: y | BA46: m | BB46: m | BC46: n | BD46: m | BH46: weird data | BI46: 0 | BJ46: prefer-relative | BK46: transformed-marketshare | BL46: 0 | BM46: 1 | BN46: 0 | BO46: 1 | BP46: 0 | BQ46: 0 | BS46: 0 | BT46: 1 | BU46: 0 | BV46: 0 | BW46: 0 | BX46: 0 | BY46: 43 | CC46: check | CG46: 0 | CH46: 1 | CI46: 0 | CJ46: 1 | CK46: 0 | CL46: 0
A47: cli_glo_3.3Sci_d235_m020 | B47: climate protest | C47: Global | D47: 3.3 | E47: Risk & Uncertainty (Shared Expectations) | F47: scientific publications | G47: # publications | H47: s3 | I47: 1.1684 | J47: 0.27203 | K47: 0.87143 | L47: 2020.4 | M47: 3.761 | N47: 109.63 | O47: 1.3702 | P47: 2007.4 | Q47: -1731.3 | R47: 0.9816 | S47: 0.98052 | T47: 3.4645 | U47: 1.5596 | V47: 0.9218 | W47: 0.9188 | X47: 7.1429 | Y47: 2.9621 | Z47: 0.29329 | AA47: 0.2661 | AB47: 21.474 | AC47: 14.652 | AD47: 55 | AE47: 18 | AF47: 1.0946 | AG47: 0.0091218 | AH47: 1.0855 | AI47: 18 | AJ47: 1 | AK47: 17 | AL47: 0 | AM47: 0 | AN47: 1 | AO47: 0.83129 | AP47: 0 | AQ47: 0 | AR47: y | AS47: y | AT47: y | AU47: y | AV47: y | AW47: y | AX47: y | AY47: y | AZ47: m | BA47: y | BB47: m | BC47: y | BD47: m | BH47: good; only available global, apply to all EA regions | BI47: 0 | BL47: 1 | BM47: 1 | BN47: 0 | BO47: 0 | BP47: 1 | BQ47: 1 | BS47: 1 | BT47: 1 | BU47: 0 | BV47: 0 | BW47: 1 | BX47: 1 | BY47: 44 | CG47: 1 | CH47: 1 | CI47: 0 | CJ47: 0 | CK47: 1 | CL47: 1
A48: cli_glo_4.1Sal_d213_m100 | B48: climate protest | C48: Global | D48: 4.1 | E48: Knowledge Flows (social networks) | F48: annualised Google search frequency (index 100=monthly max.) | G48: Index 0-100 | H48: s3 | I48: 0.43091 | J48: 0.24422 | K48: 4.2507 | L48: 2021.4 | M48: 10.198 | N48: 125.06 | O48: 0.12705 | P48: 1996.5 | Q48: -8539.3 | R48: 0.94384 | S48: 0.93393 | T48: 7.3129 | U48: 4.4113 | V48: 0.92857 | W48: 0.92063 | X48: 8.2475 | Y48: 5.9196 | Z48: 0.69573 | AA48: 0.66192 | AB48: 17.022 | AC48: 14.887 | AD48: 21 | AE48: 13 | AF48: 0.7996 | AG48: 0.018351 | AH48: 0.78125 | AI48: 16 | AJ48: 0 | AK48: 15 | AL48: 0 | AM48: 0 | AN48: 1 | AO48: 0.77068 | AP48: 0 | AQ48: 1 | AR48: y | AS48: y | AT48: y | AU48: m | AV48: y | AW48: m | AX48: y | AY48: y | AZ48: y | BA48: m | BB48: m | BC48: m | BD48: m | BI48: 0 | BJ48: hide | BK48: original | BL48: 1 | BM48: 1 | BN48: 0 | BO48: 0 | BP48: 0 | BQ48: 0 | BS48: 1 | BT48: 1 | BU48: 0 | BV48: 0 | BW48: 0 | BX48: 0 | BY48: 45 | CG48: 1 | CH48: 1 | CI48: 0 | CJ48: 0 | CK48: 0 | CL48: 0
A49: cli_glo_4.1Sal_d239_m153 | B49: climate protest | C49: Global | D49: 4.1 | E49: Knowledge Flows (social networks) | F49: Partial up to max annualised Google search frequency (index 100=monthly max.) | G49: Partial up to max Index 0-100 | H49: s3 | I49: 0.43091 | J49: 0.24422 | K49: 4.2507 | L49: 2021.4 | M49: 10.198 | N49: 125.06 | O49: 0.12705 | P49: 1996.5 | Q49: -8539.3 | R49: 0.94384 | S49: 0.93393 | T49: 7.3129 | U49: 4.4113 | V49: 0.92857 | W49: 0.92063 | X49: 8.2475 | Y49: 5.9196 | Z49: 0.69573 | AA49: 0.66192 | AB49: 17.022 | AC49: 14.887 | AD49: 21 | AE49: 13 | AF49: 0.7996 | AG49: 0.018351 | AH49: 0.78125 | AI49: 16 | AJ49: 0 | AK49: 15 | AL49: 0 | AM49: 0 | AN49: 1 | AO49: 0.77068 | AP49: 0 | AQ49: 1 | AR49: y | AS49: y | AT49: y | AU49: m | AV49: y | AW49: m | AX49: y | AY49: y | AZ49: y | BA49: m | BB49: m | BC49: m | BD49: m | BI49: 0 | BJ49: prefer | BK49: transformed-partial | BL49: 1 | BM49: 1 | BN49: 0 | BO49: 0 | BP49: 0 | BQ49: 1 | BS49: 1 | BT49: 1 | BU49: 0 | BV49: 0 | BW49: 0 | BX49: 1 | BY49: 46 | CG49: 1 | CH49: 1 | CI49: 0 | CJ49: 0 | CK49: 0 | CL49: 1
A50: cli_ind_1.1Ado_d072_m017 | B50: climate protest | C50: India | D50: 1.1 | E50: Adoption over Time | F50: Count of participants at protest events related to climate | G50: # people (estimated) | H50: s3 | I50: 40.28 | J50: 0.075956 | K50: 3.6184 | L50: 2018.2 | M50: 0.1091 | N50: 65.856 | O50: 1.0927 | P50: 1975.7 | Q50: -7273.1 | R50: 0.13333 | S50: -0.15556 | T50: 81.684 | U50: 40.528 | V50: 0.013221 | W50: -0.18413 | X50: 87.16 | Y50: 47.056 | Z50: 0.02381 | AA50: -0.17143 | AB50: 86.692 | AC50: 45.648 | AD50: 13 | AE50: 1 | AF50: 5 | AG50: 5 | AH50: 0 | AI50: 1 | AJ50: 0 | AK50: 0 | AL50: 0 | AM50: 0 | AP50: 0 | AQ50: 0 | AR50: n | AS50: n | AT50: m | AU50: m | AV50: m | AW50: m | AX50: m | AY50: m | AZ50: m | BA50: n | BB50: n | BC50: n | BD50: n | BE50: 4 | BG50: convert to cum | BI50: 0 | BJ50: hide | BK50: original | BL50: 0 | BM50: 1 | BN50: 0 | BO50: 0 | BP50: 0 | BQ50: 0 | BS50: 0 | BT50: 0 | BU50: 0 | BV50: 0 | BW50: 0 | BX50: 0 | BY50: 47 | CA50: check | CG50: 0 | CH50: 1 | CI50: 0 | CJ50: 0 | CK50: 0 | CL50: 0
A51: cli_ind_1.1Ado_d073_m019 | B51: climate protest | C51: India | D51: 1.1 | E51: Adoption over Time | F51: Count of protest events related to climate | G51: # protest events | H51: s3 | I51: 27.51 | J51: 0.11054 | K51: 1.5165 | L51: 2018.1 | M51: 0.15974 | N51: 21 | O51: 10.015 | P51: 2018.9 | Q51: -3050.4 | R51: 0.22756 | S51: -0.029916 | T51: 18.389 | U51: 9.2308 | V51: 0.047804 | W51: -0.14264 | X51: 20.417 | Y51: 11.21 | Z51: 0.073545 | AA51: -0.11175 | AB51: 20.139 | AC51: 10.661 | AD51: 13 | AE51: 7 | AF51: 3.8095 | AG51: 0.095238 | AH51: 3.7143 | AI51: 8 | AJ51: 4 | AK51: 7 | AL51: 1 | AM51: 0 | AN51: 1 | AO51: 0.067222 | AP51: 0 | AQ51: 1 | AR51: n | AS51: y | AT51: y | AU51: m | AV51: m | AW51: m | AX51: m | AY51: y | AZ51: m | BA51: n | BB51: m | BC51: n | BD51: m | BE51: 4 | BG51: convert to cum | BI51: 0 | BJ51: hide | BK51: original | BL51: 0 | BM51: 1 | BN51: 0 | BO51: 0 | BP51: 0 | BQ51: 0 | BS51: 1 | BT51: 1 | BU51: 0 | BV51: 0 | BW51: 0 | BX51: 0 | BY51: 48 | BZ51: check | CG51: 1 | CH51: 1 | CI51: 0 | CJ51: 0 | CK51: 0 | CL51: 0
A52: cli_ind_1.1Ado_d240_m154 | B52: climate protest | C52: India | D52: 1.1 | E52: Adoption over Time | F52: cumulative Count of participants at protest events related to climate | G52: cumulative # people (estimated) | H52: s3 | I52: 60.066 | J52: 0.25163 | K52: 36.184 | L52: 2018.5 | M52: 0.07316 | N52: 329.28 | O52: 0.00012215 | P52: 1963.2 | Q52: -72857 | R52: 1 | S52: 1 | T52: 1.105e-11 | U52: 6.0305e-12 | V52: 0.70751 | W52: 0.64901 | X52: 86.638 | Y52: 72.408 | Z52: 0.71429 | AA52: 0.65714 | AB52: 85.628 | AC52: 71.812 | AD52: 13 | AE52: 5 | AF52: 1 | AG52: 1 | AH52: 0 | AI52: 5 | AJ52: 4 | AK52: 4 | AL52: 0 | AM52: 0 | AN52: 0 | AO52: 0.8 | AP52: 0 | AQ52: 0 | AR52: y | AS52: n | AT52: y | AU52: y | AV52: y | AW52: y | AX52: y | AY52: m | AZ52: y | BA52: n | BB52: n | BC52: n | BD52: n | BI52: 0 | BK52: transformed-cumulative | BL52: 1 | BM52: 1 | BN52: 0 | BO52: 0 | BP52: 0 | BQ52: 0 | BS52: 1 | BT52: 0 | BU52: 0 | BV52: 1 | BW52: 0 | BX52: 0 | BY52: 49 | CA52: check | CC52: **check** | CG52: 1 | CH52: 1 | CI52: 0 | CJ52: 0 | CK52: 0 | CL52: 0
A53: cli_ind_1.1Ado_d241_m155 | B53: climate protest | C53: India | D53: 1.1 | E53: Adoption over Time | F53: cumulative Count of protest events related to climate | G53: cumulative # protest events | H53: s3 | I53: 4.7521 | J53: 0.27198 | K53: 10.907 | L53: 2018.6 | M53: 0.92473 | N53: 98.854 | O53: 0.0046435 | P53: 1985.3 | Q53: -21961 | R53: 0.98958 | S53: 0.98611 | T53: 4.7477 | U53: 2.5854 | V53: 0.80288 | W53: 0.76345 | X53: 20.653 | Y53: 17.791 | Z53: 0.76959 | AA53: 0.72351 | AB53: 22.329 | AC53: 19.196 | AD53: 13 | AE53: 8 | AF53: 1.1026 | AG53: 0.020232 | AH53: 1.0824 | AI53: 8 | AJ53: 0 | AK53: 7 | AL53: 0 | AM53: 0 | AN53: 1 | AO53: 0.80069 | AP53: 0 | AQ53: 0 | AR53: y | AS53: y | AT53: y | AU53: y | AV53: y | AW53: y | AX53: y | AY53: y | AZ53: y | BA53: y | BB53: y | BC53: y | BD53: y | BI53: 0 | BJ53: prefer-absolute | BK53: transformed-cumulative | BL53: 1 | BM53: 1 | BN53: 0 | BO53: 2 | BP53: 0 | BQ53: 0 | BS53: 1 | BT53: 1 | BU53: 0 | BV53: 0 | BW53: 0 | BX53: 0 | BY53: 50 | CG53: 1 | CH53: 1 | CI53: 0 | CJ53: 0 | CK53: 0 | CL53: 0
A54: cli_ind_1.1Ado_d346_m185 | B54: climate protest | C54: India | D54: 1.1 | E54: Adoption over Time | F54: cumulative share of population participating in protest events related to climate | G54: market share | H54: s3 | I54: 66.284 | J54: 0.24875 | K54: 2.5487e-08 | L54: 2018.2 | M54: 0.066297 | N54: 2.3293e-07 | O54: 10.397 | P54: 2092.9 | Q54: -5.1317e-05 | R54: 0.99976 | S54: 0.99968 | T54: 1.7487e-09 | U54: 9.1763e-10 | V54: 0.69629 | W54: 0.63555 | X54: 6.2457e-08 | Y54: 5.2062e-08 | Z54: 0.70802 | AA54: 0.64962 | AB54: 6.1239e-08 | AC54: 5.139e-08 | AD54: 13 | AE54: 5 | AF54: 1.0177 | AG54: 0.98303 | AH54: 0.034705 | AI54: 5 | AJ54: 4 | AK54: 0 | AL54: 0 | AM54: 0 | AN54: 0 | AO54: 0.79979 | AP54: 1 | AQ54: 1 | AR54: y | AS54: n | AT54: y | AU54: y | AV54: y | AW54: y | AX54: y | AY54: m | AZ54: y | BA54: n | BB54: n | BC54: n | BD54: n | BH54: weird data | BI54: 0 | BJ54: prefer-relative | BK54: transformed-marketshare | BL54: 0 | BM54: 1 | BN54: 0 | BO54: 1 | BP54: 0 | BQ54: 0 | BS54: 1 | BT54: 1 | BU54: 0 | BV54: 0 | BW54: 0 | BX54: 0 | BY54: 51 | BZ54: check | CC54: **check** | CG54: 1 | CH54: 1 | CI54: 0 | CJ54: 1 | CK54: 0 | CL54: 0
A55: cli_ind_4.1Sal_d213_m100 | B55: climate protest | C55: India | D55: 4.1 | E55: Knowledge Flows (social networks) | F55: annualised Google search frequency (index 100=monthly max.) | G55: Index 0-100 | H55: s3 | I55: 16.231 | J55: 0.12314 | K55: 1.2987 | L55: 2024 | M55: 0.27075 | N55: 322.95 | O55: 1518.4 | P55: 161160 | Q55: -2610.8 | R55: 1 | S55: 1 | T55: 2.8253e-06 | U55: 6.3288e-07 | V55: -0.05 | W55: -0.16667 | X55: 21.822 | Y55: 4.7619 | Z55: 0.13636 | AA55: 0.040404 | AB55: 19.791 | AC55: 10.719 | AD55: 21 | AE55: 1 | AF55: 0.30965 | AG55: 0.30965 | AH55: 0 | AI55: 1 | AJ55: 0 | AK55: 0 | AL55: 0 | AM55: 0 | AP55: 0 | AQ55: 1 | AR55: y | AS55: n | AT55: m | AU55: m | AV55: m | AW55: m | AX55: m | AY55: m | AZ55: m | BA55: n | BB55: n | BC55: n | BD55: n | BH55: too few | BI55: 0 | BJ55: hide | BK55: original | BL55: 0 | BM55: 0 | BN55: 0 | BO55: 0 | BP55: 0 | BQ55: 0 | BS55: 1 | BT55: 0 | BU55: 0 | BV55: 0 | BW55: 0 | BX55: 0 | BY55: 52 | BZ55: check | CG55: 1 | CH55: 0 | CI55: 0 | CJ55: 0 | CK55: 0 | CL55: 0
A56: cli_ind_4.1Sal_d239_m153 | B56: climate protest | C56: India | D56: 4.1 | E56: Knowledge Flows (social networks) | F56: Partial up to max annualised Google search frequency (index 100=monthly max.) | G56: Partial up to max Index 0-100 | H56: s3 | I56: 16.231 | J56: 0.12314 | K56: 1.2987 | L56: 2024 | M56: 0.27075 | N56: 322.95 | O56: 1518.4 | P56: 161160 | Q56: -2610.8 | R56: 1 | S56: 1 | T56: 2.8253e-06 | U56: 6.3288e-07 | V56: -0.05 | W56: -0.16667 | X56: 21.822 | Y56: 4.7619 | Z56: 0.13636 | AA56: 0.040404 | AB56: 19.791 | AC56: 10.719 | AD56: 21 | AE56: 1 | AF56: 0.30965 | AG56: 0.30965 | AH56: 0 | AI56: 1 | AJ56: 0 | AK56: 0 | AL56: 0 | AM56: 0 | AP56: 0 | AQ56: 1 | AR56: y | AS56: n | AT56: m | AU56: m | AV56: m | AW56: m | AX56: m | AY56: m | AZ56: m | BA56: n | BB56: n | BC56: n | BD56: n | BH56: too few | BI56: 0 | BJ56: prefer | BK56: transformed-partial | BL56: 0 | BM56: 0 | BN56: 0 | BO56: 0 | BP56: 0 | BQ56: 1 | BS56: 1 | BT56: 0 | BU56: 0 | BV56: 0 | BW56: 0 | BX56: 1 | BY56: 53 | BZ56: check | CG56: 1 | CH56: 0 | CI56: 0 | CJ56: 0 | CK56: 0 | CL56: 1
A57: cli_swe_1.1Ado_d072_m017 | B57: climate protest | C57: Sweden | D57: 1.1 | E57: Adoption over Time | F57: Count of participants at protest events related to climate | G57: # people (estimated) | H57: s3 | I57: 20.526 | J57: 0.39541 | K57: 9.4124 | L57: 2021 | M57: 0.2141 | N57: 140.35 | O57: 0.007599 | P57: 1998.3 | Q57: -18958 | R57: 0.7728 | S57: 0.69706 | T57: 27.045 | U57: 11.823 | V57: 0.52763 | W57: 0.43316 | X57: 38.996 | Y57: 22.563 | Z57: 0.38528 | AA57: 0.26234 | AB57: 44.485 | AC57: 30.453 | AD57: 13 | AE57: 4 | AF57: 1.4826 | AG57: 0.12992 | AH57: 1.3527 | AI57: 4 | AJ57: 1 | AK57: 3 | AL57: 1 | AM57: 0 | AN57: 1 | AO57: 0.49868 | AP57: 0 | AQ57: 0 | AR57: y | AS57: n | AT57: y | AU57: m | AV57: y | AW57: m | AX57: m | AY57: y | AZ57: y | BA57: n | BB57: n | BC57: n | BD57: n | BE57: 2 | BI57: 0 | BJ57: hide | BK57: original | BL57: 0 | BM57: 1 | BN57: 0 | BO57: 0 | BP57: 0 | BQ57: 0 | BS57: 1 | BT57: 1 | BU57: 0 | BV57: 0 | BW57: 0 | BX57: 0 | BY57: 54 | BZ57: check | CG57: 1 | CH57: 1 | CI57: 0 | CJ57: 0 | CK57: 0 | CL57: 0
A58: cli_swe_1.1Ado_d073_m019 | B58: climate protest | C58: Sweden | D58: 1.1 | E58: Adoption over Time | F58: Count of protest events related to climate | G58: # protest events | H58: s3 | I58: 12.042 | J58: 0.32417 | K58: 56.709 | L58: 2019.8 | M58: 0.36492 | N58: 582.33 | O58: 4.7697e-06 | P58: 1964.9 | Q58: -114210 | R58: 0.99913 | S58: 0.99883 | T58: 7.7889 | U58: 3.3362 | V58: 0.75556 | W58: 0.70668 | X58: 130.26 | Y58: 105.59 | Z58: 0.64864 | AA58: 0.57837 | AB58: 156.17 | AC58: 135.72 | AD58: 13 | AE58: 4 | AF58: 1.0372 | AG58: 0.91528 | AH58: 0.12192 | AI58: 4 | AJ58: 1 | AK58: 3 | AL58: 1 | AM58: 0 | AN58: 0 | AO58: 0.76673 | AP58: 0 | AQ58: 0 | AR58: y | AS58: n | AT58: y | AU58: y | AV58: y | AW58: y | AX58: y | AY58: m | AZ58: y | BA58: n | BB58: n | BC58: n | BD58: n | BE58: 2 | BI58: 0 | BJ58: hide | BK58: original | BL58: 0 | BM58: 1 | BN58: 0 | BO58: 0 | BP58: 0 | BQ58: 0 | BS58: 1 | BT58: 1 | BU58: 0 | BV58: 0 | BW58: 0 | BX58: 0 | BY58: 55 | BZ58: check | CG58: 1 | CH58: 1 | CI58: 0 | CJ58: 0 | CK58: 0 | CL58: 0
A59: cli_swe_1.1Ado_d240_m154 | B59: climate protest | C59: Sweden | D59: 1.1 | E59: Adoption over Time | F59: cumulative Count of participants at protest events related to climate | G59: cumulative # people (estimated) | H59: s3 | I59: 2.6543 | J59: 0.66529 | K59: 20.529 | L59: 2021.5 | M59: 1.6556 | N59: 352.53 | O59: 6.7468e-07 | P59: 1992.8 | Q59: -41354 | R59: 0.99895 | S59: 0.9986 | T59: 3.5866 | U59: 1.3559 | V59: 0.93473 | W59: 0.92168 | X59: 28.297 | Y59: 17.446 | Z59: 0.48096 | AA59: 0.37715 | AB59: 79.796 | AC59: 67.345 | AD59: 13 | AE59: 4 | AF59: 0.97722 | AG59: 0.051724 | AH59: 0.92549 | AI59: 4 | AJ59: 0 | AK59: 3 | AL59: 0 | AM59: 0 | AN59: 1 | AO59: 0.56941 | AP59: 0 | AQ59: 0 | AR59: y | AS59: n | AT59: y | AU59: m | AV59: y | AW59: m | AX59: m | AY59: y | AZ59: y | BA59: n | BB59: n | BC59: n | BD59: n | BI59: 0 | BK59: transformed-cumulative | BL59: 1 | BM59: 1 | BN59: 0 | BO59: 0 | BP59: 0 | BQ59: 0 | BS59: 1 | BT59: 1 | BU59: 1 | BV59: 1 | BW59: 0 | BX59: 0 | BY59: 56 | CB59: **check** | CC59: **check** | CG59: 1 | CH59: 1 | CI59: 0 | CJ59: 0 | CK59: 0 | CL59: 0
A60: cli_swe_1.1Ado_d241_m155 | B60: climate protest | C60: Sweden | D60: 1.1 | E60: Adoption over Time | F60: cumulative Count of protest events related to climate | G60: cumulative # protest events | H60: s3 | I60: 1.2173 | J60: 0.50547 | K60: 155.48 | L60: 2021.2 | M60: 3.6101 | N60: 2506.2 | O60: 7.0126e-11 | P60: 1961.3 | Q60: -313180 | R60: 0.99421 | S60: 0.99228 | T60: 56.675 | U60: 35.322 | V60: 0.9586 | W60: 0.95032 | X60: 151.55 | Y60: 110.35 | Z60: 0.61008 | AA60: 0.53209 | AB60: 465.1 | AC60: 390.16 | AD60: 13 | AE60: 4 | AF60: 0.90975 | AG60: 0.21267 | AH60: 0.69708 | AI60: 4 | AJ60: 0 | AK60: 3 | AL60: 0 | AM60: 0 | AN60: 1 | AO60: 0.66346 | AP60: 0 | AQ60: 0 | AR60: y | AS60: n | AT60: y | AU60: y | AV60: y | AW60: y | AX60: m | AY60: y | AZ60: y | BA60: n | BB60: n | BC60: n | BD60: n | BI60: 0 | BJ60: prefer-absolute | BK60: transformed-cumulative | BL60: 1 | BM60: 1 | BN60: 2 | BO60: 2 | BP60: 0 | BQ60: 0 | BS60: 1 | BT60: 1 | BU60: 0 | BV60: 0 | BW60: 0 | BX60: 0 | BY60: 57 | CG60: 1 | CH60: 1 | CI60: 0 | CJ60: 0 | CK60: 0 | CL60: 0
A61: cli_swe_1.1Ado_d346_m185 | B61: climate protest | C61: Sweden | D61: 1.1 | E61: Adoption over Time | F61: cumulative share of population participating in protest events related to climate | G61: market share | H61: s3 | I61: 2.6659 | J61: 0.66216 | K61: 1.9522e-06 | L61: 2021.5 | M61: 1.6484 | N61: 3.3387e-05 | O61: 245 | P61: 2046.8 | Q61: -0.0039326 | R61: 0.9989 | S61: 0.99854 | T61: 3.4863e-07 | U61: 1.3193e-07 | V61: 0.93382 | W61: 0.92058 | X61: 2.7066e-06 | Y61: 1.6697e-06 | Z61: 0.48205 | AA61: 0.37846 | AB61: 7.5717e-06 | AC61: 6.3947e-06 | AD61: 13 | AE61: 4 | AF61: 0.97791 | AG61: 0.052749 | AH61: 0.92516 | AI61: 4 | AJ61: 0 | AK61: 3 | AL61: 0 | AM61: 0 | AN61: 1 | AO61: 0.57122 | AP61: 1 | AQ61: 1 | AR61: y | AS61: n | AT61: y | AU61: m | AV61: y | AW61: m | AX61: m | AY61: y | AZ61: y | BA61: n | BB61: n | BC61: n | BD61: n | BH61: weird data | BI61: 0 | BJ61: prefer-relative | BK61: transformed-marketshare | BL61: 0 | BM61: 1 | BN61: 1 | BO61: 1 | BP61: 0 | BQ61: 0 | BS61: 1 | BT61: 1 | BU61: 0 | BV61: 0 | BW61: 0 | BX61: 0 | BY61: 58 | BZ61: check | CB61: **check** | CC61: **check** | CG61: 1 | CH61: 1 | CI61: 1 | CJ61: 1 | CK61: 0 | CL61: 0
A62: cli_uki_1.1Ado_d072_m017 | B62: climate protest | C62: UK | D62: 1.1 | E62: Adoption over Time | F62: Count of participants at protest events related to climate | G62: # people (estimated) | H62: s3 | I62: 24.031 | J62: 0.30546 | K62: 7.7839 | L62: 2020 | M62: 0.18287 | N62: 90.488 | O62: 0.038129 | P62: 1997.4 | Q62: -15676 | R62: 0.76956 | S62: 0.69274 | T62: 20.826 | U62: 8.9845 | V62: 0.50406 | W62: 0.40488 | X62: 30.552 | Y62: 18.916 | Z62: 0.45069 | AA62: 0.34083 | AB62: 32.154 | AC62: 22.168 | AD62: 13 | AE62: 4 | AF62: 1.6453 | AG62: 0.48173 | AH62: 1.1636 | AI62: 4 | AJ62: 2 | AK62: 3 | AL62: 1 | AM62: 0 | AN62: 1 | AO62: 0.52026 | AP62: 0 | AQ62: 0 | AR62: y | AS62: n | AT62: y | AU62: y | AV62: y | AW62: y | AX62: m | AY62: y | AZ62: y | BA62: n | BB62: n | BC62: n | BD62: n | BI62: 0 | BJ62: hide | BK62: original | BL62: 0 | BM62: 1 | BN62: 0 | BO62: 0 | BP62: 0 | BQ62: 0 | BS62: 1 | BT62: 1 | BU62: 0 | BV62: 0 | BW62: 0 | BX62: 0 | BY62: 59 | BZ62: check | CG62: 1 | CH62: 1 | CI62: 0 | CJ62: 0 | CK62: 0 | CL62: 0
A63: cli_uki_1.1Ado_d073_m019 | B63: climate protest | C63: UK | D63: 1.1 | E63: Adoption over Time | F63: Count of protest events related to climate | G63: # protest events | H63: s3 | I63: 39.75 | J63: 0.24732 | K63: 17.473 | L63: 2019.3 | M63: 0.11055 | N63: 189.25 | O63: 0.00079707 | P63: 1972.8 | Q63: -35184 | R63: 0.87997 | S63: 0.83996 | T63: 32.259 | U63: 14.539 | V63: 0.47821 | W63: 0.37385 | X63: 67.26 | Y63: 53.355 | Z63: 0.49297 | AA63: 0.39156 | AB63: 66.302 | AC63: 56.159 | AD63: 13 | AE63: 4 | AF63: 1.2999 | AG63: 0.50198 | AH63: 0.79789 | AI63: 4 | AJ63: 2 | AK63: 0 | AL63: 1 | AM63: 0 | AN63: 0 | AO63: 0.76721 | AP63: 0 | AQ63: 0 | AR63: y | AS63: n | AT63: y | AU63: y | AV63: y | AW63: y | AX63: y | AY63: y | AZ63: y | BA63: n | BB63: n | BC63: n | BD63: n | BI63: 0 | BJ63: hide | BK63: original | BL63: 0 | BM63: 1 | BN63: 0 | BO63: 0 | BP63: 0 | BQ63: 0 | BS63: 1 | BT63: 1 | BU63: 0 | BV63: 0 | BW63: 0 | BX63: 0 | BY63: 60 | BZ63: check | CG63: 1 | CH63: 1 | CI63: 0 | CJ63: 0 | CK63: 0 | CL63: 0
A64: cli_uki_1.1Ado_d240_m154 | B64: climate protest | C64: UK | D64: 1.1 | E64: Adoption over Time | F64: cumulative Count of participants at protest events related to climate | G64: cumulative # people (estimated) | H64: s3 | I64: 1.8485 | J64: 0.49875 | K64: 21.862 | L64: 2020.8 | M64: 2.3773 | N64: 299.77 | O64: 7.557e-06 | P64: 1987.7 | Q64: -44036 | R64: 0.98664 | S64: 0.98219 | T64: 12.283 | U64: 7.1156 | V64: 0.92823 | W64: 0.91387 | X64: 28.469 | Y64: 20.974 | Z64: 0.59255 | AA64: 0.51106 | AB64: 67.831 | AC64: 59.387 | AD64: 13 | AE64: 4 | AF64: 1.051 | AG64: 0.14541 | AH64: 0.90557 | AI64: 4 | AJ64: 0 | AK64: 3 | AL64: 0 | AM64: 0 | AN64: 1 | AO64: 0.66258 | AP64: 0 | AQ64: 0 | AR64: y | AS64: n | AT64: y | AU64: y | AV64: y | AW64: y | AX64: m | AY64: y | AZ64: y | BA64: n | BB64: n | BC64: n | BD64: n | BI64: 0 | BK64: transformed-cumulative | BL64: 1 | BM64: 1 | BN64: 0 | BO64: 0 | BP64: 0 | BQ64: 0 | BS64: 1 | BT64: 1 | BU64: 0 | BV64: 1 | BW64: 0 | BX64: 0 | BY64: 61 | CC64: **check** | CG64: 1 | CH64: 1 | CI64: 0 | CJ64: 0 | CK64: 0 | CL64: 0
A65: cli_uki_1.1Ado_d241_m155 | B65: climate protest | C65: UK | D65: 1.1 | E65: Adoption over Time | F65: cumulative Count of protest events related to climate | G65: cumulative # protest events | H65: s3 | I65: 1.583 | J65: 0.44845 | K65: 57.28 | L65: 2020.7 | M65: 2.7761 | N65: 761.13 | O65: 1.5162e-07 | P65: 1973 | Q65: -115370 | R65: 0.99558 | S65: 0.99411 | T65: 17.882 | U65: 10.144 | V65: 0.92288 | W65: 0.90746 | X65: 74.721 | Y65: 56.01 | Z65: 0.63448 | AA65: 0.56138 | AB65: 162.67 | AC65: 141.98 | AD65: 13 | AE65: 4 | AF65: 0.99458 | AG65: 0.29824 | AH65: 0.69633 | AI65: 4 | AJ65: 0 | AK65: 3 | AL65: 0 | AM65: 0 | AN65: 1 | AO65: 0.71636 | AP65: 0 | AQ65: 0 | AR65: y | AS65: n | AT65: y | AU65: y | AV65: y | AW65: y | AX65: y | AY65: y | AZ65: y | BA65: n | BB65: n | BC65: n | BD65: n | BI65: 0 | BJ65: prefer-absolute | BK65: transformed-cumulative | BL65: 1 | BM65: 1 | BN65: 0 | BO65: 2 | BP65: 0 | BQ65: 0 | BS65: 1 | BT65: 1 | BU65: 0 | BV65: 0 | BW65: 0 | BX65: 0 | BY65: 62 | CG65: 1 | CH65: 1 | CI65: 0 | CJ65: 0 | CK65: 0 | CL65: 0
A66: cli_uki_1.1Ado_d346_m185 | B66: climate protest | C66: UK | D66: 1.1 | E66: Adoption over Time | F66: cumulative share of population participating in protest events related to climate | G66: market share | H66: s3 | I66: 1.9143 | J66: 0.49518 | K66: 3.2014e-07 | L66: 2020.8 | M66: 2.2956 | N66: 4.3378e-06 | O66: 9.5319 | P66: 2052.2 | Q66: -0.00064483 | R66: 0.98696 | S66: 0.98261 | T66: 1.7752e-07 | U66: 1.0134e-07 | V66: 0.9259 | W66: 0.91109 | X66: 4.231e-07 | Y66: 3.1176e-07 | Z66: 0.59388 | AA66: 0.51266 | AB66: 9.9055e-07 | AC66: 8.6926e-07 | AD66: 13 | AE66: 4 | AF66: 1.0575 | AG66: 0.1492 | AH66: 0.90826 | AI66: 4 | AJ66: 0 | AK66: 3 | AL66: 0 | AM66: 0 | AN66: 1 | AO66: 0.66527 | AP66: 1 | AQ66: 1 | AR66: y | AS66: n | AT66: y | AU66: y | AV66: y | AW66: y | AX66: m | AY66: y | AZ66: y | BA66: n | BB66: n | BC66: n | BD66: n | BH66: weird data | BI66: 0 | BJ66: prefer-relative | BK66: transformed-marketshare | BL66: 0 | BM66: 1 | BN66: 0 | BO66: 1 | BP66: 0 | BQ66: 0 | BS66: 0 | BT66: 1 | BU66: 0 | BV66: 0 | BW66: 0 | BX66: 0 | BY66: 63 | CC66: check | CG66: 0 | CH66: 1 | CI66: 0 | CJ66: 1 | CK66: 0 | CL66: 0
A67: cli_uki_4.1Sal_d213_m100 | B67: climate protest | C67: UK | D67: 4.1 | E67: Knowledge Flows (social networks) | F67: annualised Google search frequency (index 100=monthly max.) | G67: Index 0-100 | H67: s3 | I67: 0.67755 | J67: 0.30176 | K67: 3.9101 | L67: 2021.2 | M67: 6.4858 | N67: 109.82 | O67: 0.1268 | P67: 2001.7 | Q67: -7856.7 | R67: 0.95278 | S67: 0.94445 | T67: 6.641 | U67: 4.2123 | V67: 0.92657 | W67: 0.91841 | X67: 8.2817 | Y67: 5.1799 | Z67: 0.6002 | AA67: 0.55577 | AB67: 19.324 | AC67: 15.549 | AD67: 21 | AE67: 8 | AF67: 0.91056 | AG67: 0.065414 | AH67: 0.84515 | AI67: 11 | AJ67: 0 | AK67: 8 | AL67: 0 | AM67: 1 | AN67: 1 | AO67: 0.73322 | AP67: 0 | AQ67: 1 | AR67: y | AS67: y | AT67: y | AU67: y | AV67: y | AW67: y | AX67: y | AY67: y | AZ67: y | BA67: y | BB67: y | BC67: y | BD67: y | BI67: 0 | BJ67: hide | BK67: original | BL67: 1 | BM67: 1 | BN67: 0 | BO67: 0 | BP67: 0 | BQ67: 0 | BS67: 1 | BT67: 1 | BU67: 0 | BV67: 0 | BW67: 0 | BX67: 0 | BY67: 64 | CG67: 1 | CH67: 1 | CI67: 0 | CJ67: 0 | CK67: 0 | CL67: 0
A68: cli_uki_4.1Sal_d239_m153 | B68: climate protest | C68: UK | D68: 4.1 | E68: Knowledge Flows (social networks) | F68: Partial up to max annualised Google search frequency (index 100=monthly max.) | G68: Partial up to max Index 0-100 | H68: s3 | I68: 0.67755 | J68: 0.30176 | K68: 3.9101 | L68: 2021.2 | M68: 6.4858 | N68: 109.82 | O68: 0.1268 | P68: 2001.7 | Q68: -7856.7 | R68: 0.95278 | S68: 0.94445 | T68: 6.641 | U68: 4.2123 | V68: 0.92657 | W68: 0.91841 | X68: 8.2817 | Y68: 5.1799 | Z68: 0.6002 | AA68: 0.55577 | AB68: 19.324 | AC68: 15.549 | AD68: 21 | AE68: 8 | AF68: 0.91056 | AG68: 0.065414 | AH68: 0.84515 | AI68: 11 | AJ68: 0 | AK68: 8 | AL68: 0 | AM68: 1 | AN68: 1 | AO68: 0.73322 | AP68: 0 | AQ68: 1 | AR68: y | AS68: y | AT68: y | AU68: y | AV68: y | AW68: y | AX68: y | AY68: y | AZ68: y | BA68: y | BB68: y | BC68: y | BD68: y | BI68: 0 | BJ68: prefer | BK68: transformed-partial | BL68: 1 | BM68: 1 | BN68: 0 | BO68: 0 | BP68: 0 | BQ68: 1 | BS68: 1 | BT68: 1 | BU68: 0 | BV68: 0 | BW68: 1 | BX68: 1 | BY68: 65 | CD68: **check** | CG68: 1 | CH68: 1 | CI68: 0 | CJ68: 0 | CK68: 0 | CL68: 1
A69: cli_usa_1.1Ado_d072_m017 | B69: climate protest | C69: US | D69: 1.1 | E69: Adoption over Time | F69: Count of participants at protest events related to climate | G69: # people (estimated) | H69: s3 | I69: 30.816 | J69: 0.20397 | K69: 16.902 | L69: 2019.3 | M69: 0.1426 | N69: 201.62 | O69: 0.0021963 | P69: 1967.6 | Q69: -34030 | R69: 0.5588 | S69: 0.41173 | T69: 82.686 | U69: 39.374 | V69: 0.22131 | W69: 0.065567 | X69: 109.85 | Y69: 67.084 | Z69: 0.2581 | AA69: 0.10972 | AB69: 107.22 | AC69: 66.197 | AD69: 13 | AE69: 4 | AF69: 2.2694 | AG69: 0.46929 | AH69: 1.8001 | AI69: 4 | AJ69: 3 | AK69: 1 | AL69: 0 | AM69: 1 | AN69: 1 | AO69: 0.36441 | AP69: 0 | AQ69: 0 | AR69: m | AS69: n | AT69: y | AU69: y | AV69: y | AW69: y | AX69: m | AY69: y | AZ69: m | BA69: n | BB69: n | BC69: n | BD69: n | BI69: 0 | BJ69: hide | BK69: original | BL69: 0 | BM69: 1 | BN69: 0 | BO69: 0 | BP69: 0 | BQ69: 0 | BS69: 1 | BT69: 1 | BU69: 0 | BV69: 0 | BW69: 0 | BX69: 0 | BY69: 66 | BZ69: check | CG69: 1 | CH69: 1 | CI69: 0 | CJ69: 0 | CK69: 0 | CL69: 0
A70: cli_usa_1.1Ado_d073_m019 | B70: climate protest | C70: US | D70: 1.1 | E70: Adoption over Time | F70: Count of protest events related to climate | G70: # protest events | H70: s3 | I70: 19.808 | J70: 0.32844 | K70: 23.055 | L70: 2020 | M70: 0.22186 | N70: 256 | O70: 3.1735e-05 | P70: 1974.2 | Q70: -46432 | R70: 0.97725 | S70: 0.96966 | T70: 16.59 | U70: 7.2308 | V70: 0.72468 | W70: 0.66962 | X70: 57.707 | Y70: 43.032 | Z70: 0.61523 | AA70: 0.53827 | AB70: 68.22 | AC70: 54.259 | AD70: 13 | AE70: 4 | AF70: 1.1836 | AG70: 0.57031 | AH70: 0.61328 | AI70: 4 | AJ70: 2 | AK70: 3 | AL70: 1 | AM70: 0 | AN70: 1 | AO70: 0.77694 | AP70: 0 | AQ70: 0 | AR70: y | AS70: n | AT70: y | AU70: y | AV70: y | AW70: y | AX70: y | AY70: y | AZ70: y | BA70: n | BB70: n | BC70: n | BD70: n | BI70: 0 | BJ70: hide | BK70: original | BL70: 0 | BM70: 1 | BN70: 0 | BO70: 0 | BP70: 0 | BQ70: 0 | BS70: 1 | BT70: 1 | BU70: 0 | BV70: 0 | BW70: 0 | BX70: 0 | BY70: 67 | BZ70: check | CG70: 1 | CH70: 1 | CI70: 0 | CJ70: 0 | CK70: 0 | CL70: 0
A71: cli_usa_1.1Ado_d240_m154 | B71: climate protest | C71: US | D71: 1.1 | E71: Adoption over Time | F71: cumulative Count of participants at protest events related to climate | G71: cumulative # people (estimated) | H71: s3 | I71: 3.4005 | J71: 0.38546 | K71: 66.658 | L71: 2019.9 | M71: 1.2923 | N71: 711.93 | O71: 4.1231e-07 | P71: 1967.2 | Q71: -134250 | R71: 0.98408 | S71: 0.97878 | T71: 38.461 | U71: 19.407 | V71: 0.87506 | W71: 0.85007 | X71: 107.76 | Y71: 87.013 | Z71: 0.66935 | AA71: 0.60322 | AB71: 175.3 | AC71: 152.02 | AD71: 13 | AE71: 4 | AF71: 1.1328 | AG71: 0.64268 | AH71: 0.49012 | AI71: 4 | AJ71: 0 | AK71: 3 | AL71: 0 | AM71: 0 | AN71: 0 | AO71: 0.73719 | AP71: 0 | AQ71: 0 | AR71: y | AS71: n | AT71: y | AU71: y | AV71: y | AW71: y | AX71: y | AY71: y | AZ71: y | BA71: n | BB71: n | BC71: n | BD71: n | BI71: 0 | BK71: transformed-cumulative | BL71: 1 | BM71: 1 | BN71: 0 | BO71: 0 | BP71: 0 | BQ71: 0 | BS71: 1 | BT71: 1 | BU71: 0 | BV71: 1 | BW71: 0 | BX71: 0 | BY71: 68 | CC71: **check** | CG71: 1 | CH71: 1 | CI71: 0 | CJ71: 0 | CK71: 0 | CL71: 0
A72: cli_usa_1.1Ado_d241_m155 | B72: climate protest | C72: US | D72: 1.1 | E72: Adoption over Time | F72: cumulative Count of protest events related to climate | G72: cumulative # protest events | H72: s3 | I72: 1.4067 | J72: 0.52418 | K72: 61.445 | L72: 2021.2 | M72: 3.1239 | N72: 967.62 | O72: 1.9579e-08 | P72: 1976 | Q72: -123770 | R72: 0.99597 | S72: 0.99463 | T72: 19.01 | U72: 11.45 | V72: 0.95383 | W72: 0.9446 | X72: 64.338 | Y72: 48.868 | Z72: 0.58953 | AA72: 0.50743 | AB72: 191.84 | AC72: 162.25 | AD72: 13 | AE72: 4 | AF72: 0.94458 | AG72: 0.15088 | AH72: 0.7937 | AI72: 4 | AJ72: 0 | AK72: 3 | AL72: 0 | AM72: 0 | AN72: 1 | AO72: 0.65653 | AP72: 0 | AQ72: 0 | AR72: y | AS72: n | AT72: y | AU72: y | AV72: y | AW72: y | AX72: m | AY72: y | AZ72: y | BA72: n | BB72: n | BC72: n | BD72: n | BI72: 0 | BJ72: prefer-absolute | BK72: transformed-cumulative | BL72: 1 | BM72: 1 | BN72: 0 | BO72: 2 | BP72: 0 | BQ72: 0 | BS72: 1 | BT72: 1 | BU72: 0 | BV72: 0 | BW72: 0 | BX72: 0 | BY72: 69 | CG72: 1 | CH72: 1 | CI72: 0 | CJ72: 0 | CK72: 0 | CL72: 0
A73: cli_usa_1.1Ado_d346_m185 | B73: climate protest | C73: US | D73: 1.1 | E73: Adoption over Time | F73: cumulative share of population participating in protest events related to climate | G73: market share | H73: s3 | I73: 3.5566 | J73: 0.3836 | K73: 1.9503e-07 | L73: 2019.8 | M73: 1.2356 | N73: 2.0782e-06 | O73: 12.904 | P73: 2063.1 | Q73: -0.00039279 | R73: 0.98507 | S73: 0.98009 | T73: 1.0898e-07 | U73: 5.3778e-08 | V73: 0.87247 | W73: 0.84696 | X73: 3.1849e-07 | Y73: 2.5734e-07 | Z73: 0.66949 | AA73: 0.60339 | AB73: 5.1272e-07 | AC73: 4.4523e-07 | AD73: 13 | AE73: 4 | AF73: 1.1298 | AG73: 0.64861 | AH73: 0.48119 | AI73: 4 | AJ73: 0 | AK73: 3 | AL73: 0 | AM73: 0 | AN73: 0 | AO73: 0.73875 | AP73: 1 | AQ73: 1 | AR73: y | AS73: n | AT73: y | AU73: y | AV73: y | AW73: y | AX73: y | AY73: y | AZ73: y | BA73: n | BB73: n | BC73: n | BD73: n | BH73: weird data | BI73: 0 | BJ73: prefer-relative | BK73: transformed-marketshare | BL73: 0 | BM73: 1 | BN73: 0 | BO73: 1 | BP73: 0 | BQ73: 0 | BS73: 1 | BT73: 1 | BU73: 0 | BV73: 0 | BW73: 0 | BX73: 0 | BY73: 70 | BZ73: check | CC73: **check** | CG73: 1 | CH73: 1 | CI73: 0 | CJ73: 1 | CK73: 0 | CL73: 0
A74: cli_usa_4.1Sal_d213_m100 | B74: climate protest | C74: US | D74: 4.1 | E74: Knowledge Flows (social networks) | F74: annualised Google search frequency (index 100=monthly max.) | G74: Index 0-100 | H74: s3 | I74: 0.53398 | J74: 0.243 | K74: 4.6225 | L74: 2020.3 | M74: 8.2296 | N74: 111.88 | O74: 0.089383 | P74: 1994.6 | Q74: -9286.9 | R74: 0.92033 | S74: 0.90626 | T74: 9.6468 | U74: 4.87 | V74: 0.89043 | W74: 0.87826 | X74: 11.313 | Y74: 8.219 | Z74: 0.67079 | AA74: 0.63421 | AB74: 19.609 | AC74: 17.283 | AD74: 21 | AE74: 12 | AF74: 0.89378 | AG74: 0.021376 | AH74: 0.8724 | AI74: 12 | AJ74: 0 | AK74: 9 | AL74: 0 | AM74: 1 | AN74: 1 | AO74: 0.78065 | AP74: 0 | AQ74: 1 | AR74: y | AS74: y | AT74: y | AU74: m | AV74: y | AW74: m | AX74: y | AY74: y | AZ74: y | BA74: m | BB74: m | BC74: m | BD74: m | BI74: 0 | BJ74: hide | BK74: original | BL74: 1 | BM74: 1 | BN74: 0 | BO74: 0 | BP74: 0 | BQ74: 0 | BS74: 1 | BT74: 1 | BU74: 0 | BV74: 0 | BW74: 0 | BX74: 0 | BY74: 71 | CG74: 1 | CH74: 1 | CI74: 0 | CJ74: 0 | CK74: 0 | CL74: 0
A75: cli_usa_4.1Sal_d239_m153 | B75: climate protest | C75: US | D75: 4.1 | E75: Knowledge Flows (social networks) | F75: Partial up to max annualised Google search frequency (index 100=monthly max.) | G75: Partial up to max Index 0-100 | H75: s3 | I75: 0.53398 | J75: 0.243 | K75: 4.6225 | L75: 2020.3 | M75: 8.2296 | N75: 111.88 | O75: 0.089383 | P75: 1994.6 | Q75: -9286.9 | R75: 0.92033 | S75: 0.90626 | T75: 9.6468 | U75: 4.87 | V75: 0.89043 | W75: 0.87826 | X75: 11.313 | Y75: 8.219 | Z75: 0.67079 | AA75: 0.63421 | AB75: 19.609 | AC75: 17.283 | AD75: 21 | AE75: 12 | AF75: 0.89378 | AG75: 0.021376 | AH75: 0.8724 | AI75: 12 | AJ75: 0 | AK75: 9 | AL75: 0 | AM75: 1 | AN75: 1 | AO75: 0.78065 | AP75: 0 | AQ75: 1 | AR75: y | AS75: y | AT75: y | AU75: m | AV75: y | AW75: m | AX75: y | AY75: y | AZ75: y | BA75: m | BB75: m | BC75: m | BD75: m | BI75: 0 | BJ75: prefer | BK75: transformed-partial | BL75: 1 | BM75: 1 | BN75: 0 | BO75: 0 | BP75: 0 | BQ75: 1 | BS75: 1 | BT75: 1 | BU75: 0 | BV75: 0 | BW75: 0 | BX75: 1 | BY75: 72 | CG75: 1 | CH75: 1 | CI75: 0 | CJ75: 0 | CK75: 0 | CL75: 1
A76: coh_den_1.1Ado_d134_m007 | B76: co-housing | C76: Denmark | D76: 1.1 | E76: Adoption over time | F76: Number of cohousing communities | G76: # communities | H76: b11 | I76: 0.22051 | J76: 0.033741 | K76: 2.6225 | L76: 1984.9 | M76: 19.929 | N76: 101.42 | O76: 1.6723 | P76: 1886.7 | Q76: -5160.5 | R76: 0.98488 | S76: 0.97731 | T76: 4.8001 | U76: 4.2608 | V76: 0.78505 | W76: 0.72364 | X76: 18.096 | Y76: 15.686 | Z76: 0.91844 | AA76: 0.89514 | AB76: 11.147 | AC76: 9.6045 | AD76: 10 | AE76: 10 | AF76: 1.0846 | AG76: 0.0098597 | AH76: 1.0747 | AI76: 45 | AJ76: 0 | AK76: 9 | AL76: 0 | AM76: 0 | AN76: 1 | AO76: 0.87616 | AP76: 0 | AQ76: 0 | AR76: y | AS76: y | AT76: y | AU76: y | AV76: y | AW76: y | AX76: y | AY76: y | AZ76: y | BA76: y | BB76: y | BC76: y | BD76: y | BE76: 1 | BI76: 0 | BJ76: prefer-absolute | BL76: 1 | BM76: 1 | BN76: 2 | BO76: 2 | BP76: 0 | BQ76: 0 | BS76: 1 | BT76: 1 | BU76: 0 | BV76: 0 | BW76: 0 | BX76: 0 | BY76: 73 | CG76: 1 | CH76: 1 | CI76: 0 | CJ76: 0 | CK76: 0 | CL76: 0
A77: coh_den_1.1Ado_d138_m021 | B77: co-housing | C77: Denmark | D77: 1.1 | E77: Adoption over time | F77: Number of housing units in cohousing communities | G77: # residents | H77: b11 | I77: 0.21247 | J77: 0.033852 | K77: 58.453 | L77: 1985.3 | M77: 20.683 | N77: 2285.2 | O77: 0.12287 | P77: 1718.9 | Q77: -115030 | R77: 0.98448 | S77: 0.97517 | T77: 109.66 | U77: 101.47 | V77: 0.77105 | W77: 0.69473 | X77: 421.16 | Y77: 375.09 | Z77: 0.91189 | AA77: 0.88252 | AB77: 261.27 | AC77: 233.12 | AD77: 9 | AE77: 9 | AF77: 1.0542 | AG77: 0.028881 | AH77: 1.0253 | AI77: 45 | AJ77: 0 | AK77: 8 | AL77: 0 | AM77: 0 | AN77: 1 | AO77: 0.85327 | AP77: 0 | AQ77: 0 | AR77: y | AS77: y | AT77: y | AU77: y | AV77: y | AW77: y | AX77: y | AY77: y | AZ77: y | BA77: y | BB77: y | BC77: y | BD77: y | BE77: 1 | BI77: 0 | BL77: 1 | BM77: 1 | BN77: 0 | BO77: 0 | BP77: 0 | BQ77: 0 | BS77: 1 | BT77: 1 | BU77: 0 | BV77: 0 | BW77: 0 | BX77: 0 | BY77: 74 | CG77: 1 | CH77: 1 | CI77: 0 | CJ77: 0 | CK77: 0 | CL77: 0
A78: coh_den_1.1Ado_d335_m185 | B78: co-housing | C78: Denmark | D78: 1.1 | E78: Adoption over time | F78: share of population living in co-housing projects | G78: market share | H78: b11 | I78: 0.25973 | J78: 0.031685 | K78: 1.0356e-05 | L78: 1984.1 | M78: 16.92 | N78: 0.00040635 | O78: 1.8796 | P78: 2274.9 | Q78: -0.020368 | R78: 0.99084 | S78: 0.98534 | T78: 1.5266e-05 | U78: 1.3086e-05 | V78: 0.72319 | W78: 0.63091 | X78: 8.3923e-05 | Y78: 7.457e-05 | Z78: 0.87159 | AA78: 0.82879 | AB78: 5.7159e-05 | AC78: 5.155e-05 | AD78: 9 | AE78: 9 | AF78: 1.0464 | AG78: 0.032726 | AH78: 1.0137 | AI78: 45 | AJ78: 1 | AK78: 8 | AL78: 1 | AM78: 0 | AN78: 1 | AO78: 0.86448 | AP78: 1 | AQ78: 1 | AR78: y | AS78: y | AT78: y | AU78: y | AV78: y | AW78: y | AX78: y | AY78: y | AZ78: y | BA78: y | BB78: y | BC78: y | BD78: y | BI78: 0 | BJ78: prefer-relative | BK78: transformed-marketshare | BL78: 1 | BM78: 1 | BN78: 1 | BO78: 1 | BP78: 0 | BQ78: 0 | BS78: 1 | BT78: 1 | BU78: 1 | BV78: 1 | BW78: 0 | BX78: 0 | BY78: 75 | CG78: 1 | CH78: 1 | CI78: 1 | CJ78: 1 | CK78: 0 | CL78: 0
A79: coh_den_4.1Sal_d213_m100 | B79: co-housing | C79: Denmark | D79: 4.1 | E79: Knowledge Flows (social networks) | F79: annualised Google search frequency (index 100=monthly max.) | G79: Index 0-100 | H79: b11 | I79: 6.5072 | J79: -0.25292 | K79: -1.3766 | L79: 2028.4 | M79: 0.67532 | N79: 0.71605 | O79: 13.116 | P79: 2007.9 | Q79: 2779.4 | R79: -0.098235 | S79: -0.29204 | T79: 23.087 | U79: 6.9048 | V79: 0.20154 | W79: 0.11282 | X79: 19.685 | Y79: 10.513 | Z79: 0.14318 | AA79: 0.047973 | AB79: 20.392 | AC79: 11.958 | AD79: 21 | AE79: 3 | AF79: 139.65 | AG79: 18.155 | AH79: 121.5 | AI79: 10 | AJ79: 9 | AK79: 0 | AL79: 0 | AM79: 0 | AN79: 1 | AO79: 0 | AP79: 0 | AQ79: 1 | AR79: n | AS79: n | AT79: y | AU79: m | AV79: m | AW79: m | AX79: m | AY79: y | AZ79: m | BA79: n | BB79: n | BC79: n | BD79: n | BH79: too few | BI79: 0 | BJ79: hide | BK79: original | BL79: 0 | BM79: 0 | BN79: 0 | BO79: 0 | BP79: 0 | BQ79: 0 | BS79: 0 | BT79: 1 | BU79: 0 | BV79: 0 | BW79: 0 | BX79: 0 | BY79: 76 | CA79: check | CG79: 0 | CH79: 1 | CI79: 0 | CJ79: 0 | CK79: 0 | CL79: 0
A80: coh_den_4.1Sal_d239_m153 | B80: co-housing | C80: Denmark | D80: 4.1 | E80: Knowledge Flows (social networks) | F80: Partial up to max annualised Google search frequency (index 100=monthly max.) | G80: Partial up to max Index 0-100 | H80: b11 | K80: 100 | Q80: -200400 | Z80: 1 | AA80: 1 | AB80: 0 | AC80: 0 | AD80: 2 | AE80: 1 | AI80: 1 | AJ80: 0 | AK80: 0 | AL80: 0 | AM80: 0 | AP80: 0 | AQ80: 1 | AR80: n | AS80: n | AT80: y | AU80: m | AV80: m | AW80: m | AX80: m | AY80: m | AZ80: y | BA80: n | BB80: n | BC80: n | BD80: n | BH80: too few | BI80: 0 | BJ80: prefer | BK80: transformed-partial | BL80: 0 | BM80: 0 | BN80: 0 | BO80: 0 | BP80: 1 | BQ80: 1 | BS80: 0 | BT80: 0 | BU80: 0 | BV80: 0 | BW80: 1 | BX80: 1 | BY80: 77 | CG80: 0 | CH80: 0 | CI80: 0 | CJ80: 0 | CK80: 1 | CL80: 1
A81: coh_ger_1.1Ado_d141_m018 | B81: co-housing | C81: Germany | D81: 1.1 | E81: Adoption over time | F81: Number of projects | G81: # projects | H81: b11 | I81: 0.20463 | J81: 0.079755 | K81: 9.41 | L81: 1994.8 | M81: 21.475 | N81: 316.23 | O81: 0.013744 | P81: 1880.2 | Q81: -18604 | R81: 0.99968 | S81: =-inf -> #NAME? | T81: 1.9287 | U81: 1.3164 | V81: 0.96104 | W81: 0.88313 | X81: 21.387 | Y81: 19.667 | Z81: 0.94267 | AA81: 0.828 | AB81: 25.946 | AC81: 23.25 | AD81: 4 | AE81: 4 | AF81: 0.88859 | AG81: 0.02846 | AH81: 0.86013 | AI81: 31 | AJ81: 0 | AK81: 3 | AL81: 0 | AM81: 0 | AN81: 1 | AO81: 0.48336 | AP81: 0 | AQ81: 0 | AR81: y | AS81: m | AT81: y | AU81: m | AV81: y | AW81: m | AX81: m | AY81: y | AZ81: y | BA81: m | BB81: m | BC81: m | BD81: m | BE81: 1 | BI81: 0 | BL81: 1 | BM81: 1 | BN81: 0 | BO81: 2 | BP81: 0 | BQ81: 0 | BS81: 1 | BT81: 1 | BU81: 0 | BV81: 0 | BW81: 0 | BX81: 0 | BY81: 78 | CG81: 1 | CH81: 1 | CI81: 0 | CJ81: 0 | CK81: 0 | CL81: 0
A82: coh_ger_1.1Ado_d335_m185 | B82: co-housing | C82: Germany | D82: 1.1 | E82: Adoption over time | F82: share of population living in co-housing projects | G82: market share | H82: b11 | I82: 0.1981 | J82: 0.07911 | K82: 2.5151e-06 | L82: 1994.9 | M82: 22.183 | N82: 8.5627e-05 | O82: 45.292 | P82: 2172.9 | Q82: -0.0049722 | R82: 0.99973 | S82: =-inf -> #NAME? | T82: 4.7946e-07 | U82: 3.3323e-07 | V82: 0.96275 | W82: 0.88824 | X82: 5.5835e-06 | Y82: 5.1451e-06 | Z82: 0.94488 | AA82: 0.83465 | AB82: 6.7913e-06 | AC82: 6.1267e-06 | AD82: 4 | AE82: 4 | AF82: 0.87995 | AG82: 0.029381 | AH82: 0.85056 | AI82: 31 | AJ82: 0 | AK82: 3 | AL82: 0 | AM82: 0 | AN82: 1 | AO82: 0.48598 | AP82: 1 | AQ82: 1 | AR82: y | AS82: m | AT82: y | AU82: m | AV82: y | AW82: m | AX82: m | AY82: y | AZ82: y | BA82: m | BB82: m | BC82: m | BD82: m | BI82: 0 | BJ82: prefer-relative | BK82: transformed-marketshare | BL82: 1 | BM82: 1 | BN82: 0 | BO82: 1 | BP82: 0 | BQ82: 0 | BS82: 1 | BT82: 1 | BU82: 0 | BV82: 1 | BW82: 0 | BX82: 0 | BY82: 79 | CG82: 1 | CH82: 1 | CI82: 0 | CJ82: 1 | CK82: 0 | CL82: 0
A83: coh_ger_4.1Sal_d213_m100 | B83: co-housing | C83: Germany | D83: 4.1 | E83: Knowledge Flows (social networks) | F83: annualised Google search frequency (index 100=monthly max.) | G83: Index 0-100 | H83: b11 | I83: 8.4815 | J83: 0.081366 | K83: 3.1097 | L83: 2015.8 | M83: 0.51812 | N83: 60.75 | O83: 0.69242 | P83: 1968.7 | Q83: -6233.1 | R83: 0.56835 | S83: 0.49218 | T83: 21.829 | U83: 13.407 | V83: 0.26817 | W83: 0.18686 | X83: 28.423 | Y83: 24.248 | Z83: 0.32122 | AA83: 0.2458 | AB83: 27.373 | AC83: 22.15 | AD83: 21 | AE83: 13 | AF83: 1.6461 | AG83: 0.13169 | AH83: 1.5144 | AI83: 20 | AJ83: 4 | AK83: 13 | AL83: 1 | AM83: 1 | AN83: 1 | AO83: 0.85774 | AP83: 0 | AQ83: 1 | AR83: m | AS83: y | AT83: y | AU83: m | AV83: m | AW83: m | AX83: y | AY83: y | AZ83: y | BA83: m | BB83: m | BC83: m | BD83: m | BI83: 0 | BJ83: hide | BK83: original | BL83: 1 | BM83: 1 | BN83: 0 | BO83: 0 | BP83: 0 | BQ83: 0 | BS83: 0 | BT83: 1 | BU83: 0 | BV83: 0 | BW83: 0 | BX83: 0 | BY83: 80 | BZ83: check | CG83: 1 | CH83: 1 | CI83: 0 | CJ83: 0 | CK83: 0 | CL83: 0
A84: coh_ger_4.1Sal_d239_m153 | B84: co-housing | C84: Germany | D84: 4.1 | E84: Knowledge Flows (social networks) | F84: Partial up to max annualised Google search frequency (index 100=monthly max.) | G84: Partial up to max Index 0-100 | H84: b11 | I84: 0.77819 | J84: 0.27791 | K84: 5.2206 | L84: 2016.8 | M84: 5.647 | N84: 110.18 | O84: 0.027512 | P84: 1990 | Q84: -10476 | R84: 0.84239 | S84: 0.80602 | T84: 14.005 | U84: 7.0254 | V84: 0.80701 | W84: 0.77943 | X84: 15.498 | Y84: 10.367 | Z84: 0.52561 | AA84: 0.45784 | AB84: 24.298 | AC84: 19.026 | AD84: 17 | AE84: 9 | AF84: 0.9076 | AG84: 0.072608 | AH84: 0.83499 | AI84: 16 | AJ84: 0 | AK84: 9 | AL84: 0 | AM84: 1 | AN84: 1 | AO84: 0.72215 | AP84: 0 | AQ84: 1 | AR84: y | AS84: y | AT84: y | AU84: m | AV84: m | AW84: m | AX84: y | AY84: y | AZ84: y | BA84: m | BB84: m | BC84: m | BD84: m | BI84: 0 | BJ84: prefer | BK84: transformed-partial | BL84: 1 | BM84: 1 | BN84: 0 | BO84: 0 | BP84: 0 | BQ84: 1 | BS84: 1 | BT84: 1 | BU84: 0 | BV84: 0 | BW84: 0 | BX84: 1 | BY84: 81 | CG84: 1 | CH84: 1 | CI84: 0 | CJ84: 0 | CK84: 0 | CL84: 1
A85: coh_glo_3.3Sci_d235_m020 | B85: co-housing | C85: Global | D85: 3.3 | E85: Risk & Uncertainty (Shared Expectations) | F85: scientific publications | G85: # publications | H85: b11 | I85: 0.27252 | J85: 0.11544 | K85: 1.9577 | L85: 2017.1 | M85: 16.125 | N85: 163.28 | O85: 0.52109 | P85: 1974.5 | Q85: -3883.9 | R85: 0.93237 | S85: 0.92839 | T85: 10.683 | U85: 6.5047 | V85: 0.90593 | W85: 0.90231 | X85: 12.599 | Y85: 6.3893 | Z85: 0.57237 | AA85: 0.55592 | AB85: 26.862 | AC85: 21.259 | AD85: 55 | AE85: 45 | AF85: 0.98606 | AG85: 0.0061246 | AH85: 0.97994 | AI85: 48 | AJ85: 4 | AK85: 46 | AL85: 0 | AM85: 0 | AN85: 1 | AO85: 0.92044 | AP85: 0 | AQ85: 0 | AR85: y | AS85: y | AT85: y | AU85: y | AV85: y | AW85: y | AX85: y | AY85: y | AZ85: y | BA85: y | BB85: y | BC85: y | BD85: y | BH85: good; only available global, apply to all EA regions | BI85: 0 | BL85: 1 | BM85: 1 | BN85: 0 | BO85: 0 | BP85: 1 | BQ85: 1 | BS85: 1 | BT85: 1 | BU85: 0 | BV85: 0 | BW85: 1 | BX85: 1 | BY85: 82 | CG85: 1 | CH85: 1 | CI85: 0 | CJ85: 0 | CK85: 1 | CL85: 1
A86: coh_swi_4.1Sal_d213_m100 | B86: co-housing | C86: Switzerland | D86: 4.1 | E86: Knowledge Flows (social networks) | F86: annualised Google search frequency (index 100=monthly max.) | G86: Index 0-100 | H86: b11 | I86: 0.041952 | J86: 0.041932 | K86: 0.3 | L86: 2189.7 | M86: 104.75 | N86: 11625 | O86: 10.708 | P86: 2023.1 | Q86: -596.63 | R86: 0.0057694 | S86: -0.16968 | T86: 24.109 | U86: 13.495 | V86: 0.0057701 | W86: -0.1047 | X86: 24.109 | Y86: 13.495 | Z86: 0.0056446 | AA86: -0.10484 | AB86: 24.111 | AC86: 13.529 | AD86: 21 | AE86: 2 | AF86: 0.0086024 | AG86: 0.0050754 | AH86: 0.003527 | AI86: 13 | AJ86: 12 | AK86: 0 | AL86: 0 | AM86: 0 | AN86: 1 | AO86: 0 | AP86: 0 | AQ86: 1 | AR86: n | AS86: m | AT86: m | AU86: m | AV86: m | AW86: m | AX86: m | AY86: m | AZ86: m | BA86: n | BB86: m | BC86: n | BD86: m | BH86: too few | BI86: 0 | BJ86: hide | BK86: original | BL86: 0 | BM86: 0 | BN86: 0 | BO86: 0 | BP86: 0 | BQ86: 0 | BS86: 0 | BT86: 0 | BU86: 0 | BV86: 0 | BW86: 0 | BX86: 0 | BY86: 83 | CG86: 1 | CH86: 0 | CI86: 0 | CJ86: 0 | CK86: 0 | CL86: 0
A87: coh_swi_4.1Sal_d239_m153 | B87: co-housing | C87: Switzerland | D87: 4.1 | E87: Knowledge Flows (social networks) | F87: Partial up to max annualised Google search frequency (index 100=monthly max.) | G87: Partial up to max Index 0-100 | H87: b11 | I87: 22.563 | K87: 8.3333 | L87: 2011 | M87: 0.19477 | N87: 276.15 | Q87: -16717 | R87: 1 | S87: 1 | T87: 1.1648e-08 | U87: 5.809e-09 | Z87: 0.33333 | AA87: 0.066667 | AB87: 27.003 | AC87: 20.833 | AD87: 8 | AE87: 1 | AF87: 0.36213 | AG87: 0.36213 | AH87: 0 | AI87: 1 | AJ87: 0 | AK87: 0 | AL87: 0 | AM87: 0 | AP87: 0 | AQ87: 1 | AR87: y | AS87: n | AT87: y | AU87: m | AV87: m | AW87: m | AX87: m | AY87: m | AZ87: y | BA87: n | BB87: n | BC87: n | BD87: n | BH87: too few | BI87: 0 | BJ87: prefer | BK87: transformed-partial | BL87: 0 | BM87: 0 | BN87: 0 | BO87: 0 | BP87: 0 | BQ87: 1 | BS87: 0 | BT87: 0 | BU87: 0 | BV87: 0 | BW87: 0 | BX87: 1 | BY87: 84 | CG87: 0 | CH87: 0 | CI87: 0 | CJ87: 0 | CK87: 0 | CL87: 1
A88: coh_usa_1.1Ado_d142_m021 | B88: co-housing | C88: US | D88: 1.1 | E88: Adoption over time | F88: Number of residents living in cohousing communities | G88: # residents | H88: b11 | I88: 0.47637 | J88: 0.21446 | K88: 213.23 | L88: 1996.4 | M88: 9.2249 | N88: 3414.8 | O88: 2.1402e-05 | P88: 1912.4 | Q88: -423940 | R88: 0.99947 | S88: 0.99907 | T88: 23.805 | U88: 21.643 | V88: 0.96347 | W88: 0.94886 | X88: 197.86 | Y88: 179.86 | Z88: 0.89095 | AA88: 0.84734 | AB88: 341.85 | AC88: 309.88 | AD88: 8 | AE88: 8 | AF88: 0.85099 | AG88: 0.015521 | AH88: 0.83547 | AI88: 15 | AJ88: 0 | AK88: 7 | AL88: 0 | AM88: 0 | AN88: 1 | AO88: 0.70294 | AP88: 0 | AQ88: 0 | AR88: y | AS88: y | AT88: y | AU88: y | AV88: y | AW88: y | AX88: y | AY88: y | AZ88: y | BA88: y | BB88: y | BC88: y | BD88: y | BI88: 0 | BL88: 1 | BM88: 1 | BN88: 0 | BO88: 2 | BP88: 0 | BQ88: 0 | BS88: 1 | BT88: 1 | BU88: 0 | BV88: 0 | BW88: 0 | BX88: 0 | BY88: 85 | CG88: 1 | CH88: 1 | CI88: 0 | CJ88: 0 | CK88: 0 | CL88: 0
A89: coh_usa_1.1Ado_d335_m185 | B89: co-housing | C89: US | D89: 1.1 | E89: Adoption over time | F89: share of population living in co-housing projects | G89: market share | H89: b11 | I89: 0.49151 | J89: 0.20545 | K89: 7.706e-07 | L89: 1996 | M89: 8.9407 | N89: 1.1765e-05 | O89: 116.5 | P89: 2078.7 | Q89: -0.001532 | R89: 0.99944 | S89: 0.99901 | T89: 8.832e-08 | U89: 6.1584e-08 | V89: 0.95555 | W89: 0.93777 | X89: 7.8484e-07 | Y89: 7.0786e-07 | Z89: 0.89991 | AA89: 0.85987 | AB89: 1.1777e-06 | AC89: 1.0571e-06 | AD89: 8 | AE89: 8 | AF89: 0.87772 | AG89: 0.018684 | AH89: 0.85904 | AI89: 15 | AJ89: 0 | AK89: 7 | AL89: 0 | AM89: 0 | AN89: 1 | AO89: 0.71861 | AP89: 1 | AQ89: 1 | AR89: y | AS89: y | AT89: y | AU89: y | AV89: y | AW89: y | AX89: y | AY89: y | AZ89: y | BA89: y | BB89: y | BC89: m | BD89: y | BI89: 0 | BJ89: prefer-relative | BK89: transformed-marketshare | BL89: 1 | BM89: 1 | BN89: 0 | BO89: 1 | BP89: 0 | BQ89: 0 | BS89: 1 | BT89: 1 | BU89: 0 | BV89: 1 | BW89: 0 | BX89: 0 | BY89: 86 | CG89: 1 | CH89: 1 | CI89: 0 | CJ89: 1 | CK89: 0 | CL89: 0
A90: coh_usa_4.1Sal_d213_m100 | B90: co-housing | C90: US | D90: 4.1 | E90: Knowledge Flows (social networks) | F90: annualised Google search frequency (index 100=monthly max.) | G90: Index 0-100 | H90: b11 | I90: -0.33502 | J90: -0.18979 | K90: -4.687 | L90: 2006.7 | M90: -13.117 | N90: 148.14 | O90: 48.198 | P90: 2008.5 | Q90: 9469.7 | R90: 0.97488 | S90: 0.97045 | T90: 5.1376 | U90: 4.3268 | V90: 0.96038 | W90: 0.95597 | X90: 6.453 | Y90: 4.7975 | Z90: 0.76644 | AA90: 0.74048 | AB90: 15.667 | AC90: 13.556 | AD90: 21 | AE90: 20 | AF90: 0.67501 | AG90: 0.014553 | AH90: 0.66046 | AI90: 21 | AJ90: 20 | AK90: 4 | AL90: 0 | AM90: 1 | AN90: 1 | AO90: 0.86068 | AP90: 0 | AQ90: 1 | AR90: y | AS90: y | AT90: y | AU90: m | AV90: m | AW90: m | AX90: y | AY90: y | AZ90: y | BA90: m | BB90: m | BC90: m | BD90: m | BH90: downward | BI90: 0 | BJ90: hide | BK90: original | BL90: 1 | BM90: 1 | BN90: 0 | BO90: 0 | BP90: 0 | BQ90: 0 | BS90: 1 | BT90: 1 | BU90: 0 | BV90: 0 | BW90: 0 | BX90: 0 | BY90: 87 | CG90: 1 | CH90: 1 | CI90: 0 | CJ90: 0 | CK90: 0 | CL90: 0
A91: coh_usa_4.1Sal_d239_m153 | B91: co-housing | C91: US | D91: 4.1 | E91: Knowledge Flows (social networks) | F91: Partial up to max annualised Google search frequency (index 100=monthly max.) | G91: Partial up to max Index 0-100 | H91: b11 | AD91: 1 | AE91: 1 | AI91: 1 | AJ91: 0 | AK91: 0 | AL91: 0 | AM91: 0 | AP91: 0 | AQ91: 1 | AR91: n | AS91: n | AT91: y | AU91: m | AV91: m | AW91: m | AX91: m | AY91: m | AZ91: m | BA91: n | BB91: n | BC91: n | BD91: n | BH91: downward | BI91: 0 | BJ91: prefer | BK91: transformed-partial | BL91: 0 | BM91: 0 | BN91: 0 | BO91: 0 | BP91: 0 | BQ91: 1 | BS91: 0 | BT91: 0 | BU91: 0 | BV91: 0 | BW91: 0 | BX91: 1 | BY91: 88 | CG91: 0 | CH91: 0 | CI91: 0 | CJ91: 0 | CK91: 0 | CL91: 1
A92: coh_vau_1.1Ado_d137_m009 | B92: co-housing | C92: Canton de Vaud (Switzerland) | D92: 1.1 | E92: Adoption over time | F92: Number of housing cooperatives in Canton de Vaud (Switzerland) | G92: # cooperatives | H92: b11 | I92: 0.045173 | J92: 0.028481 | K92: 1.2003 | L92: 2000.2 | M92: 97.28 | N92: 198.97 | O92: 4.7043 | P92: 1895.6 | Q92: -2308.5 | R92: 0.98344 | S92: 0.97722 | T92: 5.6478 | U92: 4.5254 | V92: 0.97105 | W92: 0.96461 | X92: 7.4671 | Y92: 6.7865 | Z92: 0.89851 | AA92: 0.87596 | AB92: 13.98 | AC92: 10.883 | AD92: 12 | AE92: 12 | AF92: 0.6986 | AG92: 0.0050259 | AH92: 0.69357 | AI92: 112 | AJ92: 0 | AK92: 11 | AL92: 0 | AM92: 0 | AN92: 1 | AO92: 0.75851 | AP92: 0 | AQ92: 0 | AR92: y | AS92: y | AT92: y | AU92: y | AV92: y | AW92: y | AX92: y | AY92: y | AZ92: y | BA92: y | BB92: y | BC92: y | BD92: y | BE92: 1 | BI92: 0 | BL92: 1 | BM92: 1 | BN92: 0 | BO92: 2 | BP92: 0 | BQ92: 0 | BS92: 1 | BT92: 1 | BU92: 0 | BV92: 1 | BW92: 0 | BX92: 0 | BY92: 89 | CG92: 1 | CH92: 1 | CI92: 0 | CJ92: 0 | CK92: 0 | CL92: 0
A93: cro_ber_1.1Ado_d059_m126 | B93: car ownership | C93: Berlin | D93: 1.1 | E93: Adaption over time | F93: Berlin Car density: 2008-2024 | G93: cars per 1,000 inhabitants | H93: b5 | I93: 0.46197 | J93: 0.0019583 | K93: 0.65735 | L93: 2002 | M93: 9.5123 | N93: 334.89 | O93: 79.734 | P93: 1288.1 | Q93: -993.56 | R93: 0.57391 | S93: 0.47558 | T93: 4.627 | U93: 3.8783 | V93: 0.20393 | W93: 0.090208 | X93: 6.3244 | Y93: 5.2346 | Z93: 0.2064 | AA93: 0.093033 | AB93: 6.3146 | AC93: 5.2253 | AD93: 17 | AE93: 17 | AF93: 1.0197 | AG93: 0.94687 | AH93: 0.072859 | AI93: 17 | AJ93: 12 | AK93: 15 | AL93: 1 | AM93: 0 | AN93: 0 | AO93: 0.94371 | AP93: 0 | AQ93: 0 | AR93: m | AS93: y | AT93: y | AU93: y | AV93: y | AW93: y | AX93: y | AY93: m | AZ93: m | BA93: m | BB93: m | BC93: m | BD93: m | BE93: 2 | BH93: *needs sign reversal * negative slope = LED innovation | BI93: 0 | BL93: 0 | BM93: 1 | BN93: 0 | BO93: 0 | BP93: 0 | BQ93: 0 | BS93: 0 | BT93: 1 | BU93: 0 | BV93: 0 | BW93: 0 | BX93: 0 | BY93: 90 | CG93: 0 | CH93: 1 | CI93: 0 | CJ93: 0 | CK93: 0 | CL93: 0
A94: cro_ber_1.1Ado_d330_m185 | B94: car ownership | C94: Berlin | D94: 1.1 | E94: Adaption over time | F94: cars per person | G94: market share | H94: b5 | I94: 0.46193 | J94: 0.0019583 | K94: 0.00065735 | L94: 2002 | M94: 9.5132 | N94: 0.33489 | O94: 1.0336 | P94: 2596.5 | Q94: -0.99356 | R94: 0.57391 | S94: 0.47558 | T94: 0.004627 | U94: 0.0038783 | V94: 0.20393 | W94: 0.090208 | X94: 0.0063244 | Y94: 0.0052346 | Z94: 0.2064 | AA94: 0.093033 | AB94: 0.0063146 | AC94: 0.0052253 | AD94: 17 | AE94: 17 | AF94: 1.0197 | AG94: 0.94687 | AH94: 0.072859 | AI94: 17 | AJ94: 12 | AK94: 15 | AL94: 1 | AM94: 0 | AN94: 0 | AO94: 0.94371 | AP94: 1 | AQ94: 1 | AR94: m | AS94: y | AT94: y | AU94: y | AV94: y | AW94: y | AX94: y | AY94: m | AZ94: m | BA94: m | BB94: m | BC94: m | BD94: m | BH94: *needs sign reversal * negative slope = LED innovation | BI94: 0 | BJ94: prefer-relative | BK94: transformed-marketshare | BL94: 0 | BM94: 1 | BN94: 0 | BO94: 1 | BP94: 0 | BQ94: 0 | BS94: 0 | BT94: 1 | BU94: 0 | BV94: 1 | BW94: 0 | BX94: 0 | BY94: 91 | CG94: 0 | CH94: 1 | CI94: 0 | CJ94: 0 | CK94: 0 | CL94: 0 | CM94: SdS to fit partial from 2012 (peak year), then logfit of decline period should be useable
A95: cro_ber_1.1Ado_d358_m185 | B95: car ownership | C95: Berlin | D95: 1.1 | E95: Adaption over time | F95: cars per person PARTIAL FROM MAX ONWARDS | G95: market share | H95: b5 | I95: -0.018437 | J95: -0.0020501 | K95: -0.00068571 | L95: 2131.6 | M95: -238.34 | N95: 0.37651 | O95: 0.60667 | P95: 1728.5 | Q95: 1.7189 | R95: 0.52155 | S95: 0.36206 | T95: 0.0024402 | U95: 0.0021041 | V95: 0.52997 | W95: 0.43597 | X95: 0.0024186 | Y95: 0.0020733 | Z95: 0.52894 | AA95: 0.43472 | AB95: 0.0024213 | AC95: 0.0020774 | AD95: 13 | AE95: 13 | AF95: 0.90701 | AG95: 0.87355 | AH95: 0.033465 | AI95: 13 | AJ95: 12 | AK95: 0 | AL95: 0 | AM95: 0 | AN95: 0 | AO95: 0.923 | AP95: 1 | AQ95: 1 | AR95: m | AS95: y | AT95: y | AU95: y | AV95: y | AW95: y | AX95: y | AY95: m | AZ95: y | BA95: m | BB95: y | CG95: 1 | CH95: 1 | CI95: 0 | CJ95: 1 | CK95: 0 | CL95: 0
A96: cro_ber_4.1Sal_d213_m100 | B96: car ownership | C96: Berlin | D96: 4.1 | E96: Knowledge Flows (social networks) | F96: annualised Google search frequency (index 100=monthly max.) | G96: Index 0-100 | H96: b5 | I96: 42.576 | J96: 0.20584 | K96: 1.8826 | L96: 2021.2 | M96: 0.10321 | N96: 52.773 | O96: 6.2492 | P96: 2014.6 | Q96: -3781.5 | R96: 0.54289 | S96: 0.46222 | T96: 15.851 | U96: 6.9326 | V96: 0.29096 | W96: 0.21217 | X96: 19.741 | Y96: 11.95 | Z96: 0.23644 | AA96: 0.15159 | AB96: 20.486 | AC96: 13.69 | AD96: 21 | AE96: 5 | AF96: 1.8949 | AG96: 0.2219 | AH96: 1.673 | AI96: 11 | AJ96: 2 | AK96: 0 | AL96: 1 | AM96: 0 | AN96: 1 | AO96: 0.38198 | AP96: 0 | AQ96: 1 | AR96: m | AS96: m | AT96: y | AU96: m | AV96: m | AW96: m | AX96: m | AY96: y | AZ96: m | BA96: m | BB96: m | BC96: m | BD96: m | BI96: 0 | BJ96: hide | BK96: original | BL96: 1 | BM96: 1 | BN96: 0 | BO96: 0 | BP96: 0 | BQ96: 0 | BS96: 0 | BT96: 1 | BU96: 0 | BV96: 0 | BW96: 0 | BX96: 0 | BY96: 92 | BZ96: check | CG96: 1 | CH96: 1 | CI96: 0 | CJ96: 0 | CK96: 0 | CL96: 0
A97: cro_ber_4.1Sal_d239_m153 | B97: car ownership | C97: Berlin | D97: 4.1 | E97: Knowledge Flows (social networks) | F97: Partial up to max annualised Google search frequency (index 100=monthly max.) | G97: Partial up to max Index 0-100 | H97: b5 | I97: 20.85 | J97: 8.038 | K97: 1.8669 | L97: 2022 | M97: 0.21076 | N97: 251.01 | O97: 0.0025667 | P97: 2020.7 | Q97: -3750.1 | R97: 0.86941 | S97: 0.84329 | T97: 8.3399 | U97: 2.6912 | V97: 0.86941 | W97: 0.85308 | X97: 8.3399 | Y97: 2.6928 | Z97: 0.19632 | AA97: 0.095855 | AB97: 20.689 | AC97: 13.14 | AD97: 19 | AE97: 3 | AF97: 0.39838 | AG97: 0.091156 | AH97: 0.30723 | AI97: 9 | AJ97: 0 | AK97: 8 | AL97: 0 | AM97: 0 | AN97: 1 | AO97: 0 | AP97: 0 | AQ97: 1 | AR97: y | AS97: n | AT97: y | AU97: m | AV97: m | AW97: m | AX97: m | AY97: y | AZ97: m | BA97: n | BB97: n | BC97: n | BD97: n | BI97: 0 | BJ97: prefer | BK97: transformed-partial | BL97: 1 | BM97: 1 | BN97: 0 | BO97: 0 | BP97: 0 | BQ97: 1 | BS97: 1 | BT97: 1 | BU97: 0 | BV97: 0 | BW97: 0 | BX97: 1 | BY97: 93 | CG97: 0 | CH97: 1 | CI97: 0 | CJ97: 0 | CK97: 0 | CL97: 1
A98: cro_glo_3.3Sci_d235_m020 | B98: car ownership | C98: Global | D98: 3.3 | E98: Risk & Uncertainty (Shared Expectations) | F98: scientific publications | G98: # publications | H98: b5 | I98: 0.24766 | J98: 0.039326 | K98: 0.29062 | L98: 2020.9 | M98: 17.744 | N98: 36.793 | O98: -3.7042 | P98: 4342.6 | Q98: -576.82 | R98: 0.91648 | S98: 0.91157 | T98: 1.8905 | U98: 1.0692 | V98: -0.29374 | W98: -0.3435 | X98: 7.4407 | Y98: 3.5455 | Z98: 0.49737 | AA98: 0.47803 | AB98: 4.6378 | AC98: 3.463 | AD98: 55 | AE98: 28 | AF98: 0.67947 | AG98: 0.027179 | AH98: 0.65229 | AI98: 33 | AJ98: 3 | AK98: 32 | AL98: 0 | AM98: 0 | AN98: 1 | AO98: 0.83514 | AP98: 0 | AQ98: 1 | AR98: y | AS98: y | AT98: y | AU98: m | AV98: y | AW98: m | AX98: y | AY98: y | AZ98: y | BA98: m | BB98: m | BC98: m | BD98: m | BH98: good; only available global, apply to all EA regions | BI98: 0 | BL98: 1 | BM98: 1 | BN98: 0 | BO98: 0 | BP98: 1 | BQ98: 1 | BS98: 1 | BT98: 1 | BU98: 0 | BV98: 0 | BW98: 1 | BX98: 1 | BY98: 94 | CG98: 1 | CH98: 1 | CI98: 0 | CJ98: 0 | CK98: 1 | CL98: 1
A99: cro_ham_1.1Ado_d108_m126 | B99: car ownership | C99: Hamburg | D99: 1.1 | E99: Adaption over time | F99: Hamburg Car density 2008-2024 | G99: cars per 1,000 inhabitants | H99: b5 | I99: 0.21243 | J99: 0.0046092 | K99: 1.9703 | L99: 1996.9 | M99: 20.686 | N99: 434.74 | O99: 40.81 | P99: 1508.7 | Q99: -3549.1 | R99: 0.84235 | S99: 0.80597 | T99: 4.6163 | U99: 3.8976 | V99: 0.68223 | W99: 0.63684 | X99: 6.554 | Y99: 5.7013 | Z99: 0.68928 | AA99: 0.64489 | AB99: 6.4809 | AC99: 5.5996 | AD99: 17 | AE99: 17 | AF99: 1.0098 | AG99: 0.92353 | AH99: 0.086258 | AI99: 17 | AJ99: 2 | AK99: 15 | AL99: 1 | AM99: 0 | AN99: 0 | AO99: 0.94355 | AP99: 0 | AQ99: 0 | AR99: y | AS99: y | AT99: y | AU99: y | AV99: y | AW99: y | AX99: y | AY99: m | AZ99: y | BA99: m | BB99: y | BC99: n | BD99: y | BE99: 2 | BH99: *needs sign reversal * negative slope = LED innovation | BI99: 0 | BL99: 0 | BM99: 1 | BN99: 0 | BO99: 0 | BP99: 0 | BQ99: 0 | BS99: 1 | BT99: 1 | BU99: 0 | BV99: 0 | BW99: 0 | BX99: 0 | BY99: 95 | BZ99: check | CG99: 1 | CH99: 1 | CI99: 0 | CJ99: 0 | CK99: 0 | CL99: 0
A100: cro_ham_1.1Ado_d330_m185 | B100: car ownership | C100: Hamburg | D100: 1.1 | E100: Adaption over time | F100: cars per person | G100: market share | H100: b5 | I100: 0.21243 | J100: 0.0011445 | K100: 0.0019703 | L100: 1996.9 | M100: 20.686 | N100: 0.43474 | O100: 1555.5 | P100: 157470 | Q100: -3.5491 | R100: 0.84235 | S100: 0.80597 | T100: 0.0046163 | U100: 0.0038976 | V100: -1324.4 | W100: -1513.7 | X100: 0.42327 | Y100: 0.42311 | Z100: 0.68928 | AA100: 0.64489 | AB100: 0.0064809 | AC100: 0.0055996 | AD100: 17 | AE100: 17 | AF100: 1.0098 | AG100: 0.92353 | AH100: 0.086258 | AI100: 17 | AJ100: 2 | AK100: 15 | AL100: 1 | AM100: 0 | AN100: 0 | AO100: 0.94355 | AP100: 1 | AQ100: 1 | AR100: y | AS100: y | AT100: y | AU100: y | AV100: y | AW100: y | AX100: y | AY100: m | AZ100: y | BA100: m | BB100: y | BC100: n | BD100: y | BH100: *needs sign reversal * negative slope = LED innovation | BI100: 0 | BJ100: prefer-relative | BK100: transformed-marketshare | BL100: 0 | BM100: 1 | BN100: 0 | BO100: 1 | BP100: 0 | BQ100: 0 | BS100: 1 | BT100: 1 | BU100: 0 | BV100: 1 | BW100: 0 | BX100: 0 | BY100: 96 | BZ100: check | CG100: 1 | CH100: 1 | CI100: 0 | CJ100: 1 | CK100: 0 | CL100: 0 | CM100: Trend is in unfavorable direction but fit seems correct
...

Sheet summary_table_v26_23SIs
A1: Code | B1: Innovation Name | C1: Spatial Scale | D1: Indicator Number | E1: Indicator Name | F1: Description | G1: Metric | H1: Category | I1: slope_log | J1: slope_exp | K1: slope_lin | L1: log_t0 | M1: log_Dt | N1: log_K | O1: exp_a | P1: exp_c | Q1: lin_intercept | R1: log_r2 | S1: log_r2adj | T1: log_rmse | U1: log_mae | V1: exp_r2 | W1: exp_r2adj | X1: exp_rmse | Y1: exp_mae | Z1: lin_r2 | AA1: lin_r2adj | AB1: lin_rmse | AC1: lin_mae | AD1: n_data_points | AE1: n_non_zero_data_points | AF1: max_over_K | AG1: min_over_K | AH1: range_over_k | AI1: length_trimmed_series_years | AJ1: n_data_points_beyond_max | AK1: n_data_points_beyond_min | AL1: suspected_reversal_up2down | AM1: suspected_reversal_down2up | AN1: at_least_one_big_jump | AO1: autocorr_l1 | AP1: all_values_less_than_or_equal_to_1 | AQ1: all_values_less_than_or_equal_to_100 | AR1: C1_R2 | AS1: C2_threshold_non_zero_value_years | AT1: C3_pct_non_zero | AU1: C4_less_than_250_jump_in_second_half | AV1: C4_less_than_80_fall_in_second_half | AW1: C4_combined_less_than_80_fall_and_250_jump_in_second_half | AX1: C5_volatility_autocorrelation_lag1_threshold_0.7 | AY1: C6_{K_COVERAGE_THRESHOLD}_of_k_covered_by_data | AZ1: C7_lin_r2 | BA1: use_log_x | BB1: use_lin_x | BC1: use_log_y | BD1: use_lin_y | BE1: old GN scoring @retreat | BF1: old GN comments | BG1: old CW scoring @retreat | BH1: comments_fit_CW | BI1: comments_delete_CW | BJ1: comments_alternativeseries_CW | BK1: comments_transformations_CW | BL1: use_logfit_CW | BM1: use_linfit_CW | BN1: select_1.1_earegion_CW | BO1: select_1.1_allregions_CW | BP1: select_non1.1s_earegion_CW | BQ1: select_non1.1s_allregions_CW | BR1: GN final scoring | BS1: use_logfit_GN | BT1: use_linfit_GN | BU1: select_1.1_earegion_GN | BV1: select_1.1_allregions_GN | BW1: select_non1.1s_earegion_GN | BX1: select_non1.1s_allregions_GN | BY1: PDF page | BZ1: use_logfit_AGREE? | CA1: use_linfit_AGREE? | CB1: select_1.1_earegion_AGREE? | CC1: select_1.1_allregions_AGREE? | CD1: select_non1.1s_earegion_AGREE? | CE1: select_non1.1s_allregions_AGREE? | CF1: FINAL_AGREED | CG1: use_logfit_FIN | CH1: use_linfit_FIN | CI1: select_1.1_earegion_FIN | CJ1: select_1.1_allregions_FIN | CK1: select_non1.1s_earegion_FIN | CL1: select_non1.1s_allregions_FIN | CM1: CWnotes_6May | CN1: GN notes 9 may
A2: act_ams_1.1Ado_d063_m028 | B2: active mobility | C2: Amsterdam | D2: 1.1 | E2: Adoption over time | F2: Bike ownership | G2: % | H2: b7 | I2: 6.1161 | J2: 0.0054776 | K2: 0.0038502 | L2: 1984.7 | M2: 0.7185 | N2: 0.71167 | O2: 0.76729 | P2: 2018.3 | Q2: -7.0056 | R2: 0.67402 | S2: 0.34804 | T2: 0.022307 | U2: 0.018571 | V2: 0.78529 | W2: 0.67794 | X2: 0.018104 | Y2: 0.017715 | Z2: 0.79629 | AA2: 0.69443 | AB2: 0.017635 | AC2: 0.017232 | AD2: 7 | AE2: 7 | AF2: 1.0539 | AG2: 0.87119 | AH2: 0.18267 | AI2: 29 | AJ2: 1 | AK2: 6 | AL2: 0 | AM2: 0 | AN2: 0 | AO2: 0.86693 | AP2: 1 | AQ2: 1 | AR2: m | AS2: y | AT2: y | AU2: y | AV2: y | AW2: y | AX2: y | AY2: m | AZ2: y | BA2: m | BB2: y | BC2: n | BD2: y | BE2: 1 | BI2: 0 | BL2: 0 | BM2: 1 | BN2: 0 | BO2: 0 | BP2: 0 | BQ2: 0 | BS2: 0 | BT2: 1 | BU2: 0 | BV2: 0 | BW2: 0 | BX2: 0 | BY2: 1 | CG2: 0 | CH2: 1 | CI2: 0 | CJ2: 0 | CK2: 0 | CL2: 0 | CO2: means I've changed 0 to 1 or vice versa
A3: act_ams_1.1Ado_d121_m090 | B3: active mobility | C3: Amsterdam | D3: 1.1 | E3: Adoption over time | F3: Modal share of all trips by residents (bike) | G3: % trips by bike | H3: b7 | I3: -0.0023618 | J3: -0.0023613 | K3: -0.00056291 | L3: -1564.6 | M3: -1860.6 | N3: 1091.8 | O3: 0.67031 | P3: 1566.4 | Q3: 1.3672 | R3: 0.17886 | S3: -0.31382 | T3: 0.03044 | U3: 0.027427 | V3: 0.17886 | W3: -0.094847 | X3: 0.03044 | Y3: 0.027427 | Z3: 0.16499 | AA3: -0.11334 | AB3: 0.030696 | AC3: 0.027808 | AD3: 9 | AE3: 9 | AF3: 0.00028395 | AG3: 0.00018319 | AH3: 0.00010076 | AI3: 84 | AJ3: 8 | AK3: 2 | AL3: 0 | AM3: 0 | AN3: 0 | AO3: 0.84023 | AP3: 1 | AQ3: 1 | AR3: n | AS3: y | AT3: y | AU3: y | AV3: y | AW3: y | AX3: y | AY3: m | AZ3: m | BA3: n | BB3: m | BC3: n | BD3: m | BE3: 2 | BI3: 0 | BL3: 1 | BM3: 1 | BN3: 0 | BO3: 0 | BP3: 0 | BQ3: 0 | BS3: 1 | BT3: 1 | BU3: 0 | BV3: 0 | BW3: 0 | BX3: 0 | BY3: 2 | CG3: 1 | CH3: 1 | CI3: 0 | CJ3: 0 | CK3: 0 | CL3: 0 | CO3: means problem, dicuss with GN
A4: act_ams_1.1Ado_d122_m091 | B4: active mobility | C4: Amsterdam | D4: 1.1 | E4: Adoption over time | F4: Modal share of all trips by residents (walk) | G4: % trips by walking | H4: b7 | I4: -16.742 | J4: -0.0042167 | K4: -0.0010874 | L4: 1996.2 | M4: -0.26248 | N4: 0.272 | O4: 0.083316 | P4: 2247.9 | Q4: 2.4124 | R4: -4.8878 | S4: -8.4205 | T4: 0.16055 | U4: 0.13267 | V4: 0.1654 | W4: -0.1128 | X4: 0.060446 | Y4: 0.045681 | Z4: 0.15869 | AA4: -0.12175 | AB4: 0.060688 | AC4: 0.045795 | AD4: 9 | AE4: 9 | AF4: 1.2868 | AG4: 0.44118 | AH4: 0.84559 | AI4: 84 | AJ4: 8 | AK4: 7 | AL4: 0 | AM4: 1 | AN4: 1 | AO4: 0.78584 | AP4: 1 | AQ4: 1 | AR4: n | AS4: y | AT4: y | AU4: y | AV4: y | AW4: y | AX4: y | AY4: y | AZ4: m | BA4: n | BB4: m | BC4: n | BD4: m | BE4: 4 | BG4: ok, use logfit | BI4: 0 | BL4: 1 | BM4: 1 | BN4: 0 | BO4: 0 | BP4: 0 | BQ4: 0 | BS4: 1 | BT4: 1 | BU4: 0 | BV4: 0 | BW4: 0 | BX4: 0 | BY4: 3 | CG4: 0 | CH4: 1 | CI4: 0 | CJ4: 0 | CK4: 0 | CL4: 0 | CM4: SdS: fit partial from 1979 (drop 1930 peak year) | CO4: means new coding for changed indicators post Feb
A5: act_ams_1.1Ado_d332_m185 | B5: active mobility | C5: Amsterdam | D5: 1.1 | E5: Adoption over time | F5: % trips by walking and biking | G5: market share | H5: b7 | I5: -0.0087911 | J5: -0.0033221 | K5: -0.0016503 | L5: 2033.8 | M5: -499.87 | N5: 0.83407 | O5: 0.0026073 | P5: 3568.5 | Q5: 3.7796 | R5: 0.19777 | S5: -0.28356 | T5: 0.078513 | U5: 0.059173 | V5: 0.22115 | W5: -0.038465 | X5: 0.07736 | Y5: 0.058997 | Z5: 0.20825 | AA5: -0.055671 | AB5: 0.077999 | AC5: 0.059339 | AD5: 9 | AE5: 9 | AF5: 0.79131 | AG5: 0.40764 | AH5: 0.38366 | AI5: 84 | AJ5: 8 | AK5: 7 | AL5: 0 | AM5: 1 | AN5: 0 | AO5: 0.82455 | AP5: 1 | AQ5: 1 | AR5: n | AS5: y | AT5: y | AU5: y | AV5: y | AW5: y | AX5: y | AY5: y | AZ5: m | BA5: n | BB5: m | BC5: n | BD5: m | BI5: 0 | BJ5: prefer-relative | BK5: transformed-marketshare | BL5: 1 | BM5: 1 | BN5: 0 | BO5: 1 | BP5: 0 | BQ5: 0 | BS5: 1 | BT5: 1 | BU5: 0 | BV5: 1 | BW5: 0 | BX5: 0 | BY5: 4 | CG5: 1 | CH5: 1 | CI5: 0 | CJ5: 0 | CK5: 0 | CL5: 0 | CO5: means didn't survive _v24 to _v25 transfer
A6: act_ams_1.1Ado_d359_m091 | B6: active mobility | C6: Amsterdam | D6: 1.1 | E6: Adoption over time | F6: Modal share of all trips by residents (walk) EXCLUDING 1930 | G6: % trips by walking | H6: b7 | I6: 1.9434 | J6: 0.0020703 | K6: 0.00060028 | L6: 1970.1 | M6: 2.2612 | N6: 0.25429 | O6: 0.068688 | P6: 1396.9 | Q6: -0.96066 | R6: 0.56052 | S6: 0.23091 | T6: 0.039325 | U6: 0.033214 | V6: 0.014739 | W6: -0.37937 | X6: 0.05888 | Y6: 0.051788 | Z6: 0.018126 | AA6: -0.37462 | AB6: 0.058779 | AC6: 0.052101 | AD6: 8 | AE6: 8 | AF6: 1.2191 | AG6: 0.47191 | AH6: 0.74719 | AI6: 44 | AJ6: 6 | AK6: 7 | AL6: 1 | AM6: 0 | AN6: 1 | AO6: 0.89904 | AP6: 1 | AQ6: 1 | AR6: m | AS6: y | AT6: y | AU6: y | AV6: y | AW6: y | AX6: y | AY6: y | AZ6: m | BA6: m | BB6: m | CG6: 0 | CH6: 1 | CI6: 0 | CJ6: 0 | CK6: 0 | CL6: 0
A7: act_ams_1.1Ado_d360_m185 | B7: active mobility | C7: Amsterdam | D7: 1.1 | E7: Adoption over time | F7: % trips by walking and biking EXCLUDING 1930 | G7: market share | H7: b7 | I7: 1.0857 | J7: 0.0026517 | K7: 0.0013983 | L7: 1969.3 | M7: 4.0475 | N7: 0.49714 | O7: 0.10663 | P7: 1430.8 | Q7: -2.3135 | R7: 0.54632 | S7: 0.20607 | T7: 0.047359 | U7: 0.036072 | V7: 0.062786 | W7: -0.3121 | X7: 0.068069 | Y7: 0.06083 | Z7: 0.070004 | AA7: -0.30199 | AB7: 0.067806 | AC7: 0.060625 | AD7: 8 | AE7: 8 | AF7: 1.1264 | AG7: 0.68391 | AH7: 0.44253 | AI7: 44 | AJ7: 4 | AK7: 7 | AL7: 1 | AM7: 0 | AN7: 0 | AO7: 0.89687 | AP7: 1 | AQ7: 1 | AR7: m | AS7: y | AT7: y | AU7: y | AV7: y | AW7: y | AX7: y | AY7: y | AZ7: m | BA7: m | BB7: m | CG7: 1 | CH7: 1 | CI7: 0 | CJ7: 1 | CK7: 0 | CL7: 0
A8: act_bei_1.1Ado_d060_m028 | B8: active mobility | C8: Beijing | D8: 1.1 | E8: Adoption over time | F8: Bicycle modal share | G8: % | H8: b7 | I8: -128.93 | J8: -0.00040147 | K8: -0.01425 | L8: 1999.7 | M8: -0.034083 | N8: 0.5403 | O8: -1544.5 | P8: -152600 | Q8: 28.852 | R8: -3.1777 | S8: 9.3553 | T8: 0.25892 | U8: 0.205 | V8: -9.2413 | W8: =-inf -> #NAME? | X8: 0.4054 | Y8: 0.3851 | Z8: 0.96449 | AA8: =-inf -> #NAME? | AB8: 0.023871 | AC8: 0.0221 | AD8: 3 | AE8: 3 | AF8: 1 | AG8: 0.42569 | AH8: 0.57431 | AI8: 22 | AJ8: 2 | AK8: 0 | AL8: 0 | AM8: 0 | AN8: 0 | AO8: 0.60149 | AP8: 1 | AQ8: 1 | AR8: n | AS8: m | AT8: y | AU8: y | AV8: y | AW8: y | AX8: m | AY8: y | AZ8: y | BA8: n | BB8: m | BC8: m | BD8: m | BE8: 2 | BI8: 0 | BL8: 1 | BM8: 1 | BN8: 0 | BO8: 0 | BP8: 0 | BQ8: 0 | BS8: 1 | BT8: 1 | BU8: 0 | BV8: 0 | BW8: 0 | BX8: 0 | BY8: 5 | CG8: 0 | CH8: 1 | CI8: 0 | CJ8: 0 | CK8: 0 | CL8: 0
A9: act_bei_1.1Ado_d332_m185 | B9: active mobility | C9: Beijing | D9: 1.1 | E9: Adoption over time | F9: % trips by walking and biking | G9: market share | H9: b7 | I9: -128.93 | J9: -0.00040147 | K9: -0.01425 | L9: 1999.7 | M9: -0.034083 | N9: 0.5403 | O9: -1544.5 | P9: -152600 | Q9: 28.852 | R9: -3.1777 | S9: 9.3553 | T9: 0.25892 | U9: 0.205 | V9: -9.2413 | W9: =-inf -> #NAME? | X9: 0.4054 | Y9: 0.3851 | Z9: 0.96449 | AA9: =-inf -> #NAME? | AB9: 0.023871 | AC9: 0.0221 | AD9: 3 | AE9: 3 | AF9: 1 | AG9: 0.42569 | AH9: 0.57431 | AI9: 22 | AJ9: 2 | AK9: 0 | AL9: 0 | AM9: 0 | AN9: 0 | AO9: 0.60149 | AP9: 1 | AQ9: 1 | AR9: n | AS9: m | AT9: y | AU9: y | AV9: y | AW9: y | AX9: m | AY9: y | AZ9: y | BA9: n | BB9: m | BC9: m | BD9: m | BI9: 0 | BJ9: prefer-relative | BK9: transformed-marketshare | BL9: 1 | BM9: 1 | BN9: 0 | BO9: 1 | BP9: 0 | BQ9: 0 | BS9: 1 | BT9: 1 | BU9: 0 | BV9: 1 | BW9: 0 | BX9: 0 | BY9: 6 | CG9: 0 | CH9: 1 | CI9: 0 | CJ9: 1 | CK9: 0 | CL9: 0
A10: act_chi_1.1Ado_d061_m002 | B10: active mobility | C10: China | D10: 1.1 | E10: Adoption over time | F10: Bicycle ownership | G10: # bikes per hundred households | H10: b7 | I10: 15.465 | J10: 0.020393 | K10: 2.6286 | L10: 1814.4 | M10: 0.28415 | N10: 110.03 | O10: 3.2025 | P10: 1817.7 | Q10: -5121 | R10: 0 | S10: =-inf -> #NAME? | T10: 61.847 | U10: 47.333 | V10: 0.20425 | W10: -1.3873 | X10: 55.17 | Y10: 49.509 | Z10: 0.23213 | AA10: -1.3036 | AB10: 54.195 | AC10: 50.322 | AD10: 4 | AE10: 4 | AF10: 1.7918 | AG10: 0.20794 | AH10: 1.5839 | AI10: 30 | AJ10: 1 | AK10: 2 | AL10: 1 | AM10: 1 | AN10: 1 | AO10: 0.47132 | AP10: 0 | AQ10: 0 | AR10: n | AS10: m | AT10: y | AU10: m | AV10: y | AW10: m | AX10: m | AY10: y | AZ10: m | BA10: n | BB10: m | BC10: m | BD10: m | BE10: 4 | BG10: reject, too few points | BI10: 0 | BL10: 0 | BM10: 1 | BN10: 0 | BO10: 0 | BP10: 0 | BQ10: 0 | BS10: 0 | BT10: 1 | BU10: 0 | BV10: 0 | BW10: 0 | BX10: 0 | BY10: 7 | CG10: 0 | CH10: 1 | CI10: 0 | CJ10: 0 | CK10: 0 | CL10: 0
A11: act_chi_3.2Adc_d062_m003 | B11: active mobility | C11: China | D11: 3.2 | E11: Adopter characteristics | F11: Bicycle ownership among income groups | G11: # bikes per hundred households (highest 10% income) | H11: b7 | I11: -0.25049 | J11: -0.017188 | K11: -3.0744 | L11: 2008 | M11: -17.543 | N11: 187.66 | O11: 280.33 | P11: 1964.3 | Q11: 6300.3 | R11: 0.82934 | S11: =-inf -> #NAME? | T11: 12.667 | U11: 10.677 | V11: 0.51703 | W11: -0.4489 | X11: 21.309 | Y11: 19.229 | Z11: 0.56489 | AA11: -0.30533 | AB11: 20.226 | AC11: 18.246 | AD11: 4 | AE11: 4 | AF11: 1.0823 | AG11: 0.62879 | AH11: 0.45353 | AI11: 21 | AJ11: 2 | AK11: 0 | AL11: 1 | AM11: 0 | AN11: 0 | AO11: 0.78003 | AP11: 0 | AQ11: 0 | AR11: y | AS11: m | AT11: y | AU11: y | AV11: y | AW11: y | AX11: y | AY11: y | AZ11: y | BA11: m | BB11: m | BC11: m | BD11: m | BE11: 2 | BI11: 0 | BL11: 0 | BM11: 1 | BS11: 1 | BT11: 1 | BU11: 0 | BV11: 0 | BW11: 0 | BX11: 0 | BY11: 8 | BZ11: check | CG11: 1 | CH11: 1 | CI11: 0 | CJ11: 0 | CK11: 0 | CL11: 0
A12: act_chi_3.2Adc_d062_m004 | B12: active mobility | C12: China | D12: 3.2 | E12: Adopter characteristics | F12: Bicycle ownership among income groups | G12: # bikes per hundred households (lowest 10% income) | H12: b7 | I12: -2.6167 | J12: -0.0083411 | K12: -1.3736 | L12: 2006.3 | M12: -1.6794 | N12: 157.06 | O12: 227.52 | P12: 1941.8 | Q12: 2886.7 | R12: 0.61758 | S12: =-inf -> #NAME? | T12: 16.895 | U12: 12.122 | V12: 0.12506 | W12: -1.6248 | X12: 25.555 | Y12: 25.04 | Z12: 0.14203 | AA12: -1.5739 | AB12: 25.306 | AC12: 24.861 | AD12: 4 | AE12: 4 | AF12: 1.1498 | AG12: 0.68431 | AH12: 0.46548 | AI12: 21 | AJ12: 2 | AK12: 0 | AL12: 1 | AM12: 0 | AN12: 0 | AO12: 0.80089 | AP12: 0 | AQ12: 0 | AR12: m | AS12: m | AT12: y | AU12: y | AV12: y | AW12: y | AX12: y | AY12: y | AZ12: m | BA12: m | BB12: m | BC12: m | BD12: m | BE12: 2 | BI12: 0 | BL12: 0 | BM12: 1 | BS12: 0 | BT12: 1 | BU12: 0 | BV12: 0 | BW12: 0 | BX12: 0 | BY12: 9 | CG12: 0 | CH12: 1 | CI12: 0 | CJ12: 0 | CK12: 0 | CL12: 0
A13: act_chi_3.2Adc_d062_m005 | B13: active mobility | C13: China | D13: 3.2 | E13: Adopter characteristics | F13: Bicycle ownership among income groups | G13: # bikes per hundred households (middle income groups) | H13: b7 | I13: -0.35805 | J13: -0.013207 | K13: -2.4015 | L13: 2007.8 | M13: -12.273 | N13: 181.57 | O13: 267.65 | P13: 1958.3 | Q13: 4957 | R13: 0.75315 | S13: =-inf -> #NAME? | T13: 14.824 | U13: 11.464 | V13: 0.32729 | W13: -1.0181 | X13: 24.472 | Y13: 23.3 | Z13: 0.364 | AA13: -0.90799 | AB13: 23.795 | AC13: 22.74 | AD13: 4 | AE13: 4 | AF13: 1.1186 | AG13: 0.65538 | AH13: 0.46323 | AI13: 21 | AJ13: 2 | AK13: 0 | AL13: 1 | AM13: 0 | AN13: 0 | AO13: 0.79113 | AP13: 0 | AQ13: 0 | AR13: y | AS13: m | AT13: y | AU13: y | AV13: y | AW13: y | AX13: y | AY13: y | AZ13: y | BA13: m | BB13: m | BC13: m | BD13: m | BE13: 2 | BI13: 0 | BL13: 0 | BM13: 1 | BS13: 1 | BT13: 1 | BU13: 0 | BV13: 0 | BW13: 0 | BX13: 1 | BY13: 10 | BZ13: check | CG13: 1 | CH13: 1 | CI13: 0 | CJ13: 0 | CK13: 0 | CL13: 1
A14: act_chi_4.1Sal_d213_m100 | B14: active mobility | C14: China | D14: 4.1 | E14: Knowledge Flows (social networks) | F14: annualised Google search frequency (index 100=monthly max.) | G14: Index 0-100 | H14: b7 | I14: 2.095 | J14: 0.076912 | K14: 3.6253 | L14: 2013.4 | M14: 2.0976 | N14: 61.747 | O14: 0.65739 | P14: 1963.6 | Q14: -7267.6 | R14: 0.79934 | S14: 0.76393 | T14: 14.129 | U14: 9.9398 | V14: 0.36338 | W14: 0.29265 | X14: 25.166 | Y14: 21.242 | Z14: 0.48439 | AA14: 0.4271 | AB14: 22.649 | AC14: 17.771 | AD14: 21 | AE14: 20 | AF14: 1.6195 | AG14: 0.017461 | AH14: 1.6021 | AI14: 21 | AJ14: 8 | AK14: 20 | AL14: 1 | AM14: 0 | AN14: 1 | AO14: 0.93024 | AP14: 0 | AQ14: 1 | AR14: y | AS14: y | AT14: y | AU14: y | AV14: y | AW14: y | AX14: y | AY14: y | AZ14: y | BA14: y | BB14: y | BC14: y | BD14: y | BI14: 0 | BJ14: hide | BK14: original | BL14: 1 | BM14: 1 | BN14: 0 | BO14: 0 | BP14: 0 | BQ14: 0 | BS14: 1 | BT14: 0 | BU14: 0 | BV14: 0 | BW14: 0 | BX14: 0 | BY14: 11 | CA14: check | CG14: 1 | CH14: 1 | CI14: 0 | CJ14: 0 | CK14: 0 | CL14: 0
A15: act_chi_4.1Sal_d239_m153 | B15: active mobility | C15: China | D15: 4.1 | E15: Knowledge Flows (social networks) | F15: Partial up to max annualised Google search frequency (index 100=monthly max.) | G15: Partial up to max Index 0-100 | H15: b7 | I15: 1.0431 | J15: 0.49369 | K15: 6.5779 | L15: 2014.6 | M15: 4.213 | N15: 123.43 | O15: 0.019473 | P15: 1998.6 | Q15: -13201 | R15: 0.99639 | S15: 0.99519 | T15: 1.8903 | U15: 1.5688 | V15: 0.97515 | W15: 0.97018 | X15: 4.9601 | Y15: 3.8128 | Z15: 0.61177 | AA15: 0.53412 | AB15: 19.606 | AC15: 16.835 | AD15: 13 | AE15: 12 | AF15: 0.81017 | AG15: 0.0087349 | AH15: 0.80143 | AI15: 13 | AJ15: 0 | AK15: 12 | AL15: 0 | AM15: 0 | AN15: 1 | AO15: 0.66032 | AP15: 0 | AQ15: 1 | AR15: y | AS15: y | AT15: y | AU15: y | AV15: y | AW15: y | AX15: m | AY15: y | AZ15: y | BA15: m | BB15: m | BC15: y | BD15: y | BI15: 0 | BJ15: prefer | BK15: transformed-partial | BL15: 1 | BM15: 1 | BN15: 0 | BO15: 0 | BP15: 0 | BQ15: 1 | BS15: 1 | BT15: 1 | BU15: 0 | BV15: 0 | BW15: 0 | BX15: 1 | BY15: 12 | CG15: 1 | CH15: 1 | CI15: 0 | CJ15: 0 | CK15: 0 | CL15: 1
A16: act_cop_1.1Ado_d121_m090 | B16: active mobility | C16: Copenhagen | D16: 1.1 | E16: Adoption over time | F16: Modal share of all trips by residents (bike) | G16: % trips by bike | H16: b7 | I16: 0.014241 | J16: 0.0012979 | K16: 0.0033675 | L16: 2734.2 | M16: 308.58 | N16: 8643.2 | O16: 1555.1 | P16: 157450 | Q16: -6.4834 | R16: 0.784 | S16: =-inf -> #NAME? | T16: 0.018985 | U16: 0.018338 | V16: -38.206 | W16: -116.62 | X16: 0.25578 | Y16: 0.2525 | Z16: 0.7454 | AA16: 0.23619 | AB16: 0.020612 | AC16: 0.020026 | AD16: 4 | AE16: 4 | AF16: 3.7023e-05 | AG16: 2.5454e-05 | AH16: 1.157e-05 | AI16: 28 | AJ16: 0 | AK16: 3 | AL16: 0 | AM16: 0 | AN16: 0 | AO16: 0.7008 | AP16: 1 | AQ16: 1 | AR16: y | AS16: m | AT16: y | AU16: y | AV16: y | AW16: y | AX16: y | AY16: m | AZ16: y | BA16: m | BB16: m | BC16: m | BD16: m | BE16: 2 | BI16: 0 | BL16: 1 | BM16: 1 | BN16: 0 | BO16: 0 | BP16: 0 | BQ16: 0 | BS16: 1 | BT16: 1 | BU16: 0 | BV16: 0 | BW16: 0 | BX16: 0 | BY16: 13 | CG16: 1 | CH16: 1 | CI16: 0 | CJ16: 0 | CK16: 0 | CL16: 0
A17: act_cop_1.1Ado_d122_m091 | B17: active mobility | C17: Copenhagen | D17: 1.1 | E17: Adoption over time | F17: Modal share of all trips by residents (walk) | G17: % trips by walking | H17: b7 | I17: 0.0018687 | J17: 0.0010136 | K17: 0.00030769 | L17: 5039 | M17: 2351.6 | N17: 54.298 | O17: 1555.1 | P17: 157440 | Q17: -0.43046 | R17: 0.007873 | S17: =-inf -> #NAME? | T17: 0.038254 | U17: 0.031585 | V17: -23.203 | W17: -71.61 | X17: 0.18894 | Y17: 0.185 | Z17: 0.0070404 | AA17: -1.9789 | AB17: 0.03827 | AC17: 0.031692 | AD17: 4 | AE17: 4 | AF17: 0.0040517 | AG17: 0.00221 | AH17: 0.0018417 | AI17: 28 | AJ17: 3 | AK17: 2 | AL17: 0 | AM17: 1 | AN17: 0 | AO17: 0.63305 | AP17: 1 | AQ17: 1 | AR17: n | AS17: m | AT17: y | AU17: y | AV17: y | AW17: y | AX17: m | AY17: m | AZ17: m | BA17: n | BB17: m | BC17: n | BD17: m | BE17: 4 | BG17: ok, use logfit | BI17: 0 | BL17: 0 | BM17: 0 | BN17: 0 | BO17: 0 | BP17: 0 | BQ17: 0 | BS17: 1 | BT17: 1 | BU17: 0 | BV17: 0 | BW17: 0 | BX17: 0 | BY17: 14 | BZ17: check | CA17: check | CG17: 1 | CH17: 1 | CI17: 0 | CJ17: 0 | CK17: 0 | CL17: 0
A18: act_cop_1.1Ado_d332_m185 | B18: active mobility | C18: Copenhagen | D18: 1.1 | E18: Adoption over time | F18: % trips by walking and biking | G18: market share | H18: b7 | I18: 0.015233 | J18: 0.0013115 | K18: 0.0036752 | L18: 2016.9 | M18: 288.48 | N18: 1 | O18: 1555.2 | P18: 157440 | Q18: -6.9138 | R18: 0.36641 | S18: =-inf -> #NAME? | T18: 0.051084 | U18: 0.045033 | V18: -46.472 | W18: -141.42 | X18: 0.44218 | Y18: 0.4375 | Z18: 0.35971 | AA18: -0.92086 | AB18: 0.051353 | AC18: 0.045256 | AD18: 4 | AE18: 4 | AF18: 0.52 | AG18: 0.34 | AH18: 0.18 | AI18: 28 | AJ18: 0 | AK18: 2 | AL18: 0 | AM18: 1 | AN18: 0 | AO18: 0.6861 | AP18: 1 | AQ18: 1 | AR18: m | AS18: m | AT18: y | AU18: y | AV18: y | AW18: y | AX18: m | AY18: m | AZ18: y | BA18: m | BB18: m | BC18: m | BD18: m | BI18: 0 | BJ18: prefer-relative | BK18: transformed-marketshare | BL18: 1 | BM18: 1 | BN18: 0 | BO18: 1 | BP18: 0 | BQ18: 0 | BS18: 1 | BT18: 1 | BU18: 0 | BV18: 1 | BW18: 0 | BX18: 0 | BY18: 15 | CG18: 1 | CH18: 1 | CI18: 0 | CJ18: 1 | CK18: 0 | CL18: 0
A19: act_den_4.1Sal_d213_m100 | B19: active mobility | C19: Denmark | D19: 4.1 | E19: Knowledge Flows (social networks) | F19: annualised Google search frequency (index 100=monthly max.) | G19: Index 0-100 | H19: b7 | I19: 5.3821 | J19: 0.046164 | K19: 2.6871 | L19: 2011.1 | M19: 0.81649 | N19: 61.49 | O19: 1.3191 | P19: 1940.1 | Q19: -5371.1 | R19: 0.6915 | S19: 0.63706 | T19: 17.672 | U19: 13.516 | V19: 0.18602 | W19: 0.095577 | X19: 28.705 | Y19: 24.86 | Z19: 0.26155 | AA19: 0.1795 | AB19: 27.341 | AC19: 23.166 | AD19: 21 | AE19: 20 | AF19: 1.6263 | AG19: 0.0025937 | AH19: 1.6237 | AI19: 21 | AJ19: 9 | AK19: 16 | AL19: 1 | AM19: 1 | AN19: 1 | AO19: 0.94961 | AP19: 0 | AQ19: 1 | AR19: m | AS19: y | AT19: y | AU19: y | AV19: y | AW19: y | AX19: y | AY19: y | AZ19: m | BA19: m | BB19: m | BC19: m | BD19: m | BI19: 0 | BJ19: hide | BK19: original | BL19: 1 | BM19: 1 | BN19: 0 | BO19: 0 | BP19: 0 | BQ19: 0 | BS19: 1 | BT19: 0 | BU19: 0 | BV19: 0 | BW19: 0 | BX19: 0 | BY19: 16 | CA19: check | CG19: 1 | CH19: 1 | CI19: 0 | CJ19: 0 | CK19: 0 | CL19: 0
A20: act_den_4.1Sal_d239_m153 | B20: active mobility | C20: Denmark | D20: 4.1 | E20: Knowledge Flows (social networks) | F20: Partial up to max annualised Google search frequency (index 100=monthly max.) | G20: Partial up to max Index 0-100 | H20: b7 | I20: 1.43 | J20: 0.31327 | K20: 9.5766 | L20: 2011.7 | M20: 3.073 | N20: 98.11 | O20: 0.0079377 | P20: 1984.4 | Q20: -19211 | R20: 0.987 | S20: 0.98212 | T20: 4.3211 | U20: 3.2716 | V20: 0.89193 | W20: 0.86791 | X20: 12.458 | Y20: 10.933 | Z20: 0.76106 | AA20: 0.70796 | AB20: 18.524 | AC20: 16.71 | AD20: 12 | AE20: 11 | AF20: 1.0193 | AG20: 0.0016256 | AH20: 1.0176 | AI20: 12 | AJ20: 0 | AK20: 7 | AL20: 0 | AM20: 1 | AN20: 1 | AO20: 0.79251 | AP20: 0 | AQ20: 1 | AR20: y | AS20: y | AT20: y | AU20: y | AV20: y | AW20: y | AX20: y | AY20: y | AZ20: y | BA20: y | BB20: y | BC20: y | BD20: y | BI20: 0 | BJ20: prefer | BK20: transformed-partial | BL20: 1 | BM20: 1 | BN20: 0 | BO20: 0 | BP20: 0 | BQ20: 1 | BS20: 1 | BT20: 1 | BU20: 0 | BV20: 0 | BW20: 0 | BX20: 1 | BY20: 17 | CG20: 1 | CH20: 1 | CI20: 0 | CJ20: 0 | CK20: 0 | CL20: 1
A21: act_glo_3.3Sci_d235_m020 | B21: active mobility | C21: Global | D21: 3.3 | E21: Risk & Uncertainty (Shared Expectations) | F21: scientific publications | G21: # publications | H21: b7 | I21: 0.098082 | J21: 0.075253 | K21: 339.27 | L21: 2026.2 | M21: 44.804 | N21: 47724 | O21: 0.0059608 | P21: 1822.8 | Q21: -672090 | R21: 0.98746 | S21: 0.98672 | T21: 674.84 | U21: 429.14 | V21: 0.98322 | W21: 0.98257 | X21: 780.65 | Y21: 440.85 | Z21: 0.79877 | AA21: 0.79103 | AB21: 2703.1 | AC21: 2313.6 | AD21: 55 | AE21: 55 | AF21: 0.43486 | AG21: 0.0017811 | AH21: 0.43307 | AI21: 55 | AJ21: 2 | AK21: 54 | AL21: 0 | AM21: 0 | AN21: 1 | AO21: 0.95068 | AP21: 0 | AQ21: 0 | AR21: y | AS21: y | AT21: y | AU21: y | AV21: y | AW21: y | AX21: y | AY21: y | AZ21: y | BA21: y | BB21: y | BC21: y | BD21: y | BH21: good; only available global, apply to all EA regions | BI21: 0 | BL21: 1 | BM21: 1 | BN21: 0 | BO21: 0 | BP21: 1 | BQ21: 1 | BS21: 1 | BT21: 1 | BU21: 0 | BV21: 0 | BW21: 1 | BX21: 1 | BY21: 18 | CG21: 1 | CH21: 1 | CI21: 0 | CJ21: 0 | CK21: 1 | CL21: 1
A22: act_net_1.1Ado_d167_m096 | B22: active mobility | C22: The Netherlands | D22: 1.1 | E22: Adoption over time | F22: Passenger kilometres travelled by¬†bike | G22: Billion p.km | H22: b7 | I22: 0.17814 | J22: 0.013226 | K22: 0.21626 | L22: 1998.6 | M22: 24.668 | N22: 17.492 | O22: 6.6659 | P22: 1947.9 | Q22: -419.53 | R22: 0.71531 | S22: 0.64961 | T22: 0.77647 | U22: 0.65529 | V22: 0.60366 | W22: 0.54704 | X22: 0.91615 | Y22: 0.789 | Z22: 0.62081 | AA22: 0.56664 | AB22: 0.89611 | AC22: 0.75497 | AD22: 17 | AE22: 17 | AF22: 1.0233 | AG22: 0.79466 | AH22: 0.22868 | AI22: 18 | AJ22: 0 | AK22: 16 | AL22: 0 | AM22: 0 | AN22: 0 | AO22: 0.93926 | AP22: 0 | AQ22: 1 | AR22: y | AS22: y | AT22: y | AU22: y | AV22: y | AW22: y | AX22: y | AY22: y | AZ22: y | BA22: y | BB22: y | BC22: y | BD22: y | BE22: 1 | BI22: 0 | BJ22: prefer-absolute | BL22: 1 | BM22: 1 | BN22: 2 | BO22: 2 | BP22: 0 | BQ22: 0 | BS22: 1 | BT22: 1 | BU22: 0 | BV22: 0 | BW22: 0 | BX22: 0 | BY22: 19 | CG22: 1 | CH22: 1 | CI22: 0 | CJ22: 0 | CK22: 0 | CL22: 0
A23: act_net_1.1Ado_d168_m096 | B23: active mobility | C23: The Netherlands | D23: 1.1 | E23: Adoption over time | F23: Passenger kilometres travelled by¬†foot | G23: Billion p.km | H23: b7 | I23: 0.046231 | J23: 0.04623 | K23: 0.21548 | L23: 2244.5 | M23: 95.054 | N23: 206610 | O23: 7.9825 | P23: 2024.7 | Q23: -428.98 | R23: 0.82968 | S23: 0.79038 | T23: 0.52885 | U23: 0.38906 | V23: 0.82968 | W23: 0.80535 | X23: 0.52885 | Y23: 0.38906 | Z23: 0.7949 | AA23: 0.7656 | AB23: 0.58034 | AC23: 0.44108 | AD23: 17 | AE23: 17 | AF23: 3.9204e-05 | AG23: 1.6456e-05 | AH23: 2.2748e-05 | AI23: 18 | AJ23: 1 | AK23: 16 | AL23: 0 | AM23: 0 | AN23: 0 | AO23: 0.92009 | AP23: 0 | AQ23: 1 | AR23: y | AS23: y | AT23: y | AU23: y | AV23: y | AW23: y | AX23: y | AY23: m | AZ23: y | BA23: m | BB23: y | BC23: m | BD23: y | BE23: 2 | BI23: 0 | BL23: 1 | BM23: 1 | BN23: 0 | BO23: 0 | BP23: 0 | BQ23: 0 | BS23: 1 | BT23: 1 | BU23: 0 | BV23: 0 | BW23: 0 | BX23: 0 | BY23: 20 | CG23: 1 | CH23: 1 | CI23: 0 | CJ23: 0 | CK23: 0 | CL23: 0
A24: act_net_1.1Ado_d332_m185 | B24: active mobility | C24: The Netherlands | D24: 1.1 | E24: Adoption over time | F24: % trips by walking and biking | G24: market share | H24: b7 | I24: 0.070443 | J24: 0.026144 | K24: 0.0035545 | L24: 2006.4 | M24: 62.383 | N24: 0.21832 | O24: 0.00085118 | P24: 1820 | Q24: -7.0219 | R24: 0.97061 | S24: 0.96383 | T24: 0.0032828 | U24: 0.0025168 | V24: 0.96078 | W24: 0.95518 | X24: 0.0037921 | Y24: 0.0030679 | Z24: 0.96855 | AA24: 0.96406 | AB24: 0.0033959 | AC24: 0.0025786 | AD24: 17 | AE24: 17 | AF24: 0.7503 | AG24: 0.49115 | AH24: 0.25914 | AI24: 18 | AJ24: 0 | AK24: 16 | AL24: 0 | AM24: 0 | AN24: 0 | AO24: 0.93891 | AP24: 1 | AQ24: 1 | AR24: y | AS24: y | AT24: y | AU24: y | AV24: y | AW24: y | AX24: y | AY24: y | AZ24: y | BA24: y | BB24: y | BC24: y | BD24: y | BI24: 0 | BJ24: prefer-relative | BK24: transformed-marketshare | BL24: 1 | BM24: 1 | BN24: 1 | BO24: 1 | BP24: 0 | BQ24: 0 | BS24: 1 | BT24: 1 | BU24: 1 | BV24: 1 | BW24: 0 | BX24: 0 | BY24: 21 | CG24: 1 | CH24: 1 | CI24: 1 | CJ24: 1 | CK24: 0 | CL24: 0
A25: act_net_2.9Int_d133_m139 | B25: active mobility | C25: The Netherlands | D25: 2.9 | E25: Interdependence with hardware | F25: Number of bicycles | G25: million | H25: b7 | I25: 0.049239 | J25: 0.016526 | K25: 0.34781 | L25: 1998.8 | M25: 89.248 | N25: 31.855 | O25: 5.1298 | P25: 1927.5 | Q25: -678.94 | R25: 0.87013 | S25: 0.84416 | T25: 0.79224 | U25: 0.66204 | V25: 0.85896 | W25: 0.84133 | X25: 0.82561 | Y25: 0.71719 | Z25: 0.86573 | AA25: 0.84894 | AB25: 0.80556 | AC25: 0.69208 | AD25: 19 | AE25: 19 | AF25: 0.75026 | AG25: 0.55877 | AH25: 0.19149 | AI25: 23 | AJ25: 0 | AK25: 18 | AL25: 0 | AM25: 0 | AN25: 0 | AO25: 0.94783 | AP25: 0 | AQ25: 1 | AR25: y | AS25: y | AT25: y | AU25: y | AV25: y | AW25: y | AX25: y | AY25: m | AZ25: y | BA25: m | BB25: y | BC25: m | BD25: y | BE25: 4 | BG25: ok, use logfit | BI25: 0 | BL25: 1 | BM25: 1 | BS25: 1 | BT25: 1 | BU25: 0 | BV25: 0 | BW25: 1 | BX25: 1 | BY25: 22 | CG25: 1 | CH25: 1 | CI25: 0 | CJ25: 0 | CK25: 1 | CL25: 1
A26: act_net_4.1Sal_d213_m100 | B26: active mobility | C26: The Netherlands | D26: 4.1 | E26: Knowledge Flows (social networks) | F26: annualised Google search frequency (index 100=monthly max.) | G26: Index 0-100 | H26: b7 | I26: 3.0888 | J26: 0.038321 | K26: 1.8942 | L26: 2011.4 | M26: 1.4227 | N26: 51.304 | O26: 2.0418 | P26: 1941 | Q26: -3780.9 | R26: 0.52841 | S26: 0.44519 | T26: 19.881 | U26: 15.557 | V26: 0.10943 | W26: 0.010474 | X26: 27.321 | Y26: 22.73 | Z26: 0.15696 | AA26: 0.063294 | AB26: 26.582 | AC26: 21.903 | AD26: 21 | AE26: 20 | AF26: 1.9492 | AG26: 0.061706 | AH26: 1.8875 | AI26: 21 | AJ26: 8 | AK26: 17 | AL26: 1 | AM26: 1 | AN26: 1 | AO26: 0.93508 | AP26: 0 | AQ26: 1 | AR26: m | AS26: y | AT26: y | AU26: y | AV26: y | AW26: y | AX26: y | AY26: y | AZ26: m | BA26: m | BB26: m | BC26: m | BD26: m | BI26: 0 | BJ26: hide | BK26: original | BL26: 1 | BM26: 1 | BN26: 0 | BO26: 0 | BP26: 0 | BQ26: 0 | BS26: 1 | BT26: 0 | BU26: 0 | BV26: 0 | BW26: 0 | BX26: 0 | BY26: 23 | CA26: check | CG26: 1 | CH26: 1 | CI26: 0 | CJ26: 0 | CK26: 0 | CL26: 0
A27: act_net_4.1Sal_d239_m153 | B27: active mobility | C27: The Netherlands | D27: 4.1 | E27: Knowledge Flows (social networks) | F27: Partial up to max annualised Google search frequency (index 100=monthly max.) | G27: Partial up to max Index 0-100 | H27: b7 | I27: 1.1394 | J27: 0.28364 | K27: 8.1967 | L27: 2012.4 | M27: 3.8569 | N27: 96.414 | O27: 0.012954 | P27: 1984 | Q27: -16442 | R27: 0.96663 | S27: 0.95551 | T27: 6.5285 | U27: 5.043 | V27: 0.89473 | W27: 0.87368 | X27: 11.596 | Y27: 10.341 | Z27: 0.73634 | AA27: 0.68361 | AB27: 18.352 | AC27: 16.877 | AD27: 13 | AE27: 12 | AF27: 1.0372 | AG27: 0.032835 | AH27: 1.0044 | AI27: 13 | AJ27: 0 | AK27: 9 | AL27: 0 | AM27: 1 | AN27: 1 | AO27: 0.80207 | AP27: 0 | AQ27: 1 | AR27: y | AS27: y | AT27: y | AU27: m | AV27: y | AW27: m | AX27: y | AY27: y | AZ27: y | BA27: m | BB27: m | BC27: m | BD27: m | BI27: 0 | BJ27: prefer | BK27: transformed-partial | BL27: 1 | BM27: 1 | BN27: 0 | BO27: 0 | BP27: 1 | BQ27: 1 | BS27: 1 | BT27: 1 | BU27: 0 | BV27: 0 | BW27: 1 | BX27: 1 | BY27: 24 | CG27: 1 | CH27: 1 | CI27: 0 | CJ27: 0 | CK27: 1 | CL27: 1
A28: coh_den_1.1Ado_d134_m007 | B28: co-housing | C28: Denmark | D28: 1.1 | E28: Adoption over time | F28: Number of cohousing communities | G28: # communities | H28: b11 | I28: 0.22051 | J28: 0.033741 | K28: 2.6225 | L28: 1984.9 | M28: 19.929 | N28: 101.42 | O28: 1.6723 | P28: 1886.7 | Q28: -5160.5 | R28: 0.98488 | S28: 0.97731 | T28: 4.8001 | U28: 4.2608 | V28: 0.78505 | W28: 0.72364 | X28: 18.096 | Y28: 15.686 | Z28: 0.91844 | AA28: 0.89514 | AB28: 11.147 | AC28: 9.6045 | AD28: 10 | AE28: 10 | AF28: 1.0846 | AG28: 0.0098597 | AH28: 1.0747 | AI28: 45 | AJ28: 0 | AK28: 9 | AL28: 0 | AM28: 0 | AN28: 1 | AO28: 0.87616 | AP28: 0 | AQ28: 0 | AR28: y | AS28: y | AT28: y | AU28: y | AV28: y | AW28: y | AX28: y | AY28: y | AZ28: y | BA28: y | BB28: y | BC28: y | BD28: y | BE28: 1 | BI28: 0 | BJ28: prefer-absolute | BL28: 1 | BM28: 1 | BN28: 2 | BO28: 2 | BP28: 0 | BQ28: 0 | BS28: 1 | BT28: 1 | BU28: 0 | BV28: 0 | BW28: 0 | BX28: 0 | BY28: 73 | CG28: 1 | CH28: 1 | CI28: 0 | CJ28: 0 | CK28: 0 | CL28: 0
A29: coh_den_1.1Ado_d138_m021 | B29: co-housing | C29: Denmark | D29: 1.1 | E29: Adoption over time | F29: Number of housing units in cohousing communities | G29: # residents | H29: b11 | I29: 0.21247 | J29: 0.033852 | K29: 58.453 | L29: 1985.3 | M29: 20.683 | N29: 2285.2 | O29: 0.12287 | P29: 1718.9 | Q29: -115030 | R29: 0.98448 | S29: 0.97517 | T29: 109.66 | U29: 101.47 | V29: 0.77105 | W29: 0.69473 | X29: 421.16 | Y29: 375.09 | Z29: 0.91189 | AA29: 0.88252 | AB29: 261.27 | AC29: 233.12 | AD29: 9 | AE29: 9 | AF29: 1.0542 | AG29: 0.028881 | AH29: 1.0253 | AI29: 45 | AJ29: 0 | AK29: 8 | AL29: 0 | AM29: 0 | AN29: 1 | AO29: 0.85327 | AP29: 0 | AQ29: 0 | AR29: y | AS29: y | AT29: y | AU29: y | AV29: y | AW29: y | AX29: y | AY29: y | AZ29: y | BA29: y | BB29: y | BC29: y | BD29: y | BE29: 1 | BI29: 0 | BL29: 1 | BM29: 1 | BN29: 0 | BO29: 0 | BP29: 0 | BQ29: 0 | BS29: 1 | BT29: 1 | BU29: 0 | BV29: 0 | BW29: 0 | BX29: 0 | BY29: 74 | CG29: 1 | CH29: 1 | CI29: 0 | CJ29: 0 | CK29: 0 | CL29: 0
A30: coh_den_1.1Ado_d335_m185 | B30: co-housing | C30: Denmark | D30: 1.1 | E30: Adoption over time | F30: share of population living in co-housing projects | G30: market share | H30: b11 | I30: 0.25973 | J30: 0.031685 | K30: 1.0356e-05 | L30: 1984.1 | M30: 16.92 | N30: 0.00040635 | O30: 1.8796 | P30: 2274.9 | Q30: -0.020368 | R30: 0.99084 | S30: 0.98534 | T30: 1.5266e-05 | U30: 1.3086e-05 | V30: 0.72319 | W30: 0.63091 | X30: 8.3923e-05 | Y30: 7.457e-05 | Z30: 0.87159 | AA30: 0.82879 | AB30: 5.7159e-05 | AC30: 5.155e-05 | AD30: 9 | AE30: 9 | AF30: 1.0464 | AG30: 0.032726 | AH30: 1.0137 | AI30: 45 | AJ30: 1 | AK30: 8 | AL30: 1 | AM30: 0 | AN30: 1 | AO30: 0.86448 | AP30: 1 | AQ30: 1 | AR30: y | AS30: y | AT30: y | AU30: y | AV30: y | AW30: y | AX30: y | AY30: y | AZ30: y | BA30: y | BB30: y | BC30: y | BD30: y | BI30: 0 | BJ30: prefer-relative | BK30: transformed-marketshare | BL30: 1 | BM30: 1 | BN30: 1 | BO30: 1 | BP30: 0 | BQ30: 0 | BS30: 1 | BT30: 1 | BU30: 1 | BV30: 1 | BW30: 0 | BX30: 0 | BY30: 75 | CG30: 1 | CH30: 1 | CI30: 1 | CJ30: 1 | CK30: 0 | CL30: 0
A31: coh_den_4.1Sal_d213_m100 | B31: co-housing | C31: Denmark | D31: 4.1 | E31: Knowledge Flows (social networks) | F31: annualised Google search frequency (index 100=monthly max.) | G31: Index 0-100 | H31: b11 | I31: 6.5072 | J31: -0.25292 | K31: -1.3766 | L31: 2028.4 | M31: 0.67532 | N31: 0.71605 | O31: 13.116 | P31: 2007.9 | Q31: 2779.4 | R31: -0.098235 | S31: -0.29204 | T31: 23.087 | U31: 6.9048 | V31: 0.20154 | W31: 0.11282 | X31: 19.685 | Y31: 10.513 | Z31: 0.14318 | AA31: 0.047973 | AB31: 20.392 | AC31: 11.958 | AD31: 21 | AE31: 3 | AF31: 139.65 | AG31: 18.155 | AH31: 121.5 | AI31: 10 | AJ31: 9 | AK31: 0 | AL31: 0 | AM31: 0 | AN31: 1 | AO31: 0 | AP31: 0 | AQ31: 1 | AR31: n | AS31: n | AT31: y | AU31: m | AV31: m | AW31: m | AX31: m | AY31: y | AZ31: m | BA31: n | BB31: n | BC31: n | BD31: n | BH31: too few | BI31: 0 | BJ31: hide | BK31: original | BL31: 0 | BM31: 0 | BN31: 0 | BO31: 0 | BP31: 0 | BQ31: 0 | BS31: 0 | BT31: 1 | BU31: 0 | BV31: 0 | BW31: 0 | BX31: 0 | BY31: 76 | CA31: check | CG31: 0 | CH31: 1 | CI31: 0 | CJ31: 0 | CK31: 0 | CL31: 0
A32: coh_den_4.1Sal_d239_m153 | B32: co-housing | C32: Denmark | D32: 4.1 | E32: Knowledge Flows (social networks) | F32: Partial up to max annualised Google search frequency (index 100=monthly max.) | G32: Partial up to max Index 0-100 | H32: b11 | K32: 100 | Q32: -200400 | Z32: 1 | AA32: 1 | AB32: 0 | AC32: 0 | AD32: 2 | AE32: 1 | AI32: 1 | AJ32: 0 | AK32: 0 | AL32: 0 | AM32: 0 | AP32: 0 | AQ32: 1 | AR32: n | AS32: n | AT32: y | AU32: m | AV32: m | AW32: m | AX32: m | AY32: m | AZ32: y | BA32: n | BB32: n | BC32: n | BD32: n | BH32: too few | BI32: 0 | BJ32: prefer | BK32: transformed-partial | BL32: 0 | BM32: 0 | BN32: 0 | BO32: 0 | BP32: 1 | BQ32: 1 | BS32: 0 | BT32: 0 | BU32: 0 | BV32: 0 | BW32: 1 | BX32: 1 | BY32: 77 | CG32: 0 | CH32: 0 | CI32: 0 | CJ32: 0 | CK32: 1 | CL32: 1
A33: coh_ger_1.1Ado_d141_m018 | B33: co-housing | C33: Germany | D33: 1.1 | E33: Adoption over time | F33: Number of projects | G33: # projects | H33: b11 | I33: 0.20463 | J33: 0.079755 | K33: 9.41 | L33: 1994.8 | M33: 21.475 | N33: 316.23 | O33: 0.013744 | P33: 1880.2 | Q33: -18604 | R33: 0.99968 | S33: =-inf -> #NAME? | T33: 1.9287 | U33: 1.3164 | V33: 0.96104 | W33: 0.88313 | X33: 21.387 | Y33: 19.667 | Z33: 0.94267 | AA33: 0.828 | AB33: 25.946 | AC33: 23.25 | AD33: 4 | AE33: 4 | AF33: 0.88859 | AG33: 0.02846 | AH33: 0.86013 | AI33: 31 | AJ33: 0 | AK33: 3 | AL33: 0 | AM33: 0 | AN33: 1 | AO33: 0.48336 | AP33: 0 | AQ33: 0 | AR33: y | AS33: m | AT33: y | AU33: m | AV33: y | AW33: m | AX33: m | AY33: y | AZ33: y | BA33: m | BB33: m | BC33: m | BD33: m | BE33: 1 | BI33: 0 | BL33: 1 | BM33: 1 | BN33: 0 | BO33: 2 | BP33: 0 | BQ33: 0 | BS33: 1 | BT33: 1 | BU33: 0 | BV33: 0 | BW33: 0 | BX33: 0 | BY33: 78 | CG33: 1 | CH33: 1 | CI33: 0 | CJ33: 0 | CK33: 0 | CL33: 0
A34: coh_ger_1.1Ado_d335_m185 | B34: co-housing | C34: Germany | D34: 1.1 | E34: Adoption over time | F34: share of population living in co-housing projects | G34: market share | H34: b11 | I34: 0.1981 | J34: 0.07911 | K34: 2.5151e-06 | L34: 1994.9 | M34: 22.183 | N34: 8.5627e-05 | O34: 45.292 | P34: 2172.9 | Q34: -0.0049722 | R34: 0.99973 | S34: =-inf -> #NAME? | T34: 4.7946e-07 | U34: 3.3323e-07 | V34: 0.96275 | W34: 0.88824 | X34: 5.5835e-06 | Y34: 5.1451e-06 | Z34: 0.94488 | AA34: 0.83465 | AB34: 6.7913e-06 | AC34: 6.1267e-06 | AD34: 4 | AE34: 4 | AF34: 0.87995 | AG34: 0.029381 | AH34: 0.85056 | AI34: 31 | AJ34: 0 | AK34: 3 | AL34: 0 | AM34: 0 | AN34: 1 | AO34: 0.48598 | AP34: 1 | AQ34: 1 | AR34: y | AS34: m | AT34: y | AU34: m | AV34: y | AW34: m | AX34: m | AY34: y | AZ34: y | BA34: m | BB34: m | BC34: m | BD34: m | BI34: 0 | BJ34: prefer-relative | BK34: transformed-marketshare | BL34: 1 | BM34: 1 | BN34: 0 | BO34: 1 | BP34: 0 | BQ34: 0 | BS34: 1 | BT34: 1 | BU34: 0 | BV34: 1 | BW34: 0 | BX34: 0 | BY34: 79 | CG34: 1 | CH34: 1 | CI34: 0 | CJ34: 1 | CK34: 0 | CL34: 0
A35: coh_ger_4.1Sal_d213_m100 | B35: co-housing | C35: Germany | D35: 4.1 | E35: Knowledge Flows (social networks) | F35: annualised Google search frequency (index 100=monthly max.) | G35: Index 0-100 | H35: b11 | I35: 8.4815 | J35: 0.081366 | K35: 3.1097 | L35: 2015.8 | M35: 0.51812 | N35: 60.75 | O35: 0.69242 | P35: 1968.7 | Q35: -6233.1 | R35: 0.56835 | S35: 0.49218 | T35: 21.829 | U35: 13.407 | V35: 0.26817 | W35: 0.18686 | X35: 28.423 | Y35: 24.248 | Z35: 0.32122 | AA35: 0.2458 | AB35: 27.373 | AC35: 22.15 | AD35: 21 | AE35: 13 | AF35: 1.6461 | AG35: 0.13169 | AH35: 1.5144 | AI35: 20 | AJ35: 4 | AK35: 13 | AL35: 1 | AM35: 1 | AN35: 1 | AO35: 0.85774 | AP35: 0 | AQ35: 1 | AR35: m | AS35: y | AT35: y | AU35: m | AV35: m | AW35: m | AX35: y | AY35: y | AZ35: y | BA35: m | BB35: m | BC35: m | BD35: m | BI35: 0 | BJ35: hide | BK35: original | BL35: 1 | BM35: 1 | BN35: 0 | BO35: 0 | BP35: 0 | BQ35: 0 | BS35: 0 | BT35: 1 | BU35: 0 | BV35: 0 | BW35: 0 | BX35: 0 | BY35: 80 | BZ35: check | CG35: 1 | CH35: 1 | CI35: 0 | CJ35: 0 | CK35: 0 | CL35: 0
A36: coh_ger_4.1Sal_d239_m153 | B36: co-housing | C36: Germany | D36: 4.1 | E36: Knowledge Flows (social networks) | F36: Partial up to max annualised Google search frequency (index 100=monthly max.) | G36: Partial up to max Index 0-100 | H36: b11 | I36: 0.77819 | J36: 0.27791 | K36: 5.2206 | L36: 2016.8 | M36: 5.647 | N36: 110.18 | O36: 0.027512 | P36: 1990 | Q36: -10476 | R36: 0.84239 | S36: 0.80602 | T36: 14.005 | U36: 7.0254 | V36: 0.80701 | W36: 0.77943 | X36: 15.498 | Y36: 10.367 | Z36: 0.52561 | AA36: 0.45784 | AB36: 24.298 | AC36: 19.026 | AD36: 17 | AE36: 9 | AF36: 0.9076 | AG36: 0.072608 | AH36: 0.83499 | AI36: 16 | AJ36: 0 | AK36: 9 | AL36: 0 | AM36: 1 | AN36: 1 | AO36: 0.72215 | AP36: 0 | AQ36: 1 | AR36: y | AS36: y | AT36: y | AU36: m | AV36: m | AW36: m | AX36: y | AY36: y | AZ36: y | BA36: m | BB36: m | BC36: m | BD36: m | BI36: 0 | BJ36: prefer | BK36: transformed-partial | BL36: 1 | BM36: 1 | BN36: 0 | BO36: 0 | BP36: 0 | BQ36: 1 | BS36: 1 | BT36: 1 | BU36: 0 | BV36: 0 | BW36: 0 | BX36: 1 | BY36: 81 | CG36: 1 | CH36: 1 | CI36: 0 | CJ36: 0 | CK36: 0 | CL36: 1
A37: coh_glo_3.3Sci_d235_m020 | B37: co-housing | C37: Global | D37: 3.3 | E37: Risk & Uncertainty (Shared Expectations) | F37: scientific publications | G37: # publications | H37: b11 | I37: 0.27252 | J37: 0.11544 | K37: 1.9577 | L37: 2017.1 | M37: 16.125 | N37: 163.28 | O37: 0.52109 | P37: 1974.5 | Q37: -3883.9 | R37: 0.93237 | S37: 0.92839 | T37: 10.683 | U37: 6.5047 | V37: 0.90593 | W37: 0.90231 | X37: 12.599 | Y37: 6.3893 | Z37: 0.57237 | AA37: 0.55592 | AB37: 26.862 | AC37: 21.259 | AD37: 55 | AE37: 45 | AF37: 0.98606 | AG37: 0.0061246 | AH37: 0.97994 | AI37: 48 | AJ37: 4 | AK37: 46 | AL37: 0 | AM37: 0 | AN37: 1 | AO37: 0.92044 | AP37: 0 | AQ37: 0 | AR37: y | AS37: y | AT37: y | AU37: y | AV37: y | AW37: y | AX37: y | AY37: y | AZ37: y | BA37: y | BB37: y | BC37: y | BD37: y | BH37: good; only available global, apply to all EA regions | BI37: 0 | BL37: 1 | BM37: 1 | BN37: 0 | BO37: 0 | BP37: 1 | BQ37: 1 | BS37: 1 | BT37: 1 | BU37: 0 | BV37: 0 | BW37: 1 | BX37: 1 | BY37: 82 | CG37: 1 | CH37: 1 | CI37: 0 | CJ37: 0 | CK37: 1 | CL37: 1
A38: coh_swi_4.1Sal_d213_m100 | B38: co-housing | C38: Switzerland | D38: 4.1 | E38: Knowledge Flows (social networks) | F38: annualised Google search frequency (index 100=monthly max.) | G38: Index 0-100 | H38: b11 | I38: 0.041952 | J38: 0.041932 | K38: 0.3 | L38: 2189.7 | M38: 104.75 | N38: 11625 | O38: 10.708 | P38: 2023.1 | Q38: -596.63 | R38: 0.0057694 | S38: -0.16968 | T38: 24.109 | U38: 13.495 | V38: 0.0057701 | W38: -0.1047 | X38: 24.109 | Y38: 13.495 | Z38: 0.0056446 | AA38: -0.10484 | AB38: 24.111 | AC38: 13.529 | AD38: 21 | AE38: 2 | AF38: 0.0086024 | AG38: 0.0050754 | AH38: 0.003527 | AI38: 13 | AJ38: 12 | AK38: 0 | AL38: 0 | AM38: 0 | AN38: 1 | AO38: 0 | AP38: 0 | AQ38: 1 | AR38: n | AS38: m | AT38: m | AU38: m | AV38: m | AW38: m | AX38: m | AY38: m | AZ38: m | BA38: n | BB38: m | BC38: n | BD38: m | BH38: too few | BI38: 0 | BJ38: hide | BK38: original | BL38: 0 | BM38: 0 | BN38: 0 | BO38: 0 | BP38: 0 | BQ38: 0 | BS38: 0 | BT38: 0 | BU38: 0 | BV38: 0 | BW38: 0 | BX38: 0 | BY38: 83 | CG38: 1 | CH38: 0 | CI38: 0 | CJ38: 0 | CK38: 0 | CL38: 0
A39: coh_swi_4.1Sal_d239_m153 | B39: co-housing | C39: Switzerland | D39: 4.1 | E39: Knowledge Flows (social networks) | F39: Partial up to max annualised Google search frequency (index 100=monthly max.) | G39: Partial up to max Index 0-100 | H39: b11 | I39: 22.563 | K39: 8.3333 | L39: 2011 | M39: 0.19477 | N39: 276.15 | Q39: -16717 | R39: 1 | S39: 1 | T39: 1.1648e-08 | U39: 5.809e-09 | Z39: 0.33333 | AA39: 0.066667 | AB39: 27.003 | AC39: 20.833 | AD39: 8 | AE39: 1 | AF39: 0.36213 | AG39: 0.36213 | AH39: 0 | AI39: 1 | AJ39: 0 | AK39: 0 | AL39: 0 | AM39: 0 | AP39: 0 | AQ39: 1 | AR39: y | AS39: n | AT39: y | AU39: m | AV39: m | AW39: m | AX39: m | AY39: m | AZ39: y | BA39: n | BB39: n | BC39: n | BD39: n | BH39: too few | BI39: 0 | BJ39: prefer | BK39: transformed-partial | BL39: 0 | BM39: 0 | BN39: 0 | BO39: 0 | BP39: 0 | BQ39: 1 | BS39: 0 | BT39: 0 | BU39: 0 | BV39: 0 | BW39: 0 | BX39: 1 | BY39: 84 | CG39: 0 | CH39: 0 | CI39: 0 | CJ39: 0 | CK39: 0 | CL39: 1
A40: coh_usa_1.1Ado_d142_m021 | B40: co-housing | C40: US | D40: 1.1 | E40: Adoption over time | F40: Number of residents living in cohousing communities | G40: # residents | H40: b11 | I40: 0.47637 | J40: 0.21446 | K40: 213.23 | L40: 1996.4 | M40: 9.2249 | N40: 3414.8 | O40: 2.1402e-05 | P40: 1912.4 | Q40: -423940 | R40: 0.99947 | S40: 0.99907 | T40: 23.805 | U40: 21.643 | V40: 0.96347 | W40: 0.94886 | X40: 197.86 | Y40: 179.86 | Z40: 0.89095 | AA40: 0.84734 | AB40: 341.85 | AC40: 309.88 | AD40: 8 | AE40: 8 | AF40: 0.85099 | AG40: 0.015521 | AH40: 0.83547 | AI40: 15 | AJ40: 0 | AK40: 7 | AL40: 0 | AM40: 0 | AN40: 1 | AO40: 0.70294 | AP40: 0 | AQ40: 0 | AR40: y | AS40: y | AT40: y | AU40: y | AV40: y | AW40: y | AX40: y | AY40: y | AZ40: y | BA40: y | BB40: y | BC40: y | BD40: y | BI40: 0 | BL40: 1 | BM40: 1 | BN40: 0 | BO40: 2 | BP40: 0 | BQ40: 0 | BS40: 1 | BT40: 1 | BU40: 0 | BV40: 0 | BW40: 0 | BX40: 0 | BY40: 85 | CG40: 1 | CH40: 1 | CI40: 0 | CJ40: 0 | CK40: 0 | CL40: 0
A41: coh_usa_1.1Ado_d335_m185 | B41: co-housing | C41: US | D41: 1.1 | E41: Adoption over time | F41: share of population living in co-housing projects | G41: market share | H41: b11 | I41: 0.49151 | J41: 0.20545 | K41: 7.706e-07 | L41: 1996 | M41: 8.9407 | N41: 1.1765e-05 | O41: 116.5 | P41: 2078.7 | Q41: -0.001532 | R41: 0.99944 | S41: 0.99901 | T41: 8.832e-08 | U41: 6.1584e-08 | V41: 0.95555 | W41: 0.93777 | X41: 7.8484e-07 | Y41: 7.0786e-07 | Z41: 0.89991 | AA41: 0.85987 | AB41: 1.1777e-06 | AC41: 1.0571e-06 | AD41: 8 | AE41: 8 | AF41: 0.87772 | AG41: 0.018684 | AH41: 0.85904 | AI41: 15 | AJ41: 0 | AK41: 7 | AL41: 0 | AM41: 0 | AN41: 1 | AO41: 0.71861 | AP41: 1 | AQ41: 1 | AR41: y | AS41: y | AT41: y | AU41: y | AV41: y | AW41: y | AX41: y | AY41: y | AZ41: y | BA41: y | BB41: y | BC41: m | BD41: y | BI41: 0 | BJ41: prefer-relative | BK41: transformed-marketshare | BL41: 1 | BM41: 1 | BN41: 0 | BO41: 1 | BP41: 0 | BQ41: 0 | BS41: 1 | BT41: 1 | BU41: 0 | BV41: 1 | BW41: 0 | BX41: 0 | BY41: 86 | CG41: 1 | CH41: 1 | CI41: 0 | CJ41: 1 | CK41: 0 | CL41: 0
A42: coh_usa_4.1Sal_d213_m100 | B42: co-housing | C42: US | D42: 4.1 | E42: Knowledge Flows (social networks) | F42: annualised Google search frequency (index 100=monthly max.) | G42: Index 0-100 | H42: b11 | I42: -0.33502 | J42: -0.18979 | K42: -4.687 | L42: 2006.7 | M42: -13.117 | N42: 148.14 | O42: 48.198 | P42: 2008.5 | Q42: 9469.7 | R42: 0.97488 | S42: 0.97045 | T42: 5.1376 | U42: 4.3268 | V42: 0.96038 | W42: 0.95597 | X42: 6.453 | Y42: 4.7975 | Z42: 0.76644 | AA42: 0.74048 | AB42: 15.667 | AC42: 13.556 | AD42: 21 | AE42: 20 | AF42: 0.67501 | AG42: 0.014553 | AH42: 0.66046 | AI42: 21 | AJ42: 20 | AK42: 4 | AL42: 0 | AM42: 1 | AN42: 1 | AO42: 0.86068 | AP42: 0 | AQ42: 1 | AR42: y | AS42: y | AT42: y | AU42: m | AV42: m | AW42: m | AX42: y | AY42: y | AZ42: y | BA42: m | BB42: m | BC42: m | BD42: m | BH42: downward | BI42: 0 | BJ42: hide | BK42: original | BL42: 1 | BM42: 1 | BN42: 0 | BO42: 0 | BP42: 0 | BQ42: 0 | BS42: 1 | BT42: 1 | BU42: 0 | BV42: 0 | BW42: 0 | BX42: 0 | BY42: 87 | CG42: 1 | CH42: 1 | CI42: 0 | CJ42: 0 | CK42: 0 | CL42: 0
A43: coh_usa_4.1Sal_d239_m153 | B43: co-housing | C43: US | D43: 4.1 | E43: Knowledge Flows (social networks) | F43: Partial up to max annualised Google search frequency (index 100=monthly max.) | G43: Partial up to max Index 0-100 | H43: b11 | AD43: 1 | AE43: 1 | AI43: 1 | AJ43: 0 | AK43: 0 | AL43: 0 | AM43: 0 | AP43: 0 | AQ43: 1 | AR43: n | AS43: n | AT43: y | AU43: m | AV43: m | AW43: m | AX43: m | AY43: m | AZ43: m | BA43: n | BB43: n | BC43: n | BD43: n | BH43: downward | BI43: 0 | BJ43: prefer | BK43: transformed-partial | BL43: 0 | BM43: 0 | BN43: 0 | BO43: 0 | BP43: 0 | BQ43: 1 | BS43: 0 | BT43: 0 | BU43: 0 | BV43: 0 | BW43: 0 | BX43: 1 | BY43: 88 | CG43: 0 | CH43: 0 | CI43: 0 | CJ43: 0 | CK43: 0 | CL43: 1
A44: coh_vau_1.1Ado_d137_m009 | B44: co-housing | C44: Canton de Vaud (Switzerland) | D44: 1.1 | E44: Adoption over time | F44: Number of housing cooperatives in Canton de Vaud (Switzerland) | G44: # cooperatives | H44: b11 | I44: 0.045173 | J44: 0.028481 | K44: 1.2003 | L44: 2000.2 | M44: 97.28 | N44: 198.97 | O44: 4.7043 | P44: 1895.6 | Q44: -2308.5 | R44: 0.98344 | S44: 0.97722 | T44: 5.6478 | U44: 4.5254 | V44: 0.97105 | W44: 0.96461 | X44: 7.4671 | Y44: 6.7865 | Z44: 0.89851 | AA44: 0.87596 | AB44: 13.98 | AC44: 10.883 | AD44: 12 | AE44: 12 | AF44: 0.6986 | AG44: 0.0050259 | AH44: 0.69357 | AI44: 112 | AJ44: 0 | AK44: 11 | AL44: 0 | AM44: 0 | AN44: 1 | AO44: 0.75851 | AP44: 0 | AQ44: 0 | AR44: y | AS44: y | AT44: y | AU44: y | AV44: y | AW44: y | AX44: y | AY44: y | AZ44: y | BA44: y | BB44: y | BC44: y | BD44: y | BE44: 1 | BI44: 0 | BL44: 1 | BM44: 1 | BN44: 0 | BO44: 2 | BP44: 0 | BQ44: 0 | BS44: 1 | BT44: 1 | BU44: 0 | BV44: 1 | BW44: 0 | BX44: 0 | BY44: 89 | CG44: 1 | CH44: 1 | CI44: 0 | CJ44: 0 | CK44: 0 | CL44: 0
A45: cro_ber_1.1Ado_d059_m126 | B45: car ownership | C45: Berlin | D45: 1.1 | E45: Adaption over time | F45: Berlin Car density: 2008-2024 | G45: cars per 1,000 inhabitants | H45: b5 | I45: 0.46197 | J45: 0.0019583 | K45: 0.65735 | L45: 2002 | M45: 9.5123 | N45: 334.89 | O45: 79.734 | P45: 1288.1 | Q45: -993.56 | R45: 0.57391 | S45: 0.47558 | T45: 4.627 | U45: 3.8783 | V45: 0.20393 | W45: 0.090208 | X45: 6.3244 | Y45: 5.2346 | Z45: 0.2064 | AA45: 0.093033 | AB45: 6.3146 | AC45: 5.2253 | AD45: 17 | AE45: 17 | AF45: 1.0197 | AG45: 0.94687 | AH45: 0.072859 | AI45: 17 | AJ45: 12 | AK45: 15 | AL45: 1 | AM45: 0 | AN45: 0 | AO45: 0.94371 | AP45: 0 | AQ45: 0 | AR45: m | AS45: y | AT45: y | AU45: y | AV45: y | AW45: y | AX45: y | AY45: m | AZ45: m | BA45: m | BB45: m | BC45: m | BD45: m | BE45: 2 | BH45: *needs sign reversal * negative slope = LED innovation | BI45: 0 | BL45: 0 | BM45: 1 | BN45: 0 | BO45: 0 | BP45: 0 | BQ45: 0 | BS45: 0 | BT45: 1 | BU45: 0 | BV45: 0 | BW45: 0 | BX45: 0 | BY45: 90 | CG45: 0 | CH45: 1 | CI45: 0 | CJ45: 0 | CK45: 0 | CL45: 0
A46: cro_ber_1.1Ado_d330_m185 | B46: car ownership | C46: Berlin | D46: 1.1 | E46: Adaption over time | F46: cars per person | G46: market share | H46: b5 | I46: 0.46193 | J46: 0.0019583 | K46: 0.00065735 | L46: 2002 | M46: 9.5132 | N46: 0.33489 | O46: 1.0336 | P46: 2596.5 | Q46: -0.99356 | R46: 0.57391 | S46: 0.47558 | T46: 0.004627 | U46: 0.0038783 | V46: 0.20393 | W46: 0.090208 | X46: 0.0063244 | Y46: 0.0052346 | Z46: 0.2064 | AA46: 0.093033 | AB46: 0.0063146 | AC46: 0.0052253 | AD46: 17 | AE46: 17 | AF46: 1.0197 | AG46: 0.94687 | AH46: 0.072859 | AI46: 17 | AJ46: 12 | AK46: 15 | AL46: 1 | AM46: 0 | AN46: 0 | AO46: 0.94371 | AP46: 1 | AQ46: 1 | AR46: m | AS46: y | AT46: y | AU46: y | AV46: y | AW46: y | AX46: y | AY46: m | AZ46: m | BA46: m | BB46: m | BC46: m | BD46: m | BH46: *needs sign reversal * negative slope = LED innovation | BI46: 0 | BJ46: prefer-relative | BK46: transformed-marketshare | BL46: 0 | BM46: 1 | BN46: 0 | BO46: 1 | BP46: 0 | BQ46: 0 | BS46: 0 | BT46: 1 | BU46: 0 | BV46: 1 | BW46: 0 | BX46: 0 | BY46: 91 | CG46: 0 | CH46: 1 | CI46: 0 | CJ46: 0 | CK46: 0 | CL46: 0 | CM46: SdS to fit partial from 2012 (peak year), then logfit of decline period should be useable
A47: cro_ber_1.1Ado_d358_m185 | B47: car ownership | C47: Berlin | D47: 1.1 | E47: Adaption over time | F47: cars per person PARTIAL FROM MAX ONWARDS | G47: market share | H47: b5 | I47: -0.018437 | J47: -0.0020501 | K47: -0.00068571 | L47: 2131.6 | M47: -238.34 | N47: 0.37651 | O47: 0.60667 | P47: 1728.5 | Q47: 1.7189 | R47: 0.52155 | S47: 0.36206 | T47: 0.0024402 | U47: 0.0021041 | V47: 0.52997 | W47: 0.43597 | X47: 0.0024186 | Y47: 0.0020733 | Z47: 0.52894 | AA47: 0.43472 | AB47: 0.0024213 | AC47: 0.0020774 | AD47: 13 | AE47: 13 | AF47: 0.90701 | AG47: 0.87355 | AH47: 0.033465 | AI47: 13 | AJ47: 12 | AK47: 0 | AL47: 0 | AM47: 0 | AN47: 0 | AO47: 0.923 | AP47: 1 | AQ47: 1 | AR47: m | AS47: y | AT47: y | AU47: y | AV47: y | AW47: y | AX47: y | AY47: m | AZ47: y | BA47: m | BB47: y | CG47: 1 | CH47: 1 | CI47: 0 | CJ47: 1 | CK47: 0 | CL47: 0
A48: cro_ber_4.1Sal_d213_m100 | B48: car ownership | C48: Berlin | D48: 4.1 | E48: Knowledge Flows (social networks) | F48: annualised Google search frequency (index 100=monthly max.) | G48: Index 0-100 | H48: b5 | I48: 42.576 | J48: 0.20584 | K48: 1.8826 | L48: 2021.2 | M48: 0.10321 | N48: 52.773 | O48: 6.2492 | P48: 2014.6 | Q48: -3781.5 | R48: 0.54289 | S48: 0.46222 | T48: 15.851 | U48: 6.9326 | V48: 0.29096 | W48: 0.21217 | X48: 19.741 | Y48: 11.95 | Z48: 0.23644 | AA48: 0.15159 | AB48: 20.486 | AC48: 13.69 | AD48: 21 | AE48: 5 | AF48: 1.8949 | AG48: 0.2219 | AH48: 1.673 | AI48: 11 | AJ48: 2 | AK48: 0 | AL48: 1 | AM48: 0 | AN48: 1 | AO48: 0.38198 | AP48: 0 | AQ48: 1 | AR48: m | AS48: m | AT48: y | AU48: m | AV48: m | AW48: m | AX48: m | AY48: y | AZ48: m | BA48: m | BB48: m | BC48: m | BD48: m | BI48: 0 | BJ48: hide | BK48: original | BL48: 1 | BM48: 1 | BN48: 0 | BO48: 0 | BP48: 0 | BQ48: 0 | BS48: 0 | BT48: 1 | BU48: 0 | BV48: 0 | BW48: 0 | BX48: 0 | BY48: 92 | BZ48: check | CG48: 1 | CH48: 1 | CI48: 0 | CJ48: 0 | CK48: 0 | CL48: 0
A49: cro_ber_4.1Sal_d239_m153 | B49: car ownership | C49: Berlin | D49: 4.1 | E49: Knowledge Flows (social networks) | F49: Partial up to max annualised Google search frequency (index 100=monthly max.) | G49: Partial up to max Index 0-100 | H49: b5 | I49: 20.85 | J49: 8.038 | K49: 1.8669 | L49: 2022 | M49: 0.21076 | N49: 251.01 | O49: 0.0025667 | P49: 2020.7 | Q49: -3750.1 | R49: 0.86941 | S49: 0.84329 | T49: 8.3399 | U49: 2.6912 | V49: 0.86941 | W49: 0.85308 | X49: 8.3399 | Y49: 2.6928 | Z49: 0.19632 | AA49: 0.095855 | AB49: 20.689 | AC49: 13.14 | AD49: 19 | AE49: 3 | AF49: 0.39838 | AG49: 0.091156 | AH49: 0.30723 | AI49: 9 | AJ49: 0 | AK49: 8 | AL49: 0 | AM49: 0 | AN49: 1 | AO49: 0 | AP49: 0 | AQ49: 1 | AR49: y | AS49: n | AT49: y | AU49: m | AV49: m | AW49: m | AX49: m | AY49: y | AZ49: m | BA49: n | BB49: n | BC49: n | BD49: n | BI49: 0 | BJ49: prefer | BK49: transformed-partial | BL49: 1 | BM49: 1 | BN49: 0 | BO49: 0 | BP49: 0 | BQ49: 1 | BS49: 1 | BT49: 1 | BU49: 0 | BV49: 0 | BW49: 0 | BX49: 1 | BY49: 93 | CG49: 0 | CH49: 1 | CI49: 0 | CJ49: 0 | CK49: 0 | CL49: 1
A50: cro_glo_3.3Sci_d235_m020 | B50: car ownership | C50: Global | D50: 3.3 | E50: Risk & Uncertainty (Shared Expectations) | F50: scientific publications | G50: # publications | H50: b5 | I50: 0.24766 | J50: 0.039326 | K50: 0.29062 | L50: 2020.9 | M50: 17.744 | N50: 36.793 | O50: -3.7042 | P50: 4342.6 | Q50: -576.82 | R50: 0.91648 | S50: 0.91157 | T50: 1.8905 | U50: 1.0692 | V50: -0.29374 | W50: -0.3435 | X50: 7.4407 | Y50: 3.5455 | Z50: 0.49737 | AA50: 0.47803 | AB50: 4.6378 | AC50: 3.463 | AD50: 55 | AE50: 28 | AF50: 0.67947 | AG50: 0.027179 | AH50: 0.65229 | AI50: 33 | AJ50: 3 | AK50: 32 | AL50: 0 | AM50: 0 | AN50: 1 | AO50: 0.83514 | AP50: 0 | AQ50: 1 | AR50: y | AS50: y | AT50: y | AU50: m | AV50: y | AW50: m | AX50: y | AY50: y | AZ50: y | BA50: m | BB50: m | BC50: m | BD50: m | BH50: good; only available global, apply to all EA regions | BI50: 0 | BL50: 1 | BM50: 1 | BN50: 0 | BO50: 0 | BP50: 1 | BQ50: 1 | BS50: 1 | BT50: 1 | BU50: 0 | BV50: 0 | BW50: 1 | BX50: 1 | BY50: 94 | CG50: 1 | CH50: 1 | CI50: 0 | CJ50: 0 | CK50: 1 | CL50: 1
A51: cro_ham_1.1Ado_d108_m126 | B51: car ownership | C51: Hamburg | D51: 1.1 | E51: Adaption over time | F51: Hamburg Car density 2008-2024 | G51: cars per 1,000 inhabitants | H51: b5 | I51: 0.21243 | J51: 0.0046092 | K51: 1.9703 | L51: 1996.9 | M51: 20.686 | N51: 434.74 | O51: 40.81 | P51: 1508.7 | Q51: -3549.1 | R51: 0.84235 | S51: 0.80597 | T51: 4.6163 | U51: 3.8976 | V51: 0.68223 | W51: 0.63684 | X51: 6.554 | Y51: 5.7013 | Z51: 0.68928 | AA51: 0.64489 | AB51: 6.4809 | AC51: 5.5996 | AD51: 17 | AE51: 17 | AF51: 1.0098 | AG51: 0.92353 | AH51: 0.086258 | AI51: 17 | AJ51: 2 | AK51: 15 | AL51: 1 | AM51: 0 | AN51: 0 | AO51: 0.94355 | AP51: 0 | AQ51: 0 | AR51: y | AS51: y | AT51: y | AU51: y | AV51: y | AW51: y | AX51: y | AY51: m | AZ51: y | BA51: m | BB51: y | BC51: n | BD51: y | BE51: 2 | BH51: *needs sign reversal * negative slope = LED innovation | BI51: 0 | BL51: 0 | BM51: 1 | BN51: 0 | BO51: 0 | BP51: 0 | BQ51: 0 | BS51: 1 | BT51: 1 | BU51: 0 | BV51: 0 | BW51: 0 | BX51: 0 | BY51: 95 | BZ51: check | CG51: 1 | CH51: 1 | CI51: 0 | CJ51: 0 | CK51: 0 | CL51: 0
A52: cro_ham_1.1Ado_d330_m185 | B52: car ownership | C52: Hamburg | D52: 1.1 | E52: Adaption over time | F52: cars per person | G52: market share | H52: b5 | I52: 0.21243 | J52: 0.0011445 | K52: 0.0019703 | L52: 1996.9 | M52: 20.686 | N52: 0.43474 | O52: 1555.5 | P52: 157470 | Q52: -3.5491 | R52: 0.84235 | S52: 0.80597 | T52: 0.0046163 | U52: 0.0038976 | V52: -1324.4 | W52: -1513.7 | X52: 0.42327 | Y52: 0.42311 | Z52: 0.68928 | AA52: 0.64489 | AB52: 0.0064809 | AC52: 0.0055996 | AD52: 17 | AE52: 17 | AF52: 1.0098 | AG52: 0.92353 | AH52: 0.086258 | AI52: 17 | AJ52: 2 | AK52: 15 | AL52: 1 | AM52: 0 | AN52: 0 | AO52: 0.94355 | AP52: 1 | AQ52: 1 | AR52: y | AS52: y | AT52: y | AU52: y | AV52: y | AW52: y | AX52: y | AY52: m | AZ52: y | BA52: m | BB52: y | BC52: n | BD52: y | BH52: *needs sign reversal * negative slope = LED innovation | BI52: 0 | BJ52: prefer-relative | BK52: transformed-marketshare | BL52: 0 | BM52: 1 | BN52: 0 | BO52: 1 | BP52: 0 | BQ52: 0 | BS52: 1 | BT52: 1 | BU52: 0 | BV52: 1 | BW52: 0 | BX52: 0 | BY52: 96 | BZ52: check | CG52: 1 | CH52: 1 | CI52: 0 | CJ52: 1 | CK52: 0 | CL52: 0 | CM52: Trend is in unfavorable direction but fit seems correct
A53: cro_ham_4.1Sal_d213_m100 | B53: car ownership | C53: Hamburg | D53: 4.1 | E53: Knowledge Flows (social networks) | F53: annualised Google search frequency (index 100=monthly max.) | G53: Index 0-100 | H53: b5 | I53: -11.704 | J53: 0.03302 | K53: 0.29988 | L53: 2009.5 | M53: -0.37546 | N53: -3.2032e-09 | O53: 9.3806 | P53: 2031 | Q53: -598.58 | R53: -0.06369 | S53: -0.2514 | T53: 22.008 | U53: 5.3853 | V53: 0.0043374 | W53: -0.10629 | X53: 21.293 | Y53: 9.6077 | Z53: 0.0072415 | AA53: -0.10307 | AB53: 21.262 | AC53: 9.4306 | AD53: 21 | AE53: 2 | AF53: -31219000000 | AG53: -4086800000 | AH53: -27132000000 | AI53: 10 | AJ53: 9 | AK53: 0 | AL53: 0 | AM53: 0 | AN53: 1 | AO53: 0 | AP53: 0 | AQ53: 1 | AR53: n | AS53: n | AT53: m | AU53: m | AV53: m | AW53: m | AX53: m | AY53: m | AZ53: m | BA53: n | BB53: n | BC53: n | BD53: n | BH53: too few | BI53: 0 | BJ53: hide | BK53: original | BL53: 0 | BM53: 0 | BN53: 0 | BO53: 0 | BP53: 0 | BQ53: 0 | BS53: 0 | BT53: 0 | BU53: 0 | BV53: 0 | BW53: 0 | BX53: 0 | BY53: 97 | CG53: 0 | CH53: 0 | CI53: 0 | CJ53: 0 | CK53: 0 | CL53: 0
A54: cro_ham_4.1Sal_d239_m153 | B54: car ownership | C54: Hamburg | D54: 4.1 | E54: Knowledge Flows (social networks) | F54: Partial up to max annualised Google search frequency (index 100=monthly max.) | G54: Partial up to max Index 0-100 | H54: b5 | I54: 17.664 | K54: 3.8462 | L54: 2015 | M54: 0.24878 | N54: 327.96 | Q54: -7720.5 | R54: 1 | S54: 1 | T54: 8.8546e-07 | U54: 2.639e-07 | Z54: 0.23077 | AA54: 0.059829 | AB54: 24.241 | AC54: 16.453 | AD54: 12 | AE54: 1 | AF54: 0.30491 | AG54: 0.30491 | AH54: 0 | AI54: 1 | AJ54: 0 | AK54: 0 | AL54: 0 | AM54: 0 | AP54: 0 | AQ54: 1 | AR54: y | AS54: n | AT54: m | AU54: m | AV54: m | AW54: m | AX54: m | AY54: m | AZ54: m | BA54: n | BB54: n | BC54: n | BD54: n | BH54: too few | BI54: 0 | BJ54: prefer | BK54: transformed-partial | BL54: 0 | BM54: 0 | BN54: 0 | BO54: 0 | BP54: 0 | BQ54: 1 | BS54: 0 | BT54: 0 | BU54: 0 | BV54: 0 | BW54: 0 | BX54: 1 | BY54: 98 | CG54: 0 | CH54: 0 | CI54: 0 | CJ54: 0 | CK54: 0 | CL54: 1
A55: cro_hei_1.1Ado_d109_m127 | B55: car ownership | C55: Heidelberg | D55: 1.1 | E55: Adaption over time | F55: Heidelberg Car density 1993-2024 | G55: cars per 1000 inhabitants | H55: b5 | I55: -0.0063912 | J55: -0.0063893 | K55: -2.5196 | L55: 738.78 | M55: -687.58 | N55: 1338300 | O55: 706.32 | P55: 1919.5 | Q55: 5461.3 | R55: 0.71221 | S55: 0.679 | T55: 14.224 | U55: 12.267 | V55: 0.71221 | W55: 0.69089 | X55: 14.224 | Y55: 12.267 | Z55: 0.70349 | AA55: 0.68152 | AB55: 14.438 | AC55: 12.341 | AD55: 30 | AE55: 30 | AF55: 0.00032503 | AG55: 0.00027647 | AH55: 4.8568e-05 | AI55: 32 | AJ55: 28 | AK55: 7 | AL55: 0 | AM55: 1 | AN55: 0 | AO55: 0.96526 | AP55: 0 | AQ55: 0 | AR55: y | AS55: y | AT55: y | AU55: y | AV55: y | AW55: y | AX55: y | AY55: m | AZ55: y | BA55: m | BB55: y | BC55: m | BD55: y | BE55: 1 | BH55: *needs sign reversal * negative slope = LED innovation | BI55: 0 | BL55: 1 | BM55: 1 | BN55: 1 | BO55: 1 | BP55: 0 | BQ55: 0 | BS55: 1 | BT55: 1 | BU55: 1 | BV55: 1 | BW55: 0 | BX55: 0 | BY55: 99 | CG55: 1 | CH55: 1 | CI55: 0 | CJ55: 0 | CK55: 0 | CL55: 0
A56: cro_hei_1.1Ado_d330_m185 | B56: car ownership | C56: Heidelberg | D56: 1.1 | E56: Adaption over time | F56: cars per person | G56: market share | H56: b5 | I56: -0.010707 | J56: -0.0063893 | K56: -0.0025196 | L56: 1973.3 | M56: -410.42 | N56: 0.9841 | O56: 4.8361 | P56: 1618.4 | Q56: 5.4613 | R56: 0.70671 | S56: 0.67287 | T56: 0.014359 | U56: 0.012299 | V56: 0.71221 | W56: 0.69089 | X56: 0.014224 | Y56: 0.012267 | Z56: 0.70349 | AA56: 0.68152 | AB56: 0.014438 | AC56: 0.012341 | AD56: 30 | AE56: 30 | AF56: 0.44203 | AG56: 0.37598 | AH56: 0.06605 | AI56: 32 | AJ56: 28 | AK56: 7 | AL56: 0 | AM56: 1 | AN56: 0 | AO56: 0.96526 | AP56: 1 | AQ56: 1 | AR56: y | AS56: y | AT56: y | AU56: y | AV56: y | AW56: y | AX56: y | AY56: m | AZ56: y | BA56: m | BB56: y | CG56: 1 | CH56: 1 | CI56: 1 | CJ56: 1 | CK56: 0 | CL56: 0
A57: crs_ger_1.1Ado_d233_m012 | B57: car sharing | C57: Germany | D57: 1.1 | E57: Adoption over time | F57: registered drivers | G57: # drivers | H57: m9 | I57: 0.21557 | J57: 0.19421 | K57: 153360 | L57: 2030.2 | M57: 20.385 | N57: 25531000 | O57: 8.8746e-11 | P57: 1825 | Q57: -307270000 | R57: 0.98588 | S57: 0.98412 | T57: 175000 | U57: 124820 | V57: 0.98533 | W57: 0.98416 | X57: 178400 | Y57: 131870 | Z57: 0.70735 | AA57: 0.68394 | AB57: 796810 | AC57: 629920 | AD57: 28 | AE57: 28 | AF57: 0.21566 | AG57: 0.00074419 | AH57: 0.21491 | AI57: 28 | AJ57: 0 | AK57: 27 | AL57: 0 | AM57: 0 | AN57: 0 | AO57: 0.8164 | AP57: 0 | AQ57: 0 | AR57: y | AS57: y | AT57: y | AU57: y | AV57: y | AW57: y | AX57: y | AY57: y | AZ57: y | BA57: y | BB57: y | BC57: y | BD57: y | BE57: 1 | BI57: 0 | BL57: 1 | BM57: 1 | BN57: 2 | BO57: 2 | BP57: 0 | BQ57: 0 | BS57: 1 | BT57: 1 | BU57: 0 | BV57: 0 | BW57: 0 | BX57: 0 | BY57: 100 | CG57: 1 | CH57: 1 | CI57: 0 | CJ57: 0 | CK57: 0 | CL57: 0
A58: crs_ger_1.1Ado_d340_m185 | B58: car sharing | C58: Germany | D58: 1.1 | E58: Adoption over time | F58: share of drivers who car share | G58: market share | H58: m9 | I58: 0.2644 | J58: 0.18882 | K58: 0.0015878 | L58: 2022.2 | M58: 16.621 | N58: 0.089086 | O58: 3.0823 | P58: 2044.6 | Q58: -3.1807 | R58: 0.98312 | S58: 0.98091 | T58: 0.0018867 | U58: 0.0013394 | V58: 0.97785 | W58: 0.976 | X58: 0.002161 | Y58: 0.001641 | Z58: 0.72543 | AA58: 0.70255 | AB58: 0.0076084 | AC58: 0.0062218 | AD58: 27 | AE58: 27 | AF58: 0.59383 | AG58: 0.0025886 | AH58: 0.59124 | AI58: 27 | AJ58: 0 | AK58: 26 | AL58: 0 | AM58: 0 | AN58: 0 | AO58: 0.82154 | AP58: 1 | AQ58: 1 | AR58: y | AS58: y | AT58: y | AU58: y | AV58: y | AW58: y | AX58: y | AY58: y | AZ58: y | BA58: y | BB58: y | BC58: y | BD58: y | BI58: 0 | BJ58: prefer-relative | BK58: transformed-marketshare | BL58: 1 | BM58: 1 | BN58: 1 | BO58: 1 | BP58: 0 | BQ58: 0 | BS58: 1 | BT58: 1 | BU58: 1 | BV58: 1 | BW58: 0 | BX58: 0 | BY58: 101 | CG58: 1 | CH58: 1 | CI58: 1 | CJ58: 1 | CK58: 0 | CL58: 0
A59: crs_ger_2.5Var_d216_m012 | B59: car sharing | C59: Germany | D59: 2.5 | E59: Choice availability | F59: free-floating cars - registered drivers | G59: # drivers | H59: m9 | I59: 0.21399 | J59: 0.21398 | K59: 323690 | L59: 2073.3 | M59: 20.536 | N59: 168330000000 | O59: 5.6795e-12 | P59: 1831.5 | Q59: -651580000 | R59: 0.96965 | S59: 0.95953 | T59: 221650 | U59: 189190 | V59: 0.96965 | W59: 0.96358 | X59: 221650 | Y59: 189190 | Z59: 0.90616 | AA59: 0.88739 | AB59: 389760 | AC59: 287750 | AD59: 13 | AE59: 13 | AF59: 2.6767e-05 | AG59: 2.1981e-07 | AH59: 2.6547e-05 | AI59: 13 | AJ59: 0 | AK59: 12 | AL59: 0 | AM59: 0 | AN59: 1 | AO59: 0.79141 | AP59: 0 | AQ59: 0 | AR59: y | AS59: y | AT59: y | AU59: y | AV59: y | AW59: y | AX59: y | AY59: m | AZ59: y | BA59: m | BB59: y | BC59: m | BD59: y | BE59: 1 | BI59: 0 | BM59: 1 | BS59: 1 | BT59: 1 | BU59: 0 | BV59: 0 | BW59: 0 | BX59: 0 | BY59: 102 | CG59: 1 | CH59: 1 | CI59: 0 | CJ59: 0 | CK59: 0 | CL59: 0
A60: crs_ger_2.5Var_d217_m025 | B60: car sharing | C60: Germany | D60: 2.5 | E60: Choice availability | F60: free-floating cars - registered vehicles | G60: # vehicles | H60: m9 | I60: 0.1774 | J60: 0.1774 | K60: 1598.6 | L60: 2091.2 | M60: 24.771 | N60: 3602300000 | O60: 1.5536e-07 | P60: 1878.8 | Q60: -3215600 | R60: 0.95201 | S60: 0.93601 | T60: 1424.3 | U60: 1309.1 | V60: 0.95201 | W60: 0.94241 | X60: 1424.2 | Y60: 1309.1 | Z60: 0.84641 | AA60: 0.81569 | AB60: 2547.9 | AC60: 1923.9 | AD60: 13 | AE60: 13 | AF60: 7.3148e-06 | AG60: 3.6088e-07 | AH60: 6.9539e-06 | AI60: 13 | AJ60: 0 | AK60: 12 | AL60: 0 | AM60: 0 | AN60: 1 | AO60: 0.7929 | AP60: 0 | AQ60: 0 | AR60: y | AS60: y | AT60: y | AU60: y | AV60: y | AW60: y | AX60: y | AY60: m | AZ60: y | BA60: m | BB60: y | BC60: m | BD60: y | BE60: 1 | BI60: 0 | BM60: 1 | BS60: 1 | BT60: 1 | BU60: 0 | BV60: 0 | BW60: 0 | BX60: 0 | BY60: 103 | CG60: 1 | CH60: 1 | CI60: 0 | CJ60: 0 | CK60: 0 | CL60: 0
A61: crs_ger_2.5Var_d218_m092 | B61: car sharing | C61: Germany | D61: 2.5 | E61: Choice availability | F61: free-floating cars as % of all shared cars | G61: % vehicles | H61: m9 | I61: 2.3639 | J61: 0.11309 | K61: 0.025934 | L61: 2012.2 | M61: 1.859 | N61: 0.47376 | O61: 2.3684 | P61: 2034.8 | Q61: -51.933 | R61: 0.96928 | S61: 0.96544 | T61: 0.040667 | U61: 0.023258 | V61: 0.80496 | W61: 0.78935 | X61: 0.10247 | Y61: 0.084869 | Z61: 0.81521 | AA61: 0.80043 | AB61: 0.099738 | AC61: 0.080944 | AD61: 28 | AE61: 13 | AF61: 1.2902 | AG61: 0.38648 | AH61: 0.90368 | AI61: 13 | AJ61: 0 | AK61: 12 | AL61: 0 | AM61: 0 | AN61: 1 | AO61: 0.91266 | AP61: 1 | AQ61: 1 | AR61: y | AS61: y | AT61: y | AU61: y | AV61: y | AW61: y | AX61: y | AY61: y | AZ61: y | BA61: y | BB61: y | BC61: y | BD61: y | BE61: 1 | BI61: 0 | BL61: 1 | BM61: 1 | BS61: 1 | BT61: 1 | BU61: 0 | BV61: 0 | BW61: 1 | BX61: 1 | BY61: 104 | CG61: 1 | CH61: 1 | CI61: 0 | CJ61: 0 | CK61: 1 | CL61: 1
A62: crs_ger_2.5Var_d237_m012 | B62: car sharing | C62: Germany | D62: 2.5 | E62: Choice availability | F62: station-based or combined - registered drivers | G62: # drivers | H62: m9 | I62: 0.1802 | J62: 0.12298 | K62: 34099 | L62: 2022.1 | M62: 24.387 | N62: 1679300 | O62: 1.2683e-06 | P62: 1800.9 | Q62: -68249000 | R62: 0.99698 | S62: 0.9966 | T62: 16241 | U62: 11892 | V62: 0.98846 | W62: 0.98754 | X62: 31729 | Y62: 26770 | Z62: 0.86946 | AA62: 0.85901 | AB62: 106730 | AC62: 94183 | AD62: 28 | AE62: 28 | AF62: 0.59575 | AG62: 0.011314 | AH62: 0.58443 | AI62: 28 | AJ62: 0 | AK62: 27 | AL62: 0 | AM62: 0 | AN62: 0 | AO62: 0.89494 | AP62: 0 | AQ62: 0 | AR62: y | AS62: y | AT62: y | AU62: y | AV62: y | AW62: y | AX62: y | AY62: y | AZ62: y | BA62: y | BB62: y | BC62: y | BD62: y | BE62: 1 | BI62: 0 | BL62: 1 | BM62: 1 | BS62: 1 | BT62: 1 | BU62: 0 | BV62: 0 | BW62: 0 | BX62: 0 | BY62: 105 | CG62: 1 | CH62: 1 | CI62: 0 | CJ62: 0 | CK62: 0 | CL62: 0
A63: crs_ger_2.5Var_d238_m025 | B63: car sharing | C63: Germany | D63: 2.5 | E63: Choice availability | F63: station-based or combined - registered vehicles | G63: # vehicles | H63: m9 | I63: 0.13982 | J63: 0.092324 | K63: 574.33 | L63: 2021.1 | M63: 31.428 | N63: 27468 | O63: 0.00037292 | P63: 1832.6 | Q63: -1148200 | R63: 0.99519 | S63: 0.99459 | T63: 334.41 | U63: 282.16 | V63: 0.98509 | W63: 0.9839 | X63: 588.97 | Y63: 511.95 | Z63: 0.92514 | AA63: 0.91915 | AB63: 1319.7 | AC63: 1138.2 | AD63: 28 | AE63: 28 | AF63: 0.61017 | AG63: 0.040047 | AH63: 0.57013 | AI63: 28 | AJ63: 0 | AK63: 27 | AL63: 0 | AM63: 0 | AN63: 0 | AO63: 0.91945 | AP63: 0 | AQ63: 0 | AR63: y | AS63: y | AT63: y | AU63: y | AV63: y | AW63: y | AX63: y | AY63: y | AZ63: y | BA63: y | BB63: y | BC63: y | BD63: y | BE63: 1 | BI63: 0 | BL63: 1 | BM63: 1 | BS63: 1 | BT63: 1 | BU63: 0 | BV63: 0 | BW63: 0 | BX63: 0 | BY63: 106 | CG63: 1 | CH63: 1 | CI63: 0 | CJ63: 0 | CK63: 0 | CL63: 0
A64: crs_ger_2.9Int_d236_m025 | B64: car sharing | C64: Germany | D64: 2.9 | E64: Interdependence with Hardware | F64: shared vehicles | G64: # vehicles | H64: m9 | I64: 0.14721 | J64: 0.13432 | K64: 1286 | L64: 2034.2 | M64: 29.852 | N64: 223200 | O64: 8.1127e-06 | P64: 1857.6 | Q64: -2574100 | R64: 0.98412 | S64: 0.98214 | T64: 1444.1 | U64: 1158.1 | V64: 0.9837 | W64: 0.98239 | X64: 1463.4 | Y64: 1165.7 | Z64: 0.82147 | AA64: 0.80718 | AB64: 4842.6 | AC64: 3952.2 | AD64: 28 | AE64: 28 | AF64: 0.19314 | AG64: 0.0049282 | AH64: 0.18821 | AI64: 28 | AJ64: 0 | AK64: 27 | AL64: 0 | AM64: 0 | AN64: 0 | AO64: 0.85959 | AP64: 0 | AQ64: 0 | AR64: y | AS64: y | AT64: y | AU64: y | AV64: y | AW64: y | AX64: y | AY64: m | AZ64: y | BA64: m | BB64: y | BC64: m | BD64: y | BE64: 1 | BI64: 0 | BM64: 1 | BS64: 1 | BT64: 1 | BU64: 0 | BV64: 0 | BW64: 1 | BX64: 1 | BY64: 107 | CG64: 1 | CH64: 1 | CI64: 0 | CJ64: 0 | CK64: 1 | CL64: 1
A65: crs_ger_3.5Mar_d074_m128 | B65: car sharing | C65: Germany | D65: 3.5 | E65: Market Formation | F65: CumulativeStartups | G65: cum. # companies | H65: m9 | I65: 0.23975 | J65: 0.10589 | K65: 0.51225 | L65: 2015.7 | M65: 18.329 | N65: 27.299 | O65: 9.7867 | P65: 2014.2 | Q65: -1019.8 | R65: 0.98962 | S65: 0.98886 | T65: 0.78556 | U65: 0.55153 | V65: 0.95741 | W65: 0.95538 | X65: 1.5911 | Y65: 1.1577 | Z65: 0.74459 | AA65: 0.73243 | AB65: 3.8963 | AC65: 3.4729 | AD65: 45 | AE65: 28 | AF65: 0.84251 | AG65: 0.036631 | AH65: 0.80588 | AI65: 28 | AJ65: 2 | AK65: 27 | AL65: 0 | AM65: 0 | AN65: 0 | AO65: 0.92947 | AP65: 0 | AQ65: 1 | AR65: y | AS65: y | AT65: y | AU65: y | AV65: y | AW65: y | AX65: y | AY65: y | AZ65: y | BA65: y | BB65: y | BC65: y | BD65: y | BI65: 0 | BJ65: prefer | BK65: original | BL65: 1 | BM65: 1 | BN65: 0 | BO65: 0 | BP65: 1 | BQ65: 1 | BS65: 1 | BT65: 1 | BU65: 0 | BV65: 0 | BW65: 1 | BX65: 1 | BY65: 108 | CG65: 1 | CH65: 1 | CI65: 0 | CJ65: 0 | CK65: 1 | CL65: 1
A66: crs_ger_3.5Mar_d126_m008 | B66: car sharing | C66: Germany | D66: 3.5 | E66: Market Formation | F66: NewStartups | G66: # companies | H66: m9 | I66: 63.155 | J66: 0.054056 | K66: 0.035705 | L66: 2007.1 | M66: 0.069582 | N66: 1.2353 | O66: 0.22507 | P66: 1989.7 | Q66: -70.97 | R66: 0.31353 | S66: 0.2633 | T66: 0.83078 | U66: 0.42615 | V66: 0.18429 | W66: 0.14545 | X66: 0.90561 | Y66: 0.59713 | Z66: 0.21386 | AA66: 0.17643 | AB66: 0.88905 | AC66: 0.57887 | AD66: 45 | AE66: 13 | AF66: 4.0476 | AG66: 0.80952 | AH66: 3.2381 | AI66: 26 | AJ66: 6 | AK66: 25 | AL66: 1 | AM66: 0 | AN66: 1 | AO66: 0.40351 | AP66: 0 | AQ66: 1 | AR66: m | AS66: y | AT66: y | AU66: m | AV66: m | AW66: m | AX66: m | AY66: y | AZ66: m | BA66: m | BB66: m | BC66: m | BD66: m | BH66: noisy | BI66: 0 | BJ66: hide | BK66: original | BL66: 0 | BM66: 1 | BN66: 0 | BO66: 0 | BP66: 0 | BQ66: 0 | BS66: 0 | BT66: 0 | BU66: 0 | BV66: 0 | BW66: 0 | BX66: 0 | BY66: 109 | CA66: check | CG66: 0 | CH66: 1 | CI66: 0 | CJ66: 0 | CK66: 0 | CL66: 0
A67: crs_ger_3.5Mar_d171_m011 | B67: car sharing | C67: Germany | D67: 3.5 | E67: Market Formation | F67: PrivateEquityDeals | G67: # deals | H67: m9 | I67: 0.62558 | J67: 0.007646 | K67: 0.070224 | L67: 2014.7 | M67: 7.0246 | N67: 3.1875 | O67: 1553.7 | P67: 157600 | Q67: -139.88 | R67: 0.71447 | S67: 0.69357 | T67: 0.73545 | U67: 0.34652 | V67: -0.26694 | W67: -0.32728 | X67: 1.5492 | Y67: 0.71111 | Z67: 0.43908 | AA67: 0.41237 | AB67: 1.0308 | AC67: 0.80585 | AD67: 45 | AE67: 12 | AF67: 1.5686 | AG67: 0.31372 | AH67: 1.2549 | AI67: 13 | AJ67: 2 | AK67: 12 | AL67: 1 | AM67: 0 | AN67: 1 | AO67: 0.82407 | AP67: 0 | AQ67: 1 | AR67: y | AS67: y | AT67: y | AU67: m | AV67: y | AW67: m | AX67: y | AY67: y | AZ67: y | BA67: m | BB67: m | BC67: m | BD67: m | BI67: 0 | BJ67: hide | BK67: original | BL67: 1 | BM67: 1 | BN67: 0 | BO67: 0 | BP67: 0 | BQ67: 0 | BS67: 1 | BT67: 1 | BU67: 0 | BV67: 0 | BW67: 0 | BX67: 0 | BY67: 110 | CG67: 1 | CH67: 1 | CI67: 0 | CJ67: 0 | CK67: 0 | CL67: 0
A68: crs_ger_3.5Mar_d175_m027 | B68: car sharing | C68: Germany | D68: 3.5 | E68: Market Formation | F68: PrivateEquityInvestment | G68: $ million | H68: m9 | I68: 2.9423 | J68: 0.16696 | K68: 1.4549 | L68: 2019.5 | M68: 1.4935 | N68: 108.36 | O68: 2.4318 | P68: 2001.5 | Q68: -2899.8 | R68: 0.66154 | S68: 0.63677 | T68: 23.223 | U68: 6.3205 | V68: 0.43417 | W68: 0.40722 | X68: 30.026 | Y68: 12.79 | Z68: 0.22406 | AA68: 0.18711 | AB68: 35.162 | AC68: 21.702 | AD68: 45 | AE68: 10 | AF68: 1.9904 | AG68: 0.022675 | AH68: 1.9678 | AI68: 12 | AJ68: 2 | AK68: 8 | AL68: 1 | AM68: 1 | AN68: 1 | AO68: 0.70249 | AP68: 0 | AQ68: 0 | AR68: m | AS68: y | AT68: y | AU68: m | AV68: y | AW68: m | AX68: y | AY68: y | AZ68: m | BA68: m | BB68: m | BC68: m | BD68: m | BI68: 0 | BJ68: hide | BK68: original | BL68: 1 | BM68: 1 | BN68: 0 | BO68: 0 | BP68: 0 | BQ68: 0 | BS68: 1 | BT68: 1 | BU68: 0 | BV68: 0 | BW68: 0 | BX68: 0 | BY68: 111 | CG68: 1 | CH68: 1 | CI68: 0 | CJ68: 0 | CK68: 0 | CL68: 0
A69: crs_ger_3.5Mar_d200_m027 | B69: car sharing | C69: Germany | D69: 3.5 | E69: Market Formation | F69: TotalFundraisingAmount | G69: $ million | H69: m9 | I69: 22.479 | J69: 0.18962 | K69: 9.2407 | L69: 2020.1 | M69: 0.19549 | N69: 824.44 | O69: 5.2289e-05 | P69: 1937.3 | Q69: -18420 | R69: 0.46344 | S69: 0.42418 | T69: 250.29 | U69: 68.826 | V69: 0.26397 | W69: 0.22892 | X69: 293.15 | Y69: 95.273 | Z69: 0.12336 | AA69: 0.081614 | AB69: 319.92 | AC69: 142.01 | AD69: 45 | AE69: 12 | AF69: 2.7343 | AG69: 0.0014463 | AH69: 2.7329 | AI69: 13 | AJ69: 3 | AK69: 7 | AL69: 1 | AM69: 1 | AN69: 1 | AO69: 0.18926 | AP69: 0 | AQ69: 0 | AR69: m | AS69: y | AT69: y | AU69: m | AV69: m | AW69: m | AX69: m | AY69: y | AZ69: m | BA69: m | BB69: m | BC69: m | BD69: m | BI69: 0 | BJ69: hide | BK69: original | BL69: 1 | BM69: 1 | BN69: 0 | BO69: 0 | BP69: 0 | BQ69: 0 | BS69: 0 | BT69: 1 | BU69: 0 | BV69: 0 | BW69: 0 | BX69: 0 | BY69: 112 | BZ69: check | CG69: 0 | CH69: 1 | CI69: 0 | CJ69: 0 | CK69: 0 | CL69: 0
A70: crs_ger_3.5Mar_d204_m011 | B70: car sharing | C70: Germany | D70: 3.5 | E70: Market Formation | F70: TotalFundraisingDeals | G70: # deals | H70: m9 | I70: 0.82347 | J70: 0.012735 | K70: 0.12398 | L70: 2015.6 | M70: 5.3365 | N70: 5.9551 | O70: 1552.6 | P70: 157700 | Q70: -246.89 | R70: 0.79481 | S70: 0.7798 | T70: 1.0626 | U70: 0.533 | V70: -0.31237 | W70: -0.37486 | X70: 2.6874 | Y70: 1.3111 | Z70: 0.4711 | AA70: 0.44591 | AB70: 1.7061 | AC70: 1.2644 | AD70: 45 | AE70: 17 | AF70: 1.6792 | AG70: 0.16792 | AH70: 1.5113 | AI70: 39 | AJ70: 3 | AK70: 38 | AL70: 0 | AM70: 0 | AN70: 1 | AO70: 0.82769 | AP70: 0 | AQ70: 1 | AR70: y | AS70: y | AT70: y | AU70: m | AV70: m | AW70: m | AX70: y | AY70: y | AZ70: y | BA70: m | BB70: m | BC70: m | BD70: m | BI70: 0 | BJ70: hide | BK70: original | BL70: 1 | BM70: 1 | BN70: 0 | BO70: 0 | BP70: 0 | BQ70: 0 | BS70: 1 | BT70: 1 | BU70: 0 | BV70: 0 | BW70: 0 | BX70: 0 | BY70: 113 | CG70: 1 | CH70: 1 | CI70: 0 | CJ70: 0 | CK70: 0 | CL70: 0
A71: crs_ger_3.5Mar_d242_m156 | B71: car sharing | C71: Germany | D71: 3.5 | E71: Market Formation | F71: cumulative CumulativeStartups | G71: cumulative cum. # companies | H71: m9 | I71: 0.18789 | J71: 0.13796 | K71: 4.3711 | L71: 2023.9 | M71: 23.388 | N71: 512.33 | O71: 0.0587 | P71: 1962.8 | Q71: -8705.6 | R71: 0.99955 | S71: 0.99952 | T71: 1.4778 | U71: 1.1491 | V71: 0.99504 | W71: 0.9948 | X71: 4.9191 | Y71: 3.9433 | Z71: 0.66069 | AA71: 0.64453 | AB71: 40.683 | AC71: 33.7 | AD71: 45 | AE71: 28 | AF71: 0.50358 | AG71: 0.0019519 | AH71: 0.50163 | AI71: 28 | AJ71: 0 | AK71: 27 | AL71: 0 | AM71: 0 | AN71: 1 | AO71: 0.88686 | AP71: 0 | AQ71: 0 | AR71: y | AS71: y | AT71: y | AU71: y | AV71: y | AW71: y | AX71: y | AY71: y | AZ71: y | BA71: y | BB71: y | BC71: y | BD71: y | BI71: 1 | BJ71: delete | BK71: transformed-cumx2error | BL71: 0 | BM71: 0 | BN71: 0 | BO71: 0 | BP71: 0 | BQ71: 0 | BS71: 1 | BT71: 1 | BU71: 0 | BV71: 0 | BW71: 0 | BX71: 0 | BY71: 114 | BZ71: check | CA71: check | CG71: 1 | CH71: 1 | CI71: 0 | CJ71: 0 | CK71: 0 | CL71: 0
A72: crs_ger_3.5Mar_d243_m157 | B72: car sharing | C72: Germany | D72: 3.5 | E72: Market Formation | F72: Partial up to max CumulativeStartups | G72: Partial up to max cum. # companies | H72: m9 | I72: 0.21963 | J72: 0.045461 | K72: 0.4698 | L72: 2016.8 | M72: 20.009 | N72: 30.621 | O72: 1546 | P72: 158360 | Q72: -935.13 | R72: 0.98772 | S72: 0.98678 | T72: 0.76522 | U72: 0.5195 | V72: -0.50966 | W72: -0.58514 | X72: 8.4853 | Y72: 4.9302 | Z72: 0.71267 | AA72: 0.69831 | AB72: 3.7018 | AC72: 3.1975 | AD72: 43 | AE72: 26 | AF72: 0.75111 | AG72: 0.032657 | AH72: 0.71846 | AI72: 26 | AJ72: 0 | AK72: 25 | AL72: 0 | AM72: 0 | AN72: 0 | AO72: 0.90536 | AP72: 0 | AQ72: 1 | AR72: y | AS72: y | AT72: y | AU72: y | AV72: y | AW72: y | AX72: y | AY72: y | AZ72: y | BA72: y | BB72: y | BC72: y | BD72: y | BH72: not needed as transformed-cumulative preferred | BI72: 1 | BJ72: delete | BK72: transformed-partial | BL72: 0 | BM72: 0 | BN72: 0 | BO72: 0 | BP72: 0 | BQ72: 0 | BS72: 1 | BT72: 1 | BU72: 0 | BV72: 0 | BW72: 0 | BX72: 0 | BY72: 115 | BZ72: check | CA72: check | CG72: 1 | CH72: 1 | CI72: 0 | CJ72: 0 | CK72: 0 | CL72: 0
A73: crs_ger_3.5Mar_d244_m158 | B73: car sharing | C73: Germany | D73: 3.5 | E73: Market Formation | F73: cumulative NewStartups | G73: cumulative # companies | H73: m9 | I73: 0.23975 | J73: 0.10589 | K73: 0.51225 | L73: 2015.7 | M73: 18.329 | N73: 27.299 | O73: 9.7867 | P73: 2014.2 | Q73: -1019.8 | R73: 0.98962 | S73: 0.98886 | T73: 0.78556 | U73: 0.55153 | V73: 0.95741 | W73: 0.95538 | X73: 1.5911 | Y73: 1.1577 | Z73: 0.74459 | AA73: 0.73243 | AB73: 3.8963 | AC73: 3.4729 | AD73: 45 | AE73: 28 | AF73: 0.84251 | AG73: 0.036631 | AH73: 0.80588 | AI73: 28 | AJ73: 2 | AK73: 27 | AL73: 0 | AM73: 0 | AN73: 0 | AO73: 0.92947 | AP73: 0 | AQ73: 1 | AR73: y | AS73: y | AT73: y | AU73: y | AV73: y | AW73: y | AX73: y | AY73: y | AZ73: y | BA73: y | BB73: y | BC73: y | BD73: y | BH73: not needed as cumulative in original data | BI73: 1 | BJ73: delete | BK73: transformed-cumulative | BL73: 0 | BM73: 0 | BN73: 0 | BO73: 0 | BP73: 0 | BQ73: 0 | BS73: 1 | BT73: 1 | BU73: 0 | BV73: 0 | BW73: 0 | BX73: 0 | BY73: 116 | BZ73: check | CA73: check | CG73: 1 | CH73: 1 | CI73: 0 | CJ73: 0 | CK73: 0 | CL73: 0
A74: crs_ger_3.5Mar_d245_m159 | B74: car sharing | C74: Germany | D74: 3.5 | E74: Market Formation | F74: Partial up to max NewStartups | G74: Partial up to max # companies | H74: m9 | I74: 0.64357 | J74: 0.64295 | K74: 0.049787 | L74: 2033.1 | M74: 6.8283 | N74: 284510 | O74: 6.2872 | P74: 2016.5 | Q74: -99.041 | R74: 0.61358 | S74: 0.57845 | T74: 0.62231 | U74: 0.27558 | V74: 0.61358 | W74: 0.59085 | X74: 0.62231 | Y74: 0.27563 | Z74: 0.28195 | AA74: 0.23972 | AB74: 0.8483 | AC74: 0.58837 | AD74: 37 | AE74: 8 | AF74: 1.7574e-05 | AG74: 3.5148e-06 | AH74: 1.4059e-05 | AI74: 20 | AJ74: 0 | AK74: 19 | AL74: 0 | AM74: 0 | AN74: 1 | AO74: 0.29545 | AP74: 0 | AQ74: 1 | AR74: m | AS74: y | AT74: y | AU74: m | AV74: m | AW74: m | AX74: m | AY74: m | AZ74: m | BA74: m | BB74: m | BC74: m | BD74: m | BH74: not needed as transformed-cumulative preferred | BI74: 1 | BJ74: delete | BK74: transformed-partial | BL74: 0 | BM74: 0 | BN74: 0 | BO74: 0 | BP74: 0 | BQ74: 0 | BS74: 0 | BT74: 1 | BU74: 0 | BV74: 0 | BW74: 0 | BX74: 0 | BY74: 117 | CA74: check | CG74: 0 | CH74: 1 | CI74: 0 | CJ74: 0 | CK74: 0 | CL74: 0
A75: crs_ger_3.5Mar_d246_m160 | B75: car sharing | C75: Germany | D75: 3.5 | E75: Market Formation | F75: cumulative PrivateEquityDeals | G75: cumulative # deals | H75: m9 | I75: 0.42255 | J75: 0.18846 | K75: 0.49513 | L75: 2019.4 | M75: 10.4 | N75: 37.997 | O75: 11.729 | P75: 2017.8 | Q75: -986.73 | R75: 0.99751 | S75: 0.99733 | T75: 0.45551 | U75: 0.24898 | V75: 0.9678 | W75: 0.96626 | X75: 1.6393 | Y75: 1.0256 | Z75: 0.49549 | AA75: 0.47146 | AB75: 6.4886 | AC75: 5.1961 | AD75: 45 | AE75: 14 | AF75: 0.84216 | AG75: 0.026318 | AH75: 0.81585 | AI75: 14 | AJ75: 1 | AK75: 13 | AL75: 0 | AM75: 0 | AN75: 0 | AO75: 0.87883 | AP75: 0 | AQ75: 1 | AR75: y | AS75: y | AT75: y | AU75: y | AV75: y | AW75: y | AX75: y | AY75: y | AZ75: y | BA75: y | BB75: y | BC75: y | BD75: y | BI75: 0 | BJ75: prefer | BK75: transformed-cumulative | BL75: 1 | BM75: 1 | BN75: 0 | BO75: 0 | BP75: 0 | BQ75: 0 | BS75: 1 | BT75: 1 | BU75: 0 | BV75: 0 | BW75: 0 | BX75: 0 | BY75: 118 | CG75: 1 | CH75: 1 | CI75: 0 | CJ75: 0 | CK75: 0 | CL75: 0
A76: crs_ger_3.5Mar_d247_m161 | B76: car sharing | C76: Germany | D76: 3.5 | E76: Market Formation | F76: Partial up to max PrivateEquityDeals | G76: Partial up to max # deals | H76: m9 | I76: 0.33674 | J76: 0.0079229 | K76: 0.072766 | L76: 2019.1 | M76: 13.05 | N76: 7.6181 | O76: 1553.6 | P76: 157600 | Q76: -144.95 | R76: 0.89321 | S76: 0.88477 | T76: 0.4335 | U76: 0.21491 | V76: -0.21778 | W76: -0.28023 | X76: 1.4639 | Y76: 0.61905 | Z76: 0.44208 | AA76: 0.41347 | AB76: 0.99083 | AC76: 0.78035 | AD76: 42 | AE76: 10 | AF76: 0.65633 | AG76: 0.13127 | AH76: 0.52507 | AI76: 11 | AJ76: 0 | AK76: 10 | AL76: 0 | AM76: 0 | AN76: 1 | AO76: 0.72222 | AP76: 0 | AQ76: 1 | AR76: y | AS76: y | AT76: y | AU76: m | AV76: y | AW76: m | AX76: y | AY76: y | AZ76: y | BA76: m | BB76: m | BC76: m | BD76: m | BH76: not needed as transformed-cumulative preferred | BI76: 1 | BJ76: delete | BK76: transformed-partial | BL76: 0 | BM76: 0 | BN76: 0 | BO76: 0 | BP76: 0 | BQ76: 0 | BS76: 1 | BT76: 1 | BU76: 0 | BV76: 0 | BW76: 0 | BX76: 0 | BY76: 119 | BZ76: check | CA76: check | CG76: 1 | CH76: 1 | CI76: 0 | CJ76: 0 | CK76: 0 | CL76: 0
A77: crs_ger_3.5Mar_d248_m162 | B77: car sharing | C77: Germany | D77: 3.5 | E77: Market Formation | F77: cumulative PrivateEquityInvestment | G77: cumulative $ million | H77: m9 | I77: 1.2319 | J77: 0.32405 | K77: 5.9957 | L77: 2020.8 | M77: 3.5672 | N77: 599.02 | O77: 0.00017084 | P77: 1977.1 | Q77: -11953 | R77: 0.9971 | S77: 0.99689 | T77: 7.6783 | U77: 3.6694 | V77: 0.93933 | W77: 0.93644 | X77: 35.111 | Y77: 17.149 | Z77: 0.29838 | AA77: 0.26497 | AB77: 119.4 | AC77: 83.335 | AD77: 45 | AE77: 13 | AF77: 0.96515 | AG77: 0.0045142 | AH77: 0.96064 | AI77: 13 | AJ77: 1 | AK77: 12 | AL77: 0 | AM77: 0 | AN77: 1 | AO77: 0.79882 | AP77: 0 | AQ77: 0 | AR77: y | AS77: y | AT77: y | AU77: y | AV77: y | AW77: y | AX77: y | AY77: y | AZ77: m | BA77: y | BB77: m | BC77: y | BD77: m | BI77: 0 | BJ77: prefer | BK77: transformed-cumulative | BL77: 1 | BM77: 1 | BN77: 0 | BO77: 0 | BP77: 0 | BQ77: 0 | BS77: 1 | BT77: 1 | BU77: 0 | BV77: 0 | BW77: 0 | BX77: 0 | BY77: 120 | CG77: 1 | CH77: 1 | CI77: 0 | CJ77: 0 | CK77: 0 | CL77: 0
A78: crs_ger_3.5Mar_d249_m163 | B78: car sharing | C78: Germany | D78: 3.5 | E78: Market Formation | F78: Partial up to max PrivateEquityInvestment | G78: Partial up to max $ million | H78: m9 | I78: 1.0466 | J78: 1.0466 | K78: 1.1129 | L78: 2032.4 | M78: 4.1988 | N78: 33388000 | O78: 0.21885 | P78: 2014.4 | Q78: -2218.1 | R78: 0.99672 | S78: 0.99646 | T78: 1.9758 | U78: 0.74452 | V78: 0.99672 | W78: 0.99655 | X78: 1.9758 | Y78: 0.74451 | Z78: 0.15294 | AA78: 0.1095 | AB78: 31.747 | AC78: 15.66 | AD78: 42 | AE78: 8 | AF78: 6.4603e-06 | AG78: 7.3594e-08 | AH78: 6.3867e-06 | AI78: 10 | AJ78: 0 | AK78: 6 | AL78: 0 | AM78: 1 | AN78: 1 | AO78: 0.34108 | AP78: 0 | AQ78: 0 | AR78: y | AS78: y | AT78: y | AU78: m | AV78: m | AW78: m | AX78: m | AY78: m | AZ78: m | BA78: m | BB78: m | BC78: m | BD78: m | BH78: not needed as transformed-cumulative preferred | BI78: 1 | BJ78: delete | BK78: transformed-partial | BL78: 0 | BM78: 0 | BN78: 0 | BO78: 0 | BP78: 0 | BQ78: 0 | BS78: 1 | BT78: 1 | BU78: 0 | BV78: 0 | BW78: 0 | BX78: 0 | BY78: 121 | BZ78: check | CA78: check | CG78: 0 | CH78: 1 | CI78: 0 | CJ78: 0 | CK78: 0 | CL78: 0
A79: crs_ger_3.5Mar_d250_m162 | B79: car sharing | C79: Germany | D79: 3.5 | E79: Market Formation | F79: cumulative TotalFundraisingAmount | G79: cumulative $ million | H79: m9 | I79: 3.3991 | J79: 0.34025 | K79: 34.559 | L79: 2020.6 | M79: 1.2928 | N79: 3201.2 | O79: 1.3374e-07 | P79: 1953 | Q79: -68902 | R79: 0.98989 | S79: 0.98915 | T79: 87.06 | U79: 29.576 | V79: 0.90138 | W79: 0.89668 | X79: 271.95 | Y79: 120.88 | Z79: 0.26863 | AA79: 0.2338 | AB79: 740.57 | AC79: 517.33 | AD79: 45 | AE79: 13 | AF79: 1.127 | AG79: 0.00084471 | AH79: 1.1261 | AI79: 13 | AJ79: 0 | AK79: 12 | AL79: 0 | AM79: 0 | AN79: 1 | AO79: 0.75195 | AP79: 0 | AQ79: 0 | AR79: y | AS79: y | AT79: y | AU79: m | AV79: y | AW79: m | AX79: y | AY79: y | AZ79: m | BA79: m | BB79: m | BC79: m | BD79: m | BI79: 0 | BJ79: prefer | BK79: transformed-cumulative | BL79: 1 | BM79: 1 | BN79: 0 | BO79: 0 | BP79: 0 | BQ79: 0 | BS79: 1 | BT79: 1 | BU79: 0 | BV79: 0 | BW79: 0 | BX79: 0 | BY79: 122 | CG79: 0 | CH79: 1 | CI79: 0 | CJ79: 0 | CK79: 0 | CL79: 0
A80: crs_ger_3.5Mar_d251_m163 | B80: car sharing | C80: Germany | D80: 3.5 | E80: Market Formation | F80: Partial up to max TotalFundraisingAmount | G80: Partial up to max $ million | H80: m9 | I80: 3.3272 | J80: 3.3268 | K80: 8.4007 | L80: 2023.6 | M80: 1.3208 | N80: 10926000 | O80: 1.5991e-21 | P80: 2004.3 | Q80: -16745 | R80: 0.99523 | S80: 0.99485 | T80: 23.725 | U80: 5.7857 | V80: 0.99523 | W80: 0.99498 | X80: 23.724 | Y80: 5.786 | Z80: 0.087889 | AA80: 0.041114 | AB80: 328.03 | AC80: 133.94 | AD80: 42 | AE80: 9 | AF80: 0.00020632 | AG80: 1.0913e-07 | AH80: 0.00020621 | AI80: 10 | AJ80: 0 | AK80: 4 | AL80: 0 | AM80: 1 | AN80: 1 | AO80: 0.03599 | AP80: 0 | AQ80: 0 | AR80: y | AS80: y | AT80: y | AU80: m | AV80: m | AW80: m | AX80: m | AY80: m | AZ80: m | BA80: m | BB80: m | BC80: m | BD80: m | BH80: not needed as transformed-cumulative preferred | BI80: 1 | BJ80: delete | BK80: transformed-partial | BL80: 0 | BM80: 0 | BN80: 0 | BO80: 0 | BP80: 0 | BQ80: 0 | BS80: 1 | BT80: 1 | BU80: 0 | BV80: 0 | BW80: 0 | BX80: 0 | BY80: 123 | BZ80: check | CA80: check | CG80: 0 | CH80: 1 | CI80: 0 | CJ80: 0 | CK80: 0 | CL80: 0
A81: crs_ger_3.5Mar_d252_m160 | B81: car sharing | C81: Germany | D81: 3.5 | E81: Market Formation | F81: cumulative TotalFundraisingDeals | G81: cumulative # deals | H81: m9 | I81: 0.3087 | J81: 0.17493 | K81: 0.89499 | L81: 2020.9 | M81: 14.235 | N81: 84.934 | O81: 5.1026 | P81: 2009.3 | Q81: -1782.5 | R81: 0.99318 | S81: 0.99268 | T81: 1.3097 | U81: 1.1316 | V81: 0.98215 | W81: 0.9813 | X81: 2.1191 | Y81: 1.4207 | Z81: 0.53697 | AA81: 0.51492 | AB81: 10.794 | AC81: 8.5882 | AD81: 45 | AE81: 39 | AF81: 0.69466 | AG81: 0.011774 | AH81: 0.68288 | AI81: 39 | AJ81: 0 | AK81: 38 | AL81: 0 | AM81: 0 | AN81: 0 | AO81: 0.87454 | AP81: 0 | AQ81: 1 | AR81: y | AS81: y | AT81: y | AU81: y | AV81: y | AW81: y | AX81: y | AY81: y | AZ81: y | BA81: y | BB81: y | BC81: y | BD81: y | BI81: 0 | BJ81: prefer | BK81: transformed-cumulative | BL81: 1 | BM81: 1 | BN81: 0 | BO81: 0 | BP81: 0 | BQ81: 0 | BS81: 1 | BT81: 1 | BU81: 0 | BV81: 0 | BW81: 0 | BX81: 0 | BY81: 124 | CG81: 1 | CH81: 1 | CI81: 0 | CJ81: 0 | CK81: 0 | CL81: 0
A82: crs_ger_3.5Mar_d253_m161 | B82: car sharing | C82: Germany | D82: 3.5 | E82: Market Formation | F82: Partial up to max TotalFundraisingDeals | G82: Partial up to max # deals | H82: m9 | I82: 0.30712 | J82: 0.012404 | K82: 0.11993 | L82: 2021.3 | M82: 14.309 | N82: 18.901 | O82: 1552.7 | P82: 157690 | Q82: -238.82 | R82: 0.90258 | S82: 0.89489 | T82: 0.69729 | U82: 0.36683 | V82: -0.24035 | W82: -0.30395 | X82: 2.4881 | Y82: 1.0952 | Z82: 0.42336 | AA82: 0.39379 | AB82: 1.6965 | AC82: 1.2078 | AD82: 42 | AE82: 14 | AF82: 0.52906 | AG82: 0.052906 | AH82: 0.47616 | AI82: 36 | AJ82: 0 | AK82: 35 | AL82: 0 | AM82: 0 | AN82: 1 | AO82: 0.68077 | AP82: 0 | AQ82: 1 | AR82: y | AS82: y | AT82: y | AU82: m | AV82: m | AW82: m | AX82: m | AY82: y | AZ82: y | BA82: m | BB82: m | BC82: m | BD82: m | BH82: not needed as transformed-cumulative preferred | BI82: 1 | BJ82: delete | BK82: transformed-partial | BL82: 0 | BM82: 0 | BN82: 0 | BO82: 0 | BP82: 0 | BQ82: 0 | BS82: 1 | BT82: 1 | BU82: 0 | BV82: 0 | BW82: 0 | BX82: 0 | BY82: 125 | BZ82: check | CA82: check | CG82: 1 | CH82: 1 | CI82: 0 | CJ82: 0 | CK82: 0 | CL82: 0
A83: crs_ger_4.1Sal_d213_m100 | B83: car sharing | C83: Germany | D83: 4.1 | E83: Knowledge Flows (social networks) | F83: annualised Google search frequency (index 100=monthly max.) | G83: Index 0-100 | H83: m9 | I83: 20.545 | J83: 0.12514 | K83: 3.5117 | L83: 2016.9 | M83: 0.21389 | N83: 58.071 | O83: 0.69551 | P83: 1988 | Q83: -7051.1 | R83: 0.77386 | S83: 0.73395 | T83: 14.922 | U83: 7.5331 | V83: 0.39756 | W83: 0.33062 | X83: 24.355 | Y83: 17.743 | Z83: 0.45924 | AA83: 0.39916 | AB83: 23.075 | AC83: 16.656 | AD83: 21 | AE83: 8 | AF83: 1.722 | AG83: 0.52183 | AH83: 1.2002 | AI83: 8 | AJ83: 6 | AK83: 3 | AL83: 1 | AM83: 1 | AN83: 1 | AO83: 0.83842 | AP83: 0 | AQ83: 1 | AR83: y | AS83: y | AT83: y | AU83: y | AV83: y | AW83: y | AX83: y | AY83: y | AZ83: y | BA83: y | BB83: y | BC83: y | BD83: y | BI83: 0 | BJ83: hide | BK83: original | BL83: 1 | BM83: 1 | BN83: 0 | BO83: 0 | BP83: 0 | BQ83: 0 | BS83: 0 | BT83: 1 | BU83: 0 | BV83: 0 | BW83: 0 | BX83: 0 | BY83: 126 | BZ83: check | CG83: 0 | CH83: 1 | CI83: 0 | CJ83: 0 | CK83: 0 | CL83: 0
A84: crs_ger_4.1Sal_d239_m153 | B84: car sharing | C84: Germany | D84: 4.1 | E84: Knowledge Flows (social networks) | F84: Partial up to max annualised Google search frequency (index 100=monthly max.) | G84: Partial up to max Index 0-100 | H84: m9 | J84: 1.0466 | K84: 3.4988 | O84: 1.2016 | P84: 2013.8 | Q84: -7026.2 | V84: 0.97198 | W84: 0.96731 | X84: 4.4788 | Y84: 2.146 | Z84: 0.31916 | AA84: 0.20568 | AB84: 22.078 | AC84: 16.024 | AD84: 15 | AE84: 2 | AI84: 2 | AJ84: 0 | AK84: 1 | AL84: 0 | AM84: 0 | AN84: 1 | AO84: 0.38291 | AP84: 0 | AQ84: 1 | AR84: n | AS84: n | AT84: y | AU84: y | AV84: y | AW84: y | AX84: m | AY84: m | AZ84: y | BA84: n | BB84: n | BC84: n | BD84: n | BI84: 0 | BJ84: prefer | BK84: transformed-partial | BL84: 1 | BM84: 1 | BN84: 0 | BO84: 0 | BP84: 1 | BQ84: 1 | BS84: 0 | BT84: 1 | BU84: 0 | BV84: 0 | BW84: 1 | BX84: 1 | BY84: 127 | BZ84: check | CG84: 0 | CH84: 1 | CI84: 0 | CJ84: 0 | CK84: 1 | CL84: 1
A85: crs_ger_4.2Kme_d001_m132 | B85: car sharing | C85: Germany | D85: 4.2 | E85: Knowledge Flows (mass media) | F85: "car sharing" mention in books | G85: index (2022=100) | H85: m9 | I85: 0.20878 | J85: 0.12447 | K85: 4.1051 | L85: 2018.2 | M85: 21.049 | N85: 155.13 | O85: 0.17914 | P85: 1970.1 | Q85: -8213.7 | R85: 0.97131 | S85: 0.9674 | T85: 5.6147 | U85: 5.1835 | V85: 0.95503 | W85: 0.95112 | X85: 7.03 | Y85: 5.9975 | Z85: 0.86257 | AA85: 0.85062 | AB85: 12.29 | AC85: 10.506 | AD85: 26 | AE85: 26 | AF85: 0.64463 | AG85: 0.0036045 | AH85: 0.64102 | AI85: 26 | AJ85: 0 | AK85: 25 | AL85: 0 | AM85: 0 | AN85: 1 | AO85: 0.91067 | AP85: 0 | AQ85: 1 | AR85: y | AS85: y | AT85: y | AU85: y | AV85: y | AW85: y | AX85: y | AY85: y | AZ85: y | BA85: y | BB85: y | BC85: y | BD85: y | BE85: 1 | BI85: 0 | BL85: 1 | BM85: 1 | BS85: 1 | BT85: 1 | BU85: 0 | BV85: 0 | BW85: 1 | BX85: 1 | BY85: 128 | CG85: 1 | CH85: 1 | CI85: 0 | CJ85: 0 | CK85: 1 | CL85: 1
A86: crs_ger_4.2Kme_d254_m164 | B86: car sharing | C86: Germany | D86: 4.2 | E86: Knowledge Flows (mass media) | F86: Partial up to max "car sharing" mention in books | G86: Partial up to max index (2022=100) | H86: m9 | I86: 0.20878 | J86: 0.12447 | K86: 4.1051 | L86: 2018.2 | M86: 21.049 | N86: 155.13 | O86: 0.17914 | P86: 1970.1 | Q86: -8213.7 | R86: 0.97131 | S86: 0.9674 | T86: 5.6147 | U86: 5.1835 | V86: 0.95503 | W86: 0.95112 | X86: 7.03 | Y86: 5.9975 | Z86: 0.86257 | AA86: 0.85062 | AB86: 12.29 | AC86: 10.506 | AD86: 26 | AE86: 26 | AF86: 0.64463 | AG86: 0.0036045 | AH86: 0.64102 | AI86: 26 | AJ86: 0 | AK86: 25 | AL86: 0 | AM86: 0 | AN86: 1 | AO86: 0.91067 | AP86: 0 | AQ86: 1 | AR86: y | AS86: y | AT86: y | AU86: y | AV86: y | AW86: y | AX86: y | AY86: y | AZ86: y | BA86: y | BB86: y | BC86: y | BD86: y | BI86: 0 | BL86: 1 | BM86: 1 | BS86: 1 | BT86: 1 | BU86: 0 | BV86: 0 | BW86: 0 | BX86: 0 | BY86: 129 | CG86: 1 | CH86: 1 | CI86: 0 | CJ86: 0 | CK86: 0 | CL86: 0
A87: crs_glo_3.3Sci_d235_m020 | B87: car sharing | C87: Global | D87: 3.3 | E87: Risk & Uncertainty (Shared Expectations) | F87: scientific publications | G87: # publications | H87: m9 | I87: 0.76722 | J87: 0.15114 | K87: 7.5509 | L87: 2017.2 | M87: 5.7277 | N87: 599.57 | O87: 0.00015335 | P87: 1922.4 | Q87: -14996 | R87: 0.96724 | S87: 0.96531 | T87: 33.136 | U87: 13.306 | V87: 0.85719 | W87: 0.85169 | X87: 69.186 | Y87: 37.007 | Z87: 0.42869 | AA87: 0.40671 | AB87: 138.38 | AC87: 107.23 | AD87: 55 | AE87: 31 | AF87: 1.2142 | AG87: 0.0016679 | AH87: 1.2125 | AI87: 44 | AJ87: 3 | AK87: 43 | AL87: 0 | AM87: 0 | AN87: 1 | AO87: 0.92661 | AP87: 0 | AQ87: 0 | AR87: y | AS87: y | AT87: y | AU87: y | AV87: y | AW87: y | AX87: y | AY87: y | AZ87: y | BA87: y | BB87: y | BC87: y | BD87: y | BH87: good; only available global, apply to all EA regions | BI87: 0 | BL87: 1 | BM87: 1 | BN87: 0 | BO87: 0 | BP87: 1 | BQ87: 1 | BS87: 1 | BT87: 1 | BU87: 0 | BV87: 0 | BW87: 1 | BX87: 1 | BY87: 130 | CG87: 1 | CH87: 1 | CI87: 0 | CJ87: 0 | CK87: 1 | CL87: 1
A88: crs_glo_3.5Mar_d074_m128 | B88: car sharing | C88: Global | D88: 3.5 | E88: Market Formation | F88: CumulativeStartups | G88: cum. # companies | H88: m9 | I88: 0.25922 | J88: 0.10787 | K88: 6.0866 | L88: 2015.7 | M88: 16.952 | N88: 324.98 | O88: 0.024613 | P88: 1935.7 | Q88: -12116 | R88: 0.99432 | S88: 0.99391 | T88: 6.9906 | U88: 5.8813 | V88: 0.95891 | W88: 0.95695 | X88: 18.804 | Y88: 13.624 | Z88: 0.72618 | AA88: 0.71314 | AB88: 48.54 | AC88: 42.918 | AD88: 45 | AE88: 43 | AF88: 0.84928 | AG88: 0.0030771 | AH88: 0.8462 | AI88: 43 | AJ88: 0 | AK88: 42 | AL88: 0 | AM88: 0 | AN88: 0 | AO88: 0.93268 | AP88: 0 | AQ88: 0 | AR88: y | AS88: y | AT88: y | AU88: y | AV88: y | AW88: y | AX88: y | AY88: y | AZ88: y | BA88: y | BB88: y | BC88: y | BD88: y | BE88: 1 | BF88: cum | BI88: 0 | BJ88: prefer | BK88: original | BL88: 1 | BM88: 1 | BN88: 0 | BO88: 0 | BP88: 0 | BQ88: 1 | BS88: 1 | BT88: 1 | BU88: 0 | BV88: 0 | BW88: 0 | BX88: 1 | BY88: 131 | CG88: 1 | CH88: 1 | CI88: 0 | CJ88: 0 | CK88: 0 | CL88: 1
A89: crs_glo_3.5Mar_d126_m008 | B89: car sharing | C89: Global | D89: 3.5 | E89: Market Formation | F89: NewStartups | G89: # companies | H89: m9 | I89: 0.60418 | J89: 0.053732 | K89: 0.42714 | L89: 2008.7 | M89: 7.2735 | N89: 16.05 | O89: 9.1395 | P89: 2012.2 | Q89: -849 | R89: 0.62337 | S89: 0.59581 | T89: 5.1127 | U89: 3.081 | V89: 0.38354 | W89: 0.35418 | X89: 6.5411 | Y89: 4.5711 | Z89: 0.44339 | AA89: 0.41688 | AB89: 6.2154 | AC89: 4.4379 | AD89: 45 | AE89: 35 | AF89: 1.8068 | AG89: 0.062304 | AH89: 1.7445 | AI89: 43 | AJ89: 8 | AK89: 42 | AL89: 1 | AM89: 0 | AN89: 1 | AO89: 0.93314 | AP89: 0 | AQ89: 1 | AR89: m | AS89: y | AT89: y | AU89: y | AV89: y | AW89: y | AX89: y | AY89: y | AZ89: y | BA89: m | BB89: y | BC89: m | BD89: y | BE89: 4 | BF89: interesting | BG89: convert to cum. | BI89: 0 | BJ89: hide | BK89: original | BL89: 1 | BM89: 1 | BN89: 0 | BO89: 0 | BP89: 0 | BQ89: 0 | BS89: 1 | BT89: 1 | BU89: 0 | BV89: 0 | BW89: 0 | BX89: 0 | BY89: 132 | CG89: 1 | CH89: 1 | CI89: 0 | CJ89: 0 | CK89: 0 | CL89: 0
A90: crs_glo_3.5Mar_d171_m011 | B90: car sharing | C90: Global | D90: 3.5 | E90: Market Formation | F90: PrivateEquityDeals | G90: # deals | H90: m9 | I90: 0.81265 | J90: 0.099582 | K90: 0.91647 | L90: 2013.6 | M90: 5.4075 | N90: 38.125 | O90: 6.9255 | P90: 2004.9 | Q90: -1825.3 | R90: 0.90602 | S90: 0.89914 | T90: 4.8064 | U90: 2.169 | V90: 0.71392 | W90: 0.70029 | X90: 8.3858 | Y90: 5.9143 | Z90: 0.57633 | AA90: 0.55616 | AB90: 10.205 | AC90: 8.5432 | AD90: 45 | AE90: 19 | AF90: 1.3639 | AG90: 0.026229 | AH90: 1.3377 | AI90: 28 | AJ90: 3 | AK90: 27 | AL90: 1 | AM90: 0 | AN90: 1 | AO90: 0.95044 | AP90: 0 | AQ90: 1 | AR90: y | AS90: y | AT90: y | AU90: y | AV90: y | AW90: y | AX90: y | AY90: y | AZ90: y | BA90: y | BB90: y | BC90: y | BD90: y | BE90: 4 | BG90: convert to cum. | BI90: 0 | BJ90: hide | BK90: original | BL90: 1 | BM90: 1 | BN90: 0 | BO90: 0 | BP90: 0 | BQ90: 0 | BS90: 1 | BT90: 1 | BU90: 0 | BV90: 0 | BW90: 0 | BX90: 0 | BY90: 133 | CG90: 1 | CH90: 1 | CI90: 0 | CJ90: 0 | CK90: 0 | CL90: 0
