Workbook

Sheet Data
A1: SI | B1: co-housing | C1: co-housing | D1: co-housing | E1: co-housing | F1: mobesity | G1: microfinance | H1: microfinance | I1: microfinance | J1: eating less meat | K1: eating less meat | L1: eating less meat | M1: eating less meat | N1: eating less meat | O1: climate protest | P1: climate protest | Q1: climate protest | R1: climate protest | S1: climate protest | T1: climate protest | U1: climate protest | V1: energy community | W1: active mobility | X1: car sharing | Y1: firm ESG reporting | Z1: firm ESG reporting | AA1: firm ESG reporting | AB1: firm ESG reporting | AC1: e-bikes | AD1: e-bikes | AE1: e-bikes | AF1: low carbon long distance travel | AG1: passive building retrofits | AH1: passive building retrofits | AI1: passive building retrofits | AJ1: passive building retrofits
A2: Indicator | B2: Population | C2: Population | D2: Population | E2: Population | F2: heaviest vehicle available | G2: Population | H2: Population | I2: Population | J2: total kg food | K2: total kg food | L2: total kg food | M2: total kg food | N2: total kg food | O2: Population | P2: Population | Q2: Population | R2: Population | S2: Population | T2: Population | U2: Population | V2: Population | W2: pkm- road & rail (millions) | X2: population | Y2: # of firms | Z2: # of firms | AA2: # of firms | AB2: # of firms | AC2: total bike sales | AD2: total bike sales | AE2: total bike sales | AF2: road+rail pkm | AG2: # new renovated houses | AH2: # new renovated houses | AI2: # new renovated houses | AJ2: # new renovated houses
A3: Country | B3: US | C3: Germany | D3: Denmark | E3: Vaud | F3: Germany | G3: India | H3: Bangladesh | I3: Nigeria | J3: Germany | K3: Japan | L3: India | M3: UK | N3: US | O3: Bangladesh | P3: Germany | Q3: India | R3: Sweden | S3: UK | T3: US | U3: Global | V3: The Netherlands | W3: Netherlands | X3: Germany | Y3: Asia-Pacific | Z3: Europe | AA3: Americas | AB3: Middle East & Africa | AC3: China | AD3: Netherlands | AE3: EU | AF3: Germany | AG3: Germany | AH3: Austria | AI3: Belgium | AJ3: Ireland
A4: Source | B4: census.gov | C4: ourworldindata.org | D4: ourworldindata.org | G4: Our World in Data | H4: Our World in Data | I4: Our World in Data | J4: original eating less meat data | K4: original eating less meat data | L4: original eating less meat data | M4: original eating less meat data | N4: original eating less meat data | O4: Our World in Data | P4: Our World in Data | Q4: Our World in Data | R4: Our World in Data | S4: Our World in Data | T4: Our World in Data | U4: Our World in Data | V4: Our World in Data | W4: European Environment Agency | X4: Our World in Data | Y4: globalreporting.org | Z4: globalreporting.org | AA4: globalreporting.org | AB4: globalreporting.org | AC4: Statisa | AD4: Statisa | AE4: Statisa | AF4: Our World in Data | AG4: European Commission Joint Research Centre Data Catalogue | AH4: European Commission Joint Research Centre Data Catalogue | AI4: European Commission Joint Research Centre Data Catalogue | AJ4: European Commission Joint Research Centre Data Catalogue
A5: URL | C5: https://ourworldindata.org/grapher/population-unwpp?country=DNK~DEU~CHE | D5: https://ourworldindata.org/grapher/population-unwpp?country=DNK~DEU~CHE | E5: https://citypopulation.de/en/switzerland/cities/ | G5: https://ourworldindata.org/grapher/population?time=1890..latest&country=IND~BGD~NGA | H5: https://ourworldindata.org/grapher/population?time=1890..latest&country=IND~BGD~NGA | I5: https://ourworldindata.org/grapher/population?time=1890..latest&country=IND~BGD~NGA | O5: https://ourworldindata.org/grapher/population?time=1890..latest&country=IND~BGD~NGA | P5: https://ourworldindata.org/grapher/population-unwpp?country=DNK~DEU~CHE | Q5: https://ourworldindata.org/grapher/population?time=1890..latest&country=IND~BGD~NGA | R5: https://ourworldindata.org/grapher/population?time=1909..latest&country=USA~OWID_WRL~GBR | S5: https://ourworldindata.org/grapher/population?time=1909..latest&country=USA~OWID_WRL~GBR | T5: https://ourworldindata.org/grapher/population?time=1909..latest&country=USA~OWID_WRL~GBR | U5: https://ourworldindata.org/grapher/population?time=1909..latest&country=USA~OWID_WRL~GBR | V5: https://ourworldindata.org/grapher/population?time=1909..latest&country=~NLD | W5: https://www.eea.europa.eu/en/analysis/publications/sustainability-of-europes-mobility-systems/passenger-transport-activity/eu-27-passenger-transport-activity-gpkm-for-different-transport-modes-according-to-the-ff55-mix-scenario?activeTab=570bee2d-1316-48cf-adde-4b640f92119b | Y5: https://www.globalreporting.org/news/news-center/gri-global-adoption-by-top-companies-continues-to-grow/ | Z5: https://www.globalreporting.org/news/news-center/gri-global-adoption-by-top-companies-continues-to-grow/ | AA5: https://www.globalreporting.org/news/news-center/gri-global-adoption-by-top-companies-continues-to-grow/ | AB5: https://www.globalreporting.org/news/news-center/gri-global-adoption-by-top-companies-continues-to-grow/ | AC5: see ebikes sheet for url | AD5: see ebikes sheet for url | AE5: see ebikes sheet for url | AF5: https://ourworldindata.org/grapher/annual-reported-passenger-kilometers?country=~NLD | AG5: https://data.jrc.ec.europa.eu/dataset/82322924-506a-4c9a-8532-2bdd30d69bf5#dataaccess | AH5: https://data.jrc.ec.europa.eu/dataset/82322924-506a-4c9a-8532-2bdd30d69bf5#dataaccess | AI5: https://data.jrc.ec.europa.eu/dataset/82322924-506a-4c9a-8532-2bdd30d69bf5#dataaccess | AJ5: https://data.jrc.ec.europa.eu/dataset/82322924-506a-4c9a-8532-2bdd30d69bf5#dataaccess
A6: units | B6: people | C6: people | D6: people | E6: people | F6: kg | G6: people | H6: people | I6: people | J6: kg food | K6: kg food | L6: kg food | M6: kg food | N6: kg food | O6: people | P6: people | Q6: people | R6: people | S6: people | T6: people | U6: people | V6: people | X6: people | Y6: % | Z6: % | AA6: % | AB6: % | AC6: million | AD6: million | AE6: million | AF6: pkm | AG6: houses | AH6: houses | AI6: houses | AJ6: houses
A7: 1900 | F7: 3129 | R7: 5123503
A8: 1901 | F8: 3129 | R8: 5157047
A9: 1902 | F9: 3129 | R9: 5190268
A10: 1903 | F10: 3129 | R10: 5223160
A11: 1904 | F11: 3129 | R11: 5256260
A12: 1905 | F12: 3129 | R12: 5289570
A13: 1906 | F13: 3129 | R13: 5323091
A14: 1907 | F14: 3129 | R14: 5356825
A15: 1908 | F15: 3129 | R15: 5390772
A16: 1909 | F16: 3129 | R16: 5426317
A17: 1910 | F17: 3129 | R17: 5463482
A18: 1911 | F18: 3129 | R18: 5502286
... A76: 1969 | F76: 3129 | R76: 7968013
A77: 1970 | B77: 203211926 | C77: ='cohousing population'!D96 -> 78205102 | D77: ='cohousing population'!D22 -> 4928676 | F77: 3129 | J77: ='elm- g'!C21 -> 139.03019 | K77: ='elm- j'!C21 -> 142.01987 | L77: ='elm-i'!C21 -> 46.437518 | M77: ='elm- uk'!C21 -> 148.55998 | N77: ='elm- us'!C21 -> 210.22802 | R77: 8042783
A78: 1971 | B78: 202907917 | C78: ='cohousing population'!D97 -> 78345873 | D78: ='cohousing population'!D23 -> 4963062 | F78: 3129 | J78: ='elm- g'!C22 -> 140.8669 | K78: ='elm- j'!C22 -> 147.91391 | L78: ='elm-i'!C22 -> 47.267345 | M78: ='elm- uk'!C22 -> 149.89216 | N78: ='elm- us'!C22 -> 216.43923 | R78: 8098105
A79: 1972 | B79: 205238390 | C79: ='cohousing population'!D98 -> 78719923 | D79: ='cohousing population'!D24 -> 4991568 | F79: 3129 | J79: ='elm- g'!C23 -> 146.15464 | K79: ='elm- j'!C23 -> 149.30463 | L79: ='elm-i'!C23 -> 48.061274 | M79: ='elm- uk'!C23 -> 147.39541 | N79: ='elm- us'!C23 -> 215.37838 | R79: 8122427
A80: 1973 | B80: 207314764 | C80: ='cohousing population'!D99 -> 78966976 | D80: ='cohousing population'!D25 -> 5021765 | F80: 3129 | J80: ='elm- g'!C24 -> 147.98152 | K80: ='elm- j'!C24 -> 145.96804 | L80: ='elm-i'!C24 -> 48.533628 | M80: ='elm- uk'!C24 -> 148.58977 | N80: ='elm- us'!C24 -> 206.86047 | R80: 8137164
A81: 1974 | B81: 209277968 | C81: ='cohousing population'!D100 -> 78996693 | D81: ='cohousing population'!D26 -> 5045638 | F81: 3129 | J81: ='elm- g'!C25 -> 150.34413 | K81: ='elm- j'!C25 -> 143.07278 | L81: ='elm-i'!C25 -> 49.071266 | M81: ='elm- uk'!C25 -> 151.05761 | N81: ='elm- us'!C25 -> 217.57302 | R81: 8160636
A82: 1975 | B82: 211274535 | C82: ='cohousing population'!D101 -> 78701861 | D82: ='cohousing population'!D27 -> 5060403 | F82: 3129 | J82: ='elm- g'!C26 -> 150.21146 | K82: ='elm- j'!C26 -> 142.55302 | L82: ='elm-i'!C26 -> 49.427351 | M82: ='elm- uk'!C26 -> 139.35072 | N82: ='elm- us'!C26 -> 216.31835 | R82: 8192642
A83: 1976 | B83: 213270022 | C83: ='cohousing population'!D102 -> 78364503 | D83: ='cohousing population'!D28 -> 5072804 | F83: 3129 | J83: ='elm- g'!C27 -> 151.62391 | K83: ='elm- j'!C27 -> 143.84402 | L83: ='elm-i'!C27 -> 49.825605 | M83: ='elm- uk'!C27 -> 133.00823 | N83: ='elm- us'!C27 -> 218.84763 | R83: 8222393
A84: 1977 | B84: 215437405 | C84: ='cohousing population'!D103 -> 78185560 | D84: ='cohousing population'!D29 -> 5088574 | F84: 3129 | J84: ='elm- g'!C28 -> 157.21597 | K84: ='elm- j'!C28 -> 149.87519 | L84: ='elm-i'!C28 -> 50.27923 | M84: ='elm- uk'!C28 -> 158.25168 | N84: ='elm- us'!C28 -> 225.64588 | R84: 8251698
A85: 1978 | B85: 217881437 | C85: ='cohousing population'!D104 -> 78115357 | D85: ='cohousing population'!D30 -> 5104342 | F85: 3129 | J85: ='elm- g'!C29 -> 162.15526 | K85: ='elm- j'!C29 -> 151.75553 | L85: ='elm-i'!C29 -> 50.771496 | M85: ='elm- uk'!C29 -> 147.97242 | N85: ='elm- us'!C29 -> 223.04374 | R85: 8275793
A86: 1979 | B86: 220463115 | C86: ='cohousing population'!D105 -> 78147899 | D86: ='cohousing population'!D31 -> 5116861 | F86: 3129 | J86: ='elm- g'!C30 -> 164.33061 | K86: ='elm- j'!C30 -> 151.38652 | L86: ='elm-i'!C30 -> 51.043366 | M86: ='elm- uk'!C30 -> 152.45412 | N86: ='elm- us'!C30 -> 225.34364 | R86: 8293749
A87: 1980 | B87: 226545805 | C87: ='cohousing population'!D106 -> 78315374 | D87: ='cohousing population'!D32 -> 5123078 | E87: 528747 | F87: 3129 | J87: ='elm- g'!C31 -> 164.55313 | K87: ='elm- j'!C31 -> 150.56591 | L87: ='elm-i'!C31 -> 51.397191 | M87: ='elm- uk'!C31 -> 149.18805 | N87: ='elm- us'!C31 -> 217.19931 | R87: 8310470 | V87: ='energy communities population'!D73 -> 14162687
A88: 1981 | B88: 228670000 | C88: ='cohousing population'!D107 -> 78448044 | D88: ='cohousing population'!D33 -> 5121628 | E88: =(($E$97-$E$87)/10)+E87 -> 536053.9 | F88: =((F97-F87)/10)+F87 -> 3129 | J88: ='elm- g'!C32 -> 170.21705 | K88: ='elm- j'!C32 -> 152.45925 | L88: ='elm-i'!C32 -> 52.193175 | M88: ='elm- uk'!C32 -> 147.39294 | N88: ='elm- us'!C32 -> 216.37797 | R88: 8320460 | V88: ='energy communities population'!D74 -> 14262690
A89: 1982 | B89: 230997000 | C89: ='cohousing population'!D108 -> 78393671 | D89: ='cohousing population'!D34 -> 5117897 | E89: =(($E$97-$E$87)/10)+E88 -> 543360.8 | F89: 3129 | J89: ='elm- g'!C33 -> 167.0054 | K89: ='elm- j'!C33 -> 152.51014 | L89: ='elm-i'!C33 -> 53.235543 | M89: ='elm- uk'!C33 -> 154.86522 | N89: ='elm- us'!C33 -> 224.61058 | R89: 8325179 | V89: ='energy communities population'!D75 -> 14333902
A90: 1983 | B90: 233307000 | C90: ='cohousing population'!D109 -> 78224137 | D90: ='cohousing population'!D35 -> 5114468 | E90: =(($E$97-$E$87)/10)+E89 -> 550667.7 | F90: 3129 | J90: ='elm- g'!C34 -> 166.14676 | K90: ='elm- j'!C34 -> 148.22741 | L90: ='elm-i'!C34 -> 54.166377 | M90: ='elm- uk'!C34 -> 149.42382 | N90: ='elm- us'!C34 -> 218.85577 | R90: 8328917 | V90: ='energy communities population'!D76 -> 14396901
A91: 1984 | B91: 235825000 | C91: ='cohousing population'!D110 -> 77998199 | D91: ='cohousing population'!D36 -> 5111830 | E91: =(($E$97-$E$87)/10)+E90 -> 557974.6 | F91: 3129 | J91: ='elm- g'!C35 -> 172.89805 | K91: ='elm- j'!C35 -> 153.1616 | L91: ='elm-i'!C35 -> 54.662507 | M91: ='elm- uk'!C35 -> 153.8559 | N91: ='elm- us'!C35 -> 227.08407 | R91: 8336484 | V91: ='energy communities population'!D77 -> 14462810
A92: 1985 | B92: 238466000 | C92: ='cohousing population'!D111 -> 77863423 | D92: ='cohousing population'!D37 -> 5113878 | E92: =(($E$97-$E$87)/10)+E91 -> 565281.5 | F92: 3129 | J92: ='elm- g'!C36 -> 172.06177 | K92: ='elm- j'!C36 -> 151.79048 | L92: ='elm-i'!C36 -> 54.774746 | M92: ='elm- uk'!C36 -> 152.09297 | N92: ='elm- us'!C36 -> 228.23478 | R92: 8350249 | V92: ='energy communities population'!D78 -> 14538958
A93: 1986 | B93: 241116000 | C93: ='cohousing population'!D112 -> 77923807 | D93: ='cohousing population'!D38 -> 5120691 | E93: =(($E$97-$E$87)/10)+E92 -> 572588.4 | F93: 3129 | J93: ='elm- g'!C37 -> 173.8649 | K93: ='elm- j'!C37 -> 155.72247 | L93: ='elm-i'!C37 -> 55.263531 | M93: ='elm- uk'!C37 -> 154.55767 | N93: ='elm- us'!C37 -> 225.34665 | R93: 8369682 | V93: ='energy communities population'!D79 -> 14626489
A94: 1987 | B94: 243829000 | C94: ='cohousing population'!D113 -> 78062321 | D94: ='cohousing population'!D39 -> 5127135 | E94: =(($E$97-$E$87)/10)+E93 -> 579895.3 | F94: 3129 | J94: ='elm- g'!C38 -> 175.35144 | K94: ='elm- j'!C38 -> 156.79455 | L94: ='elm-i'!C38 -> 56.242225 | M94: ='elm- uk'!C38 -> 154.16371 | N94: ='elm- us'!C38 -> 231.13596 | R94: 8397651 | V94: ='energy communities population'!D80 -> 14724947
A95: 1988 | B95: 246551000 | C95: ='cohousing population'!D114 -> 78385993 | D95: ='cohousing population'!D40 -> 5129650 | E95: =(($E$97-$E$87)/10)+E94 -> 587202.2 | F95: 3129 | J95: ='elm- g'!C39 -> 177.01437 | K95: ='elm- j'!C39 -> 155.79831 | L95: ='elm-i'!C39 -> 56.247038 | M95: ='elm- uk'!C39 -> 161.21136 | N95: ='elm- us'!C39 -> 226.31839 | R95: 8436358 | V95: ='energy communities population'!D81 -> 14825916
A96: 1989 | B96: 249439000 | C96: ='cohousing population'!D115 -> 79007063 | D96: ='cohousing population'!D41 -> 5132717 | E96: =(($E$97-$E$87)/10)+E95 -> 594509.1 | F96: 3129 | J96: ='elm- g'!C40 -> 173.00012 | K96: ='elm- j'!C40 -> 156.91576 | L96: ='elm-i'!C40 -> 56.068005 | M96: ='elm- uk'!C40 -> 158.47103 | N96: ='elm- us'!C40 -> 238.73136 | R96: 8492819 | V96: ='energy communities population'!D82 -> 14921107
A97: 1990 | B97: 248709873 | C97: ='cohousing population'!D116 -> 79707964 | D97: ='cohousing population'!D42 -> 5141025 | E97: 601816 | F97: 3129 | J97: ='elm- g'!C41 -> 170.22194 | K97: ='elm- j'!C41 -> 153.22844 | L97: ='elm-i'!C41 -> 56.079244 | M97: ='elm- uk'!C41 -> 160.78072 | N97: ='elm- us'!C41 -> 235.36004 | R97: 8558569 | V97: ='energy communities population'!D83 -> 15030884
A98: 1991 | B98: 252153092 | C98: ='cohousing population'!D117 -> 80303189 | D98: ='cohousing population'!D43 -> 5154346 | E98: =(($E$107-$E$97)/10)+E97 -> 605700.1 | F98: 3129 | J98: ='elm- g'!C42 -> 167.16528 | K98: ='elm- j'!C42 -> 151.54672 | L98: ='elm-i'!C42 -> 56.016141 | M98: ='elm- uk'!C42 -> 162.00051 | N98: ='elm- us'!C42 -> 234.13448 | R98: 8616954 | V98: ='energy communities population'!D84 -> 15155091
A99: 1992 | B99: 255029699 | C99: ='cohousing population'!D118 -> 80934901 | D99: ='cohousing population'!D44 -> 5171371 | E99: =(($E$107-$E$97)/10)+E98 -> 609584.2 | F99: 3129 | J99: ='elm- g'!C43 -> 169.41724 | K99: ='elm- j'!C43 -> 155.34507 | L99: ='elm-i'!C43 -> 55.674421 | M99: ='elm- uk'!C43 -> 167.21096 | N99: ='elm- us'!C43 -> 234.18764 | R99: 8667577 | V99: ='energy communities population'!D85 -> 15276786
A100: 1993 | B100: 257782608 | C100: ='cohousing population'!D119 -> 81486770 | D100: ='cohousing population'!D45 -> 5188639 | E100: =(($E$107-$E$97)/10)+E99 -> 613468.3 | F100: 3129 | J100: ='elm- g'!C44 -> 158.28927 | K100: ='elm- j'!C44 -> 152.21069 | L100: ='elm-i'!C44 -> 57.144714 | M100: ='elm- uk'!C44 -> 162.26704 | N100: ='elm- us'!C44 -> 232.84619 | R100: 8718036 | V100: ='energy communities population'!D86 -> 15389718
A101: 1994 | B101: 260327021 | C101: ='cohousing population'!D120 -> 81773612 | D101: ='cohousing population'!D46 -> 5206190 | E101: =(($E$107-$E$97)/10)+E100 -> 617352.4 | F101: 3129 | J101: ='elm- g'!C45 -> 164.19633 | K101: ='elm- j'!C45 -> 153.54141 | L101: ='elm-i'!C45 -> 57.214877 | M101: ='elm- uk'!C45 -> 155.6729 | N101: ='elm- us'!C45 -> 249.73465 | R101: 8780193 | V101: ='energy communities population'!D87 -> 15485453
A102: 1995 | B102: 262803276 | C102: ='cohousing population'!D121 -> 82019890 | D102: ='cohousing population'!D47 -> 5233363 | E102: =(($E$107-$E$97)/10)+E101 -> 621236.5 | F102: 3129 | J102: ='elm- g'!C46 -> 163.05044 | K102: ='elm- j'!C46 -> 159.45189 | L102: ='elm-i'!C46 -> 58.570655 | M102: ='elm- uk'!C46 -> 151.17398 | N102: ='elm- us'!C46 -> 243.13838 | R102: 8826299 | V102: ='energy communities population'!D88 -> 15565033 | AF102: ='long distance travel'!D13 -> 954777000000
A103: 1996 | B103: 265228572 | C103: ='cohousing population'!D122 -> 82263195 | D103: ='cohousing population'!D48 -> 5263072 | E103: =(($E$107-$E$97)/10)+E102 -> 625120.6 | F103: 3129 | J103: ='elm- g'!C47 -> 174.39707 | K103: ='elm- j'!C47 -> 158.8844 | L103: ='elm-i'!C47 -> 58.114863 | M103: ='elm- uk'!C47 -> 154.92572 | N103: ='elm- us'!C47 -> 244.17342 | R103: 8840329 | V103: ='energy communities population'!D89 -> 15640031 | AF103: ='long distance travel'!D14 -> 956130000000
A104: 1997 | B104: 267783607 | C104: ='cohousing population'!D123 -> 82389631 | D104: ='cohousing population'!D49 -> 5285041 | E104: =(($E$107-$E$97)/10)+E103 -> 629004.7 | F104: 3129 | J104: ='elm- g'!C48 -> 168.72265 | K104: ='elm- j'!C48 -> 153.74635 | L104: ='elm-i'!C48 -> 54.249573 | M104: ='elm- uk'!C48 -> 158.58515 | N104: ='elm- us'!C48 -> 241.39322 | R104: 8845524 | V104: ='energy communities population'!D90 -> 15723620 | X104: ='cohousing population'!D123 -> 82389631 | AF104: ='long distance travel'!D15 -> 957503000000 | AG104: ='passive building (germany)'!H2 -> 1046790.1 | AH104: ='passive building (austria)'!H2 -> 129521.01 | AI104: ='passive building (belgium)'!H2 -> 86533.333 | AJ104: ='passive building (ireland)'!H2 -> 59650.741
A105: 1998 | B105: 270248003 | C105: ='cohousing population'!D124 -> 82011933 | D105: ='cohousing population'!D50 -> 5304264 | E105: =(($E$107-$E$97)/10)+E104 -> 632888.8 | F105: 3129 | J105: ='elm- g'!C49 -> 173.87594 | K105: ='elm- j'!C49 -> 151.36168 | L105: ='elm-i'!C49 -> 62.284037 | M105: ='elm- uk'!C49 -> 165.53501 | N105: ='elm- us'!C49 -> 240.69082 | R105: 8850606 | V105: ='energy communities population'!D91 -> 15827109 | X105: ='cohousing population'!D124 -> 82011933 | AF105: ='long distance travel'!D16 -> 968266000000 | AG105: ='passive building (germany)'!H3 -> 1042319.8 | AH105: ='passive building (austria)'!H3 -> 127771.26 | AI105: ='passive building (belgium)'!H3 -> 96413 | AJ105: ='passive building (ireland)'!H3 -> 58937.556
A106: 1999 | B106: 272690813 | C106: ='cohousing population'!D125 -> 81678279 | D106: ='cohousing population'!D51 -> 5321814 | E106: =(($E$107-$E$97)/10)+E105 -> 636772.9 | F106: 3129 | J106: ='elm- g'!C50 -> 175.5874 | K106: ='elm- j'!C50 -> 156.51034 | L106: ='elm-i'!C50 -> 67.38205 | M106: ='elm- uk'!C50 -> 169.19922 | N106: ='elm- us'!C50 -> 259.32175 | R106: 8857691 | V106: ='energy communities population'!D92 -> 15940182 | X106: ='cohousing population'!D125 -> 81678279 | Y106: ='ESG firms'!O106 -> 1946.1538 | Z106: ='ESG firms'!P106 -> 1848.0519 | AA106: ='ESG firms'!Q106 -> 2653.012 | AB106: ='ESG firms'!R106 -> 263.46154 | AF106: ='long distance travel'!D17 -> 990196000000 | AG106: ='passive building (germany)'!H4 -> 1050201.1 | AH106: ='passive building (austria)'!H4 -> 129626.44 | AI106: ='passive building (belgium)'!H4 -> 106389 | AJ106: ='passive building (ireland)'!H4 -> 59682.667
A107: 2000 | B107: 281421906 | C107: ='cohousing population'!D126 -> 81797255 | D107: ='cohousing population'!D52 -> 5339660 | E107: 640657 | F107: 3129 | G107: ='microfinance population'!D246 -> 1057922728 | H107: ='microfinance population'!D112 -> 134544303 | I107: ='microfinance population'!D380 -> 126382491 | J107: ='elm- g'!C51 -> 176.14474 | K107: ='elm- j'!C51 -> 156.70274 | L107: ='elm-i'!C51 -> 67.150782 | M107: ='elm- uk'!C51 -> 165.1022 | N107: ='elm- us'!C51 -> 256.03513 | O107: ='microfinance population'!D112 -> 134544303 | P107: ='cohousing population'!D126 -> 81797255 | Q107: ='microfinance population'!D246 -> 1057922728 | R107: 8872100 | S107: ='climate protest'!D93 -> 59057336 | T107: ='climate protest'!D208 -> 281484127 | U107: ='climate protest'!D286 -> 6171703018 | V107: ='energy communities population'!D93 -> 16058758 | X107: ='cohousing population'!D126 -> 81797255 | Y107: ='ESG firms'!O107 -> 1946.1538 | Z107: ='ESG firms'!P107 -> 1848.0519 | AA107: ='ESG firms'!Q107 -> 2653.012 | AB107: ='ESG firms'!R107 -> 263.46154 | AF107: ='long distance travel'!D18 -> 975704000000 | AG107: ='passive building (germany)'!H5 -> 1047849.3 | AH107: ='passive building (austria)'!H5 -> 131165.33 | AI107: ='passive building (belgium)'!H5 -> 56798 | AJ107: ='passive building (ireland)'!H5 -> 60332
A108: 2001 | B108: 284968955 | C108: ='cohousing population'!D127 -> 81933883 | D108: ='cohousing population'!D53 -> 5358825 | E108: =(($E$117-$E$107)/10)+E107 -> 647919.4 | F108: 3129 | G108: ='microfinance population'!D247 -> 1077898572 | H108: ='microfinance population'!D113 -> 136805812 | I108: ='microfinance population'!D381 -> 129862594 | J108: ='elm- g'!C52 -> 176.97972 | K108: ='elm- j'!C52 -> 155.08597 | L108: ='elm-i'!C52 -> 71.456875 | M108: ='elm- uk'!C52 -> 170.22395 | N108: ='elm- us'!C52 -> 246.78018 | O108: ='microfinance population'!D113 -> 136805812 | P108: ='cohousing population'!D127 -> 81933883 | Q108: ='microfinance population'!D247 -> 1077898572 | R108: 8896018 | S108: ='climate protest'!D94 -> 59288095 | T108: ='climate protest'!D209 -> 284279629 | U108: ='climate protest'!D287 -> 6254936479 | V108: ='energy communities population'!D94 -> 16182705 | X108: ='cohousing population'!D127 -> 81933883 | Y108: ='ESG firms'!O108 -> 1946.1538 | Z108: ='ESG firms'!P108 -> 1848.0519 | AA108: ='ESG firms'!Q108 -> 2653.012 | AB108: ='ESG firms'!R108 -> 263.46154 | AF108: ='long distance travel'!D19 -> 997054000000 | AG108: ='passive building (germany)'!H6 -> 1028909 | AH108: ='passive building (austria)'!H6 -> 122522 | AI108: ='passive building (belgium)'!H6 -> 126052 | AJ108: ='passive building (ireland)'!H6 -> 56798
A109: 2002 | B109: 287625193 | C109: ='cohousing population'!D128 -> 82068328 | D109: ='cohousing population'!D54 -> 5375966 | E109: =(($E$117-$E$107)/10)+E108 -> 655181.8 | F109: 3129 | G109: ='microfinance population'!D248 -> 1097600381 | H109: ='microfinance population'!D114 -> 138933659 | I109: ='microfinance population'!D382 -> 133471994 | J109: ='elm- g'!C53 -> 175.92223 | K109: ='elm- j'!C53 -> 150.93144 | L109: ='elm-i'!C53 -> 62.103716 | M109: ='elm- uk'!C53 -> 165.76831 | N109: ='elm- us'!C53 -> 256.889 | O109: ='microfinance population'!D114 -> 138933659 | P109: ='cohousing population'!D128 -> 82068328 | Q109: ='microfinance population'!D248 -> 1097600381 | R109: 8925044 | S109: ='climate protest'!D95 -> 59540763 | T109: ='climate protest'!D210 -> 287084336 | U109: ='climate protest'!D288 -> 6337730319 | V109: ='energy communities population'!D95 -> 16288060 | X109: ='cohousing population'!D128 -> 82068328 | Y109: ='ESG firms'!O109 -> 1946.1538 | Z109: ='ESG firms'!P109 -> 1848.0519 | AA109: ='ESG firms'!Q109 -> 2653.012 | AB109: ='ESG firms'!R109 -> 263.46154 | AF109: ='long distance travel'!D20 -> 1001866000000 | AG109: ='passive building (germany)'!H7 -> 1073845 | AH109: ='passive building (austria)'!H7 -> 135192 | AI109: ='passive building (belgium)'!H7 -> 136317 | AJ109: ='passive building (ireland)'!H7 -> 61918
A110: 2003 | B110: 290107933 | C110: ='cohousing population'!D129 -> 82111619 | D110: ='cohousing population'!D55 -> 5390622 | E110: =(($E$117-$E$107)/10)+E109 -> 662444.2 | F110: 3129 | G110: ='microfinance population'!D249 -> 1116802997 | H110: ='microfinance population'!D115 -> 140970356 | I110: ='microfinance population'!D383 -> 137202647 | J110: ='elm- g'!C54 -> 177.12047 | K110: ='elm- j'!C54 -> 151.52831 | L110: ='elm-i'!C54 -> 68.91136 | M110: ='elm- uk'!C54 -> 176.0301 | N110: ='elm- us'!C54 -> 251.37186 | O110: ='microfinance population'!D115 -> 140970356 | P110: ='cohousing population'!D129 -> 82111619 | Q110: ='microfinance population'!D249 -> 1116802997 | R110: 8958432 | S110: ='climate protest'!D96 -> 59820385 | T110: ='climate protest'!D211 -> 289908091 | U110: ='climate protest'!D289 -> 6420361649 | V110: ='energy communities population'!D96 -> 16366914 | X110: ='cohousing population'!D129 -> 82111619 | Y110: ='ESG firms'!O110 -> 1946.1538 | Z110: ='ESG firms'!P110 -> 1848.0519 | AA110: ='ESG firms'!Q110 -> 2653.012 | AB110: ='ESG firms'!R110 -> 263.46154 | AF110: ='long distance travel'!D21 -> 996493000000 | AG110: ='passive building (germany)'!H8 -> 1040794 | AH110: ='passive building (austria)'!H8 -> 135782 | AI110: ='passive building (belgium)'!H8 -> 137330 | AJ110: ='passive building (ireland)'!H8 -> 62280
A111: 2004 | B111: 292805298 | C111: ='cohousing population'!D130 -> 82092706 | D111: ='cohousing population'!D56 -> 5404594 | E111: =(($E$117-$E$107)/10)+E110 -> 669706.6 | F111: 3129 | G111: ='microfinance population'!D250 -> 1135991510 | H111: ='microfinance population'!D116 -> 142902855 | I111: ='microfinance population'!D384 -> 141057046 | J111: ='elm- g'!C55 -> 179.25045 | K111: ='elm- j'!C55 -> 148.69636 | L111: ='elm-i'!C55 -> 57.326627 | M111: ='elm- uk'!C55 -> 175.89597 | N111: ='elm- us'!C55 -> 259.47154 | O111: ='microfinance population'!D116 -> 142902855 | P111: ='cohousing population'!D130 -> 82092706 | Q111: ='microfinance population'!D250 -> 1135991510 | R111: 8993806 | S111: ='climate protest'!D97 -> 60169964 | T111: ='climate protest'!D212 -> 292786247 | U111: ='climate protest'!D290 -> 6503377778 | V111: ='energy communities population'!D97 -> 16425561 | X111: ='cohousing population'!D130 -> 82092706 | Y111: ='ESG firms'!O111 -> 1946.1538 | Z111: ='ESG firms'!P111 -> 1848.0519 | AA111: ='ESG firms'!Q111 -> 2653.012 | AB111: ='ESG firms'!R111 -> 263.46154 | AF111: ='long distance travel'!D22 -> 1024372000000 | AG111: ='passive building (germany)'!H9 -> 998488 | AH111: ='passive building (austria)'!H9 -> 91690 | AI111: ='passive building (belgium)'!H9 -> 136922 | AJ111: ='passive building (ireland)'!H9 -> 53403
A112: 2005 | B112: 295516599 | C112: ='cohousing population'!D131 -> 82046731 | D112: ='cohousing population'!D57 -> 5419551 | E112: =(($E$117-$E$107)/10)+E111 -> 676969 | F112: 3129 | G112: ='microfinance population'!D251 -> 1154676319 | H112: ='microfinance population'!D117 -> 144715789 | I112: ='microfinance population'!D385 -> 145017255 | J112: ='elm- g'!C56 -> 173.62394 | K112: ='elm- j'!C56 -> 153.54917 | L112: ='elm-i'!C56 -> 60.796967 | M112: ='elm- uk'!C56 -> 179.81263 | N112: ='elm- us'!C56 -> 249.38686 | O112: ='microfinance population'!D117 -> 144715789 | P112: ='cohousing population'!D131 -> 82046731 | Q112: ='microfinance population'!D251 -> 1154676319 | R112: 9029770 | S112: ='climate protest'!D98 -> 60596108 | T112: ='climate protest'!D213 -> 295716665 | U112: ='climate protest'!D291 -> 6586970145 | V112: ='energy communities population'!D98 -> 16465707 | W112: ='active mobility'!DL12 -> 161337.26 | X112: ='cohousing population'!D131 -> 82046731 | Y112: ='ESG firms'!O112 -> 1946.1538 | Z112: ='ESG firms'!P112 -> 1848.0519 | AA112: ='ESG firms'!Q112 -> 2653.012 | AB112: ='ESG firms'!R112 -> 263.46154 | AD112: ='e-bikes'!G8 -> 1.3559053 | AF112: ='long distance travel'!D23 -> 1016213000000 | AG112: ='passive building (germany)'!H10 -> 990358 | AH112: ='passive building (austria)'!H10 -> 115656 | AI112: ='passive building (belgium)'!H10 -> 145416 | AJ112: ='passive building (ireland)'!H10 -> 77210
A113: 2006 | B113: 298379912 | C113: ='cohousing population'!D132 -> 81701971 | D113: ='cohousing population'!D58 -> 5437421 | E113: =(($E$117-$E$107)/10)+E112 -> 684231.4 | F113: 3129 | G113: ='microfinance population'!D252 -> 1172878890 | H113: ='microfinance population'!D118 -> 146405982 | I113: ='microfinance population'!D386 -> 149077333 | J113: ='elm- g'!C57 -> 175.76795 | K113: ='elm- j'!C57 -> 151.03978 | L113: ='elm-i'!C57 -> 67.824573 | M113: ='elm- uk'!C57 -> 179.22697 | N113: ='elm- us'!C57 -> 252.44817 | O113: ='microfinance population'!D118 -> 146405982 | P113: ='cohousing population'!D132 -> 81701971 | Q113: ='microfinance population'!D252 -> 1172878890 | R113: 9080626 | S113: ='climate protest'!D99 -> 61051093 | T113: ='climate protest'!D214 -> 298730210 | U113: ='climate protest'!D292 -> 6671452018 | V113: ='energy communities population'!D99 -> 16493851 | W113: ='active mobility'!DL13 -> 160499.1 | X113: ='cohousing population'!D132 -> 81701971 | Y113: ='ESG firms'!O113 -> 1946.1538 | Z113: ='ESG firms'!P113 -> 1848.0519 | AA113: ='ESG firms'!Q113 -> 2653.012 | AB113: ='ESG firms'!R113 -> 263.46154 | AD113: ='e-bikes'!G9 -> 1.3480123 | AF113: ='long distance travel'!D24 -> 1024047000000 | AG113: ='passive building (germany)'!H11 -> 1208469 | AH113: ='passive building (austria)'!H11 -> 108286 | AI113: ='passive building (belgium)'!H11 -> 126020 | AJ113: ='passive building (ireland)'!H11 -> 62827
A114: 2007 | B114: 301231207 | C114: ='cohousing population'!D133 -> 81298546 | D114: ='cohousing population'!D59 -> 5461604 | E114: =(($E$117-$E$107)/10)+E113 -> 691493.8 | F114: 3129 | G114: ='microfinance population'!D253 -> 1190676028 | H114: ='microfinance population'!D119 -> 147989283 | I114: ='microfinance population'!D387 -> 153267257 | J114: ='elm- g'!C58 -> 177.78488 | K114: ='elm- j'!C58 -> 150.11646 | L114: ='elm-i'!C58 -> 72.038386 | M114: ='elm- uk'!C58 -> 176.5809 | N114: ='elm- us'!C58 -> 255.10637 | O114: ='microfinance population'!D119 -> 147989283 | P114: ='cohousing population'!D133 -> 81298546 | Q114: ='microfinance population'!D253 -> 1190676028 | R114: 9148277 | S114: ='climate protest'!D100 -> 61535860 | T114: ='climate protest'!D215 -> 301844227 | U114: ='climate protest'!D293 -> 6757308750 | V114: ='energy communities population'!D100 -> 16531360 | W114: ='active mobility'!DL14 -> 159660.94 | X114: ='cohousing population'!D133 -> 81298546 | Y114: ='ESG firms'!O114 -> 1946.1538 | Z114: ='ESG firms'!P114 -> 1848.0519 | AA114: ='ESG firms'!Q114 -> 2653.012 | AB114: ='ESG firms'!R114 -> 263.46154 | AD114: ='e-bikes'!G10 -> 1.3572593 | AF114: ='long distance travel'!D25 -> 1026914000000 | AG114: ='passive building (germany)'!H12 -> 1136430 | AH114: ='passive building (austria)'!H12 -> 100273 | AI114: ='passive building (belgium)'!H12 -> 141811 | AJ114: ='passive building (ireland)'!H12 -> 87398
A115: 2008 | B115: 304093966 | C115: ='cohousing population'!D134 -> 81110781 | D115: ='cohousing population'!D60 -> 5493766 | E115: =(($E$117-$E$107)/10)+E114 -> 698756.2 | F115: 3129 | G115: ='microfinance population'!D254 -> 1207930962 | H115: ='microfinance population'!D120 -> 149474264 | I115: ='microfinance population'!D388 -> 157595017 | J115: ='elm- g'!C59 -> 178.21204 | K115: ='elm- j'!C59 -> 148.4753 | L115: ='elm-i'!C59 -> 73.425206 | M115: ='elm- uk'!C59 -> 174.01196 | N115: ='elm- us'!C59 -> 239.77225 | O115: ='microfinance population'!D120 -> 149474264 | P115: ='cohousing population'!D134 -> 81110781 | Q115: ='microfinance population'!D254 -> 1207930962 | R115: 9219903 | S115: ='climate protest'!D101 -> 62027303 | T115: ='climate protest'!D216 -> 304970328 | U115: ='climate protest'!D294 -> 6844457675 | V115: ='energy communities population'!D101 -> 16597257 | W115: ='active mobility'!DL15 -> 158822.79 | X115: ='cohousing population'!D134 -> 81110781 | Y115: ='ESG firms'!O115 -> 1946.1538 | Z115: ='ESG firms'!P115 -> 1848.0519 | AA115: ='ESG firms'!Q115 -> 2653.012 | AB115: ='ESG firms'!R115 -> 263.46154 | AD115: ='e-bikes'!G11 -> 1.3624444 | AF115: ='long distance travel'!D26 -> 1033421000000 | AG115: ='passive building (germany)'!H13 -> 1295027 | AH115: ='passive building (austria)'!H13 -> 108763 | AI115: ='passive building (belgium)'!H13 -> 148808 | AJ115: ='passive building (ireland)'!H13 -> 97900
A116: 2009 | B116: 306771529 | C116: ='cohousing population'!D135 -> 80935275 | D116: ='cohousing population'!D61 -> 5523168 | E116: =(($E$117-$E$107)/10)+E115 -> 706018.6 | F116: 3129 | G116: ='microfinance population'!D255 -> 1225524760 | H116: ='microfinance population'!D121 -> 150873716 | I116: ='microfinance population'!D389 -> 162049465 | J116: ='elm- g'!C60 -> 181.83218 | K116: ='elm- j'!C60 -> 145.52693 | L116: ='elm-i'!C60 -> 71.798867 | M116: ='elm- uk'!C60 -> 168.61234 | N116: ='elm- us'!C60 -> 241.24386 | O116: ='microfinance population'!D121 -> 150873716 | P116: ='cohousing population'!D135 -> 80935275 | Q116: ='microfinance population'!D255 -> 1225524760 | R116: 9298738 | S116: ='climate protest'!D102 -> 62506221 | T116: ='climate protest'!D217 -> 308023451 | U116: ='climate protest'!D295 -> 6932766459 | V116: ='energy communities population'!D102 -> 16684147 | W116: ='active mobility'!DL16 -> 157984.63 | X116: ='cohousing population'!D135 -> 80935275 | Y116: ='ESG firms'!O116 -> 1946.1538 | Z116: ='ESG firms'!P116 -> 1848.0519 | AA116: ='ESG firms'!Q116 -> 2653.012 | AB116: ='ESG firms'!R116 -> 263.46154 | AD116: ='e-bikes'!G12 -> 1.3243333 | AF116: ='long distance travel'!D27 -> 1041947000000 | AG116: ='passive building (germany)'!H14 -> 959755 | AH116: ='passive building (austria)'!H14 -> 105961 | AI116: ='passive building (belgium)'!H14 -> 166094 | AJ116: ='passive building (ireland)'!H14 -> 94163
A117: 2010 | B117: 308745538 | C117: ='cohousing population'!D136 -> 80830917 | D117: ='cohousing population'!D62 -> 5547866 | E117: 713281 | F117: 3129 | G117: ='microfinance population'!D256 -> 1243481564 | H117: ='microfinance population'!D122 -> 152201977 | I117: ='microfinance population'!D390 -> 166642887 | J117: ='elm- g'!C61 -> 215.06002 | K117: ='elm- j'!C61 -> 166.76 | L117: ='elm-i'!C61 -> 76.57 | M117: ='elm- uk'!C61 -> 210.09997 | N117: ='elm- us'!C61 -> 248.39 | O117: ='microfinance population'!D122 -> 152201977 | P117: ='cohousing population'!D136 -> 80830917 | Q117: ='microfinance population'!D256 -> 1243481564 | R117: 9378234 | S117: ='climate protest'!D103 -> 63006484 | T117: ='climate protest'!D218 -> 311062786 | U117: ='climate protest'!D296 -> 7021732131 | V117: ='energy communities population'!D103 -> 16771232 | W117: ='active mobility'!DL17 -> 157146.48 | X117: ='cohousing population'!D136 -> 80830917 | Y117: ='ESG firms'!O117 -> 1946.1538 | Z117: ='ESG firms'!P117 -> 1848.0519 | AA117: ='ESG firms'!Q117 -> 2653.012 | AB117: ='ESG firms'!R117 -> 263.46154 | AD117: ='e-bikes'!G13 -> 1.385 | AF117: ='long distance travel'!D28 -> 1046778000000 | AG117: ='passive building (germany)'!H15 -> 1107977 | AH117: ='passive building (austria)'!H15 -> 107141 | AI117: ='passive building (belgium)'!H15 -> 149443 | AJ117: ='passive building (ireland)'!H15 -> 67400
A118: 2011 | B118: 311556874 | C118: ='cohousing population'!D137 -> 80857877 | D118: ='cohousing population'!D63 -> 5570846 | E118: =(($E$127-$E$117)/10)+E117 -> 723429.1 | F118: 3129 | G118: ='microfinance population'!D257 -> 1261224952 | H118: ='microfinance population'!D123 -> 153591075 | I118: ='microfinance population'!D391 -> 171379601 | J118: ='elm- g'!C62 -> 216.15 | K118: ='elm- j'!C62 -> 168.16 | L118: ='elm-i'!C62 -> 80.88 | M118: ='elm- uk'!C62 -> 215.53 | N118: ='elm- us'!C62 -> 242.98001 | O118: ='microfinance population'!D123 -> 153591075 | P118: ='cohousing population'!D137 -> 80857877 | Q118: ='microfinance population'!D257 -> 1261224952 | R118: 9449262 | S118: ='climate protest'!D104 -> 63509285 | T118: ='climate protest'!D219 -> 314105078 | U118: ='climate protest'!D297 -> 7110923797 | V118: ='energy communities population'!D104 -> 16851061 | W118: ='active mobility'!DL18 -> 157169.22 | X118: ='cohousing population'!D137 -> 80857877 | Y118: ='ESG firms'!O118 -> 1946.1538 | Z118: ='ESG firms'!P118 -> 1848.0519 | AA118: ='ESG firms'!Q118 -> 2653.012 | AB118: ='ESG firms'!R118 -> 263.46154 | AD118: ='e-bikes'!G14 -> 1.378 | AF118: ='long distance travel'!D29 -> 1057771000000 | AG118: ='passive building (germany)'!H16 -> 895482 | AH118: ='passive building (austria)'!H16 -> 96509 | AI118: ='passive building (belgium)'!H16 -> 189330 | AJ118: ='passive building (ireland)'!H16 -> 36972
A119: 2012 | B119: 313830990 | C119: ='cohousing population'!D138 -> 80916393 | D119: ='cohousing population'!D64 -> 5591912 | E119: =(($E$127-$E$117)/10)+E118 -> 733577.2 | F119: 3129 | G119: ='microfinance population'!D258 -> 1278674506 | H119: ='microfinance population'!D124 -> 155070111 | I119: ='microfinance population'!D392 -> 176200628 | J119: ='elm- g'!C63 -> 219.63 | K119: ='elm- j'!C63 -> 165.58 | L119: ='elm-i'!C63 -> 84.75001 | M119: ='elm- uk'!C63 -> 209.21 | N119: ='elm- us'!C63 -> 243.3 | O119: ='microfinance population'!D124 -> 155070111 | P119: ='cohousing population'!D138 -> 80916393 | Q119: ='microfinance population'!D258 -> 1278674506 | R119: 9519479 | S119: ='climate protest'!D105 -> 63960487 | T119: ='climate protest'!D220 -> 317115348 | U119: ='climate protest'!D298 -> 7201202531 | V119: ='energy communities population'!D105 -> 16915191 | W119: ='active mobility'!DL19 -> 157191.96 | X119: ='cohousing population'!D138 -> 80916393 | Y119: ='ESG firms'!O119 -> 1946.1538 | Z119: ='ESG firms'!P119 -> 1848.0519 | AA119: ='ESG firms'!Q119 -> 2653.012 | AB119: ='ESG firms'!R119 -> 263.46154 | AD119: ='e-bikes'!G15 -> 1.21 | AF119: ='long distance travel'!D30 -> 1061115000000 | AG119: ='passive building (germany)'!H17 -> 1133426 | AH119: ='passive building (austria)'!H17 -> 102785 | AI119: ='passive building (belgium)'!H17 -> 130271 | AJ119: ='passive building (ireland)'!H17 -> 51978
A120: 2013 | B120: 315993715 | C120: ='cohousing population'!D139 -> 81041580 | D120: ='cohousing population'!D65 -> 5615334 | E120: =(($E$127-$E$117)/10)+E119 -> 743725.3 | F120: 3129 | G120: ='microfinance population'!D259 -> 1295829506 | H120: ='microfinance population'!D125 -> 156532135 | I120: ='microfinance population'!D393 -> 181049443 | J120: ='elm- g'!C64 -> 215.02 | K120: ='elm- j'!C64 -> 165.66 | L120: ='elm-i'!C64 -> 88.45 | M120: ='elm- uk'!C64 -> 210.86002 | N120: ='elm- us'!C64 -> 238.42999 | O120: ='microfinance population'!D125 -> 156532135 | P120: ='cohousing population'!D139 -> 81041580 | Q120: ='microfinance population'!D259 -> 1295829506 | R120: 9600621 | S120: ='climate protest'!D106 -> 64389386 | T120: ='climate protest'!D221 -> 320110753 | U120: ='climate protest'!D299 -> 7291793608 | V120: ='energy communities population'!D106 -> 16967065 | W120: ='active mobility'!DL20 -> 157214.7 | X120: ='cohousing population'!D139 -> 81041580 | Y120: ='ESG firms'!O120 -> 1946.1538 | Z120: ='ESG firms'!P120 -> 1848.0519 | AA120: ='ESG firms'!Q120 -> 2653.012 | AB120: ='ESG firms'!R120 -> 263.46154 | AD120: ='e-bikes'!G16 -> 1.2 | AF120: ='long distance travel'!D31 -> 1069861000000 | AG120: ='passive building (germany)'!H18 -> 888534 | AH120: ='passive building (austria)'!H18 -> 126512 | AI120: ='passive building (belgium)'!H18 -> 129133 | AJ120: ='passive building (ireland)'!H18 -> 44215
A121: 2014 | B121: 318301008 | C121: ='cohousing population'!D140 -> 81376078 | D121: ='cohousing population'!D66 -> 5643793 | E121: =(($E$127-$E$117)/10)+E120 -> 753873.4 | F121: 3129 | G121: ='microfinance population'!D260 -> 1312277184 | H121: ='microfinance population'!D126 -> 157964931 | I121: ='microfinance population'!D394 -> 185896917 | J121: ='elm- g'!C65 -> 216.26999 | K121: ='elm- j'!C65 -> 162.87002 | L121: ='elm-i'!C65 -> 91.67 | M121: ='elm- uk'!C65 -> 208.65998 | N121: ='elm- us'!C65 -> 243.45001 | O121: ='microfinance population'!D126 -> 157964931 | P121: ='cohousing population'!D140 -> 81376078 | Q121: ='microfinance population'!D260 -> 1312277184 | R121: 9696437 | S121: ='climate protest'!D107 -> 64865914 | T121: ='climate protest'!D222 -> 323115378 | U121: ='climate protest'!D300 -> 7381616239 | V121: ='energy communities population'!D107 -> 17030087 | W121: ='active mobility'!DL21 -> 157237.44 | X121: ='cohousing population'!D140 -> 81376078 | Y121: ='ESG firms'!O121 -> 1946.1538 | Z121: ='ESG firms'!P121 -> 1848.0519 | AA121: ='ESG firms'!Q121 -> 2653.012 | AB121: ='ESG firms'!R121 -> 263.46154 | AD121: ='e-bikes'!G17 -> 1.274 | AF121: ='long distance travel'!D32 -> 1086166000000 | AG121: ='passive building (germany)'!H19 -> 1084683 | AH121: ='passive building (austria)'!H19 -> 147434 | AI121: ='passive building (belgium)'!H19 -> 129655 | AJ121: ='passive building (ireland)'!H19 -> 46222
A122: 2015 | B122: 320635163 | C122: ='cohousing population'!D141 -> 82077546 | D122: ='cohousing population'!D67 -> 5683698 | E122: =(($E$127-$E$117)/10)+E121 -> 764021.5 | F122: 3129 | G122: ='microfinance population'!D261 -> 1328024492 | H122: ='microfinance population'!D127 -> 159383180 | I122: ='microfinance population'!D395 -> 190671883 | J122: ='elm- g'!C66 -> 219.37997 | K122: ='elm- j'!C66 -> 161.00999 | L122: ='elm-i'!C66 -> 87.95 | M122: ='elm- uk'!C66 -> 209.99997 | N122: ='elm- us'!C66 -> 242.33 | O122: ='microfinance population'!D127 -> 159383180 | P122: ='cohousing population'!D141 -> 82077546 | Q122: ='microfinance population'!D261 -> 1328024492 | R122: 9799482 | S122: ='climate protest'!D108 -> 65382107 | T122: ='climate protest'!D223 -> 326126498 | U122: ='climate protest'!D301 -> 7470491904 | V122: ='energy communities population'!D108 -> 17107427 | W122: ='active mobility'!DL22 -> 157260.18 | X122: ='cohousing population'!D141 -> 82077546 | Y122: ='ESG firms'!O122 -> 1946.1538 | Z122: ='ESG firms'!P122 -> 1848.0519 | AA122: ='ESG firms'!Q122 -> 2653.012 | AB122: ='ESG firms'!R122 -> 263.46154 | AD122: ='e-bikes'!G18 -> 1.259 | AE122: ='e-bikes'!H18 -> 18.35 | AF122: ='long distance travel'!D33 -> 1100374000000 | AG122: ='passive building (germany)'!H20 -> 1424102 | AH122: ='passive building (austria)'!H20 -> 131829 | AI122: ='passive building (belgium)'!H20 -> 146828 | AJ122: ='passive building (ireland)'!H20 -> 50105
A123: 2016 | B123: 322941311 | C123: ='cohousing population'!D142 -> 82760100 | D123: ='cohousing population'!D68 -> 5728198 | E123: =(($E$127-$E$117)/10)+E122 -> 774169.6 | F123: 3129 | G123: ='microfinance population'!D262 -> 1343944293 | H123: ='microfinance population'!D128 -> 160811935 | I123: ='microfinance population'!D396 -> 195443699 | J123: ='elm- g'!C67 -> 218.65998 | K123: ='elm- j'!C67 -> 159.5 | L123: ='elm-i'!C67 -> 90.42001 | M123: ='elm- uk'!C67 -> 217.23 | N123: ='elm- us'!C67 -> 244.17998 | O123: ='microfinance population'!D128 -> 160811935 | P123: ='cohousing population'!D142 -> 82760100 | Q123: ='microfinance population'!D262 -> 1343944293 | R123: 9923281 | S123: ='climate protest'!D109 -> 65893359 | T123: ='climate protest'!D224 -> 329179421 | U123: ='climate protest'!D302 -> 7558554580 | V123: ='energy communities population'!D109 -> 17204694 | W123: ='active mobility'!DL23 -> 154276.42 | X123: ='cohousing population'!D142 -> 82760100 | Y123: ='ESG firms'!O123 -> 1946.1538 | Z123: ='ESG firms'!P123 -> 1848.0519 | AA123: ='ESG firms'!Q123 -> 2653.012 | AB123: ='ESG firms'!R123 -> 263.46154 | AC123: ='e-bikes'!F19 -> 31.49 | AD123: ='e-bikes'!G19 -> 1.197 | AE123: ='e-bikes'!H19 -> 18.94 | AF123: ='long distance travel'!D34 -> 1121952000000 | AG123: ='passive building (germany)'!H21 -> 1165580 | AH123: ='passive building (austria)'!H21 -> 136465 | AI123: ='passive building (belgium)'!H21 -> 129318 | AJ123: ='passive building (ireland)'!H21 -> 56586
A124: 2017 | B124: 324985539 | C124: ='cohousing population'!D143 -> 83104012 | D124: ='cohousing population'!D69 -> 5765168 | E124: =(($E$127-$E$117)/10)+E123 -> 784317.7 | F124: 3129 | G124: ='microfinance population'!D263 -> 1359657392 | H124: ='microfinance population'!D129 -> 162186147 | I124: ='microfinance population'!D397 -> 200254578 | J124: ='elm- g'!C68 -> 222.02 | K124: ='elm- j'!C68 -> 164.15001 | L124: ='elm-i'!C68 -> 93.699995 | M124: ='elm- uk'!C68 -> 214.23997 | N124: ='elm- us'!C68 -> 240.51999 | O124: ='microfinance population'!D129 -> 162186147 | P124: ='cohousing population'!D143 -> 83104012 | Q124: ='microfinance population'!D263 -> 1359657392 | R124: 10057864 | S124: ='climate protest'!D110 -> 66354474 | T124: ='climate protest'!D225 -> 332204656 | U124: ='climate protest'!D303 -> 7645618013 | V124: ='energy communities population'!D110 -> 17315375 | W124: ='active mobility'!DL24 -> 151292.67 | X124: ='cohousing population'!D143 -> 83104012 | AC124: ='e-bikes'!F20 -> 41.2 | AD124: ='e-bikes'!G20 -> 1.251 | AE124: ='e-bikes'!H20 -> 18.56 | AF124: ='long distance travel'!D35 -> 1072960000000 | AG124: ='passive building (germany)'!H22 -> 1263141 | AH124: ='passive building (austria)'!H22 -> 112783 | AI124: ='passive building (belgium)'!H22 -> 128103 | AJ124: ='passive building (ireland)'!H22 -> 77257
A125: 2018 | B125: 326687501 | C125: ='cohousing population'!D144 -> 83368506 | D125: ='cohousing population'!D70 -> 5793825 | E125: =(($E$127-$E$117)/10)+E124 -> 794465.8 | F125: 3129 | G125: ='microfinance population'!D264 -> 1374659068 | H125: ='microfinance population'!D130 -> 163523108 | I125: ='microfinance population'!D398 -> 204938753 | J125: ='elm- g'!C69 -> 216.99001 | K125: ='elm- j'!C69 -> 166.38999 | L125: ='elm-i'!C69 -> 92.34 | M125: ='elm- uk'!C69 -> 209.21999 | N125: ='elm- us'!C69 -> 244.4 | O125: ='microfinance population'!D130 -> 163523108 | P125: ='cohousing population'!D144 -> 83368506 | Q125: ='microfinance population'!D264 -> 1374659068 | R125: 10175401 | S125: ='climate protest'!D111 -> 66752473 | T125: ='climate protest'!D226 -> 335056495 | U125: ='climate protest'!D304 -> 7729902724 | V125: ='energy communities population'!D111 -> 17421284 | W125: ='active mobility'!DL25 -> 148308.91 | X125: ='cohousing population'!D144 -> 83368506 | AC125: ='e-bikes'!F21 -> 43.2 | AD125: ='e-bikes'!G21 -> 1.42 | AE125: ='e-bikes'!H21 -> 20.49 | AF125: ='long distance travel'!D36 -> 1076872000000 | AG125: ='passive building (germany)'!H23 -> 1174220 | AH125: ='passive building (austria)'!H23 -> 124636 | AI125: ='passive building (belgium)'!H23 -> 146479 | AJ125: ='passive building (ireland)'!H23 -> 87602
A126: 2019 | B126: 328239523 | C126: ='cohousing population'!D145 -> 83559185 | D126: ='cohousing population'!D71 -> 5814619 | E126: =(($E$127-$E$117)/10)+E125 -> 804613.9 | F126: 3129 | G126: ='microfinance population'!D265 -> 1389030303 | H126: ='microfinance population'!D131 -> 164913060 | I126: ='microfinance population'!D399 -> 209485636 | J126: ='elm- g'!C70 -> 216.77 | K126: ='elm- j'!C70 -> 169.93 | L126: ='elm-i'!C70 -> 92.959994 | M126: ='elm- uk'!C70 -> 214.46999 | N126: ='elm- us'!C70 -> 255.54997 | O126: ='microfinance population'!D131 -> 164913060 | P126: ='cohousing population'!D145 -> 83559185 | Q126: ='microfinance population'!D265 -> 1389030303 | R126: 10279122 | S126: ='climate protest'!D112 -> 67110958 | T126: ='climate protest'!D227 -> 337790068 | U126: ='climate protest'!D305 -> 7811293714 | V126: ='energy communities population'!D112 -> 17537506 | W126: ='active mobility'!DL26 -> 145325.15 | X126: ='cohousing population'!D145 -> 83559185 | AC126: ='e-bikes'!F22 -> 46.7 | AD126: ='e-bikes'!G22 -> 1.427 | AE126: ='e-bikes'!H22 -> 20.56 | AF126: ='long distance travel'!D37 -> 1083478000000 | AG126: ='passive building (germany)'!H24 -> 1034381 | AH126: ='passive building (austria)'!H24 -> 107159 | AI126: ='passive building (belgium)'!H24 -> 156283 | AJ126: ='passive building (ireland)'!H24 -> 63367
A127: 2020 | B127: 331449281 | C127: ='cohousing population'!D146 -> 83628711 | D127: ='cohousing population'!D72 -> 5831530 | E127: 814762 | F127: 3129 | J127: ='elm- g'!C71 -> 220.29 | K127: ='elm- j'!C71 -> 170.58 | L127: ='elm-i'!C71 -> 95.82 | M127: ='elm- uk'!C71 -> 227.91999 | N127: ='elm- us'!C71 -> 245.21998 | O127: ='microfinance population'!D132 -> 166298024 | P127: ='cohousing population'!D146 -> 83628711 | Q127: ='microfinance population'!D266 -> 1402617692 | R127: 10353680 | S127: ='climate protest'!D113 -> 67351860 | T127: ='climate protest'!D228 -> 339436157 | U127: ='climate protest'!D306 -> 7887001284 | V127: ='energy communities population'!D113 -> 17636732 | W127: ='active mobility'!DL27 -> 142341.39 | X127: ='cohousing population'!D146 -> 83628711 | AC127: ='e-bikes'!F23 -> 58.6 | AD127: ='e-bikes'!G23 -> 1.645 | AE127: ='e-bikes'!H23 -> 23.24 | AF127: ='long distance travel'!D38 -> 889963000000 | AG127: ='passive building (germany)'!H25 -> 923359 | AH127: ='passive building (austria)'!H25 -> 128808 | AI127: ='passive building (belgium)'!H25 -> 146280 | AJ127: ='passive building (ireland)'!H25 -> 84019
A128: 2021 | E128: =(($E$130-$E$127)/3)+E127 -> 825131.33 | F128: 3129 | J128: ='elm- g'!C72 -> 277.56995 | K128: ='elm- j'!C72 -> 171.95 | L128: ='elm-i'!C72 -> 96.44 | M128: ='elm- uk'!C72 -> 252.37 | N128: ='elm- us'!C72 -> 253.3 | O128: ='microfinance population'!D133 -> 167658855 | P128: ='cohousing population'!D147 -> 83697082 | Q128: ='microfinance population'!D267 -> 1414203889 | R128: 10416136 | S128: ='climate protest'!D114 -> 67668789 | T128: ='climate protest'!D229 -> 340161441 | U128: ='climate protest'!D307 -> 7954448405 | V128: ='energy communities population'!D114 -> 17730564 | W128: ='active mobility'!DL28 -> 147786.4 | X128: ='cohousing population'!D147 -> 83697082 | AC128: ='e-bikes'!F24 -> 52 | AD128: ='e-bikes'!G24 -> 1.401 | AE128: ='e-bikes'!H24 -> 23.98 | AG128: ='passive building (germany)'!H26 -> 928143 | AH128: ='passive building (austria)'!H26 -> 166552 | AI128: ='passive building (belgium)'!H26 -> 167921 | AJ128: ='passive building (ireland)'!H26 -> 62947
A129: 2022 | E129: =(($E$130-$E$127)/3)+E128 -> 835500.67 | F129: 3129 | O129: ='microfinance population'!D134 -> 169384890 | P129: ='cohousing population'!D148 -> 84086228 | Q129: ='microfinance population'!D268 -> 1425423212 | R129: 10487333 | S129: ='climate protest'!D115 -> 68179315 | T129: ='climate protest'!D230 -> 341534041 | U129: ='climate protest'!D308 -> 8021407170 | V129: ='energy communities population'!D115 -> 17904422 | W129: ='active mobility'!DL29 -> 153231.41 | X129: ='cohousing population'!D148 -> 84086228 | AC129: ='e-bikes'!F25 -> 54.47 | AD129: ='e-bikes'!G25 -> 1.341 | AE129: ='e-bikes'!H25 -> 23.72 | AG129: ='passive building (germany)'!H27 -> 961961 | AH129: ='passive building (austria)'!H27 -> 134173 | AI129: ='passive building (belgium)'!H27 -> 156828 | AJ129: ='passive building (ireland)'!H27 -> 70111
A130: 2023 | E130: 845870 | F130: 3129 | O130: ='microfinance population'!D135 -> 171466986 | P130: ='cohousing population'!D149 -> 84548234 | Q130: ='microfinance population'!D269 -> 1438069597 | R130: 10551493 | S130: ='climate protest'!D116 -> 68682965 | T130: ='climate protest'!D231 -> 343477332 | U130: ='climate protest'!D309 -> 8091734935 | V130: ='energy communities population'!D116 -> 18092525 | W130: ='active mobility'!DL30 -> 158676.42 | X130: ='cohousing population'!D149 -> 84548234 | AE130: ='e-bikes'!H26 -> 22.9 | AG130: ='passive building (germany)'!H28 -> 937821 | AH130: ='passive building (austria)'!H28 -> 143177.67 | AI130: ='passive building (belgium)'!H28 -> 157009.67 | AJ130: ='passive building (ireland)'!H28 -> 72359
A131: 2024 | F131: 3129 | W131: ='active mobility'!DL31 -> 164121.42 | AG131: ='passive building (germany)'!H29 -> 942641.67 | AH131: ='passive building (austria)'!H29 -> 147967.56 | AI131: ='passive building (belgium)'!H29 -> 160586.22 | AJ131: ='passive building (ireland)'!H29 -> 68472.333
A132: 2025 | F132: 3129 | W132: ='active mobility'!DL32 -> 169566.43

Sheet active mobility
A1: Column1 | B1: Column2 | C1: Column3 | D1: Column4 | E1: Column5 | F1: Column6 | G1: Column7 | H1: Column8 | I1: Column9 | J1: Column10 | K1: Column11 | L1: Column12 | M1: Column13 | N1: Column14 | O1: Column15 | P1: Column16 | Q1: Column17 | R1: Column18 | S1: Column19 | T1: Column20 | U1: Column21 | V1: Column22 | W1: Column23 | X1: Column24 | Y1: Column25 | Z1: Column26 | AA1: Column27 | AB1: Column28 | AC1: Column29 | AD1: Column30 | AE1: Column31 | AF1: Column32 | AG1: Column33 | AH1: Column34 | AI1: Column35 | AJ1: Column36 | AK1: Column37 | AL1: Column38 | AM1: Column39 | AN1: Column40 | AO1: Column41 | AP1: Column42 | AQ1: Column43 | AR1: Column44 | AS1: Column45 | AT1: Column46 | AU1: Column47 | AV1: Column48 | AW1: Column49 | AX1: Column50 | AY1: Column51 | AZ1: Column52 | BA1: Column53 | BB1: Column54 | BC1: Column55 | BD1: Column56 | BE1: Column57 | BF1: Column58 | BG1: Column59 | BH1: Column60 | BI1: Column61 | BJ1: Column62 | BK1: Column63 | BL1: Column64 | BM1: Column65 | BN1: Column66 | BO1: Column67 | BP1: Column68 | BQ1: Column69 | BR1: Column70 | BS1: Column71 | BT1: Column72 | BU1: Column73 | BV1: Column74 | BW1: Column75 | BX1: Column76 | BY1: Column77 | BZ1: Column78 | CA1: Column79 | CB1: Column80 | CC1: Column81 | CD1: Column82 | CE1: Column83 | CF1: Column84 | CG1: Column85 | CH1: Column86 | CI1: Column87 | CJ1: Column88 | CK1: Column89 | CL1: Column90 | CM1: Column91 | CN1: Column92 | CO1: Column93 | CP1: Column94 | CQ1: Column95 | CR1: Column96 | CS1: Column97 | CT1: Column98 | CU1: Column99 | CV1: Column100 | CW1: Column101 | CX1: Column102 | CY1: Column103 | CZ1: Column104 | DA1: Column105 | DB1: Column106 | DC1: Column107 | DD1: Column108 | DE1: Column109 | DF1: Column110 | DG1: Column111 | DH1: Column112 | DI1: Column113 | DJ1: Column114 | DK1: Column1142 | DL1: Column1143 | DM1: Column115 | DN1: Column116 | DO1: Column117 | DP1: Column118 | DQ1: Column119 | DR1: Column120 | DS1: Column121 | DT1: Column122 | DU1: Column123 | DV1: Column124 | DW1: Column125 | DX1: Column126 | DY1: Column127 | DZ1: Column128 | EA1: Column129 | EB1: Column130 | EC1: Column131 | ED1: Column132 | EE1: Column133 | EF1: Column134 | EG1: Column135 | EH1: Column136 | EI1: Column137 | EJ1: Column138 | EK1: Column139 | EL1: Column140 | EM1: Column141 | EN1: Column142 | EO1: Column143 | EP1: Column144 | EQ1: Column145 | ER1: Column146 | ES1: Column147 | ET1: Column148 | EU1: Column149 | EV1: Column150 | EW1: Column151 | EX1: Column152 | EY1: Column153 | EZ1: Column154 | FA1: Column155 | FB1: Column156 | FC1: Column157 | FD1: Column158 | FE1: Column159 | FF1: Column160
A2: Downloaded from: https://www.eea.europa.eu/en/analysis/publications/sustainability-of-europes-mobility-systems/passenger-transport-activity/eu-27-passenger-transport-activity-gpkm-for-different-transport-modes-according-to-the-ff55-mix-scenario
A4: Publisher | B4: European Environment Agency | C4: EEA
A6: Sources | B6: https://energy.ec.europa.eu/publications/excel-files-mix-scenario_en | C6: EC, 2021d, ‘Excel files for MIX scenario - FF55 MIX energy-transport-ghg’
A8: Geographical coverage | B8: Cyprus, Portugal, Spain, Malta, Denmark, United Kingdom, Sweden, Netherlands, Austria, Belgium, Germany, Luxembourg, Ireland, France, Slovakia, Czechia, Italy, Slovenia, Greece, Estonia, Latvia, Lithuania, Finland, Hungary, Bulgaria, Poland, Romania
A10: Scenario_EU-27_x1 | B10: Scenario_EU-27_Domestic_and_intra-EU_aviation | C10: Scenario_EU-27_Domestic_navigation_ | D10: Scenario_EU-27_Rail_ | E10: Scenario_EU-27_Powered_two-wheelers_ | F10: Scenario_EU-27_Buses_and_coaches_ | G10: Scenario_EU-27_Cars__ | H10: Scenario_BE_Domestic_and_intra-EU_aviation | I10: Scenario_BE_Domestic_navigation_ | J10: Scenario_BE_Rail_ | K10: Scenario_BE_Powered_two-wheelers_ | L10: Scenario_BE_Buses_and_coaches_ | M10: Scenario_BE_Cars__ | N10: Scenario_BG_Domestic_and_intra-EU_aviation | O10: Scenario_BG_Domestic_navigation_ | P10: Scenario_BG_Rail_ | Q10: Scenario_BG_Powered_two-wheelers_ | R10: Scenario_BG_Buses_and_coaches_ | S10: Scenario_BG_Cars__ | T10: Scenario_CZ_Domestic_and_intra-EU_aviation | U10: Scenario_CZ_Domestic_navigation_ | V10: Scenario_CZ_Rail_ | W10: Scenario_CZ_Powered_two-wheelers_ | X10: Scenario_CZ_Buses_and_coaches_ | Y10: Scenario_CZ_Cars__ | Z10: Scenario_DK_Domestic_and_intra-EU_aviation | AA10: Scenario_DK_Domestic_navigation_ | AB10: Scenario_DK_Rail_ | AC10: Scenario_DK_Powered_two-wheelers_ | AD10: Scenario_DK_Buses_and_coaches_ | AE10: Scenario_DK_Cars__ | AF10: Scenario_DE_Domestic_and_intra-EU_aviation | AG10: Scenario_DE_Domestic_navigation_ | AH10: Scenario_DE_Rail_ | AI10: Scenario_DE_Powered_two-wheelers_ | AJ10: Scenario_DE_Buses_and_coaches_ | AK10: Scenario_DE_Cars__ | AL10: Scenario_EE_Domestic_and_intra-EU_aviation | AM10: Scenario_EE_Domestic_navigation_ | AN10: Scenario_EE_Rail_ | AO10: Scenario_EE_Powered_two-wheelers_ | AP10: Scenario_EE_Buses_and_coaches_ | AQ10: Scenario_EE_Cars__ | AR10: Scenario_IE_Domestic_and_intra-EU_aviation | AS10: Scenario_IE_Domestic_navigation_ | AT10: Scenario_IE_Rail_ | AU10: Scenario_IE_Powered_two-wheelers_ | AV10: Scenario_IE_Buses_and_coaches_ | AW10: Scenario_IE_Cars__ | AX10: Scenario_EL_Domestic_and_intra-EU_aviation | AY10: Scenario_EL_Domestic_navigation_ | AZ10: Scenario_EL_Rail_ | BA10: Scenario_EL_Powered_two-wheelers_ | BB10: Scenario_EL_Buses_and_coaches_ | BC10: Scenario_EL_Cars__ | BD10: Scenario_ES_Domestic_and_intra-EU_aviation | BE10: Scenario_ES_Domestic_navigation_ | BF10: Scenario_ES_Rail_ | BG10: Scenario_ES_Powered_two-wheelers_ | BH10: Scenario_ES_Buses_and_coaches_ | BI10: Scenario_ES_Cars__ | BJ10: Scenario_FR_Domestic_and_intra-EU_aviation | BK10: Scenario_FR_Domestic_navigation_ | BL10: Scenario_FR_Rail_ | BM10: Scenario_FR_Powered_two-wheelers_ | BN10: Scenario_FR_Buses_and_coaches_ | BO10: Scenario_FR_Cars__ | BP10: Scenario_HR_Domestic_and_intra-EU_aviation | BQ10: Scenario_HR_Domestic_navigation_ | BR10: Scenario_HR_Rail_ | BS10: Scenario_HR_Powered_two-wheelers_ | BT10: Scenario_HR_Buses_and_coaches_ | BU10: Scenario_HR_Cars__ | BV10: Scenario_IT_Domestic_and_intra-EU_aviation | BW10: Scenario_IT_Domestic_navigation_ | BX10: Scenario_IT_Rail_ | BY10: Scenario_IT_Powered_two-wheelers_ | BZ10: Scenario_IT_Buses_and_coaches_ | CA10: Scenario_IT_Cars__ | CB10: Scenario_CY_Domestic_and_intra-EU_aviation | CC10: Scenario_CY_Powered_two-wheelers_ | CD10: Scenario_CY_Buses_and_coaches_ | CE10: Scenario_CY_Cars__ | CF10: Scenario_LV_Domestic_and_intra-EU_aviation | CG10: Scenario_LV_Rail_ | CH10: Scenario_LV_Powered_two-wheelers_ | CI10: Scenario_LV_Buses_and_coaches_ | CJ10: Scenario_LV_Cars__ | CK10: Scenario_LT_Domestic_and_intra-EU_aviation | CL10: Scenario_LT_Domestic_navigation_ | CM10: Scenario_LT_Rail_ | CN10: Scenario_LT_Powered_two-wheelers_ | CO10: Scenario_LT_Buses_and_coaches_ | CP10: Scenario_LT_Cars__ | CQ10: Scenario_LU_Domestic_and_intra-EU_aviation | CR10: Scenario_LU_Rail_ | CS10: Scenario_LU_Powered_two-wheelers_ | CT10: Scenario_LU_Buses_and_coaches_ | CU10: Scenario_LU_Cars__ | CV10: Scenario_HU_Domestic_and_intra-EU_aviation | CW10: Scenario_HU_Rail_ | CX10: Scenario_HU_Powered_two-wheelers_ | CY10: Scenario_HU_Buses_and_coaches_ | CZ10: Scenario_HU_Cars__ | DA10: Scenario_MT_Domestic_and_intra-EU_aviation | DB10: Scenario_MT_Powered_two-wheelers_ | DC10: Scenario_MT_Buses_and_coaches_ | DD10: Scenario_MT_Cars__ | DE10: Scenario_NL_Domestic_and_intra-EU_aviation | DF10: Scenario_NL_Domestic_navigation_ | DG10: Scenario_NL_Rail_ | DH10: Scenario_NL_Powered_two-wheelers_ | DI10: Scenario_NL_Buses_and_coaches_ | DJ10: Scenario_NL_Cars__ | DK10: total Gpkm NL | DL10: total pkm NL (millions) | DM10: Scenario_AT_Domestic_and_intra-EU_aviation | DN10: Scenario_AT_Domestic_navigation_ | DO10: Scenario_AT_Rail_ | DP10: Scenario_AT_Powered_two-wheelers_ | DQ10: Scenario_AT_Buses_and_coaches_ | DR10: Scenario_AT_Cars__ | DS10: Scenario_PL_Domestic_and_intra-EU_aviation | DT10: Scenario_PL_Domestic_navigation_ | DU10: Scenario_PL_Rail_ | DV10: Scenario_PL_Powered_two-wheelers_ | DW10: Scenario_PL_Buses_and_coaches_ | DX10: Scenario_PL_Cars__ | DY10: Scenario_PT_Domestic_and_intra-EU_aviation | DZ10: Scenario_PT_Domestic_navigation_ | EA10: Scenario_PT_Rail_ | EB10: Scenario_PT_Powered_two-wheelers_ | EC10: Scenario_PT_Buses_and_coaches_ | ED10: Scenario_PT_Cars__ | EE10: Scenario_RO_Domestic_and_intra-EU_aviation | EF10: Scenario_RO_Domestic_navigation_ | EG10: Scenario_RO_Rail_ | EH10: Scenario_RO_Powered_two-wheelers_ | EI10: Scenario_RO_Buses_and_coaches_ | EJ10: Scenario_RO_Cars__ | EK10: Scenario_SI_Domestic_and_intra-EU_aviation | EL10: Scenario_SI_Rail_ | EM10: Scenario_SI_Powered_two-wheelers_ | EN10: Scenario_SI_Buses_and_coaches_ | EO10: Scenario_SI_Cars__ | EP10: Scenario_SK_Domestic_and_intra-EU_aviation | EQ10: Scenario_SK_Rail_ | ER10: Scenario_SK_Powered_two-wheelers_ | ES10: Scenario_SK_Buses_and_coaches_ | ET10: Scenario_SK_Cars__ | EU10: Scenario_FI_Domestic_and_intra-EU_aviation | EV10: Scenario_FI_Domestic_navigation_ | EW10: Scenario_FI_Rail_ | EX10: Scenario_FI_Powered_two-wheelers_ | EY10: Scenario_FI_Buses_and_coaches_ | EZ10: Scenario_FI_Cars__ | FA10: Scenario_SE_Domestic_and_intra-EU_aviation | FB10: Scenario_SE_Domestic_navigation_ | FC10: Scenario_SE_Rail_ | FD10: Scenario_SE_Powered_two-wheelers_ | FE10: Scenario_SE_Buses_and_coaches_ | FF10: Scenario_SE_Cars__
A12: 2005 | B12: 372.7858992472852 | C12: 32.267954693360714 | D12: 417.2232059259342 | E12: 115.14315895057229 | F12: 498.20252417552103 | G12: 3841.202448424538 | H12: 7.334669746070221 | I12: 0.31036525987373126 | J12: 9.439999999580914 | K12: 1.2061707550892904 | L12: 17.51504805873601 | M12: 102.80426445720657 | N12: 2.6867978866624043 | O12: 0.017054319009891183 | P12: 2.823000400005723 | Q12: 0.7300005997425607 | R12: 13.687999999648689 | S12: 35.100000394388935 | T12: 7.901735783151914 | U12: 0 | V12: 14.601200399989139 | W12: 3.1500005999995206 | X12: 15.607899999997127 | Y12: 68.6400004000203 | Z12: 8.230279364858626 | AA12: 3.162622907706997 | AB12: 6.136000402903621 | AC12: 0.530000600004417 | AD12: 7.169000004636504 | AE12: 49.75800042521359 | AF12: 57.33419735428041 | AG12: 2.1390798828915596 | AH12: 92.28499999525916 | AI12: 18.79500063505142 | AJ12: 67.06199999873272 | AK12: 856.8750005669788 | AL12: 0.6054875415023772 | AM12: 0.3786122992229439 | AN12: 0.32330039674928507 | AO12: 0.11000219817238241 | AP12: 2.7159999675913387 | AQ12: 9.929001154406441 | AR12: 8.12194894150643 | AS12: 1.04240242544689 | AT12: 1.890999999840106 | AU12: 0.13000059999048896 | AV12: 7.915199999319714 | AW12: 44.3790005979474 | AX12: 23.03355036175256 | AY12: 7.46030379911707 | AZ12: 3.3540000002436727 | BA12: 4.700000601058661 | BB12: 21.70000000045052 | BC12: 85.00000060775538 | BD12: 96.3759805132985 | BE12: 1.8016814335940823 | BF12: 27.62399997915012 | BG12: 8.600000598831526 | BH12: 53.17599997245606 | BI12: 337.7970004477496 | BJ12: 57.06918435126796 | BK12: 3.3064960064113365 | BL12: 95.92033045742691 | BM12: 12.618933029226813 | BN12: 50.10470892826654 | BO12: 704.6155541266967 | BP12: 0.8811855101807338 | BQ12: 4.000000004251529e-7 | BR12: 1.7601664009869833 | BS12: 0.14800139949415755 | BT12: 3.403468986171076 | BU12: 24.000000726744556 | BV12: 36.62557812609449 | BW12: 4.9834166267071325 | BX12: 56.123000000078534 | BY12: 49.52100063068344 | BZ12: 100.95399999774675 | CA12: 677.0140004846444 | CB12: 2.867629441929434 | CC12: 0.1350008000026191 | CD12: 1.2599999986434272 | CE12: 4.800000600065487 | CF12: 0.654071948426312 | CG12: 1.1617003993274675 | CH12: 0.3300005997612335 | CI12: 2.8909999997028573 | CJ12: 12.111500598493969 | CK12: 0.6266148402989704 | CL12: 0.06779417980060119 | CM12: 0.2800012000009759 | CN12: 0.3400021999975373 | CO12: 3.691000000054629 | CP12: 34.79300059871458 | CQ12: 0.5789759587490495 | CR12: 0.26700120000126304 | CS12: 0.150000800000825 | CT12: 0.8000000000018809 | CU12: 6.300000800037398 | CV12: 2.8545191897262283 | CW12: 12.204000400000721 | CX12: 1.1000003999998145 | CY12: 17.844999999999178 | CZ12: 49.40300039996766 | DA12: 1.2115506418871431 | DB12: 0.05000080000818583 | DC12: 0.4899999981389671 | DD12: 2.0000006005021116 | DE12: 12.537254688854759 | DF12: 0.7500633152809575 | DG12: 15.899406410093045 | DH12: 2.700000601154671 | DI12: 4.775028044045083 | DJ12: 148.80000039109697 | DK12: =SUM(DE12+DJ12) -> 161.33726 | DL12: =DK12*1000 -> 161337.26 | DM12: 6.011271421153518 | DN12: 0.036243219902651 | DO12: 15.122253026692238 | DP12: 1.833880227445236 | DQ12: 9.658124698942634 | DR12: 70.5570004218626 | DS12: 3.0903190648935746 | DT12: 0.20812534343699068 | DU12: 22.557000443979728 | DV12: 1.29800060356116 | DW12: 49.20000003001622 | DX12: 152.30000051912316 | DY12: 12.122919717654312 | DZ12: 0.31373654863094613 | EA12: 4.656715883007572 | EB12: 2.000000568181055 | EC12: 6.3762630465726495 | ED12: 85.00000041584175 | EE12: 2.692465143617606 | EF12: 0.01586238902343719 | EG12: 14.581908400006851 | EH12: 2.350000799996887 | EI12: 11.811000000005397 | EJ12: 61.00000040000471 | EK12: 0.2886740566672655 | EL12: 0.7160022000277325 | EM12: 0.2300008000179384 | EN12: 3.0620000002236343 | EO12: 22.509000801367197 | EP12: 0.9183279376886472 | EQ12: 2.5682179314202283 | ER12: 0.5700009989923701 | ES12: 8.537782444697779 | ET12: 25.824000570251677 | EU12: 7.915123959999033 | EV12: 0.1412900000296127 | EW12: 4.004000000559068 | EX12: 0.9000006000368549 | EY12: 7.540000000086642 | EZ12: 61.91000060585705 | FA12: 12.215585755112732 | FB12: 6.1328043372738845 | FC12: 10.923999998603128 | FD12: 0.9171559040712132 | FE12: 9.254000000637138 | FF12: 107.98311631159912
A13: 2006 | B13: null | C13: null | D13: null | E13: null | F13: null | G13: null | H13: null | I13: null | J13: null | K13: null | L13: null | M13: null | N13: null | O13: null | P13: null | Q13: null | R13: null | S13: null | T13: null | U13: null | V13: null | W13: null | X13: null | Y13: null | Z13: null | AA13: null | AB13: null | AC13: null | AD13: null | AE13: null | AF13: null | AG13: null | AH13: null | AI13: null | AJ13: null | AK13: null | AL13: null | AM13: null | AN13: null | AO13: null | AP13: null | AQ13: null | AR13: null | AS13: null | AT13: null | AU13: null | AV13: null | AW13: null | AX13: null | AY13: null | AZ13: null | BA13: null | BB13: null | BC13: null | BD13: null | BE13: null | BF13: null | BG13: null | BH13: null | BI13: null | BJ13: null | BK13: null | BL13: null | BM13: null | BN13: null | BO13: null | BP13: null | BQ13: null | BR13: null | BS13: null | BT13: null | BU13: null | BV13: null | BW13: null | BX13: null | BY13: null | BZ13: null | CA13: null | CB13: null | CC13: null | CD13: null | CE13: null | CF13: null | CG13: null | CH13: null | CI13: null | CJ13: null | CK13: null | CL13: null | CM13: null | CN13: null | CO13: null | CP13: null | CQ13: null | CR13: null | CS13: null | CT13: null | CU13: null | CV13: null | CW13: null | CX13: null | CY13: null | CZ13: null | DA13: null | DB13: null | DC13: null | DD13: null | DE13: null | DF13: null | DG13: null | DH13: null | DI13: null | DJ13: null | DL13: =($DL$17-$DL$12)/5 + DL12 -> 160499.1 | DM13: null | DN13: null | DO13: null | DP13: null | DQ13: null | DR13: null | DS13: null | DT13: null | DU13: null | DV13: null | DW13: null | DX13: null | DY13: null | DZ13: null | EA13: null | EB13: null | EC13: null | ED13: null | EE13: null | EF13: null | EG13: null | EH13: null | EI13: null | EJ13: null | EK13: null | EL13: null | EM13: null | EN13: null | EO13: null | EP13: null | EQ13: null | ER13: null | ES13: null | ET13: null | EU13: null | EV13: null | EW13: null | EX13: null | EY13: null | EZ13: null | FA13: null | FB13: null | FC13: null | FD13: null | FE13: null | FF13: null
A14: 2007 | B14: null | C14: null | D14: null | E14: null | F14: null | G14: null | H14: null | I14: null | J14: null | K14: null | L14: null | M14: null | N14: null | O14: null | P14: null | Q14: null | R14: null | S14: null | T14: null | U14: null | V14: null | W14: null | X14: null | Y14: null | Z14: null | AA14: null | AB14: null | AC14: null | AD14: null | AE14: null | AF14: null | AG14: null | AH14: null | AI14: null | AJ14: null | AK14: null | AL14: null | AM14: null | AN14: null | AO14: null | AP14: null | AQ14: null | AR14: null | AS14: null | AT14: null | AU14: null | AV14: null | AW14: null | AX14: null | AY14: null | AZ14: null | BA14: null | BB14: null | BC14: null | BD14: null | BE14: null | BF14: null | BG14: null | BH14: null | BI14: null | BJ14: null | BK14: null | BL14: null | BM14: null | BN14: null | BO14: null | BP14: null | BQ14: null | BR14: null | BS14: null | BT14: null | BU14: null | BV14: null | BW14: null | BX14: null | BY14: null | BZ14: null | CA14: null | CB14: null | CC14: null | CD14: null | CE14: null | CF14: null | CG14: null | CH14: null | CI14: null | CJ14: null | CK14: null | CL14: null | CM14: null | CN14: null | CO14: null | CP14: null | CQ14: null | CR14: null | CS14: null | CT14: null | CU14: null | CV14: null | CW14: null | CX14: null | CY14: null | CZ14: null | DA14: null | DB14: null | DC14: null | DD14: null | DE14: null | DF14: null | DG14: null | DH14: null | DI14: null | DJ14: null | DL14: =($DL$17-$DL$12)/5 + DL13 -> 159660.94 | DM14: null | DN14: null | DO14: null | DP14: null | DQ14: null | DR14: null | DS14: null | DT14: null | DU14: null | DV14: null | DW14: null | DX14: null | DY14: null | DZ14: null | EA14: null | EB14: null | EC14: null | ED14: null | EE14: null | EF14: null | EG14: null | EH14: null | EI14: null | EJ14: null | EK14: null | EL14: null | EM14: null | EN14: null | EO14: null | EP14: null | EQ14: null | ER14: null | ES14: null | ET14: null | EU14: null | EV14: null | EW14: null | EX14: null | EY14: null | EZ14: null | FA14: null | FB14: null | FC14: null | FD14: null | FE14: null | FF14: null
A15: 2008 | B15: null | C15: null | D15: null | E15: null | F15: null | G15: null | H15: null | I15: null | J15: null | K15: null | L15: null | M15: null | N15: null | O15: null | P15: null | Q15: null | R15: null | S15: null | T15: null | U15: null | V15: null | W15: null | X15: null | Y15: null | Z15: null | AA15: null | AB15: null | AC15: null | AD15: null | AE15: null | AF15: null | AG15: null | AH15: null | AI15: null | AJ15: null | AK15: null | AL15: null | AM15: null | AN15: null | AO15: null | AP15: null | AQ15: null | AR15: null | AS15: null | AT15: null | AU15: null | AV15: null | AW15: null | AX15: null | AY15: null | AZ15: null | BA15: null | BB15: null | BC15: null | BD15: null | BE15: null | BF15: null | BG15: null | BH15: null | BI15: null | BJ15: null | BK15: null | BL15: null | BM15: null | BN15: null | BO15: null | BP15: null | BQ15: null | BR15: null | BS15: null | BT15: null | BU15: null | BV15: null | BW15: null | BX15: null | BY15: null | BZ15: null | CA15: null | CB15: null | CC15: null | CD15: null | CE15: null | CF15: null | CG15: null | CH15: null | CI15: null | CJ15: null | CK15: null | CL15: null | CM15: null | CN15: null | CO15: null | CP15: null | CQ15: null | CR15: null | CS15: null | CT15: null | CU15: null | CV15: null | CW15: null | CX15: null | CY15: null | CZ15: null | DA15: null | DB15: null | DC15: null | DD15: null | DE15: null | DF15: null | DG15: null | DH15: null | DI15: null | DJ15: null | DL15: =($DL$17-$DL$12)/5 + DL14 -> 158822.79 | DM15: null | DN15: null | DO15: null | DP15: null | DQ15: null | DR15: null | DS15: null | DT15: null | DU15: null | DV15: null | DW15: null | DX15: null | DY15: null | DZ15: null | EA15: null | EB15: null | EC15: null | ED15: null | EE15: null | EF15: null | EG15: null | EH15: null | EI15: null | EJ15: null | EK15: null | EL15: null | EM15: null | EN15: null | EO15: null | EP15: null | EQ15: null | ER15: null | ES15: null | ET15: null | EU15: null | EV15: null | EW15: null | EX15: null | EY15: null | EZ15: null | FA15: null | FB15: null | FC15: null | FD15: null | FE15: null | FF15: null
A16: 2009 | B16: null | C16: null | D16: null | E16: null | F16: null | G16: null | H16: null | I16: null | J16: null | K16: null | L16: null | M16: null | N16: null | O16: null | P16: null | Q16: null | R16: null | S16: null | T16: null | U16: null | V16: null | W16: null | X16: null | Y16: null | Z16: null | AA16: null | AB16: null | AC16: null | AD16: null | AE16: null | AF16: null | AG16: null | AH16: null | AI16: null | AJ16: null | AK16: null | AL16: null | AM16: null | AN16: null | AO16: null | AP16: null | AQ16: null | AR16: null | AS16: null | AT16: null | AU16: null | AV16: null | AW16: null | AX16: null | AY16: null | AZ16: null | BA16: null | BB16: null | BC16: null | BD16: null | BE16: null | BF16: null | BG16: null | BH16: null | BI16: null | BJ16: null | BK16: null | BL16: null | BM16: null | BN16: null | BO16: null | BP16: null | BQ16: null | BR16: null | BS16: null | BT16: null | BU16: null | BV16: null | BW16: null | BX16: null | BY16: null | BZ16: null | CA16: null | CB16: null | CC16: null | CD16: null | CE16: null | CF16: null | CG16: null | CH16: null | CI16: null | CJ16: null | CK16: null | CL16: null | CM16: null | CN16: null | CO16: null | CP16: null | CQ16: null | CR16: null | CS16: null | CT16: null | CU16: null | CV16: null | CW16: null | CX16: null | CY16: null | CZ16: null | DA16: null | DB16: null | DC16: null | DD16: null | DE16: null | DF16: null | DG16: null | DH16: null | DI16: null | DJ16: null | DL16: =($DL$17-$DL$12)/5 + DL15 -> 157984.63 | DM16: null | DN16: null | DO16: null | DP16: null | DQ16: null | DR16: null | DS16: null | DT16: null | DU16: null | DV16: null | DW16: null | DX16: null | DY16: null | DZ16: null | EA16: null | EB16: null | EC16: null | ED16: null | EE16: null | EF16: null | EG16: null | EH16: null | EI16: null | EJ16: null | EK16: null | EL16: null | EM16: null | EN16: null | EO16: null | EP16: null | EQ16: null | ER16: null | ES16: null | ET16: null | EU16: null | EV16: null | EW16: null | EX16: null | EY16: null | EZ16: null | FA16: null | FB16: null | FC16: null | FD16: null | FE16: null | FF16: null
A17: 2010 | B17: 398.4087817082652 | C17: 31.32039841153487 | D17: 444.22344026802347 | E17: 114.66863858633572 | F17: 483.5178151183824 | G17: 3980.9477402554776 | H17: 8.907141840677824 | I17: 0.3008757616309063 | J17: 11.634000000000004 | K17: 1.2651077980312928 | L17: 17.379999999999985 | M17: 109.3877602190548 | N17: 2.894039668955549 | O17: 0.016532877556941716 | P17: 2.9990004 | Q17: 1.0400005999999997 | R17: 10.613000000000003 | S17: 46.90000039999999 | T17: 7.144064840743311 | U17: 0 | V17: 15.556000399999995 | W17: 3.5200005999999995 | X17: 16.955599999999983 | Y17: 63.570000399999984 | Z17: 9.22831493068931 | AA17: 3.0659248987329693 | AB17: 6.577000399999999 | AC17: 0.5440006 | AD17: 6.820999999999996 | AE17: 51.69100040000001 | AF17: 56.55147769109874 | AG17: 2.0736769688309433 | AH17: 100.241 | AI17: 17.700000600000006 | AJ17: 61.76700000000001 | AK17: 887.0000003999994 | AL17: 0.48032152907636433 | AM17: 0.36703613284753883 | AN17: 0.4520995999999999 | AO17: 0.19900220250568812 | AP17: 2.060999999999998 | AQ17: 10.100001399999993 | AR17: 8.338965738027968 | AS17: 1.0105307062006406 | AT17: 1.8090000000000002 | AU17: 0.12300059999999999 | AV17: 8.459200000000001 | AW17: 48.0825006 | AX17: 17.76803686192057 | AY17: 7.23220311080188 | AZ17: 3.0757464982806515 | BA17: 5.7700006 | BB17: 21.099999999999994 | BC17: 99.60000060000006 | BD17: 102.1807493748563 | BE17: 1.7465945640094833 | BF17: 30.044899999999995 | BG17: 10.140000600000004 | BH17: 50.90200000000002 | BI17: 341.6290003999999 | BJ17: 61.21052175963105 | BK17: 3.205399046270325 | BL17: 107.43220290291087 | BM17: 13.91802422496 | BN17: 54.040974622693454 | BO17: 695.8712974248097 | BP17: 1.5103436139544488 | BQ17: 0.035135074224866315 | BR17: 2.2603573999999993 | BS17: 0.1540014000000001 | BT17: 3.2484179999999974 | BU17: 25.700000799999998 | BV17: 44.71491368630151 | BW17: 4.8310473916636 | BX17: 54.255 | BY17: 41.48000059999998 | BZ17: 102.21899999999998 | CA17: 698.3900004000001 | CB17: 2.888705966712468 | CC17: 0.13000080000000008 | CD17: 1.2900000000000005 | CE17: 5.900000599999998 | CF17: 1.5110643369980057 | CG17: 0.8640004 | CH17: 0.43000060000000007 | CI17: 2.3109999999999986 | CJ17: 12.312340600000004 | CK17: 0.8680506028721593 | CL17: 0.0657213554784777 | CM17: 0.24400120000000006 | CN17: 0.63 | CO17: 2.693599999999999 | CP17: 32.56900059999999 | CQ17: 0.5676801468664983 | CR17: 0.34700119999999984 | CS17: 0.16000080000000005 | CT17: 0.9399999999999997 | CU17: 6.5000008 | CV17: 2.9343948023316884 | CW17: 10.170000400000003 | CX17: 1.2500004000000002 | CY17: 16.460999999999977 | CZ17: 52.59500040000001 | DA17: 1.4909993561751684 | DB17: 0.060000800000000014 | DC17: 0.5 | DD17: 2.200000600000001 | DE17: 12.946477269447175 | DF17: 0.7271299380692456 | DG17: 17.753925061229808 | DH17: 3.2100005999999994 | DI17: 4.84607493877019 | DJ17: 144.2000004 | DK17: =SUM(DE17+DJ17) -> 157.14648 | DL17: =DK17*1000 -> 157146.48 | DM17: 6.518136537433558 | DN17: 0.035135074224866315 | DO17: 17.18181580782605 | DP17: 2.1358448599999993 | DQ17: 9.951612714295885 | DR17: 73.46700039999998 | DS17: 6.34171167284209 | DT17: 0.20176185766058 | DU17: 22.261000400000004 | DV17: 3.1530005999999986 | DW17: 41.70000000000001 | DX17: 188.8100005999999 | DY17: 13.49401700148777 | DZ17: 0.30414397945768823 | EA17: 5.244233000000001 | EB17: 1.8000006000000004 | EC17: 6.077555342622833 | ED17: 83.70000040000004 | EE17: 6.211370597235634 | EF17: 0.015377392443670672 | EG17: 12.575710497776036 | EH17: 2.840000799999999 | EI17: 15.812000000000006 | EJ17: 75.50000039999996 | EK17: 0.2770602403183726 | EL17: 0.7290012000000002 | EM17: 0.3300007999999998 | EN17: 3.183 | EO17: 25.636000799999994 | EP17: 0.5916190623812795 | EQ17: 2.5924435 | ER17: 0.5600009999999996 | ES17: 5.2707795000000015 | ET17: 26.87900059999999 | EU17: 7.743094874815016 | EV17: 0.1408800000000002 | EW17: 4.488999999999998 | EX17: 1.1610006000000004 | EY17: 7.540000000000002 | EZ17: 64.74500059999997 | FA17: 13.095507704415382 | FB17: 5.945292281430247 | FC17: 13.434999999999999 | FD17: 0.9656449008387554 | FE17: 9.373999999999995 | FF17: 108.01282901161349
A18: 2011 | B18: null | C18: null | D18: null | E18: null | F18: null | G18: null | H18: null | I18: null | J18: null | K18: null | L18: null | M18: null | N18: null | O18: null | P18: null | Q18: null | R18: null | S18: null | T18: null | U18: null | V18: null | W18: null | X18: null | Y18: null | Z18: null | AA18: null | AB18: null | AC18: null | AD18: null | AE18: null | AF18: null | AG18: null | AH18: null | AI18: null | AJ18: null | AK18: null | AL18: null | AM18: null | AN18: null | AO18: null | AP18: null | AQ18: null | AR18: null | AS18: null | AT18: null | AU18: null | AV18: null | AW18: null | AX18: null | AY18: null | AZ18: null | BA18: null | BB18: null | BC18: null | BD18: null | BE18: null | BF18: null | BG18: null | BH18: null | BI18: null | BJ18: null | BK18: null | BL18: null | BM18: null | BN18: null | BO18: null | BP18: null | BQ18: null | BR18: null | BS18: null | BT18: null | BU18: null | BV18: null | BW18: null | BX18: null | BY18: null | BZ18: null | CA18: null | CB18: null | CC18: null | CD18: null | CE18: null | CF18: null | CG18: null | CH18: null | CI18: null | CJ18: null | CK18: null | CL18: null | CM18: null | CN18: null | CO18: null | CP18: null | CQ18: null | CR18: null | CS18: null | CT18: null | CU18: null | CV18: null | CW18: null | CX18: null | CY18: null | CZ18: null | DA18: null | DB18: null | DC18: null | DD18: null | DE18: null | DF18: null | DG18: null | DH18: null | DI18: null | DJ18: null | DL18: =($DL$22-$DL$17)/5 + DL17 -> 157169.22 | DM18: null | DN18: null | DO18: null | DP18: null | DQ18: null | DR18: null | DS18: null | DT18: null | DU18: null | DV18: null | DW18: null | DX18: null | DY18: null | DZ18: null | EA18: null | EB18: null | EC18: null | ED18: null | EE18: null | EF18: null | EG18: null | EH18: null | EI18: null | EJ18: null | EK18: null | EL18: null | EM18: null | EN18: null | EO18: null | EP18: null | EQ18: null | ER18: null | ES18: null | ET18: null | EU18: null | EV18: null | EW18: null | EX18: null | EY18: null | EZ18: null | FA18: null | FB18: null | FC18: null | FD18: null | FE18: null | FF18: null
A19: 2012 | B19: null | C19: null | D19: null | E19: null | F19: null | G19: null | H19: null | I19: null | J19: null | K19: null | L19: null | M19: null | N19: null | O19: null | P19: null | Q19: null | R19: null | S19: null | T19: null | U19: null | V19: null | W19: null | X19: null | Y19: null | Z19: null | AA19: null | AB19: null | AC19: null | AD19: null | AE19: null | AF19: null | AG19: null | AH19: null | AI19: null | AJ19: null | AK19: null | AL19: null | AM19: null | AN19: null | AO19: null | AP19: null | AQ19: null | AR19: null | AS19: null | AT19: null | AU19: null | AV19: null | AW19: null | AX19: null | AY19: null | AZ19: null | BA19: null | BB19: null | BC19: null | BD19: null | BE19: null | BF19: null | BG19: null | BH19: null | BI19: null | BJ19: null | BK19: null | BL19: null | BM19: null | BN19: null | BO19: null | BP19: null | BQ19: null | BR19: null | BS19: null | BT19: null | BU19: null | BV19: null | BW19: null | BX19: null | BY19: null | BZ19: null | CA19: null | CB19: null | CC19: null | CD19: null | CE19: null | CF19: null | CG19: null | CH19: null | CI19: null | CJ19: null | CK19: null | CL19: null | CM19: null | CN19: null | CO19: null | CP19: null | CQ19: null | CR19: null | CS19: null | CT19: null | CU19: null | CV19: null | CW19: null | CX19: null | CY19: null | CZ19: null | DA19: null | DB19: null | DC19: null | DD19: null | DE19: null | DF19: null | DG19: null | DH19: null | DI19: null | DJ19: null | DL19: =($DL$22-$DL$17)/5 + DL18 -> 157191.96 | DM19: null | DN19: null | DO19: null | DP19: null | DQ19: null | DR19: null | DS19: null | DT19: null | DU19: null | DV19: null | DW19: null | DX19: null | DY19: null | DZ19: null | EA19: null | EB19: null | EC19: null | ED19: null | EE19: null | EF19: null | EG19: null | EH19: null | EI19: null | EJ19: null | EK19: null | EL19: null | EM19: null | EN19: null | EO19: null | EP19: null | EQ19: null | ER19: null | ES19: null | ET19: null | EU19: null | EV19: null | EW19: null | EX19: null | EY19: null | EZ19: null | FA19: null | FB19: null | FC19: null | FD19: null | FE19: null | FF19: null
A20: 2013 | B20: null | C20: null | D20: null | E20: null | F20: null | G20: null | H20: null | I20: null | J20: null | K20: null | L20: null | M20: null | N20: null | O20: null | P20: null | Q20: null | R20: null | S20: null | T20: null | U20: null | V20: null | W20: null | X20: null | Y20: null | Z20: null | AA20: null | AB20: null | AC20: null | AD20: null | AE20: null | AF20: null | AG20: null | AH20: null | AI20: null | AJ20: null | AK20: null | AL20: null | AM20: null | AN20: null | AO20: null | AP20: null | AQ20: null | AR20: null | AS20: null | AT20: null | AU20: null | AV20: null | AW20: null | AX20: null | AY20: null | AZ20: null | BA20: null | BB20: null | BC20: null | BD20: null | BE20: null | BF20: null | BG20: null | BH20: null | BI20: null | BJ20: null | BK20: null | BL20: null | BM20: null | BN20: null | BO20: null | BP20: null | BQ20: null | BR20: null | BS20: null | BT20: null | BU20: null | BV20: null | BW20: null | BX20: null | BY20: null | BZ20: null | CA20: null | CB20: null | CC20: null | CD20: null | CE20: null | CF20: null | CG20: null | CH20: null | CI20: null | CJ20: null | CK20: null | CL20: null | CM20: null | CN20: null | CO20: null | CP20: null | CQ20: null | CR20: null | CS20: null | CT20: null | CU20: null | CV20: null | CW20: null | CX20: null | CY20: null | CZ20: null | DA20: null | DB20: null | DC20: null | DD20: null | DE20: null | DF20: null | DG20: null | DH20: null | DI20: null | DJ20: null | DL20: =($DL$22-$DL$17)/5 + DL19 -> 157214.7 | DM20: null | DN20: null | DO20: null | DP20: null | DQ20: null | DR20: null | DS20: null | DT20: null | DU20: null | DV20: null | DW20: null | DX20: null | DY20: null | DZ20: null | EA20: null | EB20: null | EC20: null | ED20: null | EE20: null | EF20: null | EG20: null | EH20: null | EI20: null | EJ20: null | EK20: null | EL20: null | EM20: null | EN20: null | EO20: null | EP20: null | EQ20: null | ER20: null | ES20: null | ET20: null | EU20: null | EV20: null | EW20: null | EX20: null | EY20: null | EZ20: null | FA20: null | FB20: null | FC20: null | FD20: null | FE20: null | FF20: null
A21: 2014 | B21: null | C21: null | D21: null | E21: null | F21: null | G21: null | H21: null | I21: null | J21: null | K21: null | L21: null | M21: null | N21: null | O21: null | P21: null | Q21: null | R21: null | S21: null | T21: null | U21: null | V21: null | W21: null | X21: null | Y21: null | Z21: null | AA21: null | AB21: null | AC21: null | AD21: null | AE21: null | AF21: null | AG21: null | AH21: null | AI21: null | AJ21: null | AK21: null | AL21: null | AM21: null | AN21: null | AO21: null | AP21: null | AQ21: null | AR21: null | AS21: null | AT21: null | AU21: null | AV21: null | AW21: null | AX21: null | AY21: null | AZ21: null | BA21: null | BB21: null | BC21: null | BD21: null | BE21: null | BF21: null | BG21: null | BH21: null | BI21: null | BJ21: null | BK21: null | BL21: null | BM21: null | BN21: null | BO21: null | BP21: null | BQ21: null | BR21: null | BS21: null | BT21: null | BU21: null | BV21: null | BW21: null | BX21: null | BY21: null | BZ21: null | CA21: null | CB21: null | CC21: null | CD21: null | CE21: null | CF21: null | CG21: null | CH21: null | CI21: null | CJ21: null | CK21: null | CL21: null | CM21: null | CN21: null | CO21: null | CP21: null | CQ21: null | CR21: null | CS21: null | CT21: null | CU21: null | CV21: null | CW21: null | CX21: null | CY21: null | CZ21: null | DA21: null | DB21: null | DC21: null | DD21: null | DE21: null | DF21: null | DG21: null | DH21: null | DI21: null | DJ21: null | DL21: =($DL$22-$DL$17)/5 + DL20 -> 157237.44 | DM21: null | DN21: null | DO21: null | DP21: null | DQ21: null | DR21: null | DS21: null | DT21: null | DU21: null | DV21: null | DW21: null | DX21: null | DY21: null | DZ21: null | EA21: null | EB21: null | EC21: null | ED21: null | EE21: null | EF21: null | EG21: null | EH21: null | EI21: null | EJ21: null | EK21: null | EL21: null | EM21: null | EN21: null | EO21: null | EP21: null | EQ21: null | ER21: null | ES21: null | ET21: null | EU21: null | EV21: null | EW21: null | EX21: null | EY21: null | EZ21: null | FA21: null | FB21: null | FC21: null | FD21: null | FE21: null | FF21: null
A22: 2015 | B22: 450.35981431855737 | C22: 33.57268477439011 | D22: 470.5816893440679 | E22: 120.30175168479715 | F22: 486.8433851146974 | G22: 4056.6178971713343 | H22: 12.598975604215639 | I22: 0.31754597023881276 | J22: 11.575308747385588 | K22: 1.287201 | L22: 14.380799999999995 | M22: 107.00196859554904 | N22: 3.2502922615789016 | O22: 0.0542546961064026 | P22: 2.2894784 | Q22: 1.317664531821413 | R22: 12.508000000000008 | S22: 56.84608973803698 | T22: 7.234921946375448 | U22: 0 | V22: 17.958000399999992 | W22: 3.86625582778687 | X22: 16.262900000000013 | Y22: 69.70500040000002 | Z22: 11.050058140006577 | AA22: 3.1952660538934827 | AB22: 6.808000399999997 | AC22: 0.5430005999999998 | AD22: 6.854999999999997 | AE22: 56.844000400000006 | AF22: 65.1371628320872 | AG22: 2.212164242057685 | AH22: 108.40899999999998 | AI22: 18.800000599999994 | AJ22: 65.1 | AK22: 927.0000004000003 | AL22: 0.8167145163448785 | AM22: 0.40967286791079843 | AN22: 0.4549313999999999 | AO22: 0.44813226075605905 | AP22: 3.146414499999997 | AQ22: 12.331949886981235 | AR22: 10.3087410751781 | AS22: 1.0531616293909556 | AT22: 2.097667682 | AU22: 0.10200060000000004 | AV22: 8.513599999999999 | AW22: 51.913500599999985 | AX22: 22.08123072422334 | AY22: 7.5373056608001345 | AZ22: 2.9369048608075286 | BA22: 6.174165802996984 | BB22: 21.148271968974473 | BC22: 98.27578511557843 | BD22: 92.06467960551134 | BE22: 2.015689020447241 | BF22: 33.343900000000005 | BG22: 11.281148128539423 | BH22: 46.38900000000002 | BI22: 317.55300040000003 | BJ22: 72.92901695073317 | BK22: 3.5201392490823595 | BL22: 110.85491182656186 | BM22: 13.931942248584962 | BN22: 57.6863413999923 | BO22: 722.9000003999998 | BP22: 2.275046422719677 | BQ22: 0.041678314569269626 | BR22: 1.5389663999999998 | BS22: 0.21500139999999993 | BT22: 3.376999999999995 | BU22: 26.39300079999999 | BV22: 51.50353481426862 | BW22: 5.034853183035459 | BX22: 59.039 | BY22: 41.3260006 | BZ22: 102.50899999999994 | CA22: 676.3500003999997 | CB22: 2.481080899857317 | CC22: 0.12164336421688814 | CD22: 1.426717257084445 | CE22: 6.198134173005251 | CF22: 1.7531375542923335 | CG22: 0.7209773999999999 | CH22: 0.5606384493613551 | CI22: 2.2319999999999993 | CJ22: 13.542600600000002 | CK22: 1.5591258138980362 | CL22: 0.0741274891420644 | CM22: 0.2620012 | CN22: 0.8634470320598581 | CO22: 2.745543 | CP22: 24.865000600000016 | CQ22: 0.869961888416036 | CR22: 0.41800119999999985 | CS22: 0.10420805025339128 | CT22: 1.0928294004495047 | CU22: 7.321359060666724 | CV22: 3.5800138154020167 | CW22: 10.555669800000004 | CX22: 1.3874957747370755 | CY22: 17.813176500000008 | CZ22: 54.60300039999998 | DA22: 2.1143345320754205 | DB22: 0.1263508 | DC22: 0.539906461587028 | DD22: 2.504232339613567 | DE22: 17.760183640732773 | DF22: 0.8153360366794269 | DG22: 18.43944568886166 | DH22: 3.050207504191418 | DI22: 4.883554311138337 | DJ22: 139.50000039999998 | DK22: =SUM(DE22+DJ22) -> 157.26018 | DL22: =DK22*1000 -> 157260.18 | DM22: 7.577114541146648 | DN22: 0.03661730592883682 | DO22: 19.393042988322062 | DP22: 2.36587070004004 | DQ22: 10.295414860155592 | DR22: 78.34700040000003 | DS22: 9.559661421773361 | DT22: 0.22653441060804602 | DU22: 21.58739901310765 | DV22: 3.7030006 | DW22: 37.58000000000002 | DX22: 200.5700006000001 | DY22: 18.17604814150861 | DZ22: 0.6631251098650528 | EA22: 4.965652000000001 | EB22: 1.8435584967149894 | EC22: 6.575000000000002 | ED22: 84.46785791462881 | EE22: 6.60301446804406 | EF22: 0.0320891828348396 | EG22: 12.7730004 | EH22: 3.6510759402395454 | EI22: 17.47100000000001 | EJ22: 89.86636248053341 | EK22: 0.28595489937537505 | EL22: 0.6280012 | EM22: 0.3529018385540428 | EN22: 3.5760825660756344 | EO22: 25.99653357579791 | EP22: 0.6189235630913645 | EQ22: 3.6618005500000024 | ER22: 0.8085959870859505 | ES22: 5.367630450000003 | ET22: 27.531000600000006 | EU22: 9.301559236710773 | EV22: 0.13701999999999998 | EW22: 4.62982778702163 | EX22: 1.1610006 | EY22: 7.540000000000005 | EZ22: 66.29500060000001 | FA22: 16.86932500899038 | FB22: 6.196104351799243 | FC22: 15.240799999999997 | FD22: 0.9092429468568924 | FE22: 9.828202439240146 | FF22: 111.89551629094301
A23: 2016 | B23: null | C23: null | D23: null | E23: null | F23: null | G23: null | H23: null | I23: null | J23: null | K23: null | L23: null | M23: null | N23: null | O23: null | P23: null | Q23: null | R23: null | S23: null | T23: null | U23: null | V23: null | W23: null | X23: null | Y23: null | Z23: null | AA23: null | AB23: null | AC23: null | AD23: null | AE23: null | AF23: null | AG23: null | AH23: null | AI23: null | AJ23: null | AK23: null | AL23: null | AM23: null | AN23: null | AO23: null | AP23: null | AQ23: null | AR23: null | AS23: null | AT23: null | AU23: null | AV23: null | AW23: null | AX23: null | AY23: null | AZ23: null | BA23: null | BB23: null | BC23: null | BD23: null | BE23: null | BF23: null | BG23: null | BH23: null | BI23: null | BJ23: null | BK23: null | BL23: null | BM23: null | BN23: null | BO23: null | BP23: null | BQ23: null | BR23: null | BS23: null | BT23: null | BU23: null | BV23: null | BW23: null | BX23: null | BY23: null | BZ23: null | CA23: null | CB23: null | CC23: null | CD23: null | CE23: null | CF23: null | CG23: null | CH23: null | CI23: null | CJ23: null | CK23: null | CL23: null | CM23: null | CN23: null | CO23: null | CP23: null | CQ23: null | CR23: null | CS23: null | CT23: null | CU23: null | CV23: null | CW23: null | CX23: null | CY23: null | CZ23: null | DA23: null | DB23: null | DC23: null | DD23: null | DE23: null | DF23: null | DG23: null | DH23: null | DI23: null | DJ23: null | DL23: =($DL$27-$DL$22)/5 + DL22 -> 154276.42 | DM23: null | DN23: null | DO23: null | DP23: null | DQ23: null | DR23: null | DS23: null | DT23: null | DU23: null | DV23: null | DW23: null | DX23: null | DY23: null | DZ23: null | EA23: null | EB23: null | EC23: null | ED23: null | EE23: null | EF23: null | EG23: null | EH23: null | EI23: null | EJ23: null | EK23: null | EL23: null | EM23: null | EN23: null | EO23: null | EP23: null | EQ23: null | ER23: null | ES23: null | ET23: null | EU23: null | EV23: null | EW23: null | EX23: null | EY23: null | EZ23: null | FA23: null | FB23: null | FC23: null | FD23: null | FE23: null | FF23: null
A24: 2017 | B24: null | C24: null | D24: null | E24: null | F24: null | G24: null | H24: null | I24: null | J24: null | K24: null | L24: null | M24: null | N24: null | O24: null | P24: null | Q24: null | R24: null | S24: null | T24: null | U24: null | V24: null | W24: null | X24: null | Y24: null | Z24: null | AA24: null | AB24: null | AC24: null | AD24: null | AE24: null | AF24: null | AG24: null | AH24: null | AI24: null | AJ24: null | AK24: null | AL24: null | AM24: null | AN24: null | AO24: null | AP24: null | AQ24: null | AR24: null | AS24: null | AT24: null | AU24: null | AV24: null | AW24: null | AX24: null | AY24: null | AZ24: null | BA24: null | BB24: null | BC24: null | BD24: null | BE24: null | BF24: null | BG24: null | BH24: null | BI24: null | BJ24: null | BK24: null | BL24: null | BM24: null | BN24: null | BO24: null | BP24: null | BQ24: null | BR24: null | BS24: null | BT24: null | BU24: null | BV24: null | BW24: null | BX24: null | BY24: null | BZ24: null | CA24: null | CB24: null | CC24: null | CD24: null | CE24: null | CF24: null | CG24: null | CH24: null | CI24: null | CJ24: null | CK24: null | CL24: null | CM24: null | CN24: null | CO24: null | CP24: null | CQ24: null | CR24: null | CS24: null | CT24: null | CU24: null | CV24: null | CW24: null | CX24: null | CY24: null | CZ24: null | DA24: null | DB24: null | DC24: null | DD24: null | DE24: null | DF24: null | DG24: null | DH24: null | DI24: null | DJ24: null | DL24: =($DL$27-$DL$22)/5 + DL23 -> 151292.67 | DM24: null | DN24: null | DO24: null | DP24: null | DQ24: null | DR24: null | DS24: null | DT24: null | DU24: null | DV24: null | DW24: null | DX24: null | DY24: null | DZ24: null | EA24: null | EB24: null | EC24: null | ED24: null | EE24: null | EF24: null | EG24: null | EH24: null | EI24: null | EJ24: null | EK24: null | EL24: null | EM24: null | EN24: null | EO24: null | EP24: null | EQ24: null | ER24: null | ES24: null | ET24: null | EU24: null | EV24: null | EW24: null | EX24: null | EY24: null | EZ24: null | FA24: null | FB24: null | FC24: null | FD24: null | FE24: null | FF24: null
A25: 2018 | B25: null | C25: null | D25: null | E25: null | F25: null | G25: null | H25: null | I25: null | J25: null | K25: null | L25: null | M25: null | N25: null | O25: null | P25: null | Q25: null | R25: null | S25: null | T25: null | U25: null | V25: null | W25: null | X25: null | Y25: null | Z25: null | AA25: null | AB25: null | AC25: null | AD25: null | AE25: null | AF25: null | AG25: null | AH25: null | AI25: null | AJ25: null | AK25: null | AL25: null | AM25: null | AN25: null | AO25: null | AP25: null | AQ25: null | AR25: null | AS25: null | AT25: null | AU25: null | AV25: null | AW25: null | AX25: null | AY25: null | AZ25: null | BA25: null | BB25: null | BC25: null | BD25: null | BE25: null | BF25: null | BG25: null | BH25: null | BI25: null | BJ25: null | BK25: null | BL25: null | BM25: null | BN25: null | BO25: null | BP25: null | BQ25: null | BR25: null | BS25: null | BT25: null | BU25: null | BV25: null | BW25: null | BX25: null | BY25: null | BZ25: null | CA25: null | CB25: null | CC25: null | CD25: null | CE25: null | CF25: null | CG25: null | CH25: null | CI25: null | CJ25: null | CK25: null | CL25: null | CM25: null | CN25: null | CO25: null | CP25: null | CQ25: null | CR25: null | CS25: null | CT25: null | CU25: null | CV25: null | CW25: null | CX25: null | CY25: null | CZ25: null | DA25: null | DB25: null | DC25: null | DD25: null | DE25: null | DF25: null | DG25: null | DH25: null | DI25: null | DJ25: null | DL25: =($DL$27-$DL$22)/5 + DL24 -> 148308.91 | DM25: null | DN25: null | DO25: null | DP25: null | DQ25: null | DR25: null | DS25: null | DT25: null | DU25: null | DV25: null | DW25: null | DX25: null | DY25: null | DZ25: null | EA25: null | EB25: null | EC25: null | ED25: null | EE25: null | EF25: null | EG25: null | EH25: null | EI25: null | EJ25: null | EK25: null | EL25: null | EM25: null | EN25: null | EO25: null | EP25: null | EQ25: null | ER25: null | ES25: null | ET25: null | EU25: null | EV25: null | EW25: null | EX25: null | EY25: null | EZ25: null | FA25: null | FB25: null | FC25: null | FD25: null | FE25: null | FF25: null
A26: 2019 | B26: null | C26: null | D26: null | E26: null | F26: null | G26: null | H26: null | I26: null | J26: null | K26: null | L26: null | M26: null | N26: null | O26: null | P26: null | Q26: null | R26: null | S26: null | T26: null | U26: null | V26: null | W26: null | X26: null | Y26: null | Z26: null | AA26: null | AB26: null | AC26: null | AD26: null | AE26: null | AF26: null | AG26: null | AH26: null | AI26: null | AJ26: null | AK26: null | AL26: null | AM26: null | AN26: null | AO26: null | AP26: null | AQ26: null | AR26: null | AS26: null | AT26: null | AU26: null | AV26: null | AW26: null | AX26: null | AY26: null | AZ26: null | BA26: null | BB26: null | BC26: null | BD26: null | BE26: null | BF26: null | BG26: null | BH26: null | BI26: null | BJ26: null | BK26: null | BL26: null | BM26: null | BN26: null | BO26: null | BP26: null | BQ26: null | BR26: null | BS26: null | BT26: null | BU26: null | BV26: null | BW26: null | BX26: null | BY26: null | BZ26: null | CA26: null | CB26: null | CC26: null | CD26: null | CE26: null | CF26: null | CG26: null | CH26: null | CI26: null | CJ26: null | CK26: null | CL26: null | CM26: null | CN26: null | CO26: null | CP26: null | CQ26: null | CR26: null | CS26: null | CT26: null | CU26: null | CV26: null | CW26: null | CX26: null | CY26: null | CZ26: null | DA26: null | DB26: null | DC26: null | DD26: null | DE26: null | DF26: null | DG26: null | DH26: null | DI26: null | DJ26: null | DL26: =($DL$27-$DL$22)/5 + DL25 -> 145325.15 | DM26: null | DN26: null | DO26: null | DP26: null | DQ26: null | DR26: null | DS26: null | DT26: null | DU26: null | DV26: null | DW26: null | DX26: null | DY26: null | DZ26: null | EA26: null | EB26: null | EC26: null | ED26: null | EE26: null | EF26: null | EG26: null | EH26: null | EI26: null | EJ26: null | EK26: null | EL26: null | EM26: null | EN26: null | EO26: null | EP26: null | EQ26: null | ER26: null | ES26: null | ET26: null | EU26: null | EV26: null | EW26: null | EX26: null | EY26: null | EZ26: null | FA26: null | FB26: null | FC26: null | FD26: null | FE26: null | FF26: null
A27: 2020 | B27: 243.73775770891592 | C27: 18.54548219903256 | D27: 274.5262394321215 | E27: 100.36651818561846 | F27: 312.68533826577846 | G27: 3547.7571998140293 | H27: 5.857703925573869 | I27: 0.220958947293336 | J27: 5.564434114995458 | K27: 1.1214284584087155 | L27: 8.45582676928749 | M27: 88.48267573235374 | N27: 2.0280901969048286 | O27: 0.029442922098822003 | P27: 1.7002019092207057 | Q27: 1.324544836782311 | R27: 8.774796024745148 | S27: 52.10306554110958 | T27: 3.740228916559147 | U27: 0 | V27: 14.812618231695655 | W27: 3.8044680354219476 | X27: 14.13476161293061 | Y27: 68.37399266010158 | Z27: 5.959550827005331 | AA27: 1.7780753260242304 | AB27: 5.267916195836662 | AC27: 0.4932050555024884 | AD27: 6.961060324183774 | AE27: 59.94546338425647 | AF27: 34.57992399432344 | AG27: 1.2120203065768178 | AH27: 78.78694882843934 | AI27: 17.679074025519686 | AJ27: 51.47021362552581 | AK27: 874.6790493271151 | AL27: 0.46162346067634374 | AM27: 0.22932725973695103 | AN27: 0.3722298241754872 | AO27: 0.500373213667887 | AP27: 2.658003247488763 | AQ27: 12.613475393467013 | AR27: 5.937017849640049 | AS27: 0.5838041363999388 | AT27: 1.055519053994952 | AU27: 0.09289770796130295 | AV27: 5.121269511628614 | AW27: 45.53543497838943 | AX27: 12.133191519123809 | AY27: 3.832834938551967 | AZ27: 1.7905554279525782 | BA27: 5.695700793182848 | BB27: 15.612534521212071 | BC27: 97.00725648851235 | BD27: 52.41182734183532 | BE27: 1.1567800543487026 | BF27: 14.779301123846464 | BG27: 8.767076994502736 | BH27: 17.728890730395545 | BI27: 234.41336991992827 | BJ27: 36.27104784796808 | BK27: 1.953255021050573 | BL27: 44.23819068631395 | BM27: 11.020812421978194 | BN27: 27.119178326557886 | BO27: 565.0011918651651 | BP27: 1.4740967129277325 | BQ27: 0.02380215044301475 | BR27: 0.808006978491383 | BS27: 0.20481224826061312 | BT27: 2.8953981463568725 | BU27: 23.236324340582538 | BV27: 27.729380338091733 | BW27: 2.967045355483269 | BX27: 27.975224575437522 | BY27: 29.026442735831658 | BZ27: 55.93699260171691 | CA27: 544.4007718615384 | CB27: 1.5063653320055899 | CC27: 0.10477251355897352 | CD27: 0.9980442577704438 | CE27: 5.538702669809153 | CF27: 1.0188085307451316 | CG27: 0.5615839779796021 | CH27: 0.5850462065446841 | CI27: 1.86082633438362 | CJ27: 14.855628198769383 | CK27: 0.9118609859630572 | CL27: 0.0407559756887381 | CM27: 0.23778959033576008 | CN27: 0.9104693973523125 | CO27: 2.3137034533051013 | CP27: 33.09879213477792 | CQ27: 0.5336738395380541 | CR27: 0.18831350068029962 | CS27: 0.0934606838752423 | CT27: 0.6430840246253795 | CU27: 6.293936539787338 | CV27: 2.1932798757851697 | CW27: 6.963869757320352 | CX27: 1.3002377003579655 | CY27: 13.5922174986839 | CZ27: 55.879300145548136 | DA27: 1.1068911139793234 | DB27: 0.08384616620084183 | DC27: 0.36409176039569463 | DD27: 2.2222159735007225 | DE27: 9.472625917259647 | DF27: 0.44982758042021337 | DG27: 12.828111611563935 | DH27: 2.92559481428622 | DI27: 3.725423855048948 | DJ27: 132.86876172935794 | DK27: =SUM(DE27+DJ27) -> 142.34139 | DL27: =DK27*1000 -> 142341.39 | DM27: 4.068012605389143 | DN27: 0.020095129138320806 | DO27: 11.408593517912093 | DP27: 2.1557151834891575 | DQ27: 7.3283937139272 | DR27: 70.04118856583032 | DS27: 5.358432795385826 | DT27: 0.12466303499729035 | DU27: 16.10812618172192 | DV27: 3.776015717259032 | DW27: 26.449847908587806 | DX27: 181.0019874251461 | DY27: 10.20138218509323 | DZ27: 0.3998704882474802 | EA27: 2.3372563464363645 | EB27: 1.7174164584740712 | EC27: 3.9910157807943607 | ED27: 70.68727824605486 | EE27: 3.9046893599087533 | EF27: 0.01783014551720802 | EG27: 7.016515157115733 | EH27: 3.406185225910395 | EI27: 10.992334985364206 | EJ27: 79.04848550803365 | EK27: 0.15867680167736567 | EL27: 0.378655484101663 | EM27: 0.4425817110461337 | EN27: 2.687647385135776 | EO27: 23.7495169851259 | EP27: 0.37284475297237873 | EQ27: 2.5282682237915997 | ER27: 1.066906656684987 | ES27: 4.522234361476855 | ET27: 25.720882630767285 | EU27: 5.3691001082936 | EV27: 0.07702487306656361 | EW27: 3.3598439473674473 | EX27: 1.1278096459463571 | EY27: 6.960455873286019 | EZ27: 64.35783059411706 | FA27: 8.97743057429 | FB27: 3.428068553949119 | FC27: 13.45816518539459 | FD27: 0.9396235776117047 | FE27: 9.387091630963528 | FF27: 116.60062097488385
A28: 2021 | B28: null | C28: null | D28: null | E28: null | F28: null | G28: null | H28: null | I28: null | J28: null | K28: null | L28: null | M28: null | N28: null | O28: null | P28: null | Q28: null | R28: null | S28: null | T28: null | U28: null | V28: null | W28: null | X28: null | Y28: null | Z28: null | AA28: null | AB28: null | AC28: null | AD28: null | AE28: null | AF28: null | AG28: null | AH28: null | AI28: null | AJ28: null | AK28: null | AL28: null | AM28: null | AN28: null | AO28: null | AP28: null | AQ28: null | AR28: null | AS28: null | AT28: null | AU28: null | AV28: null | AW28: null | AX28: null | AY28: null | AZ28: null | BA28: null | BB28: null | BC28: null | BD28: null | BE28: null | BF28: null | BG28: null | BH28: null | BI28: null | BJ28: null | BK28: null | BL28: null | BM28: null | BN28: null | BO28: null | BP28: null | BQ28: null | BR28: null | BS28: null | BT28: null | BU28: null | BV28: null | BW28: null | BX28: null | BY28: null | BZ28: null | CA28: null | CB28: null | CC28: null | CD28: null | CE28: null | CF28: null | CG28: null | CH28: null | CI28: null | CJ28: null | CK28: null | CL28: null | CM28: null | CN28: null | CO28: null | CP28: null | CQ28: null | CR28: null | CS28: null | CT28: null | CU28: null | CV28: null | CW28: null | CX28: null | CY28: null | CZ28: null | DA28: null | DB28: null | DC28: null | DD28: null | DE28: null | DF28: null | DG28: null | DH28: null | DI28: null | DJ28: null | DL28: =($DL$32-$DL$27)/5 + DL27 -> 147786.4 | DM28: null | DN28: null | DO28: null | DP28: null | DQ28: null | DR28: null | DS28: null | DT28: null | DU28: null | DV28: null | DW28: null | DX28: null | DY28: null | DZ28: null | EA28: null | EB28: null | EC28: null | ED28: null | EE28: null | EF28: null | EG28: null | EH28: null | EI28: null | EJ28: null | EK28: null | EL28: null | EM28: null | EN28: null | EO28: null | EP28: null | EQ28: null | ER28: null | ES28: null | ET28: null | EU28: null | EV28: null | EW28: null | EX28: null | EY28: null | EZ28: null | FA28: null | FB28: null | FC28: null | FD28: null | FE28: null | FF28: null
A29: 2022 | B29: null | C29: null | D29: null | E29: null | F29: null | G29: null | H29: null | I29: null | J29: null | K29: null | L29: null | M29: null | N29: null | O29: null | P29: null | Q29: null | R29: null | S29: null | T29: null | U29: null | V29: null | W29: null | X29: null | Y29: null | Z29: null | AA29: null | AB29: null | AC29: null | AD29: null | AE29: null | AF29: null | AG29: null | AH29: null | AI29: null | AJ29: null | AK29: null | AL29: null | AM29: null | AN29: null | AO29: null | AP29: null | AQ29: null | AR29: null | AS29: null | AT29: null | AU29: null | AV29: null | AW29: null | AX29: null | AY29: null | AZ29: null | BA29: null | BB29: null | BC29: null | BD29: null | BE29: null | BF29: null | BG29: null | BH29: null | BI29: null | BJ29: null | BK29: null | BL29: null | BM29: null | BN29: null | BO29: null | BP29: null | BQ29: null | BR29: null | BS29: null | BT29: null | BU29: null | BV29: null | BW29: null | BX29: null | BY29: null | BZ29: null | CA29: null | CB29: null | CC29: null | CD29: null | CE29: null | CF29: null | CG29: null | CH29: null | CI29: null | CJ29: null | CK29: null | CL29: null | CM29: null | CN29: null | CO29: null | CP29: null | CQ29: null | CR29: null | CS29: null | CT29: null | CU29: null | CV29: null | CW29: null | CX29: null | CY29: null | CZ29: null | DA29: null | DB29: null | DC29: null | DD29: null | DE29: null | DF29: null | DG29: null | DH29: null | DI29: null | DJ29: null | DL29: =($DL$32-$DL$27)/5 + DL28 -> 153231.41 | DM29: null | DN29: null | DO29: null | DP29: null | DQ29: null | DR29: null | DS29: null | DT29: null | DU29: null | DV29: null | DW29: null | DX29: null | DY29: null | DZ29: null | EA29: null | EB29: null | EC29: null | ED29: null | EE29: null | EF29: null | EG29: null | EH29: null | EI29: null | EJ29: null | EK29: null | EL29: null | EM29: null | EN29: null | EO29: null | EP29: null | EQ29: null | ER29: null | ES29: null | ET29: null | EU29: null | EV29: null | EW29: null | EX29: null | EY29: null | EZ29: null | FA29: null | FB29: null | FC29: null | FD29: null | FE29: null | FF29: null
A30: 2023 | B30: null | C30: null | D30: null | E30: null | F30: null | G30: null | H30: null | I30: null | J30: null | K30: null | L30: null | M30: null | N30: null | O30: null | P30: null | Q30: null | R30: null | S30: null | T30: null | U30: null | V30: null | W30: null | X30: null | Y30: null | Z30: null | AA30: null | AB30: null | AC30: null | AD30: null | AE30: null | AF30: null | AG30: null | AH30: null | AI30: null | AJ30: null | AK30: null | AL30: null | AM30: null | AN30: null | AO30: null | AP30: null | AQ30: null | AR30: null | AS30: null | AT30: null | AU30: null | AV30: null | AW30: null | AX30: null | AY30: null | AZ30: null | BA30: null | BB30: null | BC30: null | BD30: null | BE30: null | BF30: null | BG30: null | BH30: null | BI30: null | BJ30: null | BK30: null | BL30: null | BM30: null | BN30: null | BO30: null | BP30: null | BQ30: null | BR30: null | BS30: null | BT30: null | BU30: null | BV30: null | BW30: null | BX30: null | BY30: null | BZ30: null | CA30: null | CB30: null | CC30: null | CD30: null | CE30: null | CF30: null | CG30: null | CH30: null | CI30: null | CJ30: null | CK30: null | CL30: null | CM30: null | CN30: null | CO30: null | CP30: null | CQ30: null | CR30: null | CS30: null | CT30: null | CU30: null | CV30: null | CW30: null | CX30: null | CY30: null | CZ30: null | DA30: null | DB30: null | DC30: null | DD30: null | DE30: null | DF30: null | DG30: null | DH30: null | DI30: null | DJ30: null | DL30: =($DL$32-$DL$27)/5 + DL29 -> 158676.42 | DM30: null | DN30: null | DO30: null | DP30: null | DQ30: null | DR30: null | DS30: null | DT30: null | DU30: null | DV30: null | DW30: null | DX30: null | DY30: null | DZ30: null | EA30: null | EB30: null | EC30: null | ED30: null | EE30: null | EF30: null | EG30: null | EH30: null | EI30: null | EJ30: null | EK30: null | EL30: null | EM30: null | EN30: null | EO30: null | EP30: null | EQ30: null | ER30: null | ES30: null | ET30: null | EU30: null | EV30: null | EW30: null | EX30: null | EY30: null | EZ30: null | FA30: null | FB30: null | FC30: null | FD30: null | FE30: null | FF30: null
A31: 2024 | B31: null | C31: null | D31: null | E31: null | F31: null | G31: null | H31: null | I31: null | J31: null | K31: null | L31: null | M31: null | N31: null | O31: null | P31: null | Q31: null | R31: null | S31: null | T31: null | U31: null | V31: null | W31: null | X31: null | Y31: null | Z31: null | AA31: null | AB31: null | AC31: null | AD31: null | AE31: null | AF31: null | AG31: null | AH31: null | AI31: null | AJ31: null | AK31: null | AL31: null | AM31: null | AN31: null | AO31: null | AP31: null | AQ31: null | AR31: null | AS31: null | AT31: null | AU31: null | AV31: null | AW31: null | AX31: null | AY31: null | AZ31: null | BA31: null | BB31: null | BC31: null | BD31: null | BE31: null | BF31: null | BG31: null | BH31: null | BI31: null | BJ31: null | BK31: null | BL31: null | BM31: null | BN31: null | BO31: null | BP31: null | BQ31: null | BR31: null | BS31: null | BT31: null | BU31: null | BV31: null | BW31: null | BX31: null | BY31: null | BZ31: null | CA31: null | CB31: null | CC31: null | CD31: null | CE31: null | CF31: null | CG31: null | CH31: null | CI31: null | CJ31: null | CK31: null | CL31: null | CM31: null | CN31: null | CO31: null | CP31: null | CQ31: null | CR31: null | CS31: null | CT31: null | CU31: null | CV31: null | CW31: null | CX31: null | CY31: null | CZ31: null | DA31: null | DB31: null | DC31: null | DD31: null | DE31: null | DF31: null | DG31: null | DH31: null | DI31: null | DJ31: null | DL31: =($DL$32-$DL$27)/5 + DL30 -> 164121.42 | DM31: null | DN31: null | DO31: null | DP31: null | DQ31: null | DR31: null | DS31: null | DT31: null | DU31: null | DV31: null | DW31: null | DX31: null | DY31: null | DZ31: null | EA31: null | EB31: null | EC31: null | ED31: null | EE31: null | EF31: null | EG31: null | EH31: null | EI31: null | EJ31: null | EK31: null | EL31: null | EM31: null | EN31: null | EO31: null | EP31: null | EQ31: null | ER31: null | ES31: null | ET31: null | EU31: null | EV31: null | EW31: null | EX31: null | EY31: null | EZ31: null | FA31: null | FB31: null | FC31: null | FD31: null | FE31: null | FF31: null
A32: 2025 | B32: 570.5547180423551 | C32: 35.93240667332514 | D32: 531.7391208148977 | E32: 122.9683877548704 | F32: 472.7589874002123 | G32: 4353.778321858893 | H32: 13.457611766236745 | I32: 0.44608084990935987 | J32: 12.177426097921932 | K32: 1.3403394211073736 | L32: 13.411220250765153 | M32: 100.88832523578562 | N32: 5.007393578801849 | O32: 0.05546261817212046 | P32: 2.7506273086809623 | Q32: 1.4688598809044593 | R32: 11.337750221013419 | S32: 58.60093761129116 | T32: 8.061606794076468 | U32: 0 | V32: 23.102740813016556 | W32: 4.394259616763485 | X32: 18.88007890953088 | Y32: 79.99843667237622 | Z32: 14.01630112078194 | AA32: 3.6567555119001964 | AB32: 7.344830751405071 | AC32: 0.5191900345233798 | AD32: 7.871499711582504 | AE32: 65.97875401468573 | AF32: 76.970131558817 | AG32: 2.3243615510516316 | AH32: 121.12303329620651 | AI32: 19.02290463776122 | AJ32: 64.16630494068359 | AK32: 929.7630465440488 | AL32: 1.0338991508252924 | AM32: 0.4718528033538516 | AN32: 0.6164311819846988 | AO32: 0.5502112899339453 | AP32: 3.201091505086767 | AQ32: 13.936472621145635 | AR32: 12.586233647321182 | AS32: 1.0405596920085949 | AT32: 2.4575767152626296 | AU32: 0.12181441527134669 | AV32: 9.81445274384059 | AW32: 56.21969591314096 | AX32: 29.7973844945747 | AY32: 6.945569327875282 | AZ32: 3.109264297730224 | BA32: 6.317719617567295 | BB32: 20.93975339168774 | BC32: 111.22176328266544 | BD32: 130.2017625804674 | BE32: 2.4620018135941995 | BF32: 38.8890804321576 | BG32: 12.283221932709228 | BH32: 43.19432604082131 | BI32: 339.70801430226993 | BJ32: 82.06241652632916 | BK32: 3.7154094539070037 | BL32: 122.49431458149094 | BM32: 13.800359638214013 | BN32: 51.21439001100039 | BO32: 749.7988243492579 | BP32: 3.9145597590694594 | BQ32: 0.04774777310147459 | BR32: 1.2961942311177772 | BS32: 0.2415013977451957 | BT32: 3.9262691030280505 | BU32: 28.581683886069392 | BV32: 68.1402226957311 | BW32: 6.037357777164936 | BX32: 60.08055232976155 | BY32: 38.200368091228285 | BZ32: 92.66072761735408 | CA32: 765.3689091375259 | CB32: 4.239610760439014 | CC32: 0.12395529706768896 | CD32: 1.4542219737253197 | CE32: 7.048571177799719 | CF32: 2.114741535753722 | CG32: 0.8151708097560031 | CH32: 0.6201148074681475 | CI32: 2.1900375634777083 | CJ32: 15.784441074564914 | CK32: 2.0270874972010815 | CL32: 0.08187027504634727 | CM32: 0.5881940063811036 | CN32: 1.0696608307770334 | CO32: 2.863373968639749 | CP32: 35.62090116676521 | CQ32: 1.172163166343344 | CR32: 0.47622120400961615 | CS32: 0.1214136632092985 | CT32: 1.1146500678877553 | CU32: 7.177054347053969 | CV32: 5.431623943185505 | CW32: 11.538954829775685 | CX32: 1.5010443622602798 | CY32: 17.97942522144638 | CZ32: 67.06075506592548 | DA32: 3.0712401615596105 | DB32: 0.1031508793746406 | DC32: 0.5897382224358896 | DD32: 2.9935052743820854 | DE32: 21.757834429623024 | DF32: 0.8814762088086339 | DG32: 20.376899121226426 | DH32: 3.210694778258079 | DI32: 4.787602075324761 | DJ32: 147.8085992009669 | DK32: =SUM(DE32+DJ32) -> 169.56643 | DL32: =DK32*1000 -> 169566.43 | DM32: 9.769351727699972 | DN32: 0.036351692635671944 | DO32: 21.483634943710065 | DP32: 2.5070651827169077 | DQ32: 10.653426314440694 | DR32: 84.9334779620711 | DS32: 12.983449324083463 | DT32: 0.25556840038976664 | DU32: 31.784352311863906 | DV32: 4.728545697308484 | DW32: 36.306489701816716 | DX32: 223.54780152881835 | DY32: 21.415011835767288 | DZ32: 0.7778710109502205 | EA32: 6.193969474138485 | EB32: 2.204342743483461 | EC32: 7.341622807125093 | ED32: 92.6396263613346 | EE32: 9.51044892204988 | EF32: 0.03918492349504193 | EG32: 14.775743291531294 | EH32: 4.621296489217151 | EI32: 18.397236494850222 | EJ32: 115.88765458609302 | EK32: 0.39694400201987934 | EL32: 0.8307944239113951 | EM32: 0.45410921649177877 | EN32: 3.955912100632789 | EO32: 28.78943068889282 | EP32: 0.9394922704440333 | EQ32: 4.413142282763189 | ER32: 1.2588765840887608 | ES32: 6.107730933343417 | ET32: 31.385610125255447 | EU32: 12.30600896742566 | EV32: 0.1602251304417705 | EW32: 4.959689903545078 | EX32: 1.1911788944161226 | EY32: 8.173441815832835 | EZ32: 68.61020922413655 | FA32: 18.170185825727515 | FB32: 6.496699859519032 | FC32: 18.060282175548863 | FD32: 0.9921883550033448 | FE32: 10.226213692838545 | FF32: 124.42582050457014
A33: 2026 | B33: null | C33: null | D33: null | E33: null | F33: null | G33: null | H33: null | I33: null | J33: null | K33: null | L33: null | M33: null | N33: null | O33: null | P33: null | Q33: null | R33: null | S33: null | T33: null | U33: null | V33: null | W33: null | X33: null | Y33: null | Z33: null | AA33: null | AB33: null | AC33: null | AD33: null | AE33: null | AF33: null | AG33: null | AH33: null | AI33: null | AJ33: null | AK33: null | AL33: null | AM33: null | AN33: null | AO33: null | AP33: null | AQ33: null | AR33: null | AS33: null | AT33: null | AU33: null | AV33: null | AW33: null | AX33: null | AY33: null | AZ33: null | BA33: null | BB33: null | BC33: null | BD33: null | BE33: null | BF33: null | BG33: null | BH33: null | BI33: null | BJ33: null | BK33: null | BL33: null | BM33: null | BN33: null | BO33: null | BP33: null | BQ33: null | BR33: null | BS33: null | BT33: null | BU33: null | BV33: null | BW33: null | BX33: null | BY33: null | BZ33: null | CA33: null | CB33: null | CC33: null | CD33: null | CE33: null | CF33: null | CG33: null | CH33: null | CI33: null | CJ33: null | CK33: null | CL33: null | CM33: null | CN33: null | CO33: null | CP33: null | CQ33: null | CR33: null | CS33: null | CT33: null | CU33: null | CV33: null | CW33: null | CX33: null | CY33: null | CZ33: null | DA33: null | DB33: null | DC33: null | DD33: null | DE33: null | DF33: null | DG33: null | DH33: null | DI33: null | DJ33: null | DL33: =($DL$37-$DL$32)/5 + DL32 -> 172018.21 | DM33: null | DN33: null | DO33: null | DP33: null | DQ33: null | DR33: null | DS33: null | DT33: null | DU33: null | DV33: null | DW33: null | DX33: null | DY33: null | DZ33: null | EA33: null | EB33: null | EC33: null | ED33: null | EE33: null | EF33: null | EG33: null | EH33: null | EI33: null | EJ33: null | EK33: null | EL33: null | EM33: null | EN33: null | EO33: null | EP33: null | EQ33: null | ER33: null | ES33: null | ET33: null | EU33: null | EV33: null | EW33: null | EX33: null | EY33: null | EZ33: null | FA33: null | FB33: null | FC33: null | FD33: null | FE33: null | FF33: null
A34: 2027 | B34: null | C34: null | D34: null | E34: null | F34: null | G34: null | H34: null | I34: null | J34: null | K34: null | L34: null | M34: null | N34: null | O34: null | P34: null | Q34: null | R34: null | S34: null | T34: null | U34: null | V34: null | W34: null | X34: null | Y34: null | Z34: null | AA34: null | AB34: null | AC34: null | AD34: null | AE34: null | AF34: null | AG34: null | AH34: null | AI34: null | AJ34: null | AK34: null | AL34: null | AM34: null | AN34: null | AO34: null | AP34: null | AQ34: null | AR34: null | AS34: null | AT34: null | AU34: null | AV34: null | AW34: null | AX34: null | AY34: null | AZ34: null | BA34: null | BB34: null | BC34: null | BD34: null | BE34: null | BF34: null | BG34: null | BH34: null | BI34: null | BJ34: null | BK34: null | BL34: null | BM34: null | BN34: null | BO34: null | BP34: null | BQ34: null | BR34: null | BS34: null | BT34: null | BU34: null | BV34: null | BW34: null | BX34: null | BY34: null | BZ34: null | CA34: null | CB34: null | CC34: null | CD34: null | CE34: null | CF34: null | CG34: null | CH34: null | CI34: null | CJ34: null | CK34: null | CL34: null | CM34: null | CN34: null | CO34: null | CP34: null | CQ34: null | CR34: null | CS34: null | CT34: null | CU34: null | CV34: null | CW34: null | CX34: null | CY34: null | CZ34: null | DA34: null | DB34: null | DC34: null | DD34: null | DE34: null | DF34: null | DG34: null | DH34: null | DI34: null | DJ34: null | DL34: =($DL$37-$DL$32)/5 + DL33 -> 174469.98 | DM34: null | DN34: null | DO34: null | DP34: null | DQ34: null | DR34: null | DS34: null | DT34: null | DU34: null | DV34: null | DW34: null | DX34: null | DY34: null | DZ34: null | EA34: null | EB34: null | EC34: null | ED34: null | EE34: null | EF34: null | EG34: null | EH34: null | EI34: null | EJ34: null | EK34: null | EL34: null | EM34: null | EN34: null | EO34: null | EP34: null | EQ34: null | ER34: null | ES34: null | ET34: null | EU34: null | EV34: null | EW34: null | EX34: null | EY34: null | EZ34: null | FA34: null | FB34: null | FC34: null | FD34: null | FE34: null | FF34: null
A35: 2028 | B35: null | C35: null | D35: null | E35: null | F35: null | G35: null | H35: null | I35: null | J35: null | K35: null | L35: null | M35: null | N35: null | O35: null | P35: null | Q35: null | R35: null | S35: null | T35: null | U35: null | V35: null | W35: null | X35: null | Y35: null | Z35: null | AA35: null | AB35: null | AC35: null | AD35: null | AE35: null | AF35: null | AG35: null | AH35: null | AI35: null | AJ35: null | AK35: null | AL35: null | AM35: null | AN35: null | AO35: null | AP35: null | AQ35: null | AR35: null | AS35: null | AT35: null | AU35: null | AV35: null | AW35: null | AX35: null | AY35: null | AZ35: null | BA35: null | BB35: null | BC35: null | BD35: null | BE35: null | BF35: null | BG35: null | BH35: null | BI35: null | BJ35: null | BK35: null | BL35: null | BM35: null | BN35: null | BO35: null | BP35: null | BQ35: null | BR35: null | BS35: null | BT35: null | BU35: null | BV35: null | BW35: null | BX35: null | BY35: null | BZ35: null | CA35: null | CB35: null | CC35: null | CD35: null | CE35: null | CF35: null | CG35: null | CH35: null | CI35: null | CJ35: null | CK35: null | CL35: null | CM35: null | CN35: null | CO35: null | CP35: null | CQ35: null | CR35: null | CS35: null | CT35: null | CU35: null | CV35: null | CW35: null | CX35: null | CY35: null | CZ35: null | DA35: null | DB35: null | DC35: null | DD35: null | DE35: null | DF35: null | DG35: null | DH35: null | DI35: null | DJ35: null | DL35: =($DL$37-$DL$32)/5 + DL34 -> 176921.76 | DM35: null | DN35: null | DO35: null | DP35: null | DQ35: null | DR35: null | DS35: null | DT35: null | DU35: null | DV35: null | DW35: null | DX35: null | DY35: null | DZ35: null | EA35: null | EB35: null | EC35: null | ED35: null | EE35: null | EF35: null | EG35: null | EH35: null | EI35: null | EJ35: null | EK35: null | EL35: null | EM35: null | EN35: null | EO35: null | EP35: null | EQ35: null | ER35: null | ES35: null | ET35: null | EU35: null | EV35: null | EW35: null | EX35: null | EY35: null | EZ35: null | FA35: null | FB35: null | FC35: null | FD35: null | FE35: null | FF35: null
A36: 2029 | B36: null | C36: null | D36: null | E36: null | F36: null | G36: null | H36: null | I36: null | J36: null | K36: null | L36: null | M36: null | N36: null | O36: null | P36: null | Q36: null | R36: null | S36: null | T36: null | U36: null | V36: null | W36: null | X36: null | Y36: null | Z36: null | AA36: null | AB36: null | AC36: null | AD36: null | AE36: null | AF36: null | AG36: null | AH36: null | AI36: null | AJ36: null | AK36: null | AL36: null | AM36: null | AN36: null | AO36: null | AP36: null | AQ36: null | AR36: null | AS36: null | AT36: null | AU36: null | AV36: null | AW36: null | AX36: null | AY36: null | AZ36: null | BA36: null | BB36: null | BC36: null | BD36: null | BE36: null | BF36: null | BG36: null | BH36: null | BI36: null | BJ36: null | BK36: null | BL36: null | BM36: null | BN36: null | BO36: null | BP36: null | BQ36: null | BR36: null | BS36: null | BT36: null | BU36: null | BV36: null | BW36: null | BX36: null | BY36: null | BZ36: null | CA36: null | CB36: null | CC36: null | CD36: null | CE36: null | CF36: null | CG36: null | CH36: null | CI36: null | CJ36: null | CK36: null | CL36: null | CM36: null | CN36: null | CO36: null | CP36: null | CQ36: null | CR36: null | CS36: null | CT36: null | CU36: null | CV36: null | CW36: null | CX36: null | CY36: null | CZ36: null | DA36: null | DB36: null | DC36: null | DD36: null | DE36: null | DF36: null | DG36: null | DH36: null | DI36: null | DJ36: null | DL36: =($DL$37-$DL$32)/5 + DL35 -> 179373.54 | DM36: null | DN36: null | DO36: null | DP36: null | DQ36: null | DR36: null | DS36: null | DT36: null | DU36: null | DV36: null | DW36: null | DX36: null | DY36: null | DZ36: null | EA36: null | EB36: null | EC36: null | ED36: null | EE36: null | EF36: null | EG36: null | EH36: null | EI36: null | EJ36: null | EK36: null | EL36: null | EM36: null | EN36: null | EO36: null | EP36: null | EQ36: null | ER36: null | ES36: null | ET36: null | EU36: null | EV36: null | EW36: null | EX36: null | EY36: null | EZ36: null | FA36: null | FB36: null | FC36: null | FD36: null | FE36: null | FF36: null
A37: 2030 | B37: 612.0572795429508 | C37: 39.35822926307967 | D37: 632.5275450357583 | E37: 128.63309898559388 | F37: 541.7535115280357 | G37: 4533.030539822705 | H37: 14.486416900787217 | I37: 0.4992332184851702 | J37: 14.04169812624466 | K37: 1.5423702160320512 | L37: 14.597438879541524 | M37: 103.11941457531803 | N37: 5.376718466857913 | O37: 0.06436955193015655 | P37: 3.078883480550152 | Q37: 1.5015150224056018 | R37: 12.26675074704135 | S37: 61.40275422143577 | T37: 8.552934689820523 | U37: 0 | V37: 25.92554361668216 | W37: 4.808684191631418 | X37: 23.572676517283046 | Y37: 87.47665156539851 | Z37: 16.647566940156608 | AA37: 4.0858130579320715 | AB37: 8.639106896715102 | AC37: 0.5348185060354445 | AD37: 9.006699686245467 | AE37: 70.08072136754764 | AF37: 82.03853597980942 | AG37: 2.467743701241791 | AH37: 137.39563876143495 | AI37: 19.129440889623968 | AJ37: 74.1732412093436 | AK37: 974.8843867149659 | AL37: 1.200120208946997 | AM37: 0.5214934291069443 | AN37: 0.7939315533430604 | AO37: 0.5871469877575133 | AP37: 3.949414754947037 | AQ37: 14.9983336312815 | AR37: 13.109821683093399 | AS37: 1.162025554397543 | AT37: 2.7931079542221067 | AU37: 0.13148196698720196 | AV37: 11.43943035193279 | AW37: 60.99210687007419 | AX37: 31.14854608128507 | AY37: 7.118107869353285 | AZ37: 3.4730427587896338 | BA37: 6.504202526402733 | BB37: 24.16730578968324 | BC37: 115.50615689652538 | BD37: 137.27701396192288 | BE37: 2.8771766314681564 | BF37: 50.795850744714514 | BG37: 12.693517945129603 | BH37: 49.24167222887067 | BI37: 354.93288581728046 | BJ37: 86.37728165363822 | BK37: 4.087894574386029 | BL37: 147.36148560903374 | BM37: 13.790841088002558 | BN37: 57.49217229417017 | BO37: 762.8135788921962 | BP37: 4.175462785906367 | BQ37: 0.05604515600390708 | BR37: 1.4542609858509152 | BS37: 0.2564471233448451 | BT37: 4.499796268737066 | BU37: 31.35304043434744 | BV37: 72.57104747169919 | BW37: 6.725842970069075 | BX37: 71.11325346812279 | BY37: 40.310501769882876 | BZ37: 102.64178876957313 | CA37: 748.593353499853 | CB37: 4.9337612277595895 | CC37: 0.12723398652256201 | CD37: 1.6308060898731134 | CE37: 7.961690179817142 | CF37: 2.2804312699077243 | CG37: 1.0346274467577057 | CH37: 0.6432521640849355 | CI37: 2.5050252262411563 | CJ37: 16.070521289595508 | CK37: 2.195046049065719 | CL37: 0.09234196882080924 | CM37: 1.046205564169505 | CN37: 1.1928004804751278 | CO37: 3.4725331363629803 | CP37: 35.464643445918 | CQ37: 1.2802595575324722 | CR37: 0.5852508237565232 | CS37: 0.12813643788706805 | CT37: 1.437018418640716 | CU37: 7.565750589474944 | CV37: 5.801432436867725 | CW37: 14.142207512563939 | CX37: 1.6182830940968056 | CY37: 21.696944064297494 | CZ37: 74.08566571470169 | DA37: 3.9642232744277206 | DB37: 0.11098484723679392 | DC37: 0.7406759968890995 | DD37: 3.4439372777143 | DE37: 24.53394880162844 | DF37: 0.9851944460848427 | DG37: 23.859448054243945 | DH37: 3.333288838693241 | DI37: 5.386360102993557 | DJ37: 157.2913623200478 | DK37: =SUM(DE37+DJ37) -> 181.82531 | DL37: =DK37*1000 -> 181825.31 | DM37: 10.069070281150077 | DN37: 0.039781634166585485 | DO37: 23.43073213443622 | DP37: 2.561560374633954 | DQ37: 11.032209821993117 | DR37: 88.56557335274474 | DS37: 16.14484738824981 | DT37: 0.29714157912629335 | DU37: 42.99393909154883 | DV37: 5.328364674361831 | DW37: 42.75431026021984 | DX37: 257.52826742302534 | DY37: 22.721535826001407 | DZ37: 0.8513969870965309 | EA37: 7.220309267901248 | EB37: 2.288124004668186 | EC37: 8.514941183815472 | ED37: 94.34828723236666 | EE37: 10.177211267392872 | EF37: 0.049361921005382184 | EG37: 17.208733177396034 | EH37: 5.418980791992182 | EI37: 21.874806345334456 | EJ37: 138.48065381351782 | EK37: 0.42611295577265945 | EL37: 1.1570206426748122 | EM37: 0.4561269856418565 | EN37: 5.2394784903083 | EO37: 30.077457583021097 | EP37: 1.0266874853010437 | EQ37: 5.619213257700847 | ER37: 1.3691635445426873 | ES37: 7.234466879769467 | ET37: 36.18965371854679 | EU37: 12.937002541139233 | EV37: 0.18485139154687816 | EW37: 5.7564878239485395 | EX37: 1.2227964227743329 | EY37: 9.445541084834291 | EZ37: 69.01497418274215 | FA37: 20.60424235683042 | FB37: 7.192413620858224 | FC37: 21.607566282956302 | FD37: 1.0430341047464826 | FE37: 11.740006929093665 | FF37: 130.7887172132473

Sheet passive building (ireland)
A1: IE - Residential sector summary | B1: Column2 | C1: Household consumption expenditure (M€ at 2015 prices) | D1: Population (inhabitants) | E1: Column5 | F1: Number of households | G1: Total households useful surface area (in thousand sqm) | H1: Number of new and renovated households | I1: New and renovated households useful surface area (in thousand sqm) | J1: Column10 | K1: Actual heating degree-days | L1: Mean heating degree-days over period 2000 - 2020 | M1: Relative heating degree-days | N1: Column14 | O1: Indicators | P1: Column16 | Q1: Households size (inhabitants/household) | R1: Households useful surface area (in sqm/capita) | S1: Households useful surface area (in sqm/household) | T1: New and renovated households useful surface area (in sqm/capita) | U1: New and renovated households useful surface area (in sqm/household) | V1: Household consumption expenditure per capita (€ at 2015 prices) | W1: Household consumption expenditure per household (€ at 2015 prices) | X1: Consumption expenditure per household relative to the EU average | Y1: Column25 | Z1: Energy consumption | AA1: Column27 | AB1: Energy consumption by fuel - Eurostat structure (ktoe) | AC1: Solids | AD1: Liquids | AE1: Liquified petroleum gas (LPG) | AF1: Diesel oil and other liquids (without biofuels) | AG1: Natural gas | AH1: Renewable energies and wastes | AI1: Biomass and waste | AJ1: Biogas | AK1: Liquid biofuels | AL1: Solar | AM1: Geothermal | AN1: Ambient heat | AO1: Distributed heat | AP1: Electricity | AQ1: Column43 | AR1: Energy consumption by end-uses (ktoe) | AS1: Thermal uses | AT1: Space heating | AU1: Cooling | AV1: Water heating | AW1: Cooking | AX1: Specific electricity uses (appliances and lighting) | AY1: Column51 | AZ1: Shares of energy consumption in end-uses (in %) | BA1: Thermal uses_1 | BB1: Space heating_2 | BC1: Cooling_3 | BD1: Water heating_4 | BE1: Cooking_5 | BF1: Specific electricity uses (appliances and lighting)_6 | BG1: Column59 | BH1: Emissions | BI1: Column61 | BJ1: Emissions by fuel - Eurostat structure (kt of CO2) | BK1: Solids_7 | BL1: Liquids_8 | BM1: Liquified petroleum gas (LPG)_9 | BN1: Diesel oil and other liquids (without biofuels)_10 | BO1: Natural gas_11 | BP1: Renewable energies and wastes_12 | BQ1: Biomass and waste_13 | BR1: Biogas_14 | BS1: Liquid biofuels_15 | BT1: Solar_16 | BU1: Geothermal_17 | BV1: Ambient heat_18 | BW1: Distributed heat_19 | BX1: Electricity_20 | BY1: Column77 | BZ1: Emissions by end-uses (kt of CO2) | CA1: Thermal uses_21 | CB1: Space heating_22 | CC1: Cooling_23 | CD1: Water heating_24 | CE1: Cooking_25 | CF1: Specific electricity uses (appliances and lighting)_26 | CG1: Column85 | CH1: Share of emissions in end-uses (in %) | CI1: Thermal uses_27 | CJ1: Space heating_28 | CK1: Cooling_29 | CL1: Water heating_30 | CM1: Cooking_31 | CN1: Specific electricity uses (appliances and lighting)_32 | CO1: Column93 | CP1: Additional household indicators | CQ1: Column95 | CR1: Energy consumption per household (kWh / household) | CS1: Thermal uses_33 | CT1: Space heating_34 | CU1: Cooling_35 | CV1: Water heating_36 | CW1: Cooking_37 | CX1: Specific electricity uses (appliances and lighting)_38 | CY1: Column103 | CZ1: Thermal energy service per household (kWh useful / household) | DA1: Space heating_39 | DB1: Cooling_40 | DC1: Water heating_41 | DD1: Cooking_42 | DE1: Column109 | DF1: Emissions per household (kg CO2 / household) | DG1: Thermal uses_43 | DH1: Space heating_44 | DI1: Cooling_45 | DJ1: Water heating_46 | DK1: Cooking_47 | DL1: Specific electricity uses (appliances and lighting)_48 | DM1: Column117 | DN1: Ratio of energy service to energy consumption (system efficiency indicator) | DO1: Space heating_49 | DP1: Cooling_50 | DQ1: Water heating_51 | DR1: Cooking_52 | DS1: Column123 | DT1: Column124 | DU1: Column125 | DV1: Energy consumption per surface area (kWh / sqm) | DW1: Thermal uses_53 | DX1: Space heating_54 | DY1: Cooling_55 | DZ1: Water heating_56 | EA1: Cooking_57 | EB1: Specific electricity uses (appliances and lighting)_58 | EC1: Column133 | ED1: Thermal energy service per surface area (kWh useful / sqm) | EE1: Space heating_59 | EF1: Cooling_60 | EG1: Water heating_61 | EH1: Cooking_62 | EI1: Column139 | EJ1: Emissions per surface area (kg CO2 / sqm) | EK1: Thermal uses_63 | EL1: Space heating_64 | EM1: Cooling_65 | EN1: Water heating_66 | EO1: Cooking_67 | EP1: Specific electricity uses (appliances and lighting)_68 | EQ1: Column147 | ER1: Column148 | ES1: Column149 | ET1: Energy consumption per capita (kWh / capita) | EU1: Thermal uses_69 | EV1: Space heating_70 | EW1: Cooling_71 | EX1: Water heating_72 | EY1: Cooking_73 | EZ1: Specific electricity uses (appliances and lighting)_74 | FA1: Column157 | FB1: Thermal energy service per capita (kWh useful / capita) | FC1: Space heating_75 | FD1: Cooling_76 | FE1: Water heating_77 | FF1: Cooking_78 | FG1: Column163 | FH1: Emissions per capita (kg CO2 / capita) | FI1: Thermal uses_79 | FJ1: Space heating_80 | FK1: Cooling_81 | FL1: Water heating_82 | FM1: Cooking_83 | FN1: Specific electricity uses (appliances and lighting)_84
A2: 1997 | H2: =AVERAGE(H3:H5) -> 59650.741
A3: 1998 | H3: =AVERAGE(H4:H6) -> 58937.556
A4: 1999 | H4: =AVERAGE(H5:H7) -> 59682.667
A5: 2000 | C5: 62043.386 | D5: 3777565 | F5: 1295943 | G5: 135554.07 | H5: =AVERAGE(H6:H8) -> 60332 | I5: 0 | K5: 2792.71 | L5: 2750.8305 | M5: 1.0152243 | Q5: 2.914916 | R5: 35.883981 | S5: 104.59879 | V5: 16424.174 | W5: 47875.088 | X5: 1.4637034 | AB5: 2713.2236 | AC5: 553.39561 | AD5: 1156.5985 | AE5: 56.683405 | AF5: 1099.9151 | AG5: 437.7687 | AH5: 17.309372 | AI5: 17.18994 | AJ5: 0 | AK5: 0 | AL5: 0.1194325 | AM5: 0 | AN5: 0.18489102 | AO5: 0 | AP5: 548.15133 | AR5: 2713.2236 | AS5: 2430.2515 | AT5: 1988.6569 | AU5: 0.10314958 | AV5: 386.12248 | AW5: 55.368924 | AX5: 282.97208 | AZ5: 1 | BA5: 0.89570631 | BB5: 0.73294989 | BC5: 3.8017353e-05 | BD5: 0.14231134 | BE5: 0.020407063 | BF5: 0.10429369 | BJ5: 6935.7576 | BK5: 2342.2728 | BL5: 3565.256 | BM5: 149.75023 | BN5: 3415.5057 | BO5: 1028.2289 | BP5: 0 | BQ5: 0 | BR5: 0 | BS5: 0 | BT5: 0 | BU5: 0 | BV5: 0 | BW5: 0 | BX5: 0 | BZ5: 6935.7576 | CA5: 6935.7576 | CB5: 5996.4481 | CC5: 0 | CD5: 916.82699 | CE5: 22.482543 | CF5: 0 | CH5: 1 | CI5: 1 | CJ5: 0.86457002 | CK5: 0 | CL5: 0.13218844 | CM5: 0.0032415411 | CN5: 0 | CR5: 24348.903 | CS5: 21809.466 | CT5: 17846.526 | CU5: 0.92568084 | CV5: 3465.125 | CW5: 496.88959 | CX5: 2539.4368 | CZ5: 11506.586 | DA5: 9185.3331 | DB5: 2.0622472 | DC5: 1965.6724 | DD5: 353.51816 | DF5: 5351.9002 | DG5: 5351.9002 | DH5: 4627.0925 | DI5: 0 | DJ5: 707.45935 | DK5: 17.348404 | DL5: 0 | DN5: 0.52759595 | DO5: 0.51468467 | DP5: 2.2278167 | DQ5: 0.56727316 | DR5: 0.71146219 | DV5: 232.78379 | DW5: 208.50591 | DX5: 170.61885 | DY5: 0.0088498235 | DZ5: 33.127773 | EA5: 4.7504334 | EB5: 24.277879 | ED5: 110.00687 | EE5: 87.814907 | EF5: 0.019715784 | EG5: 18.792497 | EH5: 3.3797538 | EJ5: 51.165986 | EK5: 51.165986 | EL5: 44.236577 | EM5: 0 | EN5: 6.7635519 | EO5: 0.16585664 | EP5: 0 | ET5: 8353.209 | EU5: 7482.0221 | EV5: 6122.4836 | EW5: 0.3175669 | EX5: 1188.7564 | EY5: 170.46446 | EZ5: 871.18695 | FB5: 3947.4845 | FC5: 3151.1484 | FD5: 0.70748083 | FE5: 674.34959 | FF5: 121.27902 | FH5: 1836.0393 | FI5: 1836.0393 | FJ5: 1587.3845 | FK5: 0 | FL5: 242.70317 | FM5: 5.9515966 | FN5: 0
A6: 2001 | C6: 64981.08 | D6: 3832783 | F6: 1324568 | G6: 138915.4 | H6: 56798 | I6: 6308.1937 | K6: 2800.86 | L6: 2750.8305 | M6: 1.0181871 | Q6: 2.8936098 | R6: 36.244004 | S6: 104.87601 | T6: 38.382389 | U6: 111.06366 | V6: 16954.02 | W6: 49058.319 | X6: 1.4814533 | AB6: 2887.8505 | AC6: 525.25469 | AD6: 1286.7417 | AE6: 56.592175 | AF6: 1230.1495 | AG6: 480.80396 | AH6: 16.54626 | AI6: 16.426827 | AJ6: 0 | AK6: 0 | AL6: 0.1194325 | AM6: 0 | AN6: 0.29381505 | AO6: 0 | AP6: 578.50387 | AR6: 2887.8505 | AS6: 2592.0725 | AT6: 2152.6219 | AU6: 0.095353418 | AV6: 383.86621 | AW6: 55.489102 | AX6: 295.77796 | AZ6: 1 | BA6: 0.89757851 | BB6: 0.74540627 | BC6: 3.3018821e-05 | BD6: 0.13292454 | BE6: 0.019214673 | BF6: 0.10242149 | BJ6: 7339.7665 | BK6: 2226.3012 | BL6: 3984.1555 | BM6: 149.50922 | BN6: 3834.6462 | BO6: 1129.3098 | BP6: 0 | BQ6: 0 | BR6: 0 | BS6: 0 | BT6: 0 | BU6: 0 | BV6: 0 | BW6: 0 | BX6: 0 | BZ6: 7339.7665 | CA6: 7339.7665 | CB6: 6403.1674 | CC6: 0 | CD6: 913.27327 | CE6: 23.325821 | CF6: 0 | CH6: 1 | CI6: 1 | CJ6: 0.87239388 | CK6: 0 | CL6: 0.12442811 | CM6: 0.0031780058 | CN6: 0 | CR6: 25355.966 | CS6: 22758.97 | CT6: 18900.496 | CU6: 0.8372241 | CV6: 3370.4302 | CW6: 487.20659 | CX6: 2596.9959 | CZ6: 12047.171 | DA6: 9785.9486 | DB6: 1.9270258 | DC6: 1912.0485 | DD6: 347.24705 | DF6: 5541.2531 | DG6: 5541.2531 | DH6: 4834.1553 | DI6: 0 | DJ6: 689.48764 | DK6: 17.610134 | DL6: 0 | DN6: 0.52933728 | DO6: 0.51776147 | DP6: 2.3016845 | DQ6: 0.56730104 | DR6: 0.71273062 | DV6: 241.77089 | DW6: 217.00836 | DX6: 180.21754 | DY6: 0.0079829899 | DZ6: 32.137286 | EA6: 4.6455486 | EB6: 24.762536 | ED6: 114.87061 | EE6: 93.309699 | EF6: 0.018374324 | EG6: 18.231516 | EH6: 3.3110247 | EJ6: 52.836232 | EK6: 52.836232 | EL6: 46.094006 | EM6: 0 | EN6: 6.5743125 | EO6: 0.16791385 | EP6: 0 | ET6: 8762.7452 | EU6: 7865.2518 | EV6: 6531.8053 | EW6: 0.28933552 | EX6: 1164.7839 | EY6: 168.37328 | EZ6: 897.49346 | FB6: 4163.371 | FC6: 3381.9171 | FD6: 0.66595908 | FE6: 660.78312 | FF6: 120.00479 | FH6: 1914.9966 | FI6: 1914.9966 | FJ6: 1670.6313 | FK6: 0 | FL6: 238.27941 | FM6: 6.0858704 | FN6: 0
A7: 2002 | C7: 67343.483 | D7: 3899702 | F7: 1357691 | G7: 142853.84 | H7: 61918 | I7: 6950.3638 | K7: 2699.57 | L7: 2750.8305 | M7: 0.98136545 | Q7: 2.8723045 | R7: 36.63199 | S7: 105.21823 | T7: 39.080502 | U7: 112.2511 | V7: 17268.879 | W7: 49601.48 | X7: 1.4910632 | AB7: 2880.0264 | AC7: 517.00946 | AD7: 1306.3049 | AE7: 52.028375 | AF7: 1254.2765 | AG7: 474.57008 | AH7: 16.836199 | AI7: 16.282631 | AJ7: 0 | AK7: 0 | AL7: 0.16715391 | AM7: 0 | AN7: 0.38641445 | AO7: 0 | AP7: 565.69218 | AR7: 2880.0264 | AS7: 2572.4665 | AT7: 2128.0577 | AU7: 0.1099525 | AV7: 388.30331 | AW7: 55.995519 | AX7: 307.5599 | AZ7: 1 | BA7: 0.89320935 | BB7: 0.73890216 | BC7: 3.8177603e-05 | BD7: 0.1348263 | BE7: 0.01944271 | BF7: 0.10679065 | BJ7: 7329.454 | BK7: 2194.1865 | BL7: 4020.5999 | BM7: 137.45224 | BN7: 3883.1476 | BO7: 1114.6677 | BP7: 0 | BQ7: 0 | BR7: 0 | BS7: 0 | BT7: 0 | BU7: 0 | BV7: 0 | BW7: 0 | BX7: 0 | BZ7: 7329.454 | CA7: 7329.454 | CB7: 6371.2619 | CC7: 0 | CD7: 934.50334 | CE7: 23.688813 | CF7: 0 | CH7: 1 | CI7: 1 | CJ7: 0.86926828 | CK7: 0 | CL7: 0.12749972 | CM7: 0.0032320024 | CN7: 0 | CR7: 24670.346 | CS7: 22035.784 | CT7: 18228.972 | CU7: 0.94185468 | CV7: 3326.2115 | CW7: 479.6584 | CX7: 2634.5624 | CZ7: 11753.831 | DA7: 9515.6432 | DB7: 2.3291255 | DC7: 1892.9184 | DD7: 342.9403 | DF7: 5398.4699 | DG7: 5398.4699 | DH7: 4692.7187 | DI7: 0 | DJ7: 688.30341 | DK7: 17.447868 | DL7: 0 | DN7: 0.53339746 | DO7: 0.52200657 | DP7: 2.4729139 | DQ7: 0.5690914 | DR7: 0.71496778 | DV7: 234.46836 | DW7: 209.42933 | DX7: 173.24918 | DY7: 0.00895144 | DZ7: 31.612502 | EA7: 4.5587005 | EB7: 25.039029 | ED7: 111.70907 | EE7: 90.43721 | EF7: 0.02213614 | EG7: 17.990403 | EH7: 3.259324 | EJ7: 51.307363 | EK7: 51.307363 | EL7: 44.599863 | EM7: 0 | EN7: 6.5416744 | EO7: 0.16582552 | EP7: 0 | ET7: 8589.0427 | EU7: 7671.8132 | EV7: 6346.4622 | EW7: 0.32790906 | EX7: 1158.0289 | EY7: 166.99427 | EZ7: 917.22947 | FB7: 4092.1257 | FC7: 3312.895 | FD7: 0.81089087 | FE7: 659.02427 | FF7: 119.39552 | FH7: 1879.4908 | FI7: 1879.4908 | FJ7: 1633.7817 | FK7: 0 | FL7: 239.63455 | FM7: 6.0745188 | FN7: 0
A8: 2003 | C8: 69223.604 | D8: 3964191 | F8: 1390456 | G8: 146796.93 | H8: 62280 | I8: 7030.3159 | K8: 2630.34 | L8: 2750.8305 | M8: 0.95619851 | Q8: 2.8510007 | R8: 37.03074 | S8: 105.57467 | T8: 39.593958 | U8: 112.8824 | V8: 17462.227 | W8: 49784.822 | X8: 1.4883532 | AB8: 3029.9697 | AC8: 491.90507 | AD8: 1385.6877 | AE8: 49.567412 | AF8: 1336.1203 | AG8: 537.85469 | AH8: 16.641273 | AI8: 15.339123 | AJ8: 0 | AK8: 0 | AL8: 0.21496131 | AM8: 0 | AN8: 1.0871883 | AO8: 0 | AP8: 598.96819 | AR8: 3029.9697 | AS8: 2710.2505 | AT8: 2276.1227 | AU8: 0.11286632 | AV8: 376.53295 | AW8: 57.481976 | AX8: 319.7192 | AZ8: 1 | BA8: 0.89448106 | BB8: 0.75120313 | BC8: 3.7249982e-05 | BD8: 0.12426954 | BE8: 0.018971139 | BF8: 0.10551894 | BJ8: 7616.236 | BK8: 2083.9509 | BL8: 4268.9748 | BM8: 130.9507 | BN8: 4138.0241 | BO8: 1263.3103 | BP8: 0 | BQ8: 0 | BR8: 0 | BS8: 0 | BT8: 0 | BU8: 0 | BV8: 0 | BW8: 0 | BX8: 0 | BZ8: 7616.236 | CA8: 7616.236 | CB8: 6688.4664 | CC8: 0 | CD8: 901.60242 | CE8: 26.167247 | CF8: 0 | CH8: 1 | CI8: 1 | CJ8: 0.87818528 | CK8: 0 | CL8: 0.118379 | CM8: 0.0034357191 | CN8: 0 | CR8: 25343.159 | CS8: 22668.976 | CT8: 19037.861 | CU8: 0.94403222 | CV8: 3149.3828 | CW8: 480.78859 | CX8: 2674.1834 | CZ8: 12205.574 | DA8: 10061.082 | DB8: 2.4950811 | DC8: 1798.0737 | DD8: 343.92377 | DF8: 5477.5096 | DG8: 5477.5096 | DH8: 4810.2683 | DI8: 0 | DJ8: 648.42212 | DK8: 18.819184 | DL8: 0 | DN8: 0.53842637 | DO8: 0.52847755 | DP8: 2.6430042 | DQ8: 0.57092891 | DR8: 0.71533264 | DV8: 240.04963 | DW8: 214.71985 | DX8: 180.32603 | DY8: 0.0089418443 | DZ8: 29.830858 | EA8: 4.5540148 | EB8: 25.329783 | ED8: 115.61083 | EE8: 95.29826 | EF8: 0.023633332 | EG8: 17.031299 | EH8: 3.2576355 | EJ8: 51.882803 | EK8: 51.882803 | EL8: 45.562714 | EM8: 0 | EN8: 6.1418345 | EO8: 0.17825474 | EP8: 0 | ET8: 8889.2155 | EU8: 7951.2349 | EV8: 6677.6065 | EW8: 0.33112311 | EX8: 1104.6587 | EY8: 168.63854 | EZ8: 937.98062 | FB8: 4281.1545 | FC8: 3528.9651 | FD8: 0.87515977 | FE8: 630.6816 | FF8: 120.63265 | FH8: 1921.2586 | FI8: 1921.2586 | FJ8: 1687.221 | FK8: 0 | FL8: 227.43668 | FM8: 6.6009048 | FN8: 0
A9: 2004 | C9: 71866.35 | D9: 4028851 | F9: 1413632 | G9: 149678.13 | H9: 53403 | I9: 6042.911 | K9: 2700.72 | L9: 2750.8305 | M9: 0.98178351 | Q9: 2.8499999 | R9: 37.151568 | S9: 105.88196 | T9: 39.704132 | U9: 113.15677 | V9: 17837.927 | W9: 50838.089 | X9: 1.5013369 | AB9: 3139.274 | AC9: 483.98951 | AD9: 1408.419 | AE9: 48.642734 | AF9: 1359.7763 | AG9: 599.91402 | AH9: 17.316509 | AI9: 15.022614 | AJ9: 0 | AK9: 0 | AL9: 0.28658641 | AM9: 0 | AN9: 2.0073087 | AO9: 0 | AP9: 631.6423 | AR9: 3139.274 | AS9: 2813.0461 | AT9: 2367.0408 | AU9: 0.11891423 | AV9: 387.54547 | AW9: 58.340928 | AX9: 326.22797 | AZ9: 1 | BA9: 0.89608172 | BB9: 0.75400896 | BC9: 3.7879532e-05 | BD9: 0.12345067 | BE9: 0.01858421 | BF9: 0.10391828 | BJ9: 7772.473 | BK9: 2051.2287 | BL9: 4312.1694 | BM9: 128.50782 | BN9: 4183.6616 | BO9: 1409.0749 | BP9: 0 | BQ9: 0 | BR9: 0 | BS9: 0 | BT9: 0 | BU9: 0 | BV9: 0 | BW9: 0 | BX9: 0 | BZ9: 7772.473 | CA9: 7772.473 | CB9: 6828.491 | CC9: 0 | CD9: 915.55784 | CE9: 28.424172 | CF9: 0 | CH9: 1 | CI9: 1 | CJ9: 0.87854805 | CK9: 0 | CL9: 0.11779492 | CM9: 0.0036570307 | CN9: 0 | CR9: 25826.917 | CS9: 23143.029 | CT9: 19473.727 | CU9: 0.97831154 | CV9: 3188.3502 | CW9: 479.97286 | CX9: 2683.8889 | CZ9: 12630.481 | DA9: 10451.877 | DB9: 2.7935701 | DC9: 1832.2428 | DD9: 343.56761 | DF9: 5498.2294 | DG9: 5498.2294 | DH9: 4830.4587 | DI9: 0 | DJ9: 647.66349 | DK9: 20.107194 | DL9: 0 | DN9: 0.5457575 | DO9: 0.53671684 | DP9: 2.8555016 | DQ9: 0.574668 | DR9: 0.71580633 | DV9: 243.92179 | DW9: 218.57385 | DX9: 183.91921 | DY9: 0.0092396431 | DZ9: 30.112307 | EA9: 4.5330937 | EB9: 25.347933 | ED9: 119.28832 | EE9: 98.712539 | EF9: 0.026383815 | EG9: 17.304579 | EH9: 3.2448172 | EJ9: 51.927914 | EK9: 51.927914 | EL9: 45.621167 | EM9: 0 | EN9: 6.1168444 | EO9: 0.18990197 | EP9: 0 | ET9: 9062.0768 | EU9: 8120.3613 | EV9: 6832.8871 | EW9: 0.34326723 | EX9: 1118.7194 | EY9: 168.41154 | EZ9: 941.71545 | FB9: 4431.7481 | FC9: 3667.3256 | FD9: 0.9802001 | FE9: 642.89225 | FF9: 120.55004 | FH9: 1929.2034 | FI9: 1929.2034 | FJ9: 1694.8979 | FK9: 0 | FL9: 227.25036 | FM9: 7.055156 | FN9: 0
A10: 2005 | C10: 76913.133 | D10: 4111672 | F10: 1460111 | G10: 155230.22 | H10: 77210 | I10: 8766.5188 | K10: 2608.3 | L10: 2750.8305 | M10: 0.94818638 | Q10: 2.8159996 | R10: 37.753552 | S10: 106.31399 | T10: 40.320047 | U10: 113.54124 | V10: 18706.048 | W10: 52676.223 | X10: 1.5317035 | AB10: 3298.051 | AC10: 506.53955 | AD10: 1523.6498 | AE10: 53.015047 | AF10: 1470.6347 | AG10: 605.5675 | AH10: 19.765176 | AI10: 15.952021 | AJ10: 0 | AK10: 0 | AL10: 0.46096303 | AM10: 0 | AN10: 3.3521926 | AO10: 0 | AP10: 645.88117 | AR10: 3298.051 | AS10: 2961.0169 | AT10: 2524.0713 | AU10: 0.12556663 | AV10: 379.00321 | AW10: 57.816833 | AX10: 337.03405 | AZ10: 1 | BA10: 0.89780811 | BB10: 0.76532211 | BC10: 3.807298e-05 | BD10: 0.11491733 | BE10: 0.017530606 | BF10: 0.10219189 | BJ10: 8248.0277 | BK10: 2145.0442 | BL10: 4680.6297 | BM10: 140.05891 | BN10: 4540.5707 | BO10: 1422.3538 | BP10: 0 | BQ10: 0 | BR10: 0 | BS10: 0 | BT10: 0 | BU10: 0 | BV10: 0 | BW10: 0 | BX10: 0 | BZ10: 8248.0277 | CA10: 8248.0277 | CB10: 7319.1161 | CC10: 0 | CD10: 901.5151 | CE10: 27.396439 | CF10: 0 | CH10: 1 | CI10: 1 | CJ10: 0.88737774 | CK10: 0 | CL10: 0.10930069 | CM10: 0.0033215746 | CN10: 0 | CR10: 26269.464 | CS10: 23584.938 | CT10: 20104.601 | CU10: 1.0001568 | CV10: 3018.8166 | CW10: 460.51962 | CX10: 2684.526 | CZ10: 13008.894 | DA10: 10928.82 | DB10: 3.1052139 | DC10: 1745.482 | DD10: 331.48753 | DF10: 5648.9045 | DG10: 5648.9045 | DH10: 5012.7121 | DI10: 0 | DJ10: 617.42916 | DK10: 18.763258 | DL10: 0 | DN10: 0.55157638 | DO10: 0.54359793 | DP10: 3.1047272 | DQ10: 0.57820075 | DR10: 0.71981194 | DV10: 247.0932 | DW10: 221.84228 | DX10: 189.10589 | DY10: 0.0094075746 | DZ10: 28.395291 | EA10: 4.3316936 | EB10: 25.25092 | ED10: 122.36296 | EE10: 102.79757 | EF10: 0.029207952 | EG10: 16.418178 | EH10: 3.1180048 | EJ10: 53.134161 | EK10: 53.134161 | EL10: 47.150071 | EM10: 0 | EN10: 5.8076004 | EO10: 0.17648908 | EP10: 0 | ET10: 9328.6461 | EU10: 8375.3342 | EV10: 7139.4191 | EW10: 0.35516936 | EX10: 1072.0231 | EY10: 163.53682 | EZ10: 953.31193 | FB10: 4619.6365 | FC10: 3880.9735 | FD10: 1.102704 | FE10: 619.84455 | FF10: 117.71576 | FH10: 2006.0033 | FI10: 2006.0033 | FJ10: 1780.0827 | FK10: 0 | FL10: 219.25754 | FM10: 6.6630897 | FN10: 0
A11: 2006 | C11: 81826.187 | D11: 4208156 | F11: 1491196 | G11: 159069.57 | H11: 62827 | I11: 7159.5202 | K11: 2601.42 | L11: 2750.8305 | M11: 0.94568532 | Q11: 2.8220006 | R11: 37.800302 | S11: 106.67248 | T11: 40.381318 | U11: 113.9561 | V11: 19444.666 | W11: 54872.858 | X11: 1.5732418 | AB11: 3314.5982 | AC11: 489.14884 | AD11: 1482.2585 | AE11: 49.886156 | AF11: 1432.3723 | AG11: 630.80396 | AH11: 22.31049 | AI11: 16.779966 | AJ11: 0 | AK11: 0 | AL11: 0.61762683 | AM11: 0 | AN11: 4.9128977 | AO11: 0 | AP11: 694.98934 | AR11: 3314.5982 | AS11: 2967.1817 | AT11: 2534.47 | AU11: 0.15468001 | AV11: 374.85193 | AW11: 57.705088 | AX11: 347.41654 | AZ11: 1 | BA11: 0.89518593 | BB11: 0.76463867 | BC11: 4.6666294e-05 | BD11: 0.11309121 | BE11: 0.017409376 | BF11: 0.10481407 | BJ11: 8096.4005 | BK11: 2078.2102 | BL11: 4536.5613 | BM11: 131.79278 | BN11: 4404.7685 | BO11: 1481.6291 | BP11: 0 | BQ11: 0 | BR11: 0 | BS11: 0 | BT11: 0 | BU11: 0 | BV11: 0 | BW11: 0 | BX11: 0 | BZ11: 8096.4005 | CA11: 8096.4005 | CB11: 7194.1372 | CC11: 0 | CD11: 873.94184 | CE11: 28.321489 | CF11: 0 | CH11: 1 | CI11: 1 | CJ11: 0.88855994 | CK11: 0 | CL11: 0.10794202 | CM11: 0.0034980346 | CN11: 0 | CR11: 25850.912 | CS11: 23141.373 | CT11: 19766.607 | CU11: 1.2063663 | CV11: 2923.511 | CW11: 450.04826 | CX11: 2709.5394 | CZ11: 12996.204 | DA11: 10960.526 | DB11: 4.0272551 | DC11: 1706.7725 | DD11: 324.87799 | DF11: 5429.4677 | DG11: 5429.4677 | DH11: 4824.4075 | DI11: 0 | DJ11: 586.06772 | DK11: 18.992466 | DL11: 0 | DN11: 0.56160038 | DO11: 0.55449709 | DP11: 3.3383353 | DQ11: 0.58380917 | DR11: 0.72187367 | DV11: 242.33911 | DW11: 216.93856 | DX11: 185.30185 | DY11: 0.011309068 | DZ11: 27.406423 | EA11: 4.2189727 | EB11: 25.400549 | ED11: 121.83278 | EE11: 102.74934 | EF11: 0.037753461 | EG11: 16.000121 | EH11: 3.0455653 | EJ11: 50.898488 | EK11: 50.898488 | EL11: 45.226358 | EM11: 0 | EN11: 5.4940857 | EO11: 0.17804467 | EP11: 0 | ET11: 9160.4914 | EU11: 8200.343 | EV11: 7004.466 | EW11: 0.42748618 | EX11: 1035.9711 | EY11: 159.47844 | EZ11: 960.14842 | FB11: 4605.3158 | FC11: 3883.956 | FD11: 1.4270922 | FE11: 604.80942 | FF11: 115.12329 | FH11: 1923.9782 | FI11: 1923.9782 | FJ11: 1709.57 | FK11: 0 | FL11: 207.6781 | FM11: 6.7301423 | FN11: 0
A12: 2007 | C12: 87287.456 | D12: 4340118 | F12: 1546177 | G12: 165669.57 | H12: 87398 | I12: 9990.7828 | K12: 2523.35 | L12: 2750.8305 | M12: 0.9173048 | Q12: 2.8069995 | R12: 38.171675 | S12: 107.14787 | T12: 40.724494 | U12: 114.31363 | V12: 20111.77 | W12: 56453.728 | X12: 1.5969264 | AB12: 3267.9921 | AC12: 468.11204 | AD12: 1490.2752 | AE12: 46.918315 | AF12: 1443.3569 | AG12: 591.72399 | AH12: 31.397592 | AI12: 23.205159 | AJ12: 0 | AK12: 0 | AL12: 1.3876182 | AM12: 0 | AN12: 6.8048151 | AO12: 0 | AP12: 693.28805 | AR12: 3267.9921 | AS12: 2906.4442 | AT12: 2457.1362 | AU12: 0.17988575 | AV12: 389.23158 | AW12: 59.89648 | AX12: 361.54793 | AZ12: 1 | BA12: 0.88936695 | BB12: 0.75187949 | BC12: 5.5044732e-05 | BD12: 0.1191042 | BE12: 0.018328221 | BF12: 0.11063305 | BJ12: 7948.9546 | BK12: 1990.1793 | BL12: 4568.9371 | BM12: 123.95213 | BN12: 4444.9849 | BO12: 1389.8382 | BP12: 0 | BQ12: 0 | BR12: 0 | BS12: 0 | BT12: 0 | BU12: 0 | BV12: 0 | BW12: 0 | BX12: 0 | BZ12: 7948.9546 | CA12: 7948.9546 | CB12: 7006.953 | CC12: 0 | CD12: 913.60991 | CE12: 28.39162 | CF12: 0 | CH12: 1 | CI12: 1 | CJ12: 0.88149366 | CK12: 0 | CL12: 0.1149346 | CM12: 0.0035717426 | CN12: 0 | CR12: 24581.111 | CS12: 21861.627 | CT12: 18482.033 | CU12: 1.3530606 | CV12: 2927.7135 | CW12: 450.52802 | CX12: 2719.4832 | CZ12: 12441 | DA12: 10389.715 | DB12: 4.7091151 | DC12: 1719.9529 | DD12: 326.6227 | DF12: 5141.0379 | DG12: 5141.0379 | DH12: 4531.7923 | DI12: 0 | DJ12: 590.88313 | DK12: 18.362464 | DL12: 0 | DN12: 0.56907932 | DO12: 0.56215219 | DP12: 3.4803429 | DQ12: 0.58747309 | DR12: 0.72497755 | DV12: 229.41297 | DW12: 204.03231 | DX12: 172.4909 | DY12: 0.012627975 | DZ12: 27.324048 | EA12: 4.2047314 | EB12: 25.380656 | ED12: 116.11057 | EE12: 96.966139 | EF12: 0.043949684 | EG12: 16.052143 | EH12: 3.0483359 | EJ12: 47.980775 | EK12: 47.980775 | EL12: 42.294749 | EM12: 0 | EN12: 5.5146512 | EO12: 0.17137498 | EP12: 0 | ET12: 8757.0771 | EU12: 7788.255 | EV12: 6584.2666 | EW12: 0.48203096 | EX12: 1043.0047 | EY12: 160.50164 | EZ12: 968.82214 | FB12: 4432.1348 | FC12: 3701.3599 | FD12: 1.677633 | FE12: 612.73718 | FF12: 116.36009 | FH12: 1831.5066 | FI12: 1831.5066 | FJ12: 1614.4614 | FK12: 0 | FL12: 210.50347 | FM12: 6.54167 | FN12: 0
A13: 2008 | C13: 87454.275 | D13: 4457765 | F13: 1610464 | G13: 173460.23 | H13: 97900 | I13: 11306.536 | K13: 2803.54 | L13: 2750.8305 | M13: 1.0191613 | Q13: 2.7680004 | R13: 38.911928 | S13: 107.70823 | T13: 41.723498 | U13: 115.49066 | V13: 19618.413 | W13: 54303.775 | X13: 1.5454617 | AB13: 3570.4466 | AC13: 494.9423 | AD13: 1651.3726 | AE13: 40.339639 | AF13: 1611.0329 | AG13: 667.47635 | AH13: 32.333104 | AI13: 20.430696 | AJ13: 0 | AK13: 0 | AL13: 3.1503869 | AM13: 0 | AN13: 8.7520206 | AO13: 0 | AP13: 733.07429 | AR13: 3570.4466 | AS13: 3193.9887 | AT13: 2713.0641 | AU13: 0.20130175 | AV13: 420.26515 | AW13: 60.458098 | AX13: 376.45795 | AZ13: 1 | BA13: 0.89456278 | BB13: 0.75986687 | BC13: 5.6379993e-05 | BD13: 0.11770661 | BE13: 0.016932923 | BF13: 0.10543722 | BJ13: 8721.3121 | BK13: 2099.5055 | BL13: 5054.0417 | BM13: 106.57211 | BN13: 4947.4695 | BO13: 1567.765 | BP13: 0 | BQ13: 0 | BR13: 0 | BS13: 0 | BT13: 0 | BU13: 0 | BV13: 0 | BW13: 0 | BX13: 0 | BZ13: 8721.3121 | CA13: 8721.3121 | CB13: 7703.1638 | CC13: 0 | CD13: 988.71081 | CE13: 29.437576 | CF13: 0 | CH13: 1 | CI13: 1 | CJ13: 0.88325743 | CK13: 0 | CL13: 0.11336721 | CM13: 0.003375361 | CN13: 0 | CR13: 25784.056 | CS13: 23065.457 | CT13: 19592.45 | CU13: 1.4537049 | CV13: 3034.9537 | CW13: 436.59944 | CX13: 2718.5991 | CZ13: 13321.434 | DA13: 11201.599 | DB13: 5.1757108 | DC13: 1797.9896 | DD13: 316.66949 | DF13: 5415.4033 | DG13: 5415.4033 | DH13: 4783.1952 | DI13: 0 | DJ13: 613.92916 | DK13: 18.278941 | DL13: 0 | DN13: 0.57754911 | DO13: 0.57173039 | DP13: 3.5603587 | DQ13: 0.59242736 | DR13: 0.72530896 | DV13: 239.38798 | DW13: 214.14758 | DX13: 181.903 | DY13: 0.013496693 | DZ13: 28.177547 | EA13: 4.0535383 | EB13: 25.240402 | ED13: 123.68074 | EE13: 103.99947 | EF13: 0.048053067 | EG13: 16.693149 | EH13: 2.9400677 | EJ13: 50.278454 | EK13: 50.278454 | EL13: 44.408818 | EM13: 0 | EN13: 5.6999279 | EO13: 0.16970793 | EP13: 0 | ET13: 9315.0478 | EU13: 8332.8951 | EV13: 7078.1963 | EW13: 0.52518232 | EX13: 1096.4427 | EY13: 157.73099 | EZ13: 982.15271 | FB13: 4812.6561 | FC13: 4046.8199 | FD13: 1.8698375 | FE13: 649.56263 | FF13: 114.4037 | FH13: 1956.4316 | FI13: 1956.4316 | FJ13: 1728.0327 | FK13: 0 | FL13: 221.79518 | FM13: 6.6036627 | FN13: 0
A14: 2009 | C14: 82798.401 | D14: 4521322 | F14: 1669617 | G14: 180742.36 | H14: 94163 | I14: 10944.139 | K14: 2817.65 | L14: 2750.8305 | M14: 1.0242907 | Q14: 2.7079995 | R14: 39.975557 | S14: 108.25379 | T14: 42.91931 | U14: 116.22547 | V14: 18312.874 | W14: 49591.254 | X14: 1.4381972 | AB14: 3469.0868 | AC14: 515.63087 | AD14: 1599.5505 | AE14: 29.525967 | AF14: 1570.0245 | AG14: 623.44127 | AH14: 41.40172 | AI14: 26.70258 | AJ14: 0 | AK14: 0 | AL14: 5.294497 | AM14: 0 | AN14: 9.4046432 | AO14: 0 | AP14: 698.46715 | AR14: 3469.0868 | AS14: 3082.0123 | AT14: 2575.1846 | AU14: 0.21430811 | AV14: 444.83094 | AW14: 61.782434 | AX14: 387.07454 | AZ14: 1 | BA14: 0.88842178 | BB14: 0.74232348 | BC14: 6.1776518e-05 | BD14: 0.1282271 | BE14: 0.017809423 | BF14: 0.11157822 | BJ14: 8531.714 | BK14: 2178.3169 | BL14: 4889.0614 | BM14: 78.003791 | BN14: 4811.0576 | BO14: 1464.3356 | BP14: 0 | BQ14: 0 | BR14: 0 | BS14: 0 | BT14: 0 | BU14: 0 | BV14: 0 | BW14: 0 | BX14: 0 | BZ14: 8531.714 | CA14: 8531.714 | CB14: 7440.1912 | CC14: 0 | CD14: 1062.2964 | CE14: 29.226332 | CF14: 0 | CH14: 1 | CI14: 1 | CJ14: 0.8720629 | CK14: 0 | CL14: 0.12451149 | CM14: 0.0034256108 | CN14: 0 | CR14: 24164.512 | CS14: 21468.279 | CT14: 17937.885 | CU14: 1.4927994 | CV14: 3098.5453 | CW14: 430.35601 | CX14: 2696.2333 | CZ14: 12588.095 | DA14: 10414.69 | DB14: 5.4579842 | DC14: 1854.6435 | DD14: 313.30284 | DF14: 5109.9827 | DG14: 5109.9827 | DH14: 4456.2263 | DI14: 0 | DJ14: 636.25155 | DK14: 17.504812 | DL14: 0 | DN14: 0.58635789 | DO14: 0.58059746 | DP14: 3.6562074 | DQ14: 0.59855297 | DR14: 0.7280085 | DV14: 223.22094 | DW14: 198.31434 | DX14: 165.70214 | DY14: 0.013789812 | DZ14: 28.622973 | EA14: 3.9754361 | EB14: 24.906595 | ED14: 116.28318 | EE14: 96.206244 | EF14: 0.050418413 | EG14: 17.132366 | EH14: 2.8941513 | EJ14: 47.203731 | EK14: 47.203731 | EL14: 41.164623 | EM14: 0 | EN14: 5.8774068 | EO14: 0.16170161 | EP14: 0 | ET14: 8923.3813 | EU14: 7927.7263 | EV14: 6624.0354 | EW14: 0.55125542 | EX14: 1144.2193 | EY14: 158.92027 | EZ14: 995.655 | FB14: 4648.4848 | FC14: 3845.8982 | FD14: 2.0155041 | FE14: 684.87585 | FF14: 115.69531 | FH14: 1886.9954 | FI14: 1886.9954 | FJ14: 1645.5787 | FK14: 0 | FL14: 234.95261 | FM14: 6.464112 | FN14: 0
A15: 2010 | C15: 83048.537 | D15: 4549428 | F15: 1700721 | G15: 184829.35 | H15: 67400 | I15: 7883.5013 | K15: 3166.33 | L15: 2750.8305 | M15: 1.1510451 | Q15: 2.6749996 | R15: 40.626942 | S15: 108.67705 | T15: 43.725575 | U15: 116.96589 | V15: 18254.721 | W15: 48831.37 | X15: 1.4125425 | AB15: 3625.3339 | AC15: 482.21264 | AD15: 1665.9248 | AE15: 37.345916 | AF15: 1628.5788 | AG15: 708.29106 | AH15: 44.404127 | AI15: 26.737833 | AJ15: 0 | AK15: 0 | AL15: 7.3465176 | AM15: 0 | AN15: 10.319776 | AO15: 0 | AP15: 734.82107 | AR15: 3625.3339 | AS15: 3234.9056 | AT15: 2724.442 | AU15: 0.23828329 | AV15: 447.81281 | AW15: 62.41248 | AX15: 390.42831 | AZ15: 1 | BA15: 0.89230556 | BB15: 0.75150099 | BC15: 6.5727269e-05 | BD15: 0.12352319 | BE15: 0.01721565 | BF15: 0.10769444 | BJ15: 8788.5297 | BK15: 2036.7101 | BL15: 5088.1893 | BM15: 98.663084 | BN15: 4989.5262 | BO15: 1663.6304 | BP15: 0 | BQ15: 0 | BR15: 0 | BS15: 0 | BT15: 0 | BU15: 0 | BV15: 0 | BW15: 0 | BX15: 0 | BZ15: 8788.5297 | CA15: 8788.5297 | CB15: 7699.7532 | CC15: 0 | CD15: 1056.855 | CE15: 31.921544 | CF15: 0 | CH15: 1 | CI15: 1 | CJ15: 0.87611392 | CK15: 0 | CL15: 0.1202539 | CM15: 0.0036321825 | CN15: 0 | CR15: 24791.035 | CS15: 22121.178 | CT15: 18630.487 | CU15: 1.629447 | CV15: 3062.2677 | CW15: 426.79378 | CX15: 2669.8566 | CZ15: 13180.954 | DA15: 11012.456 | DB15: 6.1281568 | DC15: 1852.1162 | DD15: 310.25356 | DF15: 5167.5317 | DG15: 5167.5317 | DH15: 4527.3465 | DI15: 0 | DJ15: 621.41583 | DK15: 18.769418 | DL15: 0 | DN15: 0.59585226 | DO15: 0.59109866 | DP15: 3.7608814 | DQ15: 0.60481852 | DR15: 0.72694022 | DV15: 228.11655 | DW15: 203.54966 | DX15: 171.42981 | DY15: 0.014993478 | DZ15: 28.177684 | EA15: 3.9271747 | EB15: 24.566884 | ED15: 121.28553 | EE15: 101.33193 | EF15: 0.056388691 | EG15: 17.042385 | EH15: 2.8548212 | EJ15: 47.549428 | EK15: 47.549428 | EL15: 41.658716 | EM15: 0 | EN15: 5.718004 | EO15: 0.1727082 | EP15: 0 | ET15: 9267.6778 | EU15: 8269.6004 | EV15: 6964.6691 | EW15: 0.60913915 | EX15: 1144.7731 | EY15: 159.5491 | EZ15: 998.07738 | FB15: 4927.4601 | FC15: 4116.8066 | FD15: 2.2909001 | FE15: 692.37999 | FF15: 115.98266 | FH15: 1931.7879 | FI15: 1931.7879 | FJ15: 1692.4662 | FK15: 0 | FL15: 232.30502 | FM15: 7.016606 | FN15: 0
A16: 2011 | C16: 81928.77 | D16: 4570881 | F16: 1696689 | G16: 184925.25 | H16: 36972 | I16: 4384.8673 | K16: 2766.1 | L16: 2750.8305 | M16: 1.0055509 | Q16: 2.6940005 | R16: 40.457244 | S16: 108.99183 | T16: 44.023629 | U16: 118.59968 | V16: 17924.065 | W16: 48287.441 | X16: 1.3950075 | AB16: 3181.9176 | AC16: 439.71522 | AD16: 1431.0659 | AE16: 34.27558 | AF16: 1396.7903 | AG16: 568.12124 | AH16: 41.805589 | AI16: 22.286758 | AJ16: 0 | AK16: 0 | AL16: 8.4990542 | AM16: 0 | AN16: 11.019776 | AO16: 0 | AP16: 712.22949 | AR16: 3181.9176 | AS16: 2796.7118 | AT16: 2280.7282 | AU16: 0.23510725 | AV16: 452.88329 | AW16: 62.865211 | AX16: 385.20578 | AZ16: 1 | BA16: 0.87893911 | BB16: 0.7167779 | BC16: 7.3888542e-05 | BD16: 0.1423303 | BE16: 0.01975702 | BF16: 0.12106089 | BJ16: 7570.11 | BK16: 1861.9967 | BL16: 4373.713 | BM16: 90.551655 | BN16: 4283.1614 | BO16: 1334.4002 | BP16: 0 | BQ16: 0 | BR16: 0 | BS16: 0 | BT16: 0 | BU16: 0 | BV16: 0 | BW16: 0 | BX16: 0 | BZ16: 7570.11 | CA16: 7570.11 | CB16: 6470.3168 | CC16: 0 | CD16: 1067.5197 | CE16: 32.27349 | CF16: 0 | CH16: 1 | CI16: 1 | CJ16: 0.854719 | CK16: 0 | CL16: 0.14101772 | CM16: 0.0042632788 | CN16: 0 | CR16: 21810.539 | CS16: 19170.136 | CT16: 15633.313 | CU16: 1.6115489 | CV16: 3104.3006 | CW16: 430.91127 | CX16: 2640.4033 | CZ16: 11642.952 | DA16: 9426.951 | DB16: 6.2265884 | DC16: 1895.8313 | DD16: 313.94326 | DF16: 4461.6957 | DG16: 4461.6957 | DH16: 3813.4961 | DI16: 0 | DJ16: 629.17817 | DK16: 19.021453 | DL16: 0 | DN16: 0.60734844 | DO16: 0.60300407 | DP16: 3.863729 | DQ16: 0.61071126 | DR16: 0.72855663 | DV16: 200.11168 | DW16: 175.88598 | DX16: 143.43563 | DY16: 0.01478596 | DZ16: 28.481956 | EA16: 3.9536106 | EB16: 24.225698 | ED16: 106.82408 | EE16: 86.492268 | EF16: 0.057128944 | EG16: 17.394251 | EH16: 2.8804292 | EJ16: 40.936055 | EK16: 40.936055 | EL16: 34.988823 | EM16: 0 | EN16: 5.7727092 | EO16: 0.17452181 | EP16: 0 | ET16: 8095.9671 | EU16: 7115.8621 | EV16: 5803.0103 | EW16: 0.5981992 | EX16: 1152.3014 | EY16: 159.95219 | EZ16: 980.10498 | FB16: 4321.8077 | FC16: 3499.2388 | FD16: 2.3112796 | FE16: 703.72345 | FF16: 116.53423 | FH16: 1656.1599 | FI16: 1656.1599 | FJ16: 1415.5514 | FK16: 0 | FL16: 233.5479 | FM16: 7.0606716 | FN16: 0
A17: 2012 | C17: 81380.297 | D17: 4589287 | F17: 1711782 | G17: 187257.33 | H17: 51978 | I17: 6190.2063 | K17: 2861.13 | L17: 2750.8305 | M17: 1.0400968 | Q17: 2.6809997 | R17: 40.803141 | S17: 109.39321 | T17: 44.421047 | U17: 119.09281 | V17: 17732.667 | W17: 47541.274 | X17: 1.3957646 | AB17: 3025.8752 | AC17: 439.25684 | AD17: 1252.3267 | AE17: 33.056922 | AF17: 1219.2697 | AG17: 599.27773 | AH17: 48.692863 | AI17: 27.575494 | AJ17: 0 | AK17: 0 | AL17: 9.2040413 | AM17: 0 | AN17: 11.913328 | AO17: 0 | AP17: 698.23448 | AR17: 3025.8752 | AS17: 2641.9936 | AT17: 2109.2352 | AU17: 0.26339318 | AV17: 468.86598 | AW17: 63.629072 | AX17: 383.88159 | AZ17: 1 | BA17: 0.8731337 | BB17: 0.69706615 | BC17: 8.7046941e-05 | BD17: 0.15495219 | BE17: 0.02102832 | BF17: 0.1268663 | BJ17: 7088.3565 | BK17: 1849.3876 | BL17: 3831.3885 | BM17: 87.332116 | BN17: 3744.0564 | BO17: 1407.5804 | BP17: 0 | BQ17: 0 | BR17: 0 | BS17: 0 | BT17: 0 | BU17: 0 | BV17: 0 | BW17: 0 | BX17: 0 | BZ17: 7088.3565 | CA17: 7088.3565 | CB17: 5956.2447 | CC17: 0 | CD17: 1099.919 | CE17: 32.192733 | CF17: 0 | CH17: 1 | CI17: 1 | CJ17: 0.84028572 | CK17: 0 | CL17: 0.15517265 | CM17: 0.0045416357 | CN17: 0 | CR17: 20558.067 | CS17: 17949.941 | CT17: 14330.333 | CU17: 1.7895168 | CV17: 3185.5174 | CW17: 432.3016 | CX17: 2608.1259 | CZ17: 11187.398 | DA17: 8890.1712 | DB17: 7.1533856 | DC17: 1973.927 | DD17: 316.14616 | DF17: 4140.9224 | DG17: 4140.9224 | DH17: 3479.558 | DI17: 0 | DJ17: 642.5579 | DK17: 18.806561 | DL17: 0 | DN17: 0.62325541 | DO17: 0.62037438 | DP17: 3.9973838 | DQ17: 0.61965665 | DR17: 0.73130924 | DV17: 187.92818 | DW17: 164.08643 | DX17: 130.99837 | DY17: 0.016358573 | DZ17: 29.119883 | EA17: 3.9518139 | EB17: 23.841753 | ED17: 102.26775 | EE17: 81.268036 | EF17: 0.065391496 | EG17: 18.044329 | EH17: 2.889998 | EJ17: 37.85356 | EK17: 37.85356 | EL17: 31.807806 | EM17: 0 | EN17: 5.8738372 | EO17: 0.17191708 | EP17: 0 | ET17: 7668.0602 | EU17: 6695.2418 | EV17: 5345.1452 | EW17: 0.66748118 | EX17: 1188.1827 | EY17: 161.24642 | EZ17: 972.81841 | FB17: 4172.8456 | FC17: 3315.9912 | FD17: 2.6681785 | FE17: 736.2653 | FF17: 117.921 | FH17: 1544.5442 | FI17: 1544.5442 | FJ17: 1297.8584 | FK17: 0 | FL17: 239.67101 | FM17: 7.014757 | FN17: 0
... A26: 2021 | C26: 95942.317 | D26: 5006324 | F26: 1934437 | G26: 221065.49 | H26: 62947 | I26: 7953.3406 | K26: 2643.76 | L26: 2750.8305 | M26: 0.96107704 | Q26: 2.5880005 | R26: 44.157249 | S26: 114.27898 | T26: 48.821395 | U26: 126.3498 | V26: 19164.225 | W26: 49597.023 | X26: 1.4118419 | AB26: 3047.6675 | AC26: 335.4405 | AD26: 1319.2797 | AE26: 47.769733 | AF26: 1271.51 | AG26: 593.7902 | AH26: 97.377816 | AI26: 26.324592 | AJ26: 0 | AK26: 0 | AL26: 13.847549 | AM26: 0 | AN26: 57.205675 | AO26: 0 | AP26: 758.98495 | AR26: 3047.6675 | AS26: 2644.5375 | AT26: 2071.3134 | AU26: 0.23013522 | AV26: 501.53584 | AW26: 71.458158 | AX26: 403.12998 | AZ26: 1 | BA26: 0.86772508 | BB26: 0.6796389 | BC26: 7.5511919e-05 | BD26: 0.16456383 | BE26: 0.023446835 | BF26: 0.13227492 | BJ26: 6836.2884 | BK26: 1422.3139 | BL26: 4019.2832 | BM26: 126.20146 | BN26: 3893.0818 | BO26: 1394.6913 | BP26: 0 | BQ26: 0 | BR26: 0 | BS26: 0 | BT26: 0 | BU26: 0 | BV26: 0 | BW26: 0 | BX26: 0 | BZ26: 6836.2884 | CA26: 6836.2884 | CB26: 5648.2554 | CC26: 0 | CD26: 1150.7756 | CE26: 37.257369 | CF26: 0 | CH26: 1 | CI26: 1 | CJ26: 0.82621667 | CK26: 0 | CL26: 0.16833339 | CM26: 0.0054499411 | CN26: 0 | CR26: 18322.837 | CS26: 15899.185 | CT26: 12452.912 | CU26: 1.3835925 | CV26: 3015.2762 | CW26: 429.61253 | CX26: 2423.6518 | CZ26: 11865.768 | DA26: 9294.0724 | DB26: 7.5550638 | DC26: 2223.441 | DD26: 340.69942 | DF26: 3533.9938 | DG26: 3533.9938 | DH26: 2919.8446 | DI26: 0 | DJ26: 594.88916 | DK26: 19.260058 | DL26: 0 | DN26: 0.74631298 | DO26: 0.74633725 | DP26: 5.4604687 | DQ26: 0.73739215 | DR26: 0.79303883 | DV26: 160.33426 | DW26: 139.12606 | DX26: 108.9694 | DY26: 0.012107148 | DZ26: 26.385221 | EA26: 3.7593311 | EB26: 21.208202 | ED26: 103.83158 | EE26: 81.327923 | EF26: 0.066110701 | EG26: 19.456255 | EH26: 2.9812955 | EJ26: 30.924267 | EK26: 30.924267 | EL26: 25.550145 | EM26: 0 | EN26: 5.2055867 | EO26: 0.16853543 | EP26: 0 | ET26: 7079.9199 | EU26: 6143.4241 | EV26: 4811.789 | EW26: 0.53461834 | EX26: 1165.0988 | EY26: 166.00172 | EZ26: 936.49586 | FB26: 4584.9171 | FC26: 3591.2173 | FD26: 2.9192667 | FE26: 859.13468 | FF26: 131.64581 | FH26: 1365.5306 | FI26: 1365.5306 | FJ26: 1128.2241 | FK26: 0 | FL26: 229.86439 | FM26: 7.4420611 | FN26: 0
A27: 2022 | H27: =AVERAGE(H24:H26) -> 70111
A28: 2023 | H28: =AVERAGE(H25:H27) -> 72359
A29: 2024 | H29: =AVERAGE(H26:H28) -> 68472.333
A108: Code | C108: Macro.Meuro2015.IE.ConsumptionExpenditure | D108: Macro.number.IE.Population | F108: NUM.number.IE.Res.HH | G108: SurfaceArea.ksqm.IE.Res.HH | H108: NUM.number.IE.Res.HHnew | I108: SurfaceArea.ksqm.IE.Res.HHnew | K108: HDD.Celsius.IE.Actual | L108: HDD.Celsius.IE.Mean | M108: HDD.ratio.IE.Relative | AB108: FEC.ktoe.IE.ES.Res | AC108: FEC.ktoe.IE.ES.Res.Solids | AE108: FEC.ktoe.IE.ES.Res.LPG | AF108: FEC.ktoe.IE.ES.Res.Oil | AG108: FEC.ktoe.IE.ES.Res.NG | AI108: FEC.ktoe.IE.ES.Res.Biomass_Waste | AJ108: FEC.ktoe.IE.ES.Res.Biogas | AK108: FEC.ktoe.IE.ES.Res.LiqBio | AL108: FEC.ktoe.IE.ES.Res.Solar | AM108: FEC.ktoe.IE.ES.Res.Geo | AN108: FEC.ktoe.IE.ES.Res.Ambient | AO108: FEC.ktoe.IE.ES.Res.Steam_Distr | AP108: FEC.ktoe.IE.ES.Res.Elec | AR108: FEC.ktoe.IE.Res.HH | AS108: FEC.ktoe.IE.Res.HH.Thermal | AT108: FEC.ktoe.IE.Res.HH.Thermal.SH | AU108: FEC.ktoe.IE.Res.HH.Thermal.SC | AV108: FEC.ktoe.IE.Res.HH.Thermal.WH | AW108: FEC.ktoe.IE.Res.HH.Thermal.CO | AX108: FEC.ktoe.IE.Res.HH.Appl | BJ108: EMI.ktCO2.IE.ES.Res | BK108: EMI.ktCO2.IE.ES.Res.Solids | BM108: EMI.ktCO2.IE.ES.Res.LPG | BN108: EMI.ktCO2.IE.ES.Res.Oil | BO108: EMI.ktCO2.IE.ES.Res.NG | BQ108: EMI.ktCO2.IE.ES.Res.Biomass_Waste | BR108: EMI.ktCO2.IE.ES.Res.Biogas | BS108: EMI.ktCO2.IE.ES.Res.LiqBio | BT108: EMI.ktCO2.IE.ES.Res.Solar | BU108: EMI.ktCO2.IE.ES.Res.Geo | BV108: EMI.ktCO2.IE.ES.Res.Ambient | BW108: EMI.ktCO2.IE.ES.Res.Steam_Distr | BX108: EMI.ktCO2.IE.ES.Res.Elec | BZ108: EMI.ktCO2.IE.Res.HH | CA108: EMI.ktCO2.IE.Res.HH.Thermal | CB108: EMI.ktCO2.IE.Res.HH.Thermal.SH | CC108: EMI.ktCO2.IE.Res.HH.Thermal.SC | CD108: EMI.ktCO2.IE.Res.HH.Thermal.WH | CE108: EMI.ktCO2.IE.Res.HH.Thermal.CO | CF108: EMI.ktCO2.IE.Res.HH.Appl | CR108: FEC_per_household.kWh.IE.Res.HH | CS108: FEC_per_household.kWh.IE.Res.HH.Thermal | CT108: FEC_per_household.kWh.IE.Res.HH.Thermal.SH | CU108: FEC_per_household.kWh.IE.Res.HH.Thermal.SC | CV108: FEC_per_household.kWh.IE.Res.HH.Thermal.WH | CW108: FEC_per_household.kWh.IE.Res.HH.Thermal.CO | CX108: FEC_per_household.kWh.IE.Res.HH.Appl | CZ108: TES_per_household.kWh.IE.Res.HH.Thermal | DA108: TES_per_household.kWh.IE.Res.HH.Thermal.SH | DB108: TES_per_household.kWh.IE.Res.HH.Thermal.SC | DC108: TES_per_household.kWh.IE.Res.HH.Thermal.WH | DD108: TES_per_household.kWh.IE.Res.HH.Thermal.CO | DF108: EMI_per_household.kgCO2.IE.Res.HH | DG108: EMI_per_household.kgCO2.IE.Res.HH.Thermal | DH108: EMI_per_household.kgCO2.IE.Res.HH.Thermal.SH | DI108: EMI_per_household.kgCO2.IE.Res.HH.Thermal.SC | DJ108: EMI_per_household.kgCO2.IE.Res.HH.Thermal.WH | DK108: EMI_per_household.kgCO2.IE.Res.HH.Thermal.CO | DL108: EMI_per_household.kgCO2.IE.Res.HH.Appl | DN108: Eff.ratio.IE.Res.HH.Thermal | DO108: Eff.ratio.IE.Res.HH.Thermal.SH | DP108: Eff.ratio.IE.Res.HH.Thermal.SC | DQ108: Eff.ratio.IE.Res.HH.Thermal.WH | DR108: Eff.ratio.IE.Res.HH.Thermal.CO | DV108: FEC_per_sqm.kWh.IE.Res.HH | DW108: FEC_per_sqm.kWh.IE.Res.HH.Thermal | DX108: FEC_per_sqm.kWh.IE.Res.HH.Thermal.SH | DY108: FEC_per_sqm.kWh.IE.Res.HH.Thermal.SC | DZ108: FEC_per_sqm.kWh.IE.Res.HH.Thermal.WH | EA108: FEC_per_sqm.kWh.IE.Res.HH.Thermal.CO | EB108: FEC_per_sqm.kWh.IE.Res.HH.Appl | ED108: TES_per_sqm.kWh.IE.Res.HH.Thermal | EE108: TES_per_sqm.kWh.IE.Res.HH.Thermal.SH | EF108: TES_per_sqm.kWh.IE.Res.HH.Thermal.SC | EG108: TES_per_sqm.kWh.IE.Res.HH.Thermal.WH | EH108: TES_per_sqm.kWh.IE.Res.HH.Thermal.CO | EJ108: EMI_per_sqm.kgCO2.IE.Res.HH | EK108: EMI_per_sqm.kgCO2.IE.Res.HH.Thermal | EL108: EMI_per_sqm.kgCO2.IE.Res.HH.Thermal.SH | EM108: EMI_per_sqm.kgCO2.IE.Res.HH.Thermal.SC | EN108: EMI_per_sqm.kgCO2.IE.Res.HH.Thermal.WH | EO108: EMI_per_sqm.kgCO2.IE.Res.HH.Thermal.CO | EP108: EMI_per_sqm.kgCO2.IE.Res.HH.Appl | ET108: FEC_per_capita.kWh.IE.Res.HH | EU108: FEC_per_capita.kWh.IE.Res.HH.Thermal | EV108: FEC_per_capita.kWh.IE.Res.HH.Thermal.SH | EW108: FEC_per_capita.kWh.IE.Res.HH.Thermal.SC | EX108: FEC_per_capita.kWh.IE.Res.HH.Thermal.WH | EY108: FEC_per_capita.kWh.IE.Res.HH.Thermal.CO | EZ108: FEC_per_capita.kWh.IE.Res.HH.Appl | FB108: TES_per_capita.kWh.IE.Res.HH.Thermal | FC108: TES_per_capita.kWh.IE.Res.HH.Thermal.SH | FD108: TES_per_capita.kWh.IE.Res.HH.Thermal.SC | FE108: TES_per_capita.kWh.IE.Res.HH.Thermal.WH | FF108: TES_per_capita.kWh.IE.Res.HH.Thermal.CO | FH108: EMI_per_capita.kgCO2.IE.Res.HH | FI108: EMI_per_capita.kgCO2.IE.Res.HH.Thermal | FJ108: EMI_per_capita.kgCO2.IE.Res.HH.Thermal.SH | FK108: EMI_per_capita.kgCO2.IE.Res.HH.Thermal.SC | FL108: EMI_per_capita.kgCO2.IE.Res.HH.Thermal.WH | FM108: EMI_per_capita.kgCO2.IE.Res.HH.Thermal.CO | FN108: EMI_per_capita.kgCO2.IE.Res.HH.Appl

Sheet passive building (belgium)
A1: BE - Residential sector summary | B1: Column2 | C1: Household consumption expenditure (M€ at 2015 prices) | D1: Population (inhabitants) | E1: Column5 | F1: Number of households | G1: Total households useful surface area (in thousand sqm) | H1: Number of new and renovated households | I1: New and renovated households useful surface area (in thousand sqm) | J1: Column10 | K1: Actual heating degree-days | L1: Mean heating degree-days over period 2000 - 2020 | M1: Relative heating degree-days | N1: Column14 | O1: Indicators | P1: Column16 | Q1: Households size (inhabitants/household) | R1: Households useful surface area (in sqm/capita) | S1: Households useful surface area (in sqm/household) | T1: New and renovated households useful surface area (in sqm/capita) | U1: New and renovated households useful surface area (in sqm/household) | V1: Household consumption expenditure per capita (€ at 2015 prices) | W1: Household consumption expenditure per household (€ at 2015 prices) | X1: Consumption expenditure per household relative to the EU average | Y1: Column25 | Z1: Energy consumption | AA1: Column27 | AB1: Energy consumption by fuel - Eurostat structure (ktoe) | AC1: Solids | AD1: Liquids | AE1: Liquified petroleum gas (LPG) | AF1: Diesel oil and other liquids (without biofuels) | AG1: Natural gas | AH1: Renewable energies and wastes | AI1: Biomass and waste | AJ1: Biogas | AK1: Liquid biofuels | AL1: Solar | AM1: Geothermal | AN1: Ambient heat | AO1: Distributed heat | AP1: Electricity | AQ1: Column43 | AR1: Energy consumption by end-uses (ktoe) | AS1: Thermal uses | AT1: Space heating | AU1: Cooling | AV1: Water heating | AW1: Cooking | AX1: Specific electricity uses (appliances and lighting) | AY1: Column51 | AZ1: Shares of energy consumption in end-uses (in %) | BA1: Thermal uses_1 | BB1: Space heating_2 | BC1: Cooling_3 | BD1: Water heating_4 | BE1: Cooking_5 | BF1: Specific electricity uses (appliances and lighting)_6 | BG1: Column59 | BH1: Emissions | BI1: Column61 | BJ1: Emissions by fuel - Eurostat structure (kt of CO2) | BK1: Solids_7 | BL1: Liquids_8 | BM1: Liquified petroleum gas (LPG)_9 | BN1: Diesel oil and other liquids (without biofuels)_10 | BO1: Natural gas_11 | BP1: Renewable energies and wastes_12 | BQ1: Biomass and waste_13 | BR1: Biogas_14 | BS1: Liquid biofuels_15 | BT1: Solar_16 | BU1: Geothermal_17 | BV1: Ambient heat_18 | BW1: Distributed heat_19 | BX1: Electricity_20 | BY1: Column77 | BZ1: Emissions by end-uses (kt of CO2) | CA1: Thermal uses_21 | CB1: Space heating_22 | CC1: Cooling_23 | CD1: Water heating_24 | CE1: Cooking_25 | CF1: Specific electricity uses (appliances and lighting)_26 | CG1: Column85 | CH1: Share of emissions in end-uses (in %) | CI1: Thermal uses_27 | CJ1: Space heating_28 | CK1: Cooling_29 | CL1: Water heating_30 | CM1: Cooking_31 | CN1: Specific electricity uses (appliances and lighting)_32 | CO1: Column93 | CP1: Additional household indicators | CQ1: Column95 | CR1: Energy consumption per household (kWh / household) | CS1: Thermal uses_33 | CT1: Space heating_34 | CU1: Cooling_35 | CV1: Water heating_36 | CW1: Cooking_37 | CX1: Specific electricity uses (appliances and lighting)_38 | CY1: Column103 | CZ1: Thermal energy service per household (kWh useful / household) | DA1: Space heating_39 | DB1: Cooling_40 | DC1: Water heating_41 | DD1: Cooking_42 | DE1: Column109 | DF1: Emissions per household (kg CO2 / household) | DG1: Thermal uses_43 | DH1: Space heating_44 | DI1: Cooling_45 | DJ1: Water heating_46 | DK1: Cooking_47 | DL1: Specific electricity uses (appliances and lighting)_48 | DM1: Column117 | DN1: Ratio of energy service to energy consumption (system efficiency indicator) | DO1: Space heating_49 | DP1: Cooling_50 | DQ1: Water heating_51 | DR1: Cooking_52 | DS1: Column123 | DT1: Column124 | DU1: Column125 | DV1: Energy consumption per surface area (kWh / sqm) | DW1: Thermal uses_53 | DX1: Space heating_54 | DY1: Cooling_55 | DZ1: Water heating_56 | EA1: Cooking_57 | EB1: Specific electricity uses (appliances and lighting)_58 | EC1: Column133 | ED1: Thermal energy service per surface area (kWh useful / sqm) | EE1: Space heating_59 | EF1: Cooling_60 | EG1: Water heating_61 | EH1: Cooking_62 | EI1: Column139 | EJ1: Emissions per surface area (kg CO2 / sqm) | EK1: Thermal uses_63 | EL1: Space heating_64 | EM1: Cooling_65 | EN1: Water heating_66 | EO1: Cooking_67 | EP1: Specific electricity uses (appliances and lighting)_68 | EQ1: Column147 | ER1: Column148 | ES1: Column149 | ET1: Energy consumption per capita (kWh / capita) | EU1: Thermal uses_69 | EV1: Space heating_70 | EW1: Cooling_71 | EX1: Water heating_72 | EY1: Cooking_73 | EZ1: Specific electricity uses (appliances and lighting)_74 | FA1: Column157 | FB1: Thermal energy service per capita (kWh useful / capita) | FC1: Space heating_75 | FD1: Cooling_76 | FE1: Water heating_77 | FF1: Cooking_78 | FG1: Column163 | FH1: Emissions per capita (kg CO2 / capita) | FI1: Thermal uses_79 | FJ1: Space heating_80 | FK1: Cooling_81 | FL1: Water heating_82 | FM1: Cooking_83 | FN1: Specific electricity uses (appliances and lighting)_84
A2: 1997 | H2: =AVERAGE(H3:H5) -> 86533.333
A3: 1998 | H3: =AVERAGE(H4:H6) -> 96413
A4: 1999 | H4: =AVERAGE(H5:H7) -> 106389
A5: 2000 | C5: 175859.98 | D5: 10239085 | F5: 4373926 | G5: 544890.53 | H5: 56798 | I5: 0 | K5: 2515.89 | L5: 2633.7271 | M5: 0.95525841 | Q5: 2.340937 | R5: 53.216721 | S5: 124.57699 | V5: 17175.361 | W5: 40206.438 | X5: 1.2292468 | AB5: 9565.7694 | AC5: 197.7196 | AD5: 3864.5672 | AE5: 98.882201 | AF5: 3765.685 | AG5: 3292.5863 | AH5: 152.38375 | AI5: 151.90602 | AJ5: 0 | AK5: 0 | AL5: 0.47773001 | AM5: 0 | AN5: 1.0669044 | AO5: 17.411866 | AP5: 2041.1006 | AR5: 9565.7694 | AS5: 8644.3237 | AT5: 7737.4061 | AU5: 1.0635561 | AV5: 784.28527 | AW5: 121.56875 | AX5: 921.44568 | AZ5: 1 | BA5: 0.9036726 | BB5: 0.80886396 | BC5: 0.00011118354 | BD5: 0.081988729 | BE5: 0.012708727 | BF5: 0.096327398 | BJ5: 20450.393 | BK5: 785.04427 | BL5: 11931.739 | BM5: 261.234 | BN5: 11670.505 | BO5: 7733.6096 | BP5: 0 | BQ5: 0 | BR5: 0 | BS5: 0 | BT5: 0 | BU5: 0 | BV5: 0 | BW5: 0 | BX5: 0 | BZ5: 20450.393 | CA5: 20450.393 | CB5: 19405.875 | CC5: 0 | CD5: 957.7762 | CE5: 86.741527 | CF5: 0 | CH5: 1 | CI5: 1 | CJ5: 0.94892432 | CK5: 0 | CL5: 0.046834123 | CM5: 0.0042415581 | CN5: 0 | CR5: 25434.792 | CS5: 22984.725 | CT5: 20573.287 | CU5: 2.8279302 | CV5: 2085.3663 | CW5: 323.24382 | CX5: 2450.0673 | CZ5: 11779.383 | DA5: 10310.603 | DB5: 5.4945361 | DC5: 1234.0794 | DD5: 229.20586 | DF5: 4675.5232 | DG5: 4675.5232 | DH5: 4436.7177 | DI5: 0 | DJ5: 218.97403 | DK5: 19.831503 | DL5: 0 | DN5: 0.51248743 | DO5: 0.50116459 | DP5: 1.9429532 | DQ5: 0.59178066 | DR5: 0.70908041 | DV5: 204.16926 | DW5: 184.50217 | DX5: 165.14516 | DY5: 0.022700261 | DZ5: 16.739578 | EA5: 2.5947314 | EB5: 19.667094 | ED5: 94.555043 | EE5: 82.764906 | EF5: 0.044105546 | EG5: 9.9061587 | EH5: 1.8398732 | EJ5: 37.531195 | EK5: 37.531195 | EL5: 35.614263 | EM5: 0 | EN5: 1.7577406 | EO5: 0.15919074 | EP5: 0 | ET5: 10865.219 | EU5: 9818.6005 | EV5: 8788.4839 | EW5: 1.2080335 | EX5: 890.82547 | EY5: 138.0831 | EZ5: 1046.6182 | FB5: 5031.9094 | FC5: 4404.4769 | FD5: 2.3471526 | FE5: 527.17329 | FF5: 97.912018 | FH5: 1997.2871 | FI5: 1997.2871 | FJ5: 1895.2743 | FK5: 0 | FL5: 93.541191 | FM5: 8.4716093 | FN5: 0
A6: 2001 | C6: 177517.78 | D6: 10263414 | F6: 4400571 | G6: 548175.63 | H6: 126052 | I6: 15668.926 | K6: 2719.01 | L6: 2633.7271 | M6: 1.0323811 | Q6: 2.3322914 | R6: 53.410652 | S6: 124.56921 | T6: 53.297479 | U6: 124.30525 | V6: 17296.173 | W6: 40339.715 | X6: 1.2181706 | AB6: 9968.1778 | AC6: 217.01393 | AD6: 3844.7622 | AE6: 98.882201 | AF6: 3745.88 | AG6: 3621.9697 | AH6: 171.51522 | AI6: 170.34488 | AJ6: 0 | AK6: 0 | AL6: 1.1703353 | AM6: 0 | AN6: 1.8951918 | AO6: 15.238349 | AP6: 2097.6784 | AR6: 9968.1778 | AS6: 9023.6283 | AT6: 8137.5103 | AU6: 1.3183077 | AV6: 762.00671 | AW6: 122.79301 | AX6: 944.54951 | AZ6: 1 | BA6: 0.90524351 | BB6: 0.81634883 | BC6: 0.00013225162 | BD6: 0.076443932 | BE6: 0.012318501 | BF6: 0.094756486 | BJ6: 21234.346 | BK6: 861.42474 | BL6: 11865.657 | BM6: 261.234 | BN6: 11604.423 | BO6: 8507.2637 | BP6: 0 | BQ6: 0 | BR6: 0 | BS6: 0 | BT6: 0 | BU6: 0 | BV6: 0 | BW6: 0 | BX6: 0 | BZ6: 21234.346 | CA6: 21234.346 | CB6: 20182.728 | CC6: 0 | CD6: 959.86684 | CE6: 91.751473 | CF6: 0 | CH6: 1 | CI6: 1 | CJ6: 0.9504756 | CK6: 0 | CL6: 0.045203504 | CM6: 0.0043208994 | CN6: 0 | CR6: 26344.288 | CS6: 23847.995 | CT6: 21506.128 | CU6: 3.4840747 | CV6: 2013.8609 | CW6: 324.52214 | CX6: 2496.2921 | CZ6: 12380.748 | DA6: 10946.926 | DB6: 7.1892002 | DC6: 1196.6156 | DD6: 230.0174 | DF6: 4825.3615 | DG6: 4825.3615 | DH6: 4586.3883 | DI6: 0 | DJ6: 218.12325 | DK6: 20.849902 | DL6: 0 | DN6: 0.51915259 | DO6: 0.50901427 | DP6: 2.0634461 | DQ6: 0.59418979 | DR6: 0.70878801 | DV6: 211.48315 | DW6: 191.44375 | DX6: 172.64402 | DY6: 0.027968989 | DZ6: 16.166603 | EA6: 2.6051554 | EB6: 20.0394 | ED6: 99.388516 | EE6: 87.87827 | EF6: 0.0577125 | EG6: 9.6060306 | EH6: 1.8465029 | EJ6: 38.736391 | EK6: 38.736391 | EL6: 36.817995 | EM6: 0 | EN6: 1.7510206 | EO6: 0.16737605 | EP6: 0 | ET6: 11295.453 | EU6: 10225.135 | EV6: 9221.0296 | EW6: 1.4938419 | EX6: 863.46882 | EY6: 139.14305 | EZ6: 1070.3174 | FB6: 5308.4054 | FC6: 4693.6357 | FD6: 3.0824622 | FE6: 513.06436 | FF6: 98.622926 | FH6: 2068.9359 | FI6: 2068.9359 | FJ6: 1966.4731 | FK6: 0 | FL6: 93.523153 | FM6: 8.9396641 | FN6: 0
A7: 2002 | C7: 178604.28 | D7: 10309725 | F7: 4436875 | G7: 552648.84 | H7: 136317 | I7: 16932.53 | K7: 2527.94 | L7: 2633.7271 | M7: 0.95983367 | Q7: 2.3236456 | R7: 53.604616 | S7: 124.55813 | T7: 53.456677 | U7: 124.21437 | V7: 17323.864 | W7: 40254.521 | X7: 1.2100856 | AB7: 9418.3338 | AC7: 187.10628 | AD7: 3380.7252 | AE7: 115.3626 | AF7: 3265.3626 | AG7: 3456.4401 | AH7: 149.68469 | AI7: 148.27549 | AJ7: 0 | AK7: 0 | AL7: 1.4092003 | AM7: 0 | AN7: 3.6320351 | AO7: 15.572743 | AP7: 2228.8048 | AR7: 9418.3338 | AS7: 8439.5957 | AT7: 7560.0091 | AU7: 1.5672987 | AV7: 756.94612 | AW7: 121.07318 | AX7: 978.73809 | AZ7: 1 | BA7: 0.89608161 | BB7: 0.80269072 | BC7: 0.00016640934 | BD7: 0.08036943 | BE7: 0.012855053 | BF7: 0.10391839 | BJ7: 19315.244 | BK7: 771.34948 | BL7: 10425.427 | BM7: 304.77308 | BN7: 10120.653 | BO7: 8118.4685 | BP7: 0 | BQ7: 0 | BR7: 0 | BS7: 0 | BT7: 0 | BU7: 0 | BV7: 0 | BW7: 0 | BX7: 0 | BZ7: 19315.244 | CA7: 19315.244 | CB7: 18266.976 | CC7: 0 | CD7: 955.99674 | CE7: 92.272016 | CF7: 0 | CH7: 1 | CI7: 1 | CJ7: 0.94572842 | CK7: 0 | CL7: 0.049494416 | CM7: 0.0047771601 | CN7: 0 | CR7: 24687.471 | CS7: 22121.989 | CT7: 19816.404 | CU7: 4.1082258 | CV7: 1984.118 | CW7: 317.35874 | CX7: 2565.4822 | CZ7: 11740.779 | DA7: 10319.347 | DB7: 8.8906421 | DC7: 1187.2469 | DD7: 225.2949 | DF7: 4353.3443 | DG7: 4353.3443 | DH7: 4117.0814 | DI7: 0 | DJ7: 215.46623 | DK7: 20.796623 | DL7: 0 | DN7: 0.53072892 | DO7: 0.5207477 | DP7: 2.1641075 | DQ7: 0.59837514 | DR7: 0.70990607 | DV7: 198.2004 | DW7: 177.60373 | DX7: 159.09362 | DY7: 0.032982398 | DZ7: 15.929253 | EA7: 2.5478766 | EB7: 20.596666 | ED7: 94.259438 | EE7: 82.847638 | EF7: 0.071377454 | EG7: 9.5316691 | EH7: 1.8087531 | EJ7: 34.950303 | EK7: 34.950303 | EL7: 33.053495 | EM7: 0 | EN7: 1.7298448 | EO7: 0.16696319 | EP7: 0 | ET7: 10624.456 | EU7: 9520.3798 | EV7: 8528.1524 | EW7: 1.7680088 | EX7: 853.88149 | EY7: 136.57794 | EZ7: 1104.0764 | FB7: 5052.7409 | FC7: 4441.0158 | FD7: 3.826161 | FE7: 510.94146 | FF7: 96.957512 | FH7: 1873.4975 | FI7: 1873.4975 | FJ7: 1771.8199 | FK7: 0 | FL7: 92.727666 | FM7: 8.9499978 | FN7: 0
A8: 2003 | C8: 179886.66 | D8: 10355844 | F8: 4473367 | G8: 557126.41 | H8: 137330 | I8: 17039.658 | K8: 2687.09 | L8: 2633.7271 | M8: 1.0202613 | Q8: 2.3149999 | R8: 53.798262 | S8: 124.54297 | T8: 53.597493 | U8: 124.07819 | V8: 17370.546 | W8: 40212.811 | X8: 1.202191 | AB8: 9944.3689 | AC8: 131.38667 | AD8: 3769.0599 | AE8: 75.809716 | AF8: 3693.2502 | AG8: 3598.6991 | AH8: 192.05606 | AI8: 189.85864 | AJ8: 0 | AK8: 0 | AL8: 2.1974205 | AM8: 0 | AN8: 5.4990293 | AO8: 15.333878 | AP8: 2237.8332 | AR8: 9944.3689 | AS8: 8937.391 | AT8: 8044.2712 | AU8: 4.1775528 | AV8: 758.19558 | AW8: 130.74663 | AX8: 1006.9779 | AZ8: 1 | BA8: 0.89873889 | BB8: 0.80892728 | BC8: 0.00042009231 | BD8: 0.076243711 | BE8: 0.013147806 | BF8: 0.10126111 | BJ8: 20637.914 | BK8: 540.76338 | BL8: 11644.544 | BM8: 200.27948 | BN8: 11444.265 | BO8: 8452.6058 | BP8: 0 | BQ8: 0 | BR8: 0 | BS8: 0 | BT8: 0 | BU8: 0 | BV8: 0 | BW8: 0 | BX8: 0 | BZ8: 20637.914 | CA8: 20637.914 | CB8: 19553.136 | CC8: 0 | CD8: 984.93476 | CE8: 99.842619 | CF8: 0 | CH8: 1 | CI8: 1 | CJ8: 0.94743764 | CK8: 0 | CL8: 0.047724532 | CM8: 0.0048378252 | CN8: 0 | CR8: 25853.682 | CS8: 23235.71 | CT8: 20913.749 | CU8: 10.860933 | CV8: 1971.1807 | CW8: 339.91919 | CX8: 2617.9727 | CZ8: 12423.515 | DA8: 10970.584 | DB8: 24.746488 | DC8: 1186.1438 | DD8: 242.04082 | DF8: 4613.5078 | DG8: 4613.5078 | DH8: 4371.011 | DI8: 0 | DJ8: 220.1775 | DK8: 22.319345 | DL8: 0 | DN8: 0.53467338 | DO8: 0.52456326 | DP8: 2.2784864 | DQ8: 0.6017428 | DR8: 0.71205401 | DV8: 207.58845 | DW8: 186.56782 | DX8: 167.92396 | DY8: 0.087206312 | DZ8: 15.827314 | EA8: 2.7293326 | EB8: 21.020638 | ED8: 99.752845 | EE8: 88.086742 | EF8: 0.1986984 | EG8: 9.5239723 | EH8: 1.9434323 | EJ8: 37.043503 | EK8: 37.043503 | EL8: 35.096409 | EM8: 0 | EN8: 1.7678838 | EO8: 0.17920999 | EP8: 0 | ET8: 11167.898 | EU8: 10037.024 | EV8: 9034.0174 | EW8: 4.691548 | EX8: 851.48199 | EY8: 146.83335 | EZ8: 1130.8738 | FB8: 5366.5297 | FC8: 4738.9136 | FD8: 10.689628 | FE8: 512.37316 | FF8: 104.55328 | FH8: 1992.8761 | FI8: 1992.8761 | FJ8: 1888.1258 | FK8: 0 | FL8: 95.109077 | FM8: 9.6411861 | FN8: 0
A9: 2004 | C9: 181800 | D9: 10396421 | F9: 4508622 | G9: 561427.66 | H9: 136922 | I9: 16966.622 | K9: 2773.96 | L9: 2633.7271 | M9: 1.053245 | Q9: 2.3058977 | R9: 54.002013 | S9: 124.52312 | T9: 53.738075 | U9: 123.9145 | V9: 17486.787 | W9: 40322.741 | X9: 1.1908004 | AB9: 9298.3169 | AC9: 146.90567 | AD9: 3726.6028 | AE9: 79.105761 | AF9: 3647.497 | AG9: 3552.8958 | AH9: 196.96062 | AI9: 194.61995 | AJ9: 0 | AK9: 0 | AL9: 2.3406707 | AM9: 0 | AN9: 8.3872305 | AO9: 14.960705 | AP9: 1659.9914 | AR9: 9298.3169 | AS9: 8281.82 | AT9: 7303.1415 | AU9: 1.8973656 | AV9: 841.34054 | AW9: 135.4406 | AX9: 1016.497 | AZ9: 1 | BA9: 0.89067947 | BB9: 0.78542617 | BC9: 0.00020405473 | BD9: 0.090483099 | BE9: 0.014566141 | BF9: 0.10932053 | BJ9: 20456.161 | BK9: 599.11918 | BL9: 11512.019 | BM9: 208.9872 | BN9: 11303.032 | BO9: 8345.0231 | BP9: 0 | BQ9: 0 | BR9: 0 | BS9: 0 | BT9: 0 | BU9: 0 | BV9: 0 | BW9: 0 | BX9: 0 | BZ9: 20456.161 | CA9: 20456.161 | CB9: 19139.661 | CC9: 0 | CD9: 1204.7562 | CE9: 111.74355 | CF9: 0 | CH9: 1 | CI9: 1 | CJ9: 0.93564287 | CK9: 0 | CL9: 0.058894539 | CM9: 0.0054625867 | CN9: 0 | CR9: 23985.028 | CS9: 21362.972 | CT9: 18838.469 | CU9: 4.8942585 | CV9: 2170.2397 | CW9: 349.36932 | CX9: 2622.0561 | CZ9: 11394.947 | DA9: 9829.4106 | DB9: 11.794525 | DC9: 1305.4775 | DD9: 248.26394 | DF9: 4537.1205 | DG9: 4537.1205 | DH9: 4245.1244 | DI9: 0 | DJ9: 267.21162 | DK9: 24.784414 | DL9: 0 | DN9: 0.53339706 | DO9: 0.52177333 | DP9: 2.4098696 | DQ9: 0.60153607 | DR9: 0.71060602 | DV9: 192.61507 | DW9: 171.55828 | DX9: 151.28491 | DY9: 0.039304016 | DZ9: 17.428408 | EA9: 2.8056583 | EB9: 21.056782 | ED9: 91.508685 | EE9: 78.936433 | EF9: 0.094717554 | EG9: 10.483816 | EH9: 1.9937177 | EJ9: 36.43597 | EK9: 36.43597 | EL9: 34.091055 | EM9: 0 | EN9: 2.1458796 | EO9: 0.19903464 | EP9: 0 | ET9: 10401.601 | EU9: 9264.4927 | EV9: 8169.6899 | EW9: 2.122496 | EX9: 941.16912 | EY9: 151.5112 | EZ9: 1137.1086 | FB9: 4941.6532 | FC9: 4262.7263 | FD9: 5.1149386 | FE9: 566.14718 | FF9: 107.66477 | FH9: 1967.6157 | FI9: 1967.6157 | FJ9: 1840.9856 | FK9: 0 | FL9: 115.88182 | FM9: 10.748271 | FN9: 0
A10: 2005 | C10: 184426.76 | D10: 10445852 | F10: 4551569 | G10: 566674.15 | H10: 145416 | I10: 18011.769 | K10: 2661.22 | L10: 2633.7271 | M10: 1.0104388 | Q10: 2.2950003 | R10: 54.248725 | S10: 124.50084 | T10: 53.971122 | U10: 123.86374 | V10: 17655.502 | W10: 40519.381 | X10: 1.1782105 | AB10: 9220.719 | AC10: 112.19837 | AD10: 3759.5633 | AE10: 116.46122 | AF10: 3643.1021 | AG10: 3493.8042 | AH10: 206.04764 | AI10: 203.65916 | AJ10: 0 | AK10: 0 | AL10: 2.3884781 | AM10: 0 | AN10: 10.207891 | AO10: 13.980825 | AP10: 1635.1247 | AR10: 9220.719 | AS10: 8170.2577 | AT10: 7160.0982 | AU10: 2.3537719 | AV10: 867.10069 | AW10: 140.7051 | AX10: 1050.4613 | AZ10: 1 | BA10: 0.88607599 | BB10: 0.77652276 | BC10: 0.00025526989 | BD10: 0.094038295 | BE10: 0.015259666 | BF10: 0.11392401 | BJ10: 20268.884 | BK10: 463.33772 | BL10: 11599.317 | BM10: 307.6755 | BN10: 11291.642 | BO10: 8206.2292 | BP10: 0 | BQ10: 0 | BR10: 0 | BS10: 0 | BT10: 0 | BU10: 0 | BV10: 0 | BW10: 0 | BX10: 0 | BZ10: 20268.884 | CA10: 20268.884 | CB10: 18881.998 | CC10: 0 | CD10: 1270.3306 | CE10: 116.55528 | CF10: 0 | CH10: 1 | CI10: 1 | CJ10: 0.93157562 | CK10: 0 | CL10: 0.062673927 | CM10: 0.0057504537 | CN10: 0 | CR10: 23560.439 | CS10: 20876.339 | CT10: 18295.217 | CU10: 6.0142705 | CV10: 2215.5835 | CW10: 359.52443 | CX10: 2684.0996 | CZ10: 11290.828 | DA10: 9677.3996 | DB10: 15.655946 | DC10: 1341.4508 | DD10: 256.32159 | DF10: 4453.1642 | DG10: 4453.1642 | DH10: 4148.4592 | DI10: 0 | DJ10: 279.09729 | DK10: 25.607715 | DL10: 0 | DN10: 0.54084329 | DO10: 0.52895791 | DP10: 2.603133 | DQ10: 0.60546163 | DR10: 0.71294622 | DV10: 189.2392 | DW10: 167.68031 | DX10: 146.94854 | DY10: 0.048307068 | DZ10: 17.795732 | EA10: 2.887727 | EB10: 21.558888 | ED10: 90.688771 | EE10: 77.729595 | EF10: 0.12574972 | EG10: 10.774633 | EH10: 2.0587941 | EJ10: 35.768146 | EK10: 35.768146 | EL10: 33.320733 | EM10: 0 | EN10: 2.2417302 | EO10: 0.20568307 | EP10: 0 | ET10: 10265.985 | EU10: 9096.443 | EV10: 7971.7712 | EW10: 2.6205969 | EX10: 965.39574 | EY10: 156.65551 | EZ10: 1169.5422 | FB10: 4919.7502 | FC10: 4216.7314 | FD10: 6.8217621 | FE10: 584.51008 | FF10: 111.68695 | FH10: 1940.3763 | FI10: 1940.3763 | FJ10: 1807.6073 | FK10: 0 | FL10: 121.611 | FM10: 11.158044 | FN10: 0
A11: 2006 | C11: 187698.13 | D11: 10511382 | F11: 4574144 | G11: 569394.29 | H11: 126020 | I11: 15607.004 | K11: 2588.67 | L11: 2633.7271 | M11: 0.98289225 | Q11: 2.2979998 | R11: 54.169308 | S11: 124.48106 | T11: 53.892716 | U11: 123.84545 | V11: 17856.656 | W11: 41034.591 | X11: 1.1764894 | AB11: 8796.1957 | AC11: 110.62966 | AD11: 3305.4505 | AE11: 118.65864 | AF11: 3186.7918 | AG11: 3487.2926 | AH11: 216.84703 | AI11: 213.9331 | AJ11: 0 | AK11: 0 | AL11: 2.9139295 | AM11: 0 | AN11: 9.7348709 | AO11: 13.705933 | AP11: 1662.27 | AR11: 8796.1957 | AS11: 7732.1199 | AT11: 6690.9558 | AU11: 5.2566313 | AV11: 896.81841 | AW11: 139.08904 | AX11: 1064.0758 | AZ11: 1 | BA11: 0.87903 | BB11: 0.76066473 | BC11: 0.00059760282 | BD11: 0.10195526 | BE11: 0.015812408 | BF11: 0.12097 | BJ11: 18837.077 | BK11: 456.19436 | BL11: 10189.948 | BM11: 313.4808 | BN11: 9876.4673 | BO11: 8190.9347 | BP11: 0 | BQ11: 0 | BR11: 0 | BS11: 0 | BT11: 0 | BU11: 0 | BV11: 0 | BW11: 0 | BX11: 0 | BZ11: 18837.077 | CA11: 18837.077 | CB11: 17368.056 | CC11: 0 | CD11: 1346.5188 | CE11: 122.50257 | CF11: 0 | CH11: 1 | CI11: 1 | CJ11: 0.92201437 | CK11: 0 | CL11: 0.071482364 | CM11: 0.0065032682 | CN11: 0 | CR11: 22364.787 | CS11: 19659.319 | CT11: 17012.105 | CU11: 13.36526 | CV11: 2280.2076 | CW11: 353.64114 | CX11: 2705.4683 | CZ11: 10871.695 | DA11: 9191.6905 | DB11: 37.452891 | DC11: 1390.7195 | DD11: 251.83173 | DF11: 4118.1644 | DG11: 4118.1644 | DH11: 3797.0068 | DI11: 0 | DJ11: 294.37613 | DK11: 26.781528 | DL11: 0 | DN11: 0.55300465 | DO11: 0.54030296 | DP11: 2.8022569 | DQ11: 0.60990917 | DR11: 0.71211094 | DV11: 179.66418 | DW11: 157.9302 | DX11: 136.6642 | DY11: 0.10736782 | DZ11: 18.317708 | EA11: 2.8409233 | EB11: 21.733976 | ED11: 87.336136 | EE11: 73.840073 | EF11: 0.30087221 | EG11: 11.172138 | EH11: 2.0230526 | EJ11: 33.082659 | EK11: 33.082659 | EL11: 30.502687 | EM11: 0 | EN11: 2.3648267 | EO11: 0.21514541 | EP11: 0 | ET11: 9732.2841 | EU11: 8554.9697 | EV11: 7403.0053 | EW11: 5.8160404 | EX11: 992.25754 | EY11: 153.89085 | EZ11: 1177.3144 | FB11: 4730.938 | FC11: 3999.8657 | FD11: 16.298039 | FE11: 605.18697 | FF11: 109.58736 | FH11: 1792.0648 | FI11: 1792.0648 | FJ11: 1652.3094 | FK11: 0 | FL11: 128.10102 | FM11: 11.654278 | FN11: 0
A12: 2007 | C12: 191626.77 | D12: 10584534 | F12: 4611997 | G12: 574000.12 | H12: 141811 | I12: 17556.608 | K12: 2439.16 | L12: 2633.7271 | M12: 0.92612479 | Q12: 2.2950002 | R12: 54.23008 | S12: 124.45804 | T12: 53.944597 | U12: 123.80286 | V12: 18104.413 | W12: 41549.63 | X12: 1.1753289 | AB12: 8136.7523 | AC12: 91.033878 | AD12: 2746.1784 | AE12: 113.16518 | AF12: 2633.0132 | AG12: 3264.4977 | AH12: 369.30473 | AI12: 365.24437 | AJ12: 0 | AK12: 0 | AL12: 4.0603611 | AM12: 0 | AN12: 10.032013 | AO12: 14.482201 | AP12: 1651.2554 | AR12: 8136.7523 | AS12: 7059.0534 | AT12: 6041.5245 | AU12: 2.4804187 | AV12: 876.68286 | AW12: 138.36563 | AX12: 1077.6989 | AZ12: 1 | BA12: 0.86755172 | BB12: 0.74249827 | BC12: 0.00030484137 | BD12: 0.10774358 | BE12: 0.017005019 | BF12: 0.13244828 | BJ12: 16502.276 | BK12: 375.58164 | BL12: 8459.0592 | BM12: 298.96777 | BN12: 8160.0914 | BO12: 7667.6352 | BP12: 0 | BQ12: 0 | BR12: 0 | BS12: 0 | BT12: 0 | BU12: 0 | BV12: 0 | BW12: 0 | BX12: 0 | BZ12: 16502.276 | CA12: 16502.276 | CB12: 15067.439 | CC12: 0 | CD12: 1310.103 | CE12: 124.73378 | CF12: 0 | CH12: 1 | CI12: 1 | CJ12: 0.91305219 | CK12: 0 | CL12: 0.079389233 | CM12: 0.0075585805 | CN12: 0 | CR12: 20518.32 | CS12: 17800.704 | CT12: 15234.817 | CU12: 6.2548328 | CV12: 2210.7173 | CW12: 348.91441 | CX12: 2717.6162 | CZ12: 10046.293 | DA12: 8418.274 | DB12: 18.230377 | DC12: 1361.3 | DD12: 248.48845 | DF12: 3578.1194 | DG12: 3578.1194 | DH12: 3267.0098 | DI12: 0 | DJ12: 284.06415 | DK12: 27.045503 | DL12: 0 | DN12: 0.56437617 | DO12: 0.55256811 | DP12: 2.9146066 | DQ12: 0.615773 | DR12: 0.71217594 | DV12: 164.86134 | DW12: 143.02574 | DX12: 122.40926 | DY12: 0.050256557 | DZ12: 17.762752 | EA12: 2.8034702 | EB12: 21.835601 | ED12: 80.720318 | EE12: 67.639453 | EF12: 0.14647809 | EG12: 10.937823 | EH12: 1.996564 | EJ12: 28.749604 | EK12: 28.749604 | EL12: 26.249889 | EM12: 0 | EN12: 2.282409 | EO12: 0.21730619 | EP12: 0 | ET12: 8940.4436 | EU12: 7756.2972 | EV12: 6638.2639 | EW12: 2.7254171 | EX12: 963.27544 | EY12: 152.03241 | EZ12: 1184.1464 | FB12: 4377.4693 | FC12: 3668.0929 | FD12: 7.9435187 | FE12: 593.159 | FF12: 108.27383 | FH12: 1559.0933 | FI12: 1559.0933 | FJ12: 1423.5335 | FK12: 0 | FL12: 123.77522 | FM12: 11.784532 | FN12: 0
A13: 2008 | C13: 194261.2 | D13: 10666866 | F13: 4655987 | G13: 579359.6 | H13: 148808 | I13: 18417.391 | K13: 2698.26 | L13: 2633.7271 | M13: 1.0245025 | Q13: 2.291 | R13: 54.313948 | S13: 124.43325 | T13: 54.022757 | U13: 123.76613 | V13: 18211.647 | W13: 41722.883 | X13: 1.187415 | AB13: 9194.3721 | AC13: 129.60989 | AD13: 3462.1906 | AE13: 118.65864 | AF13: 3343.532 | AG13: 3480.7347 | AH13: 429.92648 | AI13: 424.74807 | AJ13: 0 | AK13: 0.067153912 | AL13: 5.111264 | AM13: 0 | AN13: 12.277583 | AO13: 14.04282 | AP13: 1677.8676 | AR13: 9194.3721 | AS13: 8110.4062 | AT13: 7070.798 | AU13: 2.9794426 | AV13: 919.09834 | AW13: 117.53042 | AX13: 1083.9658 | AZ13: 1 | BA13: 0.88210551 | BB13: 0.76903545 | BC13: 0.00032405068 | BD13: 0.099963144 | BE13: 0.012782866 | BF13: 0.11789449 | BJ13: 19386.854 | BK13: 534.50674 | BL13: 10676.816 | BM13: 313.4808 | BN13: 10363.335 | BO13: 8175.5315 | BP13: 0 | BQ13: 0 | BR13: 0 | BS13: 0 | BT13: 0 | BU13: 0 | BV13: 0 | BW13: 0 | BX13: 0 | BZ13: 19386.854 | CA13: 19386.854 | CB13: 17760.018 | CC13: 0 | CD13: 1528.1881 | CE13: 98.648587 | CF13: 0 | CH13: 1 | CI13: 1 | CJ13: 0.91608558 | CK13: 0 | CL13: 0.078825997 | CM13: 0.0050884267 | CN13: 0 | CR13: 22966.247 | CS13: 20258.653 | CT13: 17661.858 | CU13: 7.442228 | CV13: 2295.7782 | CW13: 293.57445 | CX13: 2707.594 | CZ13: 11529.011 | DA13: 9883.7183 | DB13: 22.187817 | DC13: 1412.5453 | DD13: 210.55931 | DF13: 4163.8549 | DG13: 4163.8549 | DH13: 3814.4474 | DI13: 0 | DJ13: 328.22001 | DK13: 21.18747 | DL13: 0 | DN13: 0.56909069 | DO13: 0.55960807 | DP13: 2.9813406 | DQ13: 0.6152795 | DR13: 0.71722628 | DV13: 184.5668 | DW13: 162.80739 | DX13: 141.93841 | DY13: 0.059808998 | DZ13: 18.449878 | EA13: 2.3592926 | EB13: 21.759409 | ED13: 92.652169 | EE13: 79.42988 | EF13: 0.17831099 | EG13: 11.351831 | EH13: 1.6921467 | EJ13: 33.462558 | EK13: 33.462558 | EL13: 30.654567 | EM13: 0 | EN13: 2.6377195 | EO13: 0.17027177 | EP13: 0 | ET13: 10024.551 | EU13: 8842.712 | EV13: 7709.2354 | EW13: 3.2484628 | EX13: 1002.0857 | EY13: 128.14249 | EZ13: 1181.8394 | FB13: 5032.3051 | FC13: 4314.1504 | FD13: 9.6847739 | FE13: 616.56277 | FF13: 91.907164 | FH13: 1817.4836 | FI13: 1817.4836 | FJ13: 1664.9705 | FK13: 0 | FL13: 143.26496 | FM13: 9.2481322 | FN13: 0
A14: 2009 | C14: 195396.9 | D14: 10753080 | F14: 4716263 | G14: 586729.83 | H14: 166094 | I14: 20552.714 | K14: 2692.13 | L14: 2633.7271 | M14: 1.022175 | Q14: 2.2800001 | R14: 54.563886 | S14: 124.40566 | T14: 54.272569 | U14: 123.74146 | V14: 18171.25 | W14: 41430.451 | X14: 1.2015255 | AB14: 8777.1902 | AC14: 216.98753 | AD14: 2917.0965 | AE14: 123.0534 | AF14: 2794.0431 | AG14: 3493.4049 | AH14: 458.68444 | AI14: 448.93474 | AJ14: 0 | AK14: 0.19587274 | AL14: 9.5538263 | AM14: 0 | AN14: 13.078123 | AO14: 12.100258 | AP14: 1678.9166 | AR14: 8777.1902 | AS14: 7674.8305 | AT14: 6595.9967 | AU14: 3.4638621 | AV14: 949.08864 | AW14: 126.28134 | AX14: 1102.3597 | AZ14: 1 | BA14: 0.87440632 | BB14: 0.75149297 | BC14: 0.00039464362 | BD14: 0.10813126 | BE14: 0.014387445 | BF14: 0.12559368 | BJ14: 18073.811 | BK14: 880.83048 | BL14: 8987.6897 | BM14: 325.09117 | BN14: 8662.5986 | BO14: 8205.2913 | BP14: 0 | BQ14: 0 | BR14: 0 | BS14: 0 | BT14: 0 | BU14: 0 | BV14: 0 | BW14: 0 | BX14: 0 | BZ14: 18073.811 | CA14: 18073.811 | CB14: 16363.442 | CC14: 0 | CD14: 1598.6919 | CE14: 111.67774 | CF14: 0 | CH14: 1 | CI14: 1 | CJ14: 0.90536752 | CK14: 0 | CL14: 0.088453502 | CM14: 0.0061789811 | CN14: 0 | CR14: 21643.984 | CS14: 18925.637 | CT14: 16265.302 | CU14: 8.5416602 | CV14: 2340.3913 | CW14: 311.40164 | CX14: 2718.3477 | CZ14: 11061.901 | DA14: 9356.5328 | DB14: 26.167774 | DC14: 1456.4523 | DD14: 222.74814 | DF14: 3832.2315 | DG14: 3832.2315 | DH14: 3469.5779 | DI14: 0 | DJ14: 338.97429 | DK14: 23.679286 | DL14: 0 | DN14: 0.58449295 | DO14: 0.57524495 | DP14: 3.0635466 | DQ14: 0.62231146 | DR14: 0.71530819 | DV14: 173.97909 | DW14: 152.12842 | DX14: 130.74406 | DY14: 0.068659738 | DZ14: 18.812579 | EA14: 2.5031146 | EB14: 21.850675 | ED14: 88.917986 | EE14: 75.209862 | EF14: 0.21034231 | EG14: 11.707283 | EH14: 1.7904984 | EJ14: 30.804317 | EK14: 30.804317 | EL14: 27.889228 | EM14: 0 | EN14: 2.7247497 | EO14: 0.19033929 | EP14: 0 | ET14: 9492.9752 | EU14: 8300.7175 | EV14: 7133.9041 | EW14: 3.7463421 | EX14: 1026.4874 | EY14: 136.57966 | EZ14: 1192.2577 | FB14: 4851.7108 | FC14: 4103.7423 | FD14: 11.477094 | FE14: 638.79486 | FF14: 97.696549 | FH14: 1680.8032 | FI14: 1680.8032 | FJ14: 1521.7446 | FK14: 0 | FL14: 148.67293 | FM14: 10.385651 | FN14: 0
A15: 2010 | C15: 201276.13 | D15: 10839905 | F15: 4758518 | G15: 591848.06 | H15: 149443 | I15: 18471.391 | K15: 3193.64 | L15: 2633.7271 | M15: 1.2125933 | Q15: 2.2780002 | R15: 54.599008 | S15: 124.37655 | T15: 54.258809 | U15: 123.60158 | V15: 18568.071 | W15: 42298.071 | X15: 1.2235541 | AB15: 9672.7586 | AC15: 120.40516 | AD15: 3171.4985 | AE15: 141.73113 | AF15: 3029.7673 | AG15: 3985.6564 | AH15: 687.24256 | AI15: 650.89209 | AJ15: 0 | AK15: 7.6817713 | AL15: 11.256836 | AM15: 0 | AN15: 17.411866 | AO15: 12.117627 | AP15: 1713.2502 | AR15: 9672.7586 | AS15: 8573.8521 | AT15: 7510.9362 | AU15: 4.9626179 | AV15: 930.30295 | AW15: 127.65035 | AX15: 1098.9064 | AZ15: 1 | BA15: 0.88639162 | BB15: 0.77650405 | BC15: 0.00051305094 | BD15: 0.096177626 | BE15: 0.013196892 | BF15: 0.11360838 | BJ15: 19622.582 | BK15: 496.20159 | BL15: 9764.8911 | BM15: 374.43532 | BN15: 9390.4558 | BO15: 9361.489 | BP15: 0 | BQ15: 0 | BR15: 0 | BS15: 0 | BT15: 0 | BU15: 0 | BV15: 0 | BW15: 0 | BX15: 0 | BZ15: 19622.582 | CA15: 19622.582 | CB15: 17919.492 | CC15: 0 | CD15: 1588.1024 | CE15: 114.98758 | CF15: 0 | CH15: 1 | CI15: 1 | CJ15: 0.91320765 | CK15: 0 | CL15: 0.080932391 | CM15: 0.0058599617 | CN15: 0 | CR15: 23640.592 | CS15: 20954.823 | CT15: 18357.015 | CU15: 12.128828 | CV15: 2273.696 | CW15: 311.98235 | CX15: 2685.7694 | CZ15: 12486.126 | DA15: 10796.671 | DB15: 38.244768 | DC15: 1428.0283 | DD15: 223.18156 | DF15: 4123.675 | DG15: 4123.675 | DH15: 3765.7716 | DI15: 0 | DJ15: 333.73888 | DK15: 24.164578 | DL15: 0 | DN15: 0.59585929 | DO15: 0.58814959 | DP15: 3.1532122 | DQ15: 0.62806474 | DR15: 0.71536599 | DV15: 190.07274 | DW15: 168.47888 | DX15: 147.59225 | DY15: 0.097516998 | DZ15: 18.280745 | EA15: 2.5083695 | EB15: 21.593856 | ED15: 100.38971 | EE15: 86.806323 | EF15: 0.30749178 | EG15: 11.481491 | EH15: 1.7944022 | EJ15: 33.154762 | EK15: 33.154762 | EL15: 30.277183 | EM15: 0 | EN15: 2.6832942 | EO15: 0.19428564 | EP15: 0 | ET15: 10377.783 | EU15: 9198.7799 | EV15: 8058.3905 | EW15: 5.3243313 | EX15: 998.11053 | EY15: 136.95449 | EZ15: 1179.0031 | FB15: 5481.1785 | FC15: 4739.5391 | FD15: 16.788746 | FE15: 626.87803 | FF15: 97.972581 | FH15: 1810.2171 | FI15: 1810.2171 | FJ15: 1653.1041 | FK15: 0 | FL15: 146.5052 | FM15: 10.607803 | FN15: 0
